Workbook

Sheet Verdict
A1: VERDICT — BEST INDUSTRY FOR NEW MONEY, ALL AI CAVEATS APPLIED (July 2026)
A4: Rank | B4: Name | C4: AI-weighted value | D4: Price | E4: Weighted upside | F4: AI-BUST downside | G4: Net caveat score | H4: One-line verdict
A5: 1 | B5: SNPS | C5: =AI_Stress_DCF!AR7 -> 399.77836 | D5: =AI_Stress_DCF!B7 -> 384.28 | E5: =AI_Stress_DCF!AS7 -> 0.040330893 | F5: =AI_Stress_DCF!AT7 -> -0.56384411 | G5: =AI_Caveat_Matrix!B13 -> -1 | H5: Positive upside even with a 20% bust weight; moat survives every state; fear already in the price. China is the caveat that matters.
A6: 2 | B6: META | C6: =AI_Stress_DCF!AR10 -> 729.91886 | D6: =AI_Stress_DCF!B10 -> 656.73 | E6: =AI_Stress_DCF!AS10 -> 0.11144437 | F6: =AI_Stress_DCF!AT10 -> -0.49401264 | G6: =AI_Caveat_Matrix!E13 -> -2 | H6: Most bust-RESILIENT equity in the set (−49%): net cash, and ad demand exists without the AI narrative. But it IS the capex cycle — caveat score −2.
A7: 3 | B7: VST | C7: =AI_Stress_DCF!AR9 -> 146.6221 | D7: =AI_Stress_DCF!B9 -> 155.44 | E7: =AI_Stress_DCF!AS9 -> -0.056728662 | F7: =AI_Stress_DCF!AT9 -> -0.70590814 | G7: =AI_Caveat_Matrix!D13 -> 0 | H7: Business is bust-resilient (electrification persists) but the EQUITY is levered ($21.6B net debt) so bust drawdown is deceptively large. Full model (+16%) is kinder than this stress engine — the truth is between them. Still the portfolio's non-tech diversifier.
A8: 4 | B8: CDNS | C8: =AI_Stress_DCF!AR8 -> 270.00189 | D8: =AI_Stress_DCF!B8 -> 330.1 | E8: =AI_Stress_DCF!AS8 -> -0.18206033 | F8: =AI_Stress_DCF!AT8 -> -0.65826599 | G8: =AI_Caveat_Matrix!C13 -> -1 | H8: Same moat as SNPS but no fear discount — the stress test punishes paying fair price for AI-exposed cash flows.
A9: 5 | B9: NOW | C9: =AI_Stress_DCF!AR11 -> 175.82804 | D9: =AI_Stress_DCF!B11 -> 101.6 | E9: =AI_Stress_DCF!AS11 -> 0.73059097 | F9: =AI_Stress_DCF!AT11 -> -0.58671005 | G9: =AI_Caveat_Matrix!F13 -> 0 | H9: +73% weighted upside, biggest in the set — but it's the one name where the BUST case is commoditization of the product itself, not just a slower cycle. Deep value if agents don't eat SaaS; trap if they do.
A10: 6 | B10: XE | C10: =AI_Stress_DCF!AR14 -> 10.905678 | D10: =AI_Stress_DCF!B14 -> 14.02 | E10: =AI_Stress_DCF!AS14 -> -0.22213423 | F10: =AI_Stress_DCF!AT14 -> -0.71325681 | G10: =AI_Caveat_Matrix!I13 -> 0 | H10: Energy-scarcity tailwind survives, but a capex bust removes the anchor-tenant thesis for a pre-commercial company.
A11: 7 | B11: SYM | C11: =AI_Stress_DCF!AR13 -> 19.136948 | D11: =AI_Stress_DCF!B13 -> 42.51 | E11: =AI_Stress_DCF!AS13 -> -0.5498248 | F11: =AI_Stress_DCF!AT13 -> -0.82238439 | G11: =AI_Caveat_Matrix!H13 -> 1 | H11: AI tailwind is real; the price pre-pays ~29% CAGR for it. Negative weighted upside in every framework we've built.
A12: 8 | B12: VECO | C12: =AI_Stress_DCF!AR12 -> 34.308643 | D12: =AI_Stress_DCF!B12 -> 55.13 | E12: =AI_Stress_DCF!AS12 -> -0.37767744 | F12: =AI_Stress_DCF!AT12 -> -0.9065619 | G12: =AI_Caveat_Matrix!G13 -> -7 | H12: Max capex-cycle dependence × hype price = worst bust downside (−91%). Great industry, wrong vehicle, wrong price.
A14: THE ANSWER
A15: This stress test deliberately adds a 20%-probability AI BUST state that the full models didn't carry — so every upside number here is compressed vs. the standalone workbooks. Read it as a floor-finder, not a forecast: it asks 'which industries keep their value if the AI cycle itself breaks?'
A16: The answer stands: EDA via SNPS is #1 — the only fear-discounted name whose moat (foundry sign-off certification, subscription backlog) survives all three AI states. Pairing it with VST still makes sense for the PORTFOLIO even though VST ranks #3 here: its equity leverage amplifies a bust, but its demand driver (electrification) is the least AI-dependent of anything you own — it diversifies the scenario, which is what you need, not the drawdown statistic.
A17: META's #2 is the surprise worth knowing: net cash + self-funded AI + ad demand that exists without the narrative = best bust floor. Your $20/wk there is better justified than it looked.
A18: NOW: +73% on paper, but its bust is structural, not cyclical. Hold, don't add, until agentic evidence lands.
A19: Your diligence checklist before deploying: (1) SNPS next 10-Q — China revenue % and Ansys synergy language; (2) VST — data-center PPA announcements and the hedge book; (3) any yellow cell on the stress sheet you disagree with, change it and watch the verdict — the model is a hypothesis, your reading is the test.

Sheet AI_Caveat_Matrix
A1: AI CAVEAT MATRIX — HOW EACH AI-SPECIFIC RISK/TAILWIND HITS EACH INDUSTRY (score: +2 strong tailwind … −2 severe threat)
A4: Caveat | B4: SNPS | C4: CDNS | D4: VST | E4: META | F4: NOW | G4: VECO | H4: SYM | I4: XE | J4: Notes
A5: AI commoditizes the product (K3 / agentic / open-source) | B5: -1 | C5: -1 | D5: 0 | E5: 0 | F5: -2 | G5: 0 | H5: 1 | I5: 0 | J5: The existential caveat. NOW worst (agents may replace seat-based software). EDA: real but distant (45nm demo vs certified 2nm sign-off). SYM benefits (AI IS its product).
A6: Dependence on the AI capex cycle (demand concentration) | B6: -1 | C6: -1 | D6: -1 | E6: -2 | F6: 0 | G6: -2 | H6: 0 | I6: -1 | J6: If hyperscaler capex breaks, who loses revenue? META loses its own ROI bet; VECO's CPO orders vanish; VST loses growth (not base) demand; EDA cushioned by backlog/subscriptions.
A7: Efficiency shocks (DeepSeek-type: less compute per unit of AI) | B7: 0 | C7: 0 | D7: -1 | E7: 1 | F7: 0 | G7: -2 | H7: 0 | I7: -1 | J7: Cheaper AI hurts compute/power/equipment sellers, HELPS AI users (META inference costs fall). VST/XE lose the scarcity premium; VECO loses the buildout.
A8: AI as the company's own tool/product (margin & pricing upside) | B8: 2 | C8: 2 | D8: 0 | E8: 2 | F8: 1 | G8: 0 | H8: 2 | I8: 0 | J8: EDA sells AI design (DSO.ai/Cerebrus) at premium prices; META's ad targeting/agents are AI products; SYM's robots improve with AI; NOW's agentic offerings could win — or cannibalize.
A9: China / export controls × AI | B9: -2 | C9: -1 | D9: 0 | E9: -1 | F9: 0 | G9: -1 | H9: 0 | I9: 0 | J9: SNPS most exposed (China revenue + EDA is an export-control weapon + K3 accelerates domestication). META banned in China anyway. VST/SYM/XE domestic.
A10: Energy constraint (AI power scarcity) | B10: 0 | C10: 0 | D10: 2 | E10: -1 | F10: 0 | G10: 0 | H10: 0 | I10: 2 | J10: The ONLY two names where AI's energy hunger is pure tailwind: VST and XE sell the scarce input. META pays for it.
A11: AI narrative already in the price (froth risk) | B11: 1 | C11: 0 | D11: 0 | E11: 0 | F11: 1 | G11: -2 | H11: -2 | I11: -1 | J11: Positive score = fear discount (SNPS, NOW cheap on AI fears). Negative = hype premium (VECO ~80% above analyst targets; SYM prices 29% CAGR).
A12: Regulation / antitrust of AI | B12: 0 | C12: 0 | D12: 0 | E12: -1 | F12: 0 | G12: 0 | H12: 0 | I12: 1 | J12: META faces AI content/privacy regimes. XE benefits from pro-nuclear energy policy. Others largely untouched.
A13: NET AI SCORE (sum) | B13: =SUM(B5:B12) -> -1 | C13: =SUM(C5:C12) -> -1 | D13: =SUM(D5:D12) -> 0 | E13: =SUM(E5:E12) -> -2 | F13: =SUM(F5:F12) -> 0 | G13: =SUM(G5:G12) -> -7 | H13: =SUM(H5:H12) -> 1 | I13: =SUM(I5:I12) -> 0
A15: Scores are structured judgments, not model outputs — argue with any cell (they're editable inputs). The stress-test sheet converts the same logic into valuation scenarios.

Sheet AI_Stress_DCF
A1: AI-STATE STRESS TEST — VALUE PER SHARE UNDER AI BUST / BASE / AI BOOM (same state probabilities for every name — the comparison axis is industry sensitivity)
A2: Engine: compact DCF (Rev35 = rev26×(1+avg g)^9; FCF = EBITDA×(1−21%) − capex; interim = avg(FCF26,FCF35)×9-yr annuity; TV = avg of exit-multiple & Gordon, PV @ 9 yrs; equity = EV + net cash). AI-state probabilities in yellow.
A4: AI-state probabilities: | B4: Bust | C4: 0.2 | D4: Base | E4: 0.5 | F4: Boom | G4: 0.3
A6: Company | B6: Price | C6: Shares mm | D6: Net cash/(debt) | E6: FY26E rev | F6: WACC | G6: Capex % rev | H6: BUST: g FY27 | I6: BUST: g FY35 | J6: BUST: Term margin | K6: BUST: Exit x | L6: BUST: Rev35 | M6: BUST: EBITDA35 | N6: BUST: FCF35 | O6: BUST: FCF26 | P6: BUST: PV interim | Q6: BUST: PV TV-exit | R6: BUST: PV TV-gordon | S6: BUST: Value/sh | T6: BASE: g FY27 | U6: BASE: g FY35 | V6: BASE: Term margin | W6: BASE: Exit x | X6: BASE: Rev35 | Y6: BASE: EBITDA35 | Z6: BASE: FCF35 | AA6: BASE: FCF26 | AB6: BASE: PV interim | AC6: BASE: PV TV-exit | AD6: BASE: PV TV-gordon | AE6: BASE: Value/sh | AF6: BOOM: g FY27 | AG6: BOOM: g FY35 | AH6: BOOM: Term margin | AI6: BOOM: Exit x | AJ6: BOOM: Rev35 | AK6: BOOM: EBITDA35 | AL6: BOOM: FCF35 | AM6: BOOM: FCF26 | AN6: BOOM: PV interim | AO6: BOOM: PV TV-exit | AP6: BOOM: PV TV-gordon | AQ6: BOOM: Value/sh | AR6: Weighted value/sh | AS6: Upside vs price | AT6: Bust downside vs price
A7: SNPS | B7: 384.28 | C7: 191.6 | D7: -8670 | E7: 9665 | F7: 0.104 | G7: 0.015 | H7: 0.04 | I7: 0.01 | J7: 0.41 | K7: 13 | L7: =$E7*(1+(H7+I7)/2)^9 -> 12070.261 | M7: =L7*J7 -> 4948.8068 | N7: =M7*0.79-L7*$G7 -> 3728.5035 | O7: =$E7*J7*0.67*0.79-$E7*$G7 -> 1952.4556 | P7: =AVERAGE(O7:N7)*(1-(1+$F7)^-9)/$F7 -> 16101.502 | Q7: =K7*M7/(1+$F7)^9 -> 26407.19 | R7: =N7*1.035/($F7-0.035)/(1+$F7)^9 -> 22956.42 | S7: =MAX(0,(P7+AVERAGE(Q7:R7)+$D7))/$C7 -> 167.60599 | T7: 0.1 | U7: 0.06 | V7: 0.47 | W7: 18 | X7: =$E7*(1+(T7+U7)/2)^9 -> 19320.38 | Y7: =X7*V7 -> 9080.5785 | Z7: =Y7*0.79-X7*$G7 -> 6883.8513 | AA7: =$E7*V7*0.67*0.79-$E7*$G7 -> 2259.3967 | AB7: =AVERAGE(AA7:Z7)*(1-(1+$F7)^-9)/$F7 -> 25914.642 | AC7: =W7*Y7/(1+$F7)^9 -> 67091.015 | AD7: =Z7*1.035/($F7-0.035)/(1+$F7)^9 -> 42383.916 | AE7: =MAX(0,(AB7+AVERAGE(AC7:AD7)+$D7))/$C7 -> 375.6895 | AF7: 0.14 | AG7: 0.09 | AH7: 0.51 | AI7: 21 | AJ7: =$E7*(1+(AF7+AG7)/2)^9 -> 25743.979 | AK7: =AJ7*AH7 -> 13129.429 | AL7: =AK7*0.79-AJ7*$G7 -> 9986.0893 | AM7: =$E7*AH7*0.67*0.79-$E7*$G7 -> 2464.0241 | AN7: =AVERAGE(AM7:AL7)*(1-(1+$F7)^-9)/$F7 -> 35287.267 | AO7: =AI7*AK7/(1+$F7)^9 -> 113173.17 | AP7: =AL7*1.035/($F7-0.035)/(1+$F7)^9 -> 61484.415 | AQ7: =MAX(0,(AN7+AVERAGE(AO7:AP7)+$D7))/$C7 -> 594.70803 | AR7: =$C$4*S7+$E$4*AE7+$G$4*AQ7 -> 399.77836 | AS7: =AR7/$B7-1 -> 0.040330893 | AT7: =S7/$B7-1 -> -0.56384411
A8: CDNS | B8: 330.1 | C8: 275.8 | D8: -1710 | E8: 6175 | F8: 0.099 | G8: 0.025 | H8: 0.05 | I8: 0.02 | J8: 0.44 | K8: 15 | L8: =$E8*(1+(H8+I8)/2)^9 -> 8415.8912 | M8: =L8*J8 -> 3702.9921 | N8: =M8*0.79-L8*$G8 -> 2714.9665 | O8: =$E8*J8*0.67*0.79-$E8*$G8 -> 1283.7331 | P8: =AVERAGE(O8:N8)*(1-(1+$F8)^-9)/$F8 -> 11560.214 | Q8: =K8*M8/(1+$F8)^9 -> 23750.066 | R8: =N8*1.035/($F8-0.035)/(1+$F8)^9 -> 18773.516 | S8: =MAX(0,(P8+AVERAGE(Q8:R8)+$D8))/$C8 -> 112.8064 | T8: 0.13 | U8: 0.08 | V8: 0.5 | W8: 20 | X8: =$E8*(1+(T8+U8)/2)^9 -> 15166.922 | Y8: =X8*V8 -> 7583.4612 | Z8: =Y8*0.79-X8*$G8 -> 5611.7613 | AA8: =$E8*V8*0.67*0.79-$E8*$G8 -> 1479.8387 | AB8: =AVERAGE(AA8:Z8)*(1-(1+$F8)^-9)/$F8 -> 20501.768 | AC8: =W8*Y8/(1+$F8)^9 -> 64851.232 | AD8: =Z8*1.035/($F8-0.035)/(1+$F8)^9 -> 38804.343 | AE8: =MAX(0,(AB8+AVERAGE(AC8:AD8)+$D8))/$C8 -> 256.0535 | AF8: 0.17 | AG8: 0.11 | AH8: 0.54 | AI8: 24 | AJ8: =$E8*(1+(AF8+AG8)/2)^9 -> 20080.782 | AK8: =AJ8*AH8 -> 10843.622 | AL8: =AK8*0.79-AJ8*$G8 -> 8064.4421 | AM8: =$E8*AH8*0.67*0.79-$E8*$G8 -> 1610.5758 | AN8: =AVERAGE(AM8:AL8)*(1-(1+$F8)^-9)/$F8 -> 27970.412 | AO8: =AI8*AK8/(1+$F8)^9 -> 111277.25 | AP8: =AL8*1.035/($F8-0.035)/(1+$F8)^9 -> 55764.199 | AQ8: =MAX(0,(AN8+AVERAGE(AO8:AP8)+$D8))/$C8 -> 398.04618 | AR8: =$C$4*S8+$E$4*AE8+$G$4*AQ8 -> 270.00189 | AS8: =AR8/$B8-1 -> -0.18206033 | AT8: =S8/$B8-1 -> -0.65826599
A9: VST | B9: 155.44 | C9: 337.2 | D9: -21600 | E9: 23272 | F9: 0.094 | G9: 0.11 | H9: 0.01 | I9: 0 | J9: 0.29 | K9: 9 | L9: =$E9*(1+(H9+I9)/2)^9 -> 24340.431 | M9: =L9*J9 -> 7058.725 | N9: =M9*0.79-L9*$G9 -> 2898.9453 | O9: =$E9*J9*0.67*0.79-$E9*$G9 -> 1012.2622 | P9: =AVERAGE(O9:N9)*(1-(1+$F9)^-9)/$F9 -> 11536.059 | Q9: =K9*M9/(1+$F9)^9 -> 28301.723 | R9: =N9*1.035/($F9-0.035)/(1+$F9)^9 -> 22655.438 | S9: =MAX(0,(P9+AVERAGE(Q9:R9)+$D9))/$C9 -> 45.713639 | T9: 0.086 | U9: 0.025 | V9: 0.325 | W9: 10 | X9: =$E9*(1+(T9+U9)/2)^9 -> 37840.585 | Y9: =X9*V9 -> 12298.19 | Z9: =Y9*0.79-X9*$G9 -> 5553.1059 | AA9: =$E9*V9*0.67*0.79-$E9*$G9 -> 1443.3876 | AB9: =AVERAGE(AA9:Z9)*(1-(1+$F9)^-9)/$F9 -> 20636.072 | AC9: =W9*Y9/(1+$F9)^9 -> 54787.983 | AD9: =Z9*1.035/($F9-0.035)/(1+$F9)^9 -> 43397.868 | AE9: =MAX(0,(AB9+AVERAGE(AC9:AD9)+$D9))/$C9 -> 142.73131 | AF9: 0.12 | AG9: 0.04 | AH9: 0.34 | AI9: 11.5 | AJ9: =$E9*(1+(AF9+AG9)/2)^9 -> 46520.836 | AK9: =AJ9*AH9 -> 15817.084 | AL9: =AK9*0.79-AJ9*$G9 -> 7378.2045 | AM9: =$E9*AH9*0.67*0.79-$E9*$G9 -> 1628.1557 | AN9: =AVERAGE(AM9:AL9)*(1-(1+$F9)^-9)/$F9 -> 26564.149 | AO9: =AI9*AK9/(1+$F9)^9 -> 81034.203 | AP9: =AL9*1.035/($F9-0.035)/(1+$F9)^9 -> 57661.128 | AQ9: =MAX(0,(AN9+AVERAGE(AO9:AP9)+$D9))/$C9 -> 220.37905 | AR9: =$C$4*S9+$E$4*AE9+$G$4*AQ9 -> 146.6221 | AS9: =AR9/$B9-1 -> -0.056728662 | AT9: =S9/$B9-1 -> -0.70590814
A10: META | B10: 656.73 | C10: 2510 | D10: 35000 | E10: 245000 | F10: 0.102 | G10: 0.2 | H10: 0.06 | I10: 0.03 | J10: 0.48 | K10: 10 | L10: =$E10*(1+(H10+I10)/2)^9 -> 364093.31 | M10: =L10*J10 -> 174764.79 | N10: =M10*0.79-L10*$G10 -> 65245.521 | O10: =$E10*J10*0.67*0.79-$E10*$G10 -> 13245.68 | P10: =AVERAGE(O10:N10)*(1-(1+$F10)^-9)/$F10 -> 224230.7 | Q10: =K10*M10/(1+$F10)^9 -> 729154.54 | R10: =N10*1.035/($F10-0.035)/(1+$F10)^9 -> 420515.4 | S10: =MAX(0,(P10+AVERAGE(Q10:R10)+$D10))/$C10 -> 332.29708 | T10: 0.14 | U10: 0.07 | V10: 0.52 | W10: 14 | X10: =$E10*(1+(T10+U10)/2)^9 -> 601764.53 | Y10: =X10*V10 -> 312917.56 | Z10: =Y10*0.79-X10*$G10 -> 126851.96 | AA10: =$E10*V10*0.67*0.79-$E10*$G10 -> 18432.82 | AB10: =AVERAGE(AA10:Z10)*(1-(1+$F10)^-9)/$F10 -> 415044.08 | AC10: =W10*Y10/(1+$F10)^9 -> 1827778.7 | AD10: =Z10*1.035/($F10-0.035)/(1+$F10)^9 -> 817576.48 | AE10: =MAX(0,(AB10+AVERAGE(AC10:AD10)+$D10))/$C10 -> 706.26362 | AF10: 0.18 | AG10: 0.09 | AH10: 0.55 | AI10: 16 | AJ10: =$E10*(1+(AF10+AG10)/2)^9 -> 765823.76 | AK10: =AJ10*AH10 -> 421203.07 | AL10: =AK10*0.79-AJ10*$G10 -> 179585.67 | AM10: =$E10*AH10*0.67*0.79-$E10*$G10 -> 22323.175 | AN10: =AVERAGE(AM10:AL10)*(1-(1+$F10)^-9)/$F10 -> 576805.56 | AO10: =AI10*AK10/(1+$F10)^9 -> 2811753 | AP10: =AL10*1.035/($F10-0.035)/(1+$F10)^9 -> 1157451.7 | AQ10: =MAX(0,(AN10+AVERAGE(AO10:AP10)+$D10))/$C10 -> 1034.4255 | AR10: =$C$4*S10+$E$4*AE10+$G$4*AQ10 -> 729.91886 | AS10: =AR10/$B10-1 -> 0.11144437 | AT10: =S10/$B10-1 -> -0.49401264
A11: NOW | B11: 101.6 | C11: 1050 | D11: 5000 | E11: 15800 | F11: 0.098 | G11: 0.02 | H11: 0.04 | I11: -0.03 | J11: 0.3 | K11: 9 | L11: =$E11*(1+(H11+I11)/2)^9 -> 16525.387 | M11: =L11*J11 -> 4957.6161 | N11: =M11*0.79-L11*$G11 -> 3586.009 | O11: =$E11*J11*0.67*0.79-$E11*$G11 -> 2192.882 | P11: =AVERAGE(O11:N11)*(1-(1+$F11)^-9)/$F11 -> 16773.499 | Q11: =K11*M11/(1+$F11)^9 -> 19235.095 | R11: =N11*1.035/($F11-0.035)/(1+$F11)^9 -> 25397.45 | S11: =MAX(0,(P11+AVERAGE(Q11:R11)+$D11))/$C11 -> 41.990259 | T11: 0.15 | U11: 0.08 | V11: 0.4 | W11: 20 | X11: =$E11*(1+(T11+U11)/2)^9 -> 42085.345 | Y11: =X11*V11 -> 16834.138 | Z11: =Y11*0.79-X11*$G11 -> 12457.262 | AA11: =$E11*V11*0.67*0.79-$E11*$G11 -> 3029.176 | AB11: =AVERAGE(AA11:Z11)*(1-(1+$F11)^-9)/$F11 -> 44950.105 | AC11: =W11*Y11/(1+$F11)^9 -> 145144.24 | AD11: =Z11*1.035/($F11-0.035)/(1+$F11)^9 -> 88226.966 | AE11: =MAX(0,(AB11+AVERAGE(AC11:AD11)+$D11))/$C11 -> 158.70068 | AF11: 0.21 | AG11: 0.12 | AH11: 0.46 | AI11: 25 | AJ11: =$E11*(1+(AF11+AG11)/2)^9 -> 62458.337 | AK11: =AJ11*AH11 -> 28730.835 | AL11: =AK11*0.79-AJ11*$G11 -> 21448.193 | AM11: =$E11*AH11*0.67*0.79-$E11*$G11 -> 3530.9524 | AN11: =AVERAGE(AM11:AL11)*(1-(1+$F11)^-9)/$F11 -> 72503.128 | AO11: =AI11*AK11/(1+$F11)^9 -> 309647.23 | AP11: =AL11*1.035/($F11-0.035)/(1+$F11)^9 -> 151904.08 | AQ11: =MAX(0,(AN11+AVERAGE(AO11:AP11)+$D11))/$C11 -> 293.59884 | AR11: =$C$4*S11+$E$4*AE11+$G$4*AQ11 -> 175.82804 | AS11: =AR11/$B11-1 -> 0.73059097 | AT11: =S11/$B11-1 -> -0.58671005
A12: VECO | B12: 55.13 | C12: 61.03 | D12: 80 | E12: 770 | F12: 0.121 | G12: 0.02 | H12: -0.05 | I12: 0 | J12: 0.08 | K12: 7 | L12: =$E12*(1+(H12+I12)/2)^9 -> 613.10134 | M12: =L12*J12 -> 49.048107 | N12: =M12*0.79-L12*$G12 -> 26.485978 | O12: =$E12*J12*0.67*0.79-$E12*$G12 -> 17.20488 | P12: =AVERAGE(O12:N12)*(1-(1+$F12)^-9)/$F12 -> 115.95677 | Q12: =K12*M12/(1+$F12)^9 -> 122.82019 | R12: =N12*1.035/($F12-0.035)/(1+$F12)^9 -> 114.02692 | S12: =MAX(0,(P12+AVERAGE(Q12:R12)+$D12))/$C12 -> 5.1512425 | T12: 0.12 | U12: 0.04 | V12: 0.18 | W12: 12 | X12: =$E12*(1+(T12+U12)/2)^9 -> 1539.2336 | Y12: =X12*V12 -> 277.06204 | Z12: =Y12*0.79-X12*$G12 -> 188.09434 | AA12: =$E12*V12*0.67*0.79-$E12*$G12 -> 57.96098 | AB12: =AVERAGE(AA12:Z12)*(1-(1+$F12)^-9)/$F12 -> 653.03778 | AC12: =W12*Y12/(1+$F12)^9 -> 1189.3448 | AD12: =Z12*1.035/($F12-0.035)/(1+$F12)^9 -> 809.78013 | AE12: =MAX(0,(AB12+AVERAGE(AC12:AD12)+$D12))/$C12 -> 28.38932 | AF12: 0.2 | AG12: 0.08 | AH12: 0.23 | AI12: 16 | AJ12: =$E12*(1+(AF12+AG12)/2)^9 -> 2504.0004 | AK12: =AJ12*AH12 -> 575.92008 | AL12: =AK12*0.79-AJ12*$G12 -> 404.89686 | AM12: =$E12*AH12*0.67*0.79-$E12*$G12 -> 78.33903 | AN12: =AVERAGE(AM12:AL12)*(1-(1+$F12)^-9)/$F12 -> 1282.5217 | AO12: =AI12*AK12/(1+$F12)^9 -> 3296.3377 | AP12: =AL12*1.035/($F12-0.035)/(1+$F12)^9 -> 1743.1541 | AQ12: =MAX(0,(AN12+AVERAGE(AO12:AP12)+$D12))/$C12 -> 63.612446 | AR12: =$C$4*S12+$E$4*AE12+$G$4*AQ12 -> 34.308643 | AS12: =AR12/$B12-1 -> -0.37767744 | AT12: =S12/$B12-1 -> -0.9065619
A13: SYM | B13: 42.51 | C13: 630 | D13: 2086 | E13: 2771 | F13: 0.134 | G13: 0.025 | H13: 0.08 | I13: 0.02 | J13: 0.14 | K13: 8 | L13: =$E13*(1+(H13+I13)/2)^9 -> 4298.7305 | M13: =L13*J13 -> 601.82227 | N13: =M13*0.79-L13*$G13 -> 367.97133 | O13: =$E13*J13*0.67*0.79-$E13*$G13 -> 136.06164 | P13: =AVERAGE(O13:N13)*(1-(1+$F13)^-9)/$F13 -> 1274.2538 | Q13: =K13*M13/(1+$F13)^9 -> 1552.5327 | R13: =N13*1.035/($F13-0.035)/(1+$F13)^9 -> 1240.5139 | S13: =MAX(0,(P13+AVERAGE(Q13:R13)+$D13))/$C13 -> 7.5504398 | T13: 0.2 | U13: 0.05 | V13: 0.21 | W13: 12 | X13: =$E13*(1+(T13+U13)/2)^9 -> 7998.5125 | Y13: =X13*V13 -> 1679.6876 | Z13: =Y13*0.79-X13*$G13 -> 1126.9904 | AA13: =$E13*V13*0.67*0.79-$E13*$G13 -> 238.72996 | AB13: =AVERAGE(AA13:Z13)*(1-(1+$F13)^-9)/$F13 -> 3452.6994 | AC13: =W13*Y13/(1+$F13)^9 -> 6499.6845 | AD13: =Z13*1.035/($F13-0.035)/(1+$F13)^9 -> 3799.3376 | AE13: =MAX(0,(AB13+AVERAGE(AC13:AD13)+$D13))/$C13 -> 16.965413 | AF13: 0.28 | AG13: 0.08 | AH13: 0.25 | AI13: 15 | AJ13: =$E13*(1+(AF13+AG13)/2)^9 -> 12290.643 | AK13: =AJ13*AH13 -> 3072.6607 | AL13: =AK13*0.79-AJ13*$G13 -> 2120.1359 | AM13: =$E13*AH13*0.67*0.79-$E13*$G13 -> 297.39758 | AN13: =AVERAGE(AM13:AL13)*(1-(1+$F13)^-9)/$F13 -> 6111.8047 | AO13: =AI13*AK13/(1+$F13)^9 -> 14862.38 | AP13: =AL13*1.035/($F13-0.035)/(1+$F13)^9 -> 7147.4538 | AQ13: =MAX(0,(AN13+AVERAGE(AO13:AP13)+$D13))/$C13 -> 30.480511 | AR13: =$C$4*S13+$E$4*AE13+$G$4*AQ13 -> 19.136948 | AS13: =AR13/$B13-1 -> -0.5498248 | AT13: =S13/$B13-1 -> -0.82238439
A14: XE | B14: 14.02 | C14: 406 | D14: 1700 | E14: 180 | F14: 0.14 | G14: 0.08 | H14: 0.2 | I14: 0.05 | J14: 0.05 | K14: 10 | L14: =$E14*(1+(H14+I14)/2)^9 -> 519.57136 | M14: =L14*J14 -> 25.978568 | N14: =M14*0.79-L14*$G14 -> -21.04264 | O14: =$E14*J14*0.67*0.79-$E14*$G14 -> -9.6363 | P14: =AVERAGE(O14:N14)*(1-(1+$F14)^-9)/$F14 -> -75.874723 | Q14: =K14*M14/(1+$F14)^9 -> 79.886161 | R14: =N14*1.035/($F14-0.035)/(1+$F14)^9 -> -63.783393 | S14: =MAX(0,(P14+AVERAGE(Q14:R14)+$D14))/$C14 -> 4.0201396 | T14: 0.55 | U14: 0.25 | V14: 0.135 | W14: 15 | X14: =$E14*(1+(T14+U14)/2)^9 -> 3718.9884 | Y14: =X14*V14 -> 502.06344 | Z14: =Y14*0.79-X14*$G14 -> 99.111041 | AA14: =$E14*V14*0.67*0.79-$E14*$G14 -> -1.53801 | AB14: =AVERAGE(AA14:Z14)*(1-(1+$F14)^-9)/$F14 -> 241.31625 | AC14: =W14*Y14/(1+$F14)^9 -> 2315.8274 | AD14: =Z14*1.035/($F14-0.035)/(1+$F14)^9 -> 300.42041 | AE14: =MAX(0,(AB14+AVERAGE(AC14:AD14)+$D14))/$C14 -> 8.0035472 | AF14: 0.7 | AG14: 0.33 | AH14: 0.2 | AI14: 18 | AJ14: =$E14*(1+(AF14+AG14)/2)^9 -> 7568.0885 | AK14: =AJ14*AH14 -> 1513.6177 | AL14: =AK14*0.79-AJ14*$G14 -> 590.3109 | AM14: =$E14*AH14*0.67*0.79-$E14*$G14 -> 4.6548 | AN14: =AVERAGE(AM14:AL14)*(1-(1+$F14)^-9)/$F14 -> 1471.4608 | AO14: =AI14*AK14/(1+$F14)^9 -> 8378.0903 | AP14: =AL14*1.035/($F14-0.035)/(1+$F14)^9 -> 1789.3207 | AQ14: =MAX(0,(AN14+AVERAGE(AO14:AP14)+$D14))/$C14 -> 20.332922 | AR14: =$C$4*S14+$E$4*AE14+$G$4*AQ14 -> 10.905678 | AS14: =AR14/$B14-1 -> -0.22213423 | AT14: =S14/$B14-1 -> -0.71325681
A16: VST net debt includes $2.0B preferred. META capex held at 20% of terminal revenue in all states (real co. would cut in a bust — conservative). XE compact engine approximates its fixed-cost model. Value floored at 0.
