Workbook

Sheet Cover
A1: CADENCE DESIGN SYSTEMS (NASDAQ: CDNS) — DCF VALUATION & 3-STATEMENT OPERATING MODEL
A2: Prepared July 20, 2026 · $ millions except per-share · Calendar fiscal year
A4: CONTENTS
A5: Assumptions | C5: Scenario switch & levers (edit yellow cells)
A6: Historicals | C6: FY2022–FY2025 actuals, Q1-2026, FY2026E guidance build
A7: Model_3S | C7: Linked IS/BS/CF FY2026E–FY2035E: working capital, capex, debt schedule, buybacks, Hexagon acquisition
A8: WACC | C8: CAPM with current market data (beta 1.13, 10Y 4.55%)
A9: DCF | C9: Unlevered FCF, Gordon + exit-multiple terminal values, sensitivities
A10: Comps | C10: EDA / design-software peers (SNPS, ADSK, MSFT, ORCL)
A11: Precedents | C11: EDA & engineering-software M&A (Synopsys–Ansys, Siemens–Altair, Renesas–Altium…)
A12: LBO | C12: Leveraged buyout at 6.5x; max price at 15/20/25/30% IRR
A13: Monte_Carlo | C13: 500 live trials + scenario probability weights
A14: Football_Field | C14: Valuation summary chart vs. current price
A16: LEGEND
A17: Blue font / yellow fill | C17: Hardcoded input or scenario lever — edit these
A18: Black font | C18: Formula — do not overwrite
A19: Green font | C19: Link to another sheet
A20: 'e' | C20: Estimated figure — see notes
A22: KEY MODELING NOTES
A23: 1. | C23: FY2026E revenue $6,175mm = guidance midpoint ($6,125–6,225mm, ~17% growth incl. ~$160mm Hexagon contribution). Non-GAAP EPS guide $7.85–7.95.
A24: 2. | C24: The Hexagon acquisition is modeled as a $3.1B(e) FY2026 cash outflow landing in goodwill, funded partly by ~$0.6B(e) new debt — both editable inputs.
A25: 3. | C25: The model is GAAP-normalized: EBITDA excludes SBC (~8.5% of revenue, shown separately); consensus non-GAAP EPS adds SBC/amortization back, so it runs higher than model EPS.
A26: 4. | C26: Share price ambiguity at build time: stockanalysis.com stats imply ~$330 (mkt cap $91.05B / 275.8mm shares) while a same-week Zacks note quotes $373. $330.10 used — edit Assumptions!B49.
A28: KEY SOURCES
A29: Q1-2026 results & FY26 guidance (8-K, 4/27/2026) | C29: sec.gov/Archives/edgar/data/0000813672/000081367226000044/cfocommentary04272026ex9902.htm; tradingview 10-Q summary
A30: FY2025 results | C30: investor.cadence.com FY2025 press release: revenue $5,296.8mm, op income $1,649.8mm, net income $1,108.9mm
A31: FY2024 10-K | C31: sec.gov CDNS 10-K: debt $2.5B ('27 $0.5B / '29 $1B / '34 $1B); TA $8,974mm
A32: Market data | C32: stockanalysis.com/stocks/cdns/statistics (mkt cap $91.05B, 275.8mm shares, beta 1.13, cash $1.55B, debt $3.08B); macrotrends 52-wk $262.75–$416.69; 32-analyst avg target $387
A33: 10Y UST 4.55% (7/17/2026) | C33: tradingeconomics.com / FRED DGS10
A35: DISCLAIMER | C35: Educational model, not investment advice. Estimated cells flagged on-sheet; verify against Cadence filings.

Sheet Assumptions
A1: ASSUMPTIONS & SCENARIO LEVERS — CADENCE
A2: Edit yellow cells. Switch drives Model_3S, DCF, LBO, Monte Carlo.
A4: SCENARIO SWITCH (1 = Base, 2 = Bull, 3 = Bear) | B4: 1 | C4: =CHOOSE($B$4,"BASE — durable low-teens EDA growth","BULL — AI/agentic design supercycle","BEAR — semis downcycle + China restrictions") -> BASE — durable low-teens EDA growth
A6: Scenario probability weights
B7: Base | C7: Bull | D7: Bear | E7: Total
A8: Probability | B8: 0.5 | C8: 0.3 | D8: 0.2 | E8: =SUM(B8:D8) -> 1
A10: Revenue growth — decays linearly FY2027 → FY2035
B11: Base | C11: Bull | D11: Bear | E11: Selected
A12: FY2027 revenue growth | B12: 0.13 | C12: 0.17 | D12: 0.07 | E12: =CHOOSE($B$4,B12,C12,D12) -> 0.13
A13: FY2035 revenue growth (terminal-year) | B13: 0.08 | C13: 0.11 | D13: 0.03 | E13: =CHOOSE($B$4,B13,C13,D13) -> 0.08
A14: Base ≈ EDA secular growth (design activity, AI compute, backlog $8.0B). Bull +4pp; Bear −6pp. FY2026E = guidance $6,175mm.
A15: Operating drivers — FY2026 start ramps linearly to FY2035 target
A16: Driver | B16: FY26 start | C16: Base target | D16: Bull target | E16: Bear target | F16: Selected
A17: Gross margin (excl. D&A) | B17: 0.88 | C17: 0.89 | D17: 0.9 | E17: 0.87 | F17: =CHOOSE($B$4,C17,D17,E17) -> 0.89
A18: Cash opex — R&D + SG&A (% revenue) | B18: 0.425 | C18: 0.39 | D18: 0.355 | E18: 0.45 | F18: =CHOOSE($B$4,C18,D18,E18) -> 0.39
A19: Stock-based compensation (% revenue) | B19: 0.085 | C19: 0.07 | D19: 0.07 | E19: 0.08 | F19: =CHOOSE($B$4,C19,D19,E19) -> 0.07
A20: D&A incl. acquisition amortization (% revenue) | B20: 0.03 | C20: 0.03 | D20: 0.03 | E20: 0.03 | F20: =CHOOSE($B$4,C20,D20,E20) -> 0.03
A21: Capex incl. emulation hardware (% revenue) | B21: 0.03 | C21: 0.025 | D21: 0.03 | E21: 0.02 | F21: =CHOOSE($B$4,C21,D21,E21) -> 0.025
A22: Cash tax rate | B22: 0.2 | C22: 0.22 | D22: 0.22 | E22: 0.2 | F22: =CHOOSE($B$4,C22,D22,E22) -> 0.22
A23: Other current assets (% revenue) | B23: 0.11 | C23: 0.11 | D23: 0.11 | E23: 0.11 | F23: =CHOOSE($B$4,C23,D23,E23) -> 0.11
A24: Deferred revenue (% revenue) | B24: 0.155 | C24: 0.16 | D24: 0.16 | E24: 0.15 | F24: =CHOOSE($B$4,C24,D24,E24) -> 0.16
A25: Implied Adj. EBITDA margin (pre-SBC): FY26 45.5% (ties to ~43.5% non-GAAP op margin guide + D&A) → Base 50% / Bull 54.5% / Bear 42% by FY2035.
A26: Working capital (held constant)
A27: Days sales outstanding (DSO) | B27: 60
A28: Days inventory — emulation hardware (DIO, on COGS) | B28: 150
A29: Days payable (DPO, on COGS + cash opex) | B29: 45
A33: Capital & shareholder returns
A34: Interest earned on cash | B34: 0.04
A35: Revolver interest rate | B35: 0.06
A36: Minimum cash balance ($mm) | B36: 500
A37: Diluted shares outstanding (mm) | B37: 275.8
A38: Marginal tax rate (valuation) | B38: 0.22
A39: Average rate on debt | B39: 0.048
A40: Share buybacks per year ($mm) | B40: 1300
A41: Acquisitions FY2026 — Hexagon, net cash (e, $mm) | B41: 3100 | C41: Deal size estimated from disclosed $160mm revenue contribution and $0.28 EPS dilution incl. financing costs; edit when terms are confirmed
A42: New debt issued FY2026 (Hexagon financing, e, $mm) | B42: 600
A46: Terminal value & market inputs
A47: Terminal (perpetuity) growth rate g | B47: 0.035
A48: Exit EV / Adj. EBITDA multiple (FY2035) | B48: 20
A49: Current share price (7/17/2026, see Cover note 4) | B49: 330.1

Sheet Historicals
A1: HISTORICAL FINANCIALS ($mm)
B4: FY2022A | C4: FY2023A | D4: FY2024A | E4: FY2025A | G4: Q1-26A | H4: FY2026E
A5: Revenue | B5: 3562 | C5: 4090 | D5: 4641 | E5: 5297 | G5: 1474 | H5: 6175 | I5: FY2026E = guidance midpoint $6,125–6,225mm incl. ~$160mm Hexagon
A6: Operating income (GAAP) | D6: 1383 | E6: 1650
A7: Net income (GAAP) | D7: 1055 | E7: 1109
A8: % revenue growth y/y | C8: =C5/B5-1 -> 0.14823133 | D8: =D5/C5-1 -> 0.13471883 | E8: =E5/D5-1 -> 0.14134885 | H8: =H5/E5-1 -> 0.1657542
A10: Q1-26: revenue / GAAP EPS / non-GAAP EPS | B10: $1,474mm · $1.23 · $1.96 (+19% y/y)
A11: Backlog (Q1-26, record) | B11: $8.0B
A12: FY2026 non-GAAP EPS guidance | B12: $7.85 – $7.95 (incl. ~$0.28 Hexagon dilution)
A13: Debt (7/2026) | B13: $3.08B — '27 notes $0.5B, '29 $1.0B, '34 $1.0B + Hexagon financing (e)
A14: Cash (7/2026) | B14: $1.55B (stockanalysis.com)
A15: Non-GAAP operating margin FY2024 | B15: 42.5%
A17: Opening balance sheet, 12/31/2025 (partly estimated):
A18: Cash + short-term investments e | B18: 2800
A19: Receivables e | B19: 1650
A20: Inventory e | B20: 300
A21: Other current assets e | B21: 700
A22: PP&E net e | B22: 480
A23: Goodwill + intangibles + other LT e | B23: 4970
A24: AP + accrued e | B24: 900
A25: Deferred revenue e | B25: 950
A26: Total debt | B26: 2480
A27: Other LT liabilities e | B27: 1070
A29: FY2024 10-K anchors: TA $8,974mm, TL $4,301mm, equity $4,674mm, debt $2,476mm carrying. FY2025 items estimated from those + FY25 cash generation. Sources on Cover.

Sheet Model_3S
A1: 3-STATEMENT OPERATING MODEL — FY2026E–FY2035E ($mm)
A2: =CONCATENATE("Active scenario: ",CHOOSE(Assumptions!$B$4,"BASE","BULL","BEAR")) -> Active scenario: BASE
B4: FY2025A | C4: FY2026E | D4: FY2027E | E4: FY2028E | F4: FY2029E | G4: FY2030E | H4: FY2031E | I4: FY2032E | J4: FY2033E | K4: FY2034E | L4: FY2035E
A6: DRIVERS (linked to Assumptions; linear ramps FY26 → FY35)
A7: Revenue growth % | C7: =C18/B18-1 -> 0.1657542 | D7: =Assumptions!$E$12+(Assumptions!$E$13-Assumptions!$E$12)*0/8 -> 0.13 | E7: =Assumptions!$E$12+(Assumptions!$E$13-Assumptions!$E$12)*1/8 -> 0.12375 | F7: =Assumptions!$E$12+(Assumptions!$E$13-Assumptions!$E$12)*2/8 -> 0.1175 | G7: =Assumptions!$E$12+(Assumptions!$E$13-Assumptions!$E$12)*3/8 -> 0.11125 | H7: =Assumptions!$E$12+(Assumptions!$E$13-Assumptions!$E$12)*4/8 -> 0.105 | I7: =Assumptions!$E$12+(Assumptions!$E$13-Assumptions!$E$12)*5/8 -> 0.09875 | J7: =Assumptions!$E$12+(Assumptions!$E$13-Assumptions!$E$12)*6/8 -> 0.0925 | K7: =Assumptions!$E$12+(Assumptions!$E$13-Assumptions!$E$12)*7/8 -> 0.08625 | L7: =Assumptions!$E$12+(Assumptions!$E$13-Assumptions!$E$12)*8/8 -> 0.08
A8: Gross margin % | C8: =Assumptions!$B$17 -> 0.88 | D8: =Assumptions!$B$17+(Assumptions!$F$17-Assumptions!$B$17)*1/9 -> 0.88111111 | E8: =Assumptions!$B$17+(Assumptions!$F$17-Assumptions!$B$17)*2/9 -> 0.88222222 | F8: =Assumptions!$B$17+(Assumptions!$F$17-Assumptions!$B$17)*3/9 -> 0.88333333 | G8: =Assumptions!$B$17+(Assumptions!$F$17-Assumptions!$B$17)*4/9 -> 0.88444444 | H8: =Assumptions!$B$17+(Assumptions!$F$17-Assumptions!$B$17)*5/9 -> 0.88555556 | I8: =Assumptions!$B$17+(Assumptions!$F$17-Assumptions!$B$17)*6/9 -> 0.88666667 | J8: =Assumptions!$B$17+(Assumptions!$F$17-Assumptions!$B$17)*7/9 -> 0.88777778 | K8: =Assumptions!$B$17+(Assumptions!$F$17-Assumptions!$B$17)*8/9 -> 0.88888889 | L8: =Assumptions!$B$17+(Assumptions!$F$17-Assumptions!$B$17)*9/9 -> 0.89
A9: Cash opex % rev | C9: =Assumptions!$B$18 -> 0.425 | D9: =Assumptions!$B$18+(Assumptions!$F$18-Assumptions!$B$18)*1/9 -> 0.42111111 | E9: =Assumptions!$B$18+(Assumptions!$F$18-Assumptions!$B$18)*2/9 -> 0.41722222 | F9: =Assumptions!$B$18+(Assumptions!$F$18-Assumptions!$B$18)*3/9 -> 0.41333333 | G9: =Assumptions!$B$18+(Assumptions!$F$18-Assumptions!$B$18)*4/9 -> 0.40944444 | H9: =Assumptions!$B$18+(Assumptions!$F$18-Assumptions!$B$18)*5/9 -> 0.40555556 | I9: =Assumptions!$B$18+(Assumptions!$F$18-Assumptions!$B$18)*6/9 -> 0.40166667 | J9: =Assumptions!$B$18+(Assumptions!$F$18-Assumptions!$B$18)*7/9 -> 0.39777778 | K9: =Assumptions!$B$18+(Assumptions!$F$18-Assumptions!$B$18)*8/9 -> 0.39388889 | L9: =Assumptions!$B$18+(Assumptions!$F$18-Assumptions!$B$18)*9/9 -> 0.39
A10: SBC % rev | C10: =Assumptions!$B$19 -> 0.085 | D10: =Assumptions!$B$19+(Assumptions!$F$19-Assumptions!$B$19)*1/9 -> 0.083333333 | E10: =Assumptions!$B$19+(Assumptions!$F$19-Assumptions!$B$19)*2/9 -> 0.081666667 | F10: =Assumptions!$B$19+(Assumptions!$F$19-Assumptions!$B$19)*3/9 -> 0.08 | G10: =Assumptions!$B$19+(Assumptions!$F$19-Assumptions!$B$19)*4/9 -> 0.078333333 | H10: =Assumptions!$B$19+(Assumptions!$F$19-Assumptions!$B$19)*5/9 -> 0.076666667 | I10: =Assumptions!$B$19+(Assumptions!$F$19-Assumptions!$B$19)*6/9 -> 0.075 | J10: =Assumptions!$B$19+(Assumptions!$F$19-Assumptions!$B$19)*7/9 -> 0.073333333 | K10: =Assumptions!$B$19+(Assumptions!$F$19-Assumptions!$B$19)*8/9 -> 0.071666667 | L10: =Assumptions!$B$19+(Assumptions!$F$19-Assumptions!$B$19)*9/9 -> 0.07
A11: D&A % rev | C11: =Assumptions!$B$20 -> 0.03 | D11: =Assumptions!$B$20+(Assumptions!$F$20-Assumptions!$B$20)*1/9 -> 0.03 | E11: =Assumptions!$B$20+(Assumptions!$F$20-Assumptions!$B$20)*2/9 -> 0.03 | F11: =Assumptions!$B$20+(Assumptions!$F$20-Assumptions!$B$20)*3/9 -> 0.03 | G11: =Assumptions!$B$20+(Assumptions!$F$20-Assumptions!$B$20)*4/9 -> 0.03 | H11: =Assumptions!$B$20+(Assumptions!$F$20-Assumptions!$B$20)*5/9 -> 0.03 | I11: =Assumptions!$B$20+(Assumptions!$F$20-Assumptions!$B$20)*6/9 -> 0.03 | J11: =Assumptions!$B$20+(Assumptions!$F$20-Assumptions!$B$20)*7/9 -> 0.03 | K11: =Assumptions!$B$20+(Assumptions!$F$20-Assumptions!$B$20)*8/9 -> 0.03 | L11: =Assumptions!$B$20+(Assumptions!$F$20-Assumptions!$B$20)*9/9 -> 0.03
A12: Capex % rev | C12: =Assumptions!$B$21 -> 0.03 | D12: =Assumptions!$B$21+(Assumptions!$F$21-Assumptions!$B$21)*1/9 -> 0.029444444 | E12: =Assumptions!$B$21+(Assumptions!$F$21-Assumptions!$B$21)*2/9 -> 0.028888889 | F12: =Assumptions!$B$21+(Assumptions!$F$21-Assumptions!$B$21)*3/9 -> 0.028333333 | G12: =Assumptions!$B$21+(Assumptions!$F$21-Assumptions!$B$21)*4/9 -> 0.027777778 | H12: =Assumptions!$B$21+(Assumptions!$F$21-Assumptions!$B$21)*5/9 -> 0.027222222 | I12: =Assumptions!$B$21+(Assumptions!$F$21-Assumptions!$B$21)*6/9 -> 0.026666667 | J12: =Assumptions!$B$21+(Assumptions!$F$21-Assumptions!$B$21)*7/9 -> 0.026111111 | K12: =Assumptions!$B$21+(Assumptions!$F$21-Assumptions!$B$21)*8/9 -> 0.025555556 | L12: =Assumptions!$B$21+(Assumptions!$F$21-Assumptions!$B$21)*9/9 -> 0.025
A13: Cash tax rate % | C13: =Assumptions!$B$22 -> 0.2 | D13: =Assumptions!$B$22+(Assumptions!$F$22-Assumptions!$B$22)*1/9 -> 0.20222222 | E13: =Assumptions!$B$22+(Assumptions!$F$22-Assumptions!$B$22)*2/9 -> 0.20444444 | F13: =Assumptions!$B$22+(Assumptions!$F$22-Assumptions!$B$22)*3/9 -> 0.20666667 | G13: =Assumptions!$B$22+(Assumptions!$F$22-Assumptions!$B$22)*4/9 -> 0.20888889 | H13: =Assumptions!$B$22+(Assumptions!$F$22-Assumptions!$B$22)*5/9 -> 0.21111111 | I13: =Assumptions!$B$22+(Assumptions!$F$22-Assumptions!$B$22)*6/9 -> 0.21333333 | J13: =Assumptions!$B$22+(Assumptions!$F$22-Assumptions!$B$22)*7/9 -> 0.21555556 | K13: =Assumptions!$B$22+(Assumptions!$F$22-Assumptions!$B$22)*8/9 -> 0.21777778 | L13: =Assumptions!$B$22+(Assumptions!$F$22-Assumptions!$B$22)*9/9 -> 0.22
A14: Other current assets % rev | C14: =Assumptions!$B$23 -> 0.11 | D14: =Assumptions!$B$23+(Assumptions!$F$23-Assumptions!$B$23)*1/9 -> 0.11 | E14: =Assumptions!$B$23+(Assumptions!$F$23-Assumptions!$B$23)*2/9 -> 0.11 | F14: =Assumptions!$B$23+(Assumptions!$F$23-Assumptions!$B$23)*3/9 -> 0.11 | G14: =Assumptions!$B$23+(Assumptions!$F$23-Assumptions!$B$23)*4/9 -> 0.11 | H14: =Assumptions!$B$23+(Assumptions!$F$23-Assumptions!$B$23)*5/9 -> 0.11 | I14: =Assumptions!$B$23+(Assumptions!$F$23-Assumptions!$B$23)*6/9 -> 0.11 | J14: =Assumptions!$B$23+(Assumptions!$F$23-Assumptions!$B$23)*7/9 -> 0.11 | K14: =Assumptions!$B$23+(Assumptions!$F$23-Assumptions!$B$23)*8/9 -> 0.11 | L14: =Assumptions!$B$23+(Assumptions!$F$23-Assumptions!$B$23)*9/9 -> 0.11
A15: Deferred revenue % rev | C15: =Assumptions!$B$24 -> 0.155 | D15: =Assumptions!$B$24+(Assumptions!$F$24-Assumptions!$B$24)*1/9 -> 0.15555556 | E15: =Assumptions!$B$24+(Assumptions!$F$24-Assumptions!$B$24)*2/9 -> 0.15611111 | F15: =Assumptions!$B$24+(Assumptions!$F$24-Assumptions!$B$24)*3/9 -> 0.15666667 | G15: =Assumptions!$B$24+(Assumptions!$F$24-Assumptions!$B$24)*4/9 -> 0.15722222 | H15: =Assumptions!$B$24+(Assumptions!$F$24-Assumptions!$B$24)*5/9 -> 0.15777778 | I15: =Assumptions!$B$24+(Assumptions!$F$24-Assumptions!$B$24)*6/9 -> 0.15833333 | J15: =Assumptions!$B$24+(Assumptions!$F$24-Assumptions!$B$24)*7/9 -> 0.15888889 | K15: =Assumptions!$B$24+(Assumptions!$F$24-Assumptions!$B$24)*8/9 -> 0.15944444 | L15: =Assumptions!$B$24+(Assumptions!$F$24-Assumptions!$B$24)*9/9 -> 0.16
A17: INCOME STATEMENT
A18: Revenue | B18: =Historicals!E5 -> 5297 | C18: =Historicals!H5 -> 6175 | D18: =C18*(1+D7) -> 6977.75 | E18: =D18*(1+E7) -> 7841.2466 | F18: =E18*(1+F7) -> 8762.593 | G18: =F18*(1+G7) -> 9737.4315 | H18: =G18*(1+H7) -> 10759.862 | I18: =H18*(1+I7) -> 11822.398 | J18: =I18*(1+J7) -> 12915.97 | K18: =J18*(1+K7) -> 14029.972 | L18: =K18*(1+L7) -> 15152.37
A19: Cost of revenue (excl. D&A) | C19: =-C18*(1-C8) -> -741 | D19: =-D18*(1-D8) -> -829.57694 | E19: =-E18*(1-E8) -> -923.5246 | F19: =-F18*(1-F8) -> -1022.3025 | G19: =-G18*(1-G8) -> -1125.2143 | H19: =-H18*(1-H8) -> -1231.4064 | I19: =-I18*(1-I8) -> -1339.8718 | J19: =-J18*(1-J8) -> -1449.4589 | ... L19: =-L18*(1-L8) -> -1666.7607
A20: Gross profit | C20: =C18+C19 -> 5434 | D20: =D18+D19 -> 6148.1731 | E20: =E18+E19 -> 6917.722 | F20: =F18+F19 -> 7740.2905 | G20: =G18+G19 -> 8612.2172 | H20: =H18+H19 -> 9528.4554 | I20: =I18+I19 -> 10482.526 | J20: =J18+J19 -> 11466.511 | ... L20: =L18+L19 -> 13485.609
A21: Cash opex (R&D + SG&A) | C21: =-C18*C9 -> -2624.375 | D21: =-D18*D9 -> -2938.4081 | E21: =-E18*E9 -> -3271.5423 | F21: =-F18*F9 -> -3621.8718 | G21: =-G18*G9 -> -3986.9372 | H21: =-H18*H9 -> -4363.7217 | I21: =-I18*I9 -> -4748.6633 | J21: =-J18*J9 -> -5137.6858 | ... L21: =-L18*L9 -> -5909.4244
A22: Adjusted EBITDA (pre-SBC) | C22: =C20+C21 -> 2809.625 | D22: =D20+D21 -> 3209.765 | E22: =E20+E21 -> 3646.1797 | F22: =F20+F21 -> 4118.4187 | G22: =G20+G21 -> 4625.28 | H22: =H20+H21 -> 5164.7337 | I22: =I20+I21 -> 5733.8631 | J22: =J20+J21 -> 6328.8253 | ... L22: =L20+L21 -> 7576.1851
A23: Stock-based compensation | C23: =-C18*C10 -> -524.875 | D23: =-D18*D10 -> -581.47917 | E23: =-E18*E10 -> -640.36847 | F23: =-F18*F10 -> -701.00744 | G23: =-G18*G10 -> -762.76547 | H23: =-H18*H10 -> -824.92274 | I23: =-I18*I10 -> -886.67986 | J23: =-J18*J10 -> -947.17113 | ... L23: =-L18*L10 -> -1060.6659
A24: D&A incl. acquisition amortization | C24: =-C18*C11 -> -185.25 | D24: =-D18*D11 -> -209.3325 | E24: =-E18*E11 -> -235.2374 | F24: =-F18*F11 -> -262.87779 | G24: =-G18*G11 -> -292.12295 | H24: =-H18*H11 -> -322.79585 | I24: =-I18*I11 -> -354.67195 | J24: =-J18*J11 -> -387.4791 | ... L24: =-L18*L11 -> -454.57111
A25: EBIT | C25: =C22+C23+C24 -> 2099.5 | D25: =D22+D23+D24 -> 2418.9533 | E25: =E22+E23+E24 -> 2770.5738 | F25: =F22+F23+F24 -> 3154.5335 | G25: =G22+G23+G24 -> 3570.3916 | H25: =H22+H23+H24 -> 4017.0151 | I25: =I22+I23+I24 -> 4492.5113 | J25: =J22+J23+J24 -> 4994.1751 | ... L25: =L22+L23+L24 -> 6060.9481
A26: Interest income (on beginning cash) | C26: =B70*Assumptions!$B$34 -> 112 | D26: =C70*Assumptions!$B$34 -> 54.881528 | E26: =D70*Assumptions!$B$34 -> 97.371906 | F26: =E70*Assumptions!$B$34 -> 154.52671 | G26: =F70*Assumptions!$B$34 -> 227.89419 | H26: =G70*Assumptions!$B$34 -> 319.02901 | I26: =H70*Assumptions!$B$34 -> 429.46628 | J26: =I70*Assumptions!$B$34 -> 560.69304 | ... L26: =K70*Assumptions!$B$34 -> 891.03808
A27: Interest expense (beginning debt) | C27: =-(B50*Assumptions!$B$39+B54*Assumptions!$B$35) -> -119.04 | D27: =-(C50*Assumptions!$B$39+C54*Assumptions!$B$35) -> -147.84 | E27: =-(D50*Assumptions!$B$39+D54*Assumptions!$B$35) -> -147.84 | F27: =-(E50*Assumptions!$B$39+E54*Assumptions!$B$35) -> -147.84 | G27: =-(F50*Assumptions!$B$39+F54*Assumptions!$B$35) -> -147.84 | H27: =-(G50*Assumptions!$B$39+G54*Assumptions!$B$35) -> -147.84 | I27: =-(H50*Assumptions!$B$39+H54*Assumptions!$B$35) -> -147.84 | J27: =-(I50*Assumptions!$B$39+I54*Assumptions!$B$35) -> -147.84 | ... L27: =-(K50*Assumptions!$B$39+K54*Assumptions!$B$35) -> -147.84
A28: Pre-tax income | C28: =C25+C26+C27 -> 2092.46 | D28: =D25+D26+D27 -> 2325.9949 | E28: =E25+E26+E27 -> 2720.1057 | F28: =F25+F26+F27 -> 3161.2202 | G28: =G25+G26+G27 -> 3650.4457 | H28: =H25+H26+H27 -> 4188.2041 | I28: =I25+I26+I27 -> 4774.1376 | J28: =J25+J26+J27 -> 5407.0281 | ... L28: =L25+L26+L27 -> 6804.1462
A29: Taxes | C29: =-MAX(0,C28)*C13 -> -418.492 | D29: =-MAX(0,D28)*D13 -> -470.36785 | E29: =-MAX(0,E28)*E13 -> -556.1105 | F29: =-MAX(0,F28)*F13 -> -653.31884 | G29: =-MAX(0,G28)*G13 -> -762.53756 | H29: =-MAX(0,H28)*H13 -> -884.17642 | I29: =-MAX(0,I28)*I13 -> -1018.4827 | J29: =-MAX(0,J28)*J13 -> -1165.5149 | ... L29: =-MAX(0,L28)*L13 -> -1496.9122
A30: Net income (GAAP-normalized) | C30: =C28+C29 -> 1673.968 | D30: =D28+D29 -> 1855.627 | E30: =E28+E29 -> 2163.9952 | F30: =F28+F29 -> 2507.9014 | G30: =G28+G29 -> 2887.9082 | H30: =H28+H29 -> 3304.0277 | I30: =I28+I29 -> 3755.6549 | J30: =J28+J29 -> 4241.5132 | ... L30: =L28+L29 -> 5307.234
A31: EPS (constant shares; non-GAAP consensus is higher) | C31: =C30/Assumptions!$B$37 -> 6.0694996 | D31: =D30/Assumptions!$B$37 -> 6.7281618 | E31: =E30/Assumptions!$B$37 -> 7.846248 | F31: =F30/Assumptions!$B$37 -> 9.0931884 | G31: =G30/Assumptions!$B$37 -> 10.471023 | H31: =H30/Assumptions!$B$37 -> 11.979796 | I31: =I30/Assumptions!$B$37 -> 13.617313 | J31: =J30/Assumptions!$B$37 -> 15.378945 | ... L31: =L30/Assumptions!$B$37 -> 19.243053
A32: Adj. EBITDA margin % | C32: =C22/C18 -> 0.455 | D32: =D22/D18 -> 0.46 | E32: =E22/E18 -> 0.465 | F32: =F22/F18 -> 0.47 | G32: =G22/G18 -> 0.475 | H32: =H22/H18 -> 0.48 | I32: =I22/I18 -> 0.485 | J32: =J22/J18 -> 0.49 | ... L32: =L22/L18 -> 0.5
A34: WORKING CAPITAL
A35: Accounts receivable | B35: 1650 | C35: =C18*Assumptions!$B$27/365 -> 1015.0685 | D35: =D18*Assumptions!$B$27/365 -> 1147.0274 | E35: =E18*Assumptions!$B$27/365 -> 1288.972 | F35: =F18*Assumptions!$B$27/365 -> 1440.4263 | G35: =G18*Assumptions!$B$27/365 -> 1600.6737 | H35: =H18*Assumptions!$B$27/365 -> 1768.7444 | I35: =I18*Assumptions!$B$27/365 -> 1943.4079 | J35: =J18*Assumptions!$B$27/365 -> 2123.1732 | ... L35: =L18*Assumptions!$B$27/365 -> 2490.8006
A36: Inventory (emulation hardware) | B36: 300 | C36: =-C19*Assumptions!$B$28/365 -> 304.52055 | D36: =-D19*Assumptions!$B$28/365 -> 340.92203 | E36: =-E19*Assumptions!$B$28/365 -> 379.53066 | F36: =-F19*Assumptions!$B$28/365 -> 420.12432 | G36: =-G19*Assumptions!$B$28/365 -> 462.41684 | H36: =-H19*Assumptions!$B$28/365 -> 506.05743 | I36: =-I19*Assumptions!$B$28/365 -> 550.63224 | J36: =-J19*Assumptions!$B$28/365 -> 595.66802 | ... L36: =-L19*Assumptions!$B$28/365 -> 684.97016
A37: Other current assets | B37: 700 | C37: =C18*C14 -> 679.25 | D37: =D18*D14 -> 767.5525 | E37: =E18*E14 -> 862.53712 | F37: =F18*F14 -> 963.88523 | G37: =G18*G14 -> 1071.1175 | H37: =H18*H14 -> 1183.5848 | I37: =I18*I14 -> 1300.4638 | J37: =J18*J14 -> 1420.7567 | ... L37: =L18*L14 -> 1666.7607
A38: AP + accrued | B38: -900 | C38: =(C19+C21)*Assumptions!$B$29/365 -> -414.90925 | D38: =(D19+D21)*Assumptions!$B$29/365 -> -464.5461 | E38: =(E19+E21)*Assumptions!$B$29/365 -> -517.20003 | F38: =(F19+F21)*Assumptions!$B$29/365 -> -572.56944 | G38: =(G19+G21)*Assumptions!$B$29/365 -> -630.26526 | H38: =(H19+H21)*Assumptions!$B$29/365 -> -689.81032 | I38: =(I19+I21)*Assumptions!$B$29/365 -> -750.64131 | J38: =(J19+J21)*Assumptions!$B$29/365 -> -812.11373 | ... L38: =(L19+L21)*Assumptions!$B$29/365 -> -934.05022
A39: Deferred revenue | B39: -950 | C39: =-C18*C15 -> -957.125 | D39: =-D18*D15 -> -1085.4278 | E39: =-E18*E15 -> -1224.1057 | F39: =-F18*F15 -> -1372.8062 | G39: =-G18*G15 -> -1530.9406 | H39: =-H18*H15 -> -1697.6671 | I39: =-I18*I15 -> -1871.8797 | J39: =-J18*J15 -> -2052.2041 | ... L39: =-L18*L15 -> -2424.3792
A40: Net working capital | B40: =SUM(B35:B39) -> 800 | C40: =SUM(C35:C39) -> 626.80479 | D40: =SUM(D35:D39) -> 705.52806 | E40: =SUM(E35:E39) -> 789.73407 | F40: =SUM(F35:F39) -> 879.06013 | G40: =SUM(G35:G39) -> 973.0021 | H40: =SUM(H35:H39) -> 1070.9092 | I40: =SUM(I35:I39) -> 1171.9829 | ... L40: =SUM(L35:L39) -> 1484.102
A41: (Increase) / decrease in NWC — cash impact | C41: =-(C40-B40) -> 173.19521 | D41: =-(D40-C40) -> -78.723261 | E41: =-(E40-D40) -> -84.206016 | F41: =-(F40-E40) -> -89.326061 | G41: =-(G40-F40) -> -93.941966 | H41: =-(H40-G40) -> -97.907132 | I41: =-(I40-H40) -> -101.07371 | J41: =-(J40-I40) -> -103.29708 | ... L41: =-(L40-K40) -> -104.38129
A43: CAPEX & PP&E
A44: Capex | C44: =C18*C12 -> 185.25 | D44: =D18*D12 -> 205.45597 | E44: =E18*E12 -> 226.5249 | F44: =F18*F12 -> 248.27347 | G44: =G18*G12 -> 270.48421 | H44: =H18*H12 -> 292.90735 | I44: =I18*I12 -> 315.26395 | J44: =J18*J12 -> 337.25033 | ... L44: =L18*L12 -> 378.80926
A45: PP&E, net | B45: 480 | C45: =B45+C44+C24*0.4 -> 591.15 | D45: =C45+D44+D24*0.4 -> 712.87297 | E45: =D45+E44+E24*0.4 -> 845.30291 | F45: =E45+F44+F24*0.4 -> 988.42527 | G45: =F45+G44+G24*0.4 -> 1142.0603 | H45: =G45+H44+H24*0.4 -> 1305.8493 | I45: =H45+I44+I24*0.4 -> 1479.2445 | J45: =I45+J44+J24*0.4 -> 1661.5032 | ... L45: =K45+L44+L24*0.4 -> 2048.668 | M45: 60% of D&A assumed to be acquisition amortization (hits the goodwill/intangibles line), 40% depreciation of PP&E
A47: DEBT SCHEDULE ('27/'29/'34 notes + Hexagon financing; refinanced at maturity)
A48: Notes & term debt — beginning | C48: =B50 -> 2480 | D48: =C50 -> 3080 | E48: =D50 -> 3080 | F48: =E50 -> 3080 | G48: =F50 -> 3080 | H48: =G50 -> 3080 | I48: =H50 -> 3080 | J48: =I50 -> 3080 | ... L48: =K50 -> 3080
A49: Net issuance / (repayment) — input | C49: =Assumptions!$B$42 -> 600 | D49: 0 | E49: 0 | F49: 0 | G49: 0 | H49: 0 | I49: 0 | J49: 0 | K49: 0 | L49: 0
A50: Notes & term debt — ending | B50: 2480 | C50: =C48+C49 -> 3080 | D50: =D48+D49 -> 3080 | E50: =E48+E49 -> 3080 | F50: =F48+F49 -> 3080 | G50: =G48+G49 -> 3080 | H50: =H48+H49 -> 3080 | I50: =I48+I49 -> 3080 | J50: =J48+J49 -> 3080 | ... L50: =L48+L49 -> 3080
A51: Revolver — beginning | C51: =B54 -> 0 | D51: =C54 -> 0 | E51: =D54 -> 0 | F51: =E54 -> 0 | G51: =F54 -> 0 | H51: =G54 -> 0 | I51: =H54 -> 0 | J51: =I54 -> 0 | ... L51: =K54 -> 0
A52: Draw (if cash < minimum) | C52: =MAX(0,Assumptions!$B$36-(B70+C30-C23-C24+C41-C44+C65+C66+C49)) -> 0 | D52: =MAX(0,Assumptions!$B$36-(C70+D30-D23-D24+D41-D44+D65+D66+D49)) -> 0 | E52: =MAX(0,Assumptions!$B$36-(D70+E30-E23-E24+E41-E44+E65+E66+E49)) -> 0 | F52: =MAX(0,Assumptions!$B$36-(E70+F30-F23-F24+F41-F44+F65+F66+F49)) -> 0 | G52: =MAX(0,Assumptions!$B$36-(F70+G30-G23-G24+G41-G44+G65+G66+G49)) -> 0 | H52: =MAX(0,Assumptions!$B$36-(G70+H30-H23-H24+H41-H44+H65+H66+H49)) -> 0 | I52: =MAX(0,Assumptions!$B$36-(H70+I30-I23-I24+I41-I44+I65+I66+I49)) -> 0 | J52: =MAX(0,Assumptions!$B$36-(I70+J30-J23-J24+J41-J44+J65+J66+J49)) -> 0 | ... L52: =MAX(0,Assumptions!$B$36-(K70+L30-L23-L24+L41-L44+L65+L66+L49)) -> 0
A53: (Repayment) | C53: =-MIN(C51,MAX(0,(B70+C30-C23-C24+C41-C44+C65+C66+C49)-Assumptions!$B$36)) -> 0 | D53: =-MIN(D51,MAX(0,(C70+D30-D23-D24+D41-D44+D65+D66+D49)-Assumptions!$B$36)) -> 0 | E53: =-MIN(E51,MAX(0,(D70+E30-E23-E24+E41-E44+E65+E66+E49)-Assumptions!$B$36)) -> 0 | F53: =-MIN(F51,MAX(0,(E70+F30-F23-F24+F41-F44+F65+F66+F49)-Assumptions!$B$36)) -> 0 | G53: =-MIN(G51,MAX(0,(F70+G30-G23-G24+G41-G44+G65+G66+G49)-Assumptions!$B$36)) -> 0 | H53: =-MIN(H51,MAX(0,(G70+H30-H23-H24+H41-H44+H65+H66+H49)-Assumptions!$B$36)) -> 0 | I53: =-MIN(I51,MAX(0,(H70+I30-I23-I24+I41-I44+I65+I66+I49)-Assumptions!$B$36)) -> 0 | J53: =-MIN(J51,MAX(0,(I70+J30-J23-J24+J41-J44+J65+J66+J49)-Assumptions!$B$36)) -> 0 | ... L53: =-MIN(L51,MAX(0,(K70+L30-L23-L24+L41-L44+L65+L66+L49)-Assumptions!$B$36)) -> 0
A54: Revolver — ending | B54: 0 | C54: =C51+C52+C53 -> 0 | D54: =D51+D52+D53 -> 0 | E54: =E51+E52+E53 -> 0 | F54: =F51+F52+F53 -> 0 | G54: =G51+G52+G53 -> 0 | H54: =H51+H52+H53 -> 0 | I54: =I51+I52+I53 -> 0 | J54: =J51+J52+J53 -> 0 | ... L54: =L51+L52+L53 -> 0
A55: Total debt — ending | B55: =B50+B54 -> 2480 | C55: =C50+C54 -> 3080 | D55: =D50+D54 -> 3080 | E55: =E50+E54 -> 3080 | F55: =F50+F54 -> 3080 | G55: =G50+G54 -> 3080 | H55: =H50+H54 -> 3080 | I55: =I50+I54 -> 3080 | ... L55: =L50+L54 -> 3080
A57: CASH FLOW STATEMENT
A58: Net income | C58: =C30 -> 1673.968 | D58: =D30 -> 1855.627 | E58: =E30 -> 2163.9952 | F58: =F30 -> 2507.9014 | G58: =G30 -> 2887.9082 | H58: =H30 -> 3304.0277 | I58: =I30 -> 3755.6549 | J58: =J30 -> 4241.5132 | ... L58: =L30 -> 5307.234
A59: + D&A | C59: =-C24 -> 185.25 | D59: =-D24 -> 209.3325 | E59: =-E24 -> 235.2374 | F59: =-F24 -> 262.87779 | G59: =-G24 -> 292.12295 | H59: =-H24 -> 322.79585 | I59: =-I24 -> 354.67195 | J59: =-J24 -> 387.4791 | ... L59: =-L24 -> 454.57111
A60: + Stock-based compensation | C60: =-C23 -> 524.875 | D60: =-D23 -> 581.47917 | E60: =-E23 -> 640.36847 | F60: =-F23 -> 701.00744 | G60: =-G23 -> 762.76547 | H60: =-H23 -> 824.92274 | I60: =-I23 -> 886.67986 | J60: =-J23 -> 947.17113 | ... L60: =-L23 -> 1060.6659
A61: +/- Change in NWC | C61: =C41 -> 173.19521 | D61: =D41 -> -78.723261 | E61: =E41 -> -84.206016 | F61: =F41 -> -89.326061 | G61: =G41 -> -93.941966 | H61: =H41 -> -97.907132 | I61: =I41 -> -101.07371 | J61: =J41 -> -103.29708 | ... L61: =L41 -> -104.38129
A62: Cash from operations | C62: =SUM(C58:C61) -> 2557.2882 | D62: =SUM(D58:D61) -> 2567.7154 | E62: =SUM(E58:E61) -> 2955.395 | F62: =SUM(F58:F61) -> 3382.4605 | G62: =SUM(G58:G61) -> 3848.8546 | H62: =SUM(H58:H61) -> 4353.8391 | I62: =SUM(I58:I61) -> 4895.933 | J62: =SUM(J58:J61) -> 5472.8663 | ... L62: =SUM(L58:L61) -> 6718.0897
A63: - Capex | C63: =-C44 -> -185.25 | D63: =-D44 -> -205.45597 | E63: =-E44 -> -226.5249 | F63: =-F44 -> -248.27347 | G63: =-G44 -> -270.48421 | H63: =-H44 -> -292.90735 | I63: =-I44 -> -315.26395 | J63: =-J44 -> -337.25033 | ... L63: =-L44 -> -378.80926
A64: Free cash flow | C64: =C62+C63 -> 2372.0382 | D64: =D62+D63 -> 2362.2594 | E64: =E62+E63 -> 2728.8701 | F64: =F62+F63 -> 3134.1871 | G64: =G62+G63 -> 3578.3704 | H64: =H62+H63 -> 4060.9318 | I64: =I62+I63 -> 4580.669 | J64: =J62+J63 -> 5135.616 | ... L64: =L62+L63 -> 6339.2805
A65: - Acquisitions, net (Hexagon FY26) | C65: =-Assumptions!$B$41 -> -3100 | D65: 0 | E65: 0 | F65: 0 | G65: 0 | H65: 0 | I65: 0 | J65: 0 | K65: 0 | L65: 0
A66: - Share buybacks | C66: =-Assumptions!$B$40 -> -1300 | D66: =-Assumptions!$B$40 -> -1300 | E66: =-Assumptions!$B$40 -> -1300 | F66: =-Assumptions!$B$40 -> -1300 | G66: =-Assumptions!$B$40 -> -1300 | H66: =-Assumptions!$B$40 -> -1300 | I66: =-Assumptions!$B$40 -> -1300 | J66: =-Assumptions!$B$40 -> -1300 | ... L66: =-Assumptions!$B$40 -> -1300
A67: + Debt draws / (repayments) | C67: =C49+C52+C53 -> 600 | D67: =D49+D52+D53 -> 0 | E67: =E49+E52+E53 -> 0 | F67: =F49+F52+F53 -> 0 | G67: =G49+G52+G53 -> 0 | H67: =H49+H52+H53 -> 0 | I67: =I49+I52+I53 -> 0 | J67: =J49+J52+J53 -> 0 | ... L67: =L49+L52+L53 -> 0
A68: Net change in cash | C68: =C64+C65+C66+C67 -> -1427.9618 | D68: =D64+D65+D66+D67 -> 1062.2594 | E68: =E64+E65+E66+E67 -> 1428.8701 | F68: =F64+F65+F66+F67 -> 1834.1871 | G68: =G64+G65+G66+G67 -> 2278.3704 | H68: =H64+H65+H66+H67 -> 2760.9318 | I68: =I64+I65+I66+I67 -> 3280.669 | J68: =J64+J65+J66+J67 -> 3835.616 | ... L68: =L64+L65+L66+L67 -> 5039.2805
A69: Cash — beginning | C69: =B70 -> 2800 | D69: =C70 -> 1372.0382 | E69: =D70 -> 2434.2977 | F69: =E70 -> 3863.1678 | G69: =F70 -> 5697.3549 | H69: =G70 -> 7975.7253 | I69: =H70 -> 10736.657 | J69: =I70 -> 14017.326 | ... L69: =K70 -> 22275.952
A70: Cash — ending | B70: 2800 | C70: =C69+C68 -> 1372.0382 | D70: =D69+D68 -> 2434.2977 | E70: =E69+E68 -> 3863.1678 | F70: =F69+F68 -> 5697.3549 | G70: =G69+G68 -> 7975.7253 | H70: =H69+H68 -> 10736.657 | I70: =I69+I68 -> 14017.326 | J70: =J69+J68 -> 17852.942 | ... L70: =L69+L68 -> 27315.232
A72: BALANCE SHEET
A73: Cash + short-term investments | B73: =B70 -> 2800 | C73: =C70 -> 1372.0382 | D73: =D70 -> 2434.2977 | E73: =E70 -> 3863.1678 | F73: =F70 -> 5697.3549 | G73: =G70 -> 7975.7253 | H73: =H70 -> 10736.657 | I73: =I70 -> 14017.326 | ... L73: =L70 -> 27315.232
A74: Accounts receivable | B74: =B35 -> 1650 | C74: =C35 -> 1015.0685 | D74: =D35 -> 1147.0274 | E74: =E35 -> 1288.972 | F74: =F35 -> 1440.4263 | G74: =G35 -> 1600.6737 | H74: =H35 -> 1768.7444 | I74: =I35 -> 1943.4079 | ... L74: =L35 -> 2490.8006
A75: Inventory | B75: =B36 -> 300 | C75: =C36 -> 304.52055 | D75: =D36 -> 340.92203 | E75: =E36 -> 379.53066 | F75: =F36 -> 420.12432 | G75: =G36 -> 462.41684 | H75: =H36 -> 506.05743 | I75: =I36 -> 550.63224 | ... L75: =L36 -> 684.97016
A76: Other current assets | B76: =B37 -> 700 | C76: =C37 -> 679.25 | D76: =D37 -> 767.5525 | E76: =E37 -> 862.53712 | F76: =F37 -> 963.88523 | G76: =G37 -> 1071.1175 | H76: =H37 -> 1183.5848 | I76: =I37 -> 1300.4638 | ... L76: =L37 -> 1666.7607
A77: PP&E, net | B77: =B45 -> 480 | C77: =C45 -> 591.15 | D77: =D45 -> 712.87297 | E77: =E45 -> 845.30291 | F77: =F45 -> 988.42527 | G77: =G45 -> 1142.0603 | H77: =H45 -> 1305.8493 | I77: =I45 -> 1479.2445 | ... L77: =L45 -> 2048.668
A78: Goodwill + intangibles + other LT | B78: 4970 | C78: =B78+-C65+C24*0.6 -> 7958.85 | D78: =C78+-D65+D24*0.6 -> 7833.2505 | E78: =D78+-E65+E24*0.6 -> 7692.1081 | F78: =E78+-F65+F24*0.6 -> 7534.3814 | G78: =F78+-G65+G24*0.6 -> 7359.1076 | H78: =G78+-H65+H24*0.6 -> 7165.4301 | I78: =H78+-I65+I24*0.6 -> 6952.6269 | J78: =I78+-J65+J24*0.6 -> 6720.1395 | ... L78: =K78+-L65+L24*0.6 -> 6194.8573
A79: TOTAL ASSETS | B79: =SUM(B73:B78) -> 10900 | C79: =SUM(C73:C78) -> 11920.877 | D79: =SUM(D73:D78) -> 13235.923 | E79: =SUM(E73:E78) -> 14931.619 | F79: =SUM(F73:F78) -> 17044.597 | G79: =SUM(G73:G78) -> 19611.101 | H79: =SUM(H73:H78) -> 22666.323 | I79: =SUM(I73:I78) -> 26243.702 | ... L79: =SUM(L73:L78) -> 40401.289
A80: AP + accrued | B80: =-B38 -> 900 | C80: =-C38 -> 414.90925 | D80: =-D38 -> 464.5461 | E80: =-E38 -> 517.20003 | F80: =-F38 -> 572.56944 | G80: =-G38 -> 630.26526 | H80: =-H38 -> 689.81032 | I80: =-I38 -> 750.64131 | ... L80: =-L38 -> 934.05022
A81: Deferred revenue | B81: =-B39 -> 950 | C81: =-C39 -> 957.125 | D81: =-D39 -> 1085.4278 | E81: =-E39 -> 1224.1057 | F81: =-F39 -> 1372.8062 | G81: =-G39 -> 1530.9406 | H81: =-H39 -> 1697.6671 | I81: =-I39 -> 1871.8797 | ... L81: =-L39 -> 2424.3792
A82: Total debt | B82: =B55 -> 2480 | C82: =C55 -> 3080 | D82: =D55 -> 3080 | E82: =E55 -> 3080 | F82: =F55 -> 3080 | G82: =G55 -> 3080 | H82: =H55 -> 3080 | I82: =I55 -> 3080 | ... L82: =L55 -> 3080
A83: Other LT liabilities | B83: 1070 | C83: =B83 -> 1070 | D83: =B83 -> 1070 | E83: =B83 -> 1070 | F83: =B83 -> 1070 | G83: =B83 -> 1070 | H83: =B83 -> 1070 | I83: =B83 -> 1070 | J83: =B83 -> 1070 | K83: =B83 -> 1070 | L83: =B83 -> 1070
A84: TOTAL LIABILITIES | B84: =SUM(B80:B83) -> 5400 | C84: =SUM(C80:C83) -> 5522.0342 | D84: =SUM(D80:D83) -> 5699.9739 | E84: =SUM(E80:E83) -> 5891.3057 | F84: =SUM(F80:F83) -> 6095.3757 | G84: =SUM(G80:G83) -> 6311.2059 | H84: =SUM(H80:H83) -> 6537.4774 | I84: =SUM(I80:I83) -> 6772.521 | ... L84: =SUM(L80:L83) -> 7508.4295
A85: Total equity (opening = plug; rolls with NI + SBC − buybacks) | B85: =B79-B84 -> 5500 | C85: =B85+C30-C23+C66 -> 6398.843 | D85: =C85+D30-D23+D66 -> 7535.9492 | E85: =D85+E30-E23+E66 -> 9040.3128 | F85: =E85+F30-F23+F66 -> 10949.222 | G85: =F85+G30-G23+G66 -> 13299.895 | H85: =G85+H30-H23+H66 -> 16128.846 | I85: =H85+I30-I23+I66 -> 19471.18 | J85: =I85+J30-J23+J66 -> 23359.865 | ... L85: =K85+L30-L23+L66 -> 32892.86
A86: TOTAL LIABILITIES + EQUITY | B86: =B84+B85 -> 10900 | C86: =C84+C85 -> 11920.877 | D86: =D84+D85 -> 13235.923 | E86: =E84+E85 -> 14931.619 | F86: =F84+F85 -> 17044.597 | G86: =G84+G85 -> 19611.101 | H86: =H84+H85 -> 22666.323 | I86: =I84+I85 -> 26243.702 | ... L86: =L84+L85 -> 40401.289
A87: Balance check (must be 0) | B87: =B79-B86 -> 0 | C87: =C79-C86 -> 0 | D87: =D79-D86 -> 0 | E87: =E79-E86 -> 0 | F87: =F79-F86 -> 0 | G87: =G79-G86 -> 0 | H87: =H79-H86 -> 0 | I87: =I79-I86 -> 0 | ... L87: =L79-L86 -> 0

Sheet WACC
A1: WEIGHTED AVERAGE COST OF CAPITAL — CURRENT MARKET DATA (JULY 2026)
A4: COST OF EQUITY (CAPM)
A5: Risk-free rate — 10Y UST, 7/17/2026 | B5: 0.0455 | C5: tradingeconomics.com / FRED DGS10
A6: Levered beta | B6: 1.13 | C6: stockanalysis.com statistics, July 2026
A7: Equity risk premium | B7: 0.0475 | C7: Damodaran implied ERP, mid-2026
A8: Company-specific premium | B8: 0
A9: Cost of equity | B9: =B5+B6*B7+B8 -> 0.099175
A11: COST OF DEBT
A12: Pre-tax cost of debt | B12: 0.048 | C12: Blended '27/'29/'34 notes + Hexagon financing
A13: Tax rate | B13: =Assumptions!B38 -> 0.22
A14: After-tax cost of debt | B14: =B12*(1-B13) -> 0.03744
A16: CAPITAL STRUCTURE (market weights)
A17: Debt / total capitalization | B17: 0.03 | C17: $3.08B debt vs ~$91B market cap
A18: Equity / total capitalization | B18: =1-B17 -> 0.97
A20: WACC | B20: =B18*B9+B17*B14 -> 0.09732295
A22: WACC ≈ 9.7%. Sensitivity range in DCF tables: 8.75% – 10.75%.

Sheet DCF
A1: DISCOUNTED CASH FLOW — UNLEVERED FCF ($mm; valuation as of FY2026 year-end, mid-year convention)
B4: FY2027E | C4: FY2028E | D4: FY2029E | E4: FY2030E | F4: FY2031E | G4: FY2032E | H4: FY2033E | I4: FY2034E | J4: FY2035E
A5: EBIT (post-SBC) | B5: =Model_3S!D25 -> 2418.9533 | C5: =Model_3S!E25 -> 2770.5738 | D5: =Model_3S!F25 -> 3154.5335 | E5: =Model_3S!G25 -> 3570.3916 | F5: =Model_3S!H25 -> 4017.0151 | G5: =Model_3S!I25 -> 4492.5113 | H5: =Model_3S!J25 -> 4994.1751 | I5: =Model_3S!K25 -> 5518.4558 | J5: =Model_3S!L25 -> 6060.9481
A6: Cash taxes on EBIT | B6: =-MAX(0,B5)*Model_3S!D13 -> -489.16612 | C6: =-MAX(0,C5)*Model_3S!E13 -> -566.42842 | D6: =-MAX(0,D5)*Model_3S!F13 -> -651.93692 | E6: =-MAX(0,E5)*Model_3S!G13 -> -745.81512 | F6: =-MAX(0,F5)*Model_3S!H13 -> -848.03652 | G6: =-MAX(0,G5)*Model_3S!I13 -> -958.40241 | H6: =-MAX(0,H5)*Model_3S!J13 -> -1076.5222 | I6: =-MAX(0,I5)*Model_3S!K13 -> -1201.797 | J6: =-MAX(0,J5)*Model_3S!L13 -> -1333.4086
A7: + D&A | B7: =-Model_3S!D24 -> 209.3325 | C7: =-Model_3S!E24 -> 235.2374 | D7: =-Model_3S!F24 -> 262.87779 | E7: =-Model_3S!G24 -> 292.12295 | F7: =-Model_3S!H24 -> 322.79585 | G7: =-Model_3S!I24 -> 354.67195 | H7: =-Model_3S!J24 -> 387.4791 | I7: =-Model_3S!K24 -> 420.89917 | J7: =-Model_3S!L24 -> 454.57111
A8: − Capex | B8: =-Model_3S!D44 -> -205.45597 | C8: =-Model_3S!E44 -> -226.5249 | D8: =-Model_3S!F44 -> -248.27347 | E8: =-Model_3S!G44 -> -270.48421 | F8: =-Model_3S!H44 -> -292.90735 | G8: =-Model_3S!I44 -> -315.26395 | H8: =-Model_3S!J44 -> -337.25033 | I8: =-Model_3S!K44 -> -358.54374 | J8: =-Model_3S!L44 -> -378.80926
A9: +/− Change in NWC | B9: =Model_3S!D41 -> -78.723261 | C9: =Model_3S!E41 -> -84.206016 | D9: =Model_3S!F41 -> -89.326061 | E9: =Model_3S!G41 -> -93.941966 | F9: =Model_3S!H41 -> -97.907132 | G9: =Model_3S!I41 -> -101.07371 | H9: =Model_3S!J41 -> -103.29708 | I9: =Model_3S!K41 -> -104.44071 | J9: =Model_3S!L41 -> -104.38129
A10: Unlevered free cash flow | B10: =SUM(B5:B9) -> 1854.9405 | C10: =SUM(C5:C9) -> 2128.6518 | D10: =SUM(D5:D9) -> 2427.8748 | E10: =SUM(E5:E9) -> 2752.2732 | F10: =SUM(F5:F9) -> 3100.9599 | G10: =SUM(G5:G9) -> 3472.4432 | H10: =SUM(H5:H9) -> 3864.5846 | I10: =SUM(I5:I9) -> 4274.5735 | J10: =SUM(J5:J9) -> 4698.9201
A11: Discount period (mid-year) | B11: 0.5 | C11: 1.5 | D11: 2.5 | E11: 3.5 | F11: 4.5 | G11: 5.5 | H11: 6.5 | I11: 7.5 | J11: 8.5
A12: Discount factor @ WACC | B12: =(1+$B$16)^-B11 -> 0.95462492 | C12: =(1+$B$16)^-C11 -> 0.86995804 | D12: =(1+$B$16)^-D11 -> 0.79280037 | E12: =(1+$B$16)^-E11 -> 0.72248591 | F12: =(1+$B$16)^-F11 -> 0.65840773 | G12: =(1+$B$16)^-G11 -> 0.60001272 | H12: =(1+$B$16)^-H11 -> 0.54679684 | I12: =(1+$B$16)^-I11 -> 0.49830074 | J12: =(1+$B$16)^-J11 -> 0.45410582
A13: PV of FCF | B13: =B10*B12 -> 1770.7724 | C13: =C10*C12 -> 1851.8378 | D13: =D10*D12 -> 1924.8201 | E13: =E10*E12 -> 1988.4786 | F13: =F10*F12 -> 2041.696 | G13: =G10*G12 -> 2083.5101 | H13: =H10*H12 -> 2113.1426 | I13: =I10*I12 -> 2130.0231 | J13: =J10*J12 -> 2133.807
A14: SBC deducted in EBIT (not added back) with a constant share count — conservative.
A15: Sum of PV of explicit FCF (FY27–35) | B15: =SUM(B13:J13) -> 18038.088
A16: WACC | B16: =WACC!B20 -> 0.09732295
A18: TERMINAL VALUE — METHOD 1: GORDON GROWTH
A19: Terminal growth g | B19: =Assumptions!B47 -> 0.035
A20: Terminal value | B20: =J10*(1+B19)/(B16-B19) -> 78035.174
A21: PV of terminal value (9.0 yrs) | B21: =B20/(1+B16)^9 -> 33828.306
A22: Implied exit EV/EBITDA | B22: =B20/Model_3S!L22 -> 10.300062
A24: TERMINAL VALUE — METHOD 2: EXIT MULTIPLE
A25: Exit EV/Adj. EBITDA multiple | B25: =Assumptions!B48 -> 20
A26: Terminal value | B26: =B25*Model_3S!L22 -> 151523.7
A27: PV of terminal value | B27: =B26/(1+B16)^9 -> 65685.636
A28: Implied perpetuity growth | B28: =(B16*B26-J10)/(B26+J10) -> 0.064317277
A30: ENTERPRISE → EQUITY VALUE BRIDGE
A31: Net debt, FY2026E year-end (debt − cash) | B31: =Model_3S!C55-Model_3S!C70 -> 1707.9618
A32: Diluted shares (mm) | B32: =Assumptions!B37 -> 275.8
B33: Gordon growth | C33: Exit multiple | D33: Average
A34: Enterprise value | B34: =B15+B21 -> 51866.393 | C34: =B15+B27 -> 83723.724 | D34: =AVERAGE(B34:C34) -> 67795.059
A35: − Net debt | B35: =-$B$31 -> -1707.9618 | C35: =-$B$31 -> -1707.9618 | D35: =-$B$31 -> -1707.9618
A36: Equity value | B36: =B34+B35 -> 50158.431 | C36: =C34+C35 -> 82015.762 | D36: =D34+D35 -> 66087.097
A37: Implied value per share | B37: =B36/$B$32 -> 181.86523 | C37: =C36/$B$32 -> 297.37405 | D37: =D36/$B$32 -> 239.61964
A38: Upside / (downside) vs current price | B38: =B37/Assumptions!$B$49-1 -> -0.44906018 | C38: =C37/Assumptions!$B$49-1 -> -0.099139512 | D38: =D37/Assumptions!$B$49-1 -> -0.27409985
A42: SENSITIVITY — VALUE PER SHARE: WACC × TERMINAL GROWTH (Gordon)
B43: WACC \ g | C43: 0.025 | D43: 0.03 | E43: 0.035 | F43: 0.04 | G43: 0.045
B44: 0.0875 | C44: =(SUMPRODUCT($B$10:$J$10,(1+$B$44)^-($B$11:$J$11))+$J$10*(1+C$43)/($B$44-C$43)/(1+$B$44)^9-$B$31)/$B$32 -> 193.35867 | D44: =(SUMPRODUCT($B$10:$J$10,(1+$B$44)^-($B$11:$J$11))+$J$10*(1+D$43)/($B$44-D$43)/(1+$B$44)^9-$B$31)/$B$32 -> 205.47558 | E44: =(SUMPRODUCT($B$10:$J$10,(1+$B$44)^-($B$11:$J$11))+$J$10*(1+E$43)/($B$44-E$43)/(1+$B$44)^9-$B$31)/$B$32 -> 219.90047 | F44: =(SUMPRODUCT($B$10:$J$10,(1+$B$44)^-($B$11:$J$11))+$J$10*(1+F$43)/($B$44-F$43)/(1+$B$44)^9-$B$31)/$B$32 -> 237.36218 | G44: =(SUMPRODUCT($B$10:$J$10,(1+$B$44)^-($B$11:$J$11))+$J$10*(1+G$43)/($B$44-G$43)/(1+$B$44)^9-$B$31)/$B$32 -> 258.93253
B45: 0.0925 | C45: =(SUMPRODUCT($B$10:$J$10,(1+$B$45)^-($B$11:$J$11))+$J$10*(1+C$43)/($B$45-C$43)/(1+$B$45)^9-$B$31)/$B$32 -> 177.25782 | D45: =(SUMPRODUCT($B$10:$J$10,(1+$B$45)^-($B$11:$J$11))+$J$10*(1+D$43)/($B$45-D$43)/(1+$B$45)^9-$B$31)/$B$32 -> 187.20772 | E45: =(SUMPRODUCT($B$10:$J$10,(1+$B$45)^-($B$11:$J$11))+$J$10*(1+E$43)/($B$45-E$43)/(1+$B$45)^9-$B$31)/$B$32 -> 198.88803 | F45: =(SUMPRODUCT($B$10:$J$10,(1+$B$45)^-($B$11:$J$11))+$J$10*(1+F$43)/($B$45-F$43)/(1+$B$45)^9-$B$31)/$B$32 -> 212.79316 | G45: =(SUMPRODUCT($B$10:$J$10,(1+$B$45)^-($B$11:$J$11))+$J$10*(1+G$43)/($B$45-G$43)/(1+$B$45)^9-$B$31)/$B$32 -> 229.62569
B46: 0.097 | C46: =(SUMPRODUCT($B$10:$J$10,(1+$B$46)^-($B$11:$J$11))+$J$10*(1+C$43)/($B$46-C$43)/(1+$B$46)^9-$B$31)/$B$32 -> 164.72272 | D46: =(SUMPRODUCT($B$10:$J$10,(1+$B$46)^-($B$11:$J$11))+$J$10*(1+D$43)/($B$46-D$43)/(1+$B$46)^9-$B$31)/$B$32 -> 173.14275 | E46: =(SUMPRODUCT($B$10:$J$10,(1+$B$46)^-($B$11:$J$11))+$J$10*(1+E$43)/($B$46-E$43)/(1+$B$46)^9-$B$31)/$B$32 -> 182.92084 | F46: =(SUMPRODUCT($B$10:$J$10,(1+$B$46)^-($B$11:$J$11))+$J$10*(1+F$43)/($B$46-F$43)/(1+$B$46)^9-$B$31)/$B$32 -> 194.41439 | G46: =(SUMPRODUCT($B$10:$J$10,(1+$B$46)^-($B$11:$J$11))+$J$10*(1+G$43)/($B$46-G$43)/(1+$B$46)^9-$B$31)/$B$32 -> 208.11824
B47: 0.1025 | C47: =(SUMPRODUCT($B$10:$J$10,(1+$B$47)^-($B$11:$J$11))+$J$10*(1+C$43)/($B$47-C$43)/(1+$B$47)^9-$B$31)/$B$32 -> 151.42866 | D47: =(SUMPRODUCT($B$10:$J$10,(1+$B$47)^-($B$11:$J$11))+$J$10*(1+D$43)/($B$47-D$43)/(1+$B$47)^9-$B$31)/$B$32 -> 158.37419 | E47: =(SUMPRODUCT($B$10:$J$10,(1+$B$47)^-($B$11:$J$11))+$J$10*(1+E$43)/($B$47-E$43)/(1+$B$47)^9-$B$31)/$B$32 -> 166.34869 | F47: =(SUMPRODUCT($B$10:$J$10,(1+$B$47)^-($B$11:$J$11))+$J$10*(1+F$43)/($B$47-F$43)/(1+$B$47)^9-$B$31)/$B$32 -> 175.5991 | G47: =(SUMPRODUCT($B$10:$J$10,(1+$B$47)^-($B$11:$J$11))+$J$10*(1+G$43)/($B$47-G$43)/(1+$B$47)^9-$B$31)/$B$32 -> 186.45829
B48: 0.1075 | C48: =(SUMPRODUCT($B$10:$J$10,(1+$B$48)^-($B$11:$J$11))+$J$10*(1+C$43)/($B$48-C$43)/(1+$B$48)^9-$B$31)/$B$32 -> 140.92387 | D48: =(SUMPRODUCT($B$10:$J$10,(1+$B$48)^-($B$11:$J$11))+$J$10*(1+D$43)/($B$48-D$43)/(1+$B$48)^9-$B$31)/$B$32 -> 146.81052 | E48: =(SUMPRODUCT($B$10:$J$10,(1+$B$48)^-($B$11:$J$11))+$J$10*(1+E$43)/($B$48-E$43)/(1+$B$48)^9-$B$31)/$B$32 -> 153.50912 | F48: =(SUMPRODUCT($B$10:$J$10,(1+$B$48)^-($B$11:$J$11))+$J$10*(1+F$43)/($B$48-F$43)/(1+$B$48)^9-$B$31)/$B$32 -> 161.20011 | G48: =(SUMPRODUCT($B$10:$J$10,(1+$B$48)^-($B$11:$J$11))+$J$10*(1+G$43)/($B$48-G$43)/(1+$B$48)^9-$B$31)/$B$32 -> 170.12166
A50: SENSITIVITY — VALUE PER SHARE: WACC × EXIT EV/EBITDA MULTIPLE
B51: WACC \ x | C51: 15 | D51: 17.5 | E51: 20 | F51: 22.5 | G51: 25
B52: 0.0875 | C52: =(SUMPRODUCT($B$10:$J$10,(1+$B$52)^-($B$11:$J$11))+C$51*Model_3S!$L$22/(1+$B$52)^9-$B$31)/$B$32 -> 255.70227 | D52: =(SUMPRODUCT($B$10:$J$10,(1+$B$52)^-($B$11:$J$11))+D$51*Model_3S!$L$22/(1+$B$52)^9-$B$31)/$B$32 -> 287.98222 | E52: =(SUMPRODUCT($B$10:$J$10,(1+$B$52)^-($B$11:$J$11))+E$51*Model_3S!$L$22/(1+$B$52)^9-$B$31)/$B$32 -> 320.26218 | F52: =(SUMPRODUCT($B$10:$J$10,(1+$B$52)^-($B$11:$J$11))+F$51*Model_3S!$L$22/(1+$B$52)^9-$B$31)/$B$32 -> 352.54213 | G52: =(SUMPRODUCT($B$10:$J$10,(1+$B$52)^-($B$11:$J$11))+G$51*Model_3S!$L$22/(1+$B$52)^9-$B$31)/$B$32 -> 384.82209
B53: 0.0925 | C53: =(SUMPRODUCT($B$10:$J$10,(1+$B$53)^-($B$11:$J$11))+C$51*Model_3S!$L$22/(1+$B$53)^9-$B$31)/$B$32 -> 246.41514 | D53: =(SUMPRODUCT($B$10:$J$10,(1+$B$53)^-($B$11:$J$11))+D$51*Model_3S!$L$22/(1+$B$53)^9-$B$31)/$B$32 -> 277.38957 | E53: =(SUMPRODUCT($B$10:$J$10,(1+$B$53)^-($B$11:$J$11))+E$51*Model_3S!$L$22/(1+$B$53)^9-$B$31)/$B$32 -> 308.364 | F53: =(SUMPRODUCT($B$10:$J$10,(1+$B$53)^-($B$11:$J$11))+F$51*Model_3S!$L$22/(1+$B$53)^9-$B$31)/$B$32 -> 339.33843 | G53: =(SUMPRODUCT($B$10:$J$10,(1+$B$53)^-($B$11:$J$11))+G$51*Model_3S!$L$22/(1+$B$53)^9-$B$31)/$B$32 -> 370.31286
B54: 0.097 | C54: =(SUMPRODUCT($B$10:$J$10,(1+$B$54)^-($B$11:$J$11))+C$51*Model_3S!$L$22/(1+$B$54)^9-$B$31)/$B$32 -> 238.39652 | D54: =(SUMPRODUCT($B$10:$J$10,(1+$B$54)^-($B$11:$J$11))+D$51*Model_3S!$L$22/(1+$B$54)^9-$B$31)/$B$32 -> 268.246 | E54: =(SUMPRODUCT($B$10:$J$10,(1+$B$54)^-($B$11:$J$11))+E$51*Model_3S!$L$22/(1+$B$54)^9-$B$31)/$B$32 -> 298.09547 | F54: =(SUMPRODUCT($B$10:$J$10,(1+$B$54)^-($B$11:$J$11))+F$51*Model_3S!$L$22/(1+$B$54)^9-$B$31)/$B$32 -> 327.94495 | G54: =(SUMPRODUCT($B$10:$J$10,(1+$B$54)^-($B$11:$J$11))+G$51*Model_3S!$L$22/(1+$B$54)^9-$B$31)/$B$32 -> 357.79442
B55: 0.1025 | C55: =(SUMPRODUCT($B$10:$J$10,(1+$B$55)^-($B$11:$J$11))+C$51*Model_3S!$L$22/(1+$B$55)^9-$B$31)/$B$32 -> 229.01226 | D55: =(SUMPRODUCT($B$10:$J$10,(1+$B$55)^-($B$11:$J$11))+D$51*Model_3S!$L$22/(1+$B$55)^9-$B$31)/$B$32 -> 257.54799 | E55: =(SUMPRODUCT($B$10:$J$10,(1+$B$55)^-($B$11:$J$11))+E$51*Model_3S!$L$22/(1+$B$55)^9-$B$31)/$B$32 -> 286.08371 | F55: =(SUMPRODUCT($B$10:$J$10,(1+$B$55)^-($B$11:$J$11))+F$51*Model_3S!$L$22/(1+$B$55)^9-$B$31)/$B$32 -> 314.61944 | G55: =(SUMPRODUCT($B$10:$J$10,(1+$B$55)^-($B$11:$J$11))+G$51*Model_3S!$L$22/(1+$B$55)^9-$B$31)/$B$32 -> 343.15517
B56: 0.1075 | C56: =(SUMPRODUCT($B$10:$J$10,(1+$B$56)^-($B$11:$J$11))+C$51*Model_3S!$L$22/(1+$B$56)^9-$B$31)/$B$32 -> 220.85956 | D56: =(SUMPRODUCT($B$10:$J$10,(1+$B$56)^-($B$11:$J$11))+D$51*Model_3S!$L$22/(1+$B$56)^9-$B$31)/$B$32 -> 248.25654 | E56: =(SUMPRODUCT($B$10:$J$10,(1+$B$56)^-($B$11:$J$11))+E$51*Model_3S!$L$22/(1+$B$56)^9-$B$31)/$B$32 -> 275.65352 | F56: =(SUMPRODUCT($B$10:$J$10,(1+$B$56)^-($B$11:$J$11))+F$51*Model_3S!$L$22/(1+$B$56)^9-$B$31)/$B$32 -> 303.0505 | G56: =(SUMPRODUCT($B$10:$J$10,(1+$B$56)^-($B$11:$J$11))+G$51*Model_3S!$L$22/(1+$B$56)^9-$B$31)/$B$32 -> 330.44748
A58: SENSITIVITY — VALUE PER SHARE: FY2027 GROWTH × TERMINAL ADJ. EBITDA MARGIN (compact approximation, exit-multiple TV)
A59: Rev35 ≈ FY26E rev × (1+avg(g1, FY35 g))^9; interim-FCF PV scaled by terminal-EBITDA ratio. Exact at base point.
B60: FY27 g \ margin | C60: 0.42 | D60: 0.46 | E60: 0.5 | F60: 0.525 | G60: 0.545
B61: 0.07 | C61: =($B$15*(Model_3S!$C$18*(1+($B$61+Assumptions!$E$13)/2)^9*C$60)/Model_3S!$L$22+$B$25*(Model_3S!$C$18*(1+($B$61+Assumptions!$E$13)/2)^9*C$60)/(1+$B$16)^9-$B$31)/$B$32 -> 193.04247 | D61: =($B$15*(Model_3S!$C$18*(1+($B$61+Assumptions!$E$13)/2)^9*D$60)/Model_3S!$L$22+$B$25*(Model_3S!$C$18*(1+($B$61+Assumptions!$E$13)/2)^9*D$60)/(1+$B$16)^9-$B$31)/$B$32 -> 212.01726 | E61: =($B$15*(Model_3S!$C$18*(1+($B$61+Assumptions!$E$13)/2)^9*E$60)/Model_3S!$L$22+$B$25*(Model_3S!$C$18*(1+($B$61+Assumptions!$E$13)/2)^9*E$60)/(1+$B$16)^9-$B$31)/$B$32 -> 230.99204 | F61: =($B$15*(Model_3S!$C$18*(1+($B$61+Assumptions!$E$13)/2)^9*F$60)/Model_3S!$L$22+$B$25*(Model_3S!$C$18*(1+($B$61+Assumptions!$E$13)/2)^9*F$60)/(1+$B$16)^9-$B$31)/$B$32 -> 242.85128 | G61: =($B$15*(Model_3S!$C$18*(1+($B$61+Assumptions!$E$13)/2)^9*G$60)/Model_3S!$L$22+$B$25*(Model_3S!$C$18*(1+($B$61+Assumptions!$E$13)/2)^9*G$60)/(1+$B$16)^9-$B$31)/$B$32 -> 252.33867
B62: 0.1 | C62: =($B$15*(Model_3S!$C$18*(1+($B$62+Assumptions!$E$13)/2)^9*C$60)/Model_3S!$L$22+$B$25*(Model_3S!$C$18*(1+($B$62+Assumptions!$E$13)/2)^9*C$60)/(1+$B$16)^9-$B$31)/$B$32 -> 219.50562 | D62: =($B$15*(Model_3S!$C$18*(1+($B$62+Assumptions!$E$13)/2)^9*D$60)/Model_3S!$L$22+$B$25*(Model_3S!$C$18*(1+($B$62+Assumptions!$E$13)/2)^9*D$60)/(1+$B$16)^9-$B$31)/$B$32 -> 241.0007 | E62: =($B$15*(Model_3S!$C$18*(1+($B$62+Assumptions!$E$13)/2)^9*E$60)/Model_3S!$L$22+$B$25*(Model_3S!$C$18*(1+($B$62+Assumptions!$E$13)/2)^9*E$60)/(1+$B$16)^9-$B$31)/$B$32 -> 262.49579 | F62: =($B$15*(Model_3S!$C$18*(1+($B$62+Assumptions!$E$13)/2)^9*F$60)/Model_3S!$L$22+$B$25*(Model_3S!$C$18*(1+($B$62+Assumptions!$E$13)/2)^9*F$60)/(1+$B$16)^9-$B$31)/$B$32 -> 275.93021 | G62: =($B$15*(Model_3S!$C$18*(1+($B$62+Assumptions!$E$13)/2)^9*G$60)/Model_3S!$L$22+$B$25*(Model_3S!$C$18*(1+($B$62+Assumptions!$E$13)/2)^9*G$60)/(1+$B$16)^9-$B$31)/$B$32 -> 286.67776
B63: 0.13 | C63: =($B$15*(Model_3S!$C$18*(1+($B$63+Assumptions!$E$13)/2)^9*C$60)/Model_3S!$L$22+$B$25*(Model_3S!$C$18*(1+($B$63+Assumptions!$E$13)/2)^9*C$60)/(1+$B$16)^9-$B$31)/$B$32 -> 249.04825 | D63: =($B$15*(Model_3S!$C$18*(1+($B$63+Assumptions!$E$13)/2)^9*D$60)/Model_3S!$L$22+$B$25*(Model_3S!$C$18*(1+($B$63+Assumptions!$E$13)/2)^9*D$60)/(1+$B$16)^9-$B$31)/$B$32 -> 273.35692 | E63: =($B$15*(Model_3S!$C$18*(1+($B$63+Assumptions!$E$13)/2)^9*E$60)/Model_3S!$L$22+$B$25*(Model_3S!$C$18*(1+($B$63+Assumptions!$E$13)/2)^9*E$60)/(1+$B$16)^9-$B$31)/$B$32 -> 297.66559 | F63: =($B$15*(Model_3S!$C$18*(1+($B$63+Assumptions!$E$13)/2)^9*F$60)/Model_3S!$L$22+$B$25*(Model_3S!$C$18*(1+($B$63+Assumptions!$E$13)/2)^9*F$60)/(1+$B$16)^9-$B$31)/$B$32 -> 312.85851 | G63: =($B$15*(Model_3S!$C$18*(1+($B$63+Assumptions!$E$13)/2)^9*G$60)/Model_3S!$L$22+$B$25*(Model_3S!$C$18*(1+($B$63+Assumptions!$E$13)/2)^9*G$60)/(1+$B$16)^9-$B$31)/$B$32 -> 325.01284
B64: 0.15 | C64: =($B$15*(Model_3S!$C$18*(1+($B$64+Assumptions!$E$13)/2)^9*C$60)/Model_3S!$L$22+$B$25*(Model_3S!$C$18*(1+($B$64+Assumptions!$E$13)/2)^9*C$60)/(1+$B$16)^9-$B$31)/$B$32 -> 270.60576 | D64: =($B$15*(Model_3S!$C$18*(1+($B$64+Assumptions!$E$13)/2)^9*D$60)/Model_3S!$L$22+$B$25*(Model_3S!$C$18*(1+($B$64+Assumptions!$E$13)/2)^9*D$60)/(1+$B$16)^9-$B$31)/$B$32 -> 296.96752 | E64: =($B$15*(Model_3S!$C$18*(1+($B$64+Assumptions!$E$13)/2)^9*E$60)/Model_3S!$L$22+$B$25*(Model_3S!$C$18*(1+($B$64+Assumptions!$E$13)/2)^9*E$60)/(1+$B$16)^9-$B$31)/$B$32 -> 323.32929 | F64: =($B$15*(Model_3S!$C$18*(1+($B$64+Assumptions!$E$13)/2)^9*F$60)/Model_3S!$L$22+$B$25*(Model_3S!$C$18*(1+($B$64+Assumptions!$E$13)/2)^9*F$60)/(1+$B$16)^9-$B$31)/$B$32 -> 339.80539 | G64: =($B$15*(Model_3S!$C$18*(1+($B$64+Assumptions!$E$13)/2)^9*G$60)/Model_3S!$L$22+$B$25*(Model_3S!$C$18*(1+($B$64+Assumptions!$E$13)/2)^9*G$60)/(1+$B$16)^9-$B$31)/$B$32 -> 352.98627
B65: 0.17 | C65: =($B$15*(Model_3S!$C$18*(1+($B$65+Assumptions!$E$13)/2)^9*C$60)/Model_3S!$L$22+$B$25*(Model_3S!$C$18*(1+($B$65+Assumptions!$E$13)/2)^9*C$60)/(1+$B$16)^9-$B$31)/$B$32 -> 293.76677 | D65: =($B$15*(Model_3S!$C$18*(1+($B$65+Assumptions!$E$13)/2)^9*D$60)/Model_3S!$L$22+$B$25*(Model_3S!$C$18*(1+($B$65+Assumptions!$E$13)/2)^9*D$60)/(1+$B$16)^9-$B$31)/$B$32 -> 322.33434 | E65: =($B$15*(Model_3S!$C$18*(1+($B$65+Assumptions!$E$13)/2)^9*E$60)/Model_3S!$L$22+$B$25*(Model_3S!$C$18*(1+($B$65+Assumptions!$E$13)/2)^9*E$60)/(1+$B$16)^9-$B$31)/$B$32 -> 350.90191 | F65: =($B$15*(Model_3S!$C$18*(1+($B$65+Assumptions!$E$13)/2)^9*F$60)/Model_3S!$L$22+$B$25*(Model_3S!$C$18*(1+($B$65+Assumptions!$E$13)/2)^9*F$60)/(1+$B$16)^9-$B$31)/$B$32 -> 368.75665 | G65: =($B$15*(Model_3S!$C$18*(1+($B$65+Assumptions!$E$13)/2)^9*G$60)/Model_3S!$L$22+$B$25*(Model_3S!$C$18*(1+($B$65+Assumptions!$E$13)/2)^9*G$60)/(1+$B$16)^9-$B$31)/$B$32 -> 383.04043

Sheet Comps
A1: TRADING COMPARABLES — EDA / DESIGN SOFTWARE (July 2026; peer multiples estimated from public data)
A4: Company | B4: Ticker | C4: EV/Revenue | D4: EV/EBITDA | E4: Note
A5: Synopsys (incl. Ansys) | B5: SNPS | C5: 11 | D5: 28 | E5: e — closest comp; post-Ansys integration
A6: Autodesk | B6: ADSK | C6: 7 | D6: 25 | E6: e — design software, similar margin structure
A7: Microsoft | B7: MSFT | C7: 11.5 | D7: 22 | E7: e — mega-cap software quality benchmark
A8: Oracle | B8: ORCL | C8: 9 | D8: 18 | E8: e — mature enterprise software
A9: Cadence (self, current) | B9: CDNS | C9: =(Assumptions!B49*Assumptions!B37+DCF!B31)/Model_3S!C18 -> 15.020169 | D9: =(Assumptions!B49*Assumptions!B37+DCF!B31)/Model_3S!C22 -> 33.01136 | E9: computed below
A10: Peer median (ex-CDNS) | C10: =MEDIAN(C5:C8) -> 10 | D10: =MEDIAN(D5:D8) -> 23.5
A12: IMPLIED VALUE PER SHARE
A13: Method | B13: Low x | C13: High x | D13: Metric | E13: $/sh low | F13: $/sh high
A14: EV/Adj. EBITDA × FY2026E ($mm) | B14: 25 | C14: 35 | D14: =Model_3S!C22 -> 2809.625 | E14: =(B14*D14-DCF!$B$31)/Assumptions!$B$37 -> 248.48681 | F14: =(C14*D14-DCF!$B$31)/Assumptions!$B$37 -> 350.35864
A15: P/E × FY2026E non-GAAP EPS guide ($7.90) | B15: 35 | C15: 45 | D15: 7.9 | E15: =B15*D15 -> 276.5 | F15: =C15*D15 -> 355.5
A17: CDNS has traded 35-50x forward non-GAAP EPS for most of the AI-design cycle; band reflects that history and SNPS parity.

Sheet Precedents
A1: PRECEDENT TRANSACTIONS — EDA & ENGINEERING SOFTWARE M&A
A4: Date | B4: Acquirer | C4: Target | D4: EV ($mm) | E4: EV/Revenue | F4: Note
A5: Jan-2024 | B5: Synopsys | C5: Ansys | D5: 35000 | E5: 15.4 | F5: ~$2.27B revenue; closed 2025
A6: Oct-2024 | B6: Siemens | C6: Altair Engineering | D6: 10600 | E6: 15 | F6: e — simulation software
A7: Feb-2024 | B7: Renesas | C7: Altium | D7: 5900 | E7: 20 | F7: e — PCB design SaaS
A8: Mar-2024 | B8: Cadence | C8: BETA CAE | D8: 1240 | E8: 14 | F8: e — CAE simulation
A9: Nov-2016 | B9: Siemens | C9: Mentor Graphics | D9: 4500 | E9: 3.7 | F9: pre-AI-cycle EDA benchmark
A10: 2026 | B10: Cadence | C10: Hexagon (e) | D10: 3100 | E10: 19.4 | F10: e — implied from $160mm revenue contribution
A11: Median EV/Revenue | E11: =MEDIAN(E5:E10) -> 15.2
A13: APPLIED RANGE
A14: Modern EDA/engineering-software control deals cluster at 14–20x revenue — but those are for $1-35B targets. A CDNS takeover (~$100B+) has no real precedent; the band is applied at a size discount.
B15: Low | C15: High
A16: EV/Revenue applied to FY2026E | B16: 10 | C16: 15
A17: Implied EV | B17: =B16*Model_3S!C18 -> 61750 | C17: =C16*Model_3S!C18 -> 92625
A18: Implied value per share | B18: =(B17-DCF!$B$31)/Assumptions!$B$37 -> 217.70137 | C18: =(C17-DCF!$B$31)/Assumptions!$B$37 -> 329.64843

Sheet LBO
A1: LBO ANALYSIS — 5-YEAR HOLD (ENTRY END-FY2026, EXIT END-FY2031) ($mm)
A4: ENTRY & FINANCING
A5: Entry premium to current price | B5: 0.2
A6: Entry price per share | B6: =Assumptions!B49*(1+B5) -> 396.12
A7: Diluted shares (mm) | B7: =Assumptions!B37 -> 275.8
A8: Equity purchase price | B8: =B6*B7 -> 109249.9
A9: Plus: net debt assumed/refinanced | B9: =DCF!B31 -> 1707.9618
A10: Entry enterprise value | B10: =B8+B9 -> 110957.86
A11: Transaction fees (% of EV) | B11: 0.02
A12: FY2026E Adj. EBITDA (debt sizing basis) | B12: =Model_3S!C22 -> 2809.625
A13: Entry EV / EBITDA | B13: =B10/B12 -> 39.492052
A14: Debt tranche | B14: Multiple | C14: Rate | D14: Amount
A15: Term Loan B | B15: 4.5 | C15: 0.075 | D15: =B15*$B$12 -> 12643.312
A16: Senior notes | B16: 2 | C16: 0.09 | D16: =B16*$B$12 -> 5619.25
A17: Total new debt | B17: =B15+B16 -> 6.5 | D17: =D15+D16 -> 18262.562
A18: Sponsor equity = EV×(1+fees) − debt | B18: =B10*(1+B11)-D17 -> 94914.452
A20: DEBT PAYDOWN — 100% FCF SWEEP
B21: FY2027E | C21: FY2028E | D21: FY2029E | E21: FY2030E | F21: FY2031E
A22: Unlevered FCF (DCF sheet) | B22: =DCF!B10 -> 1854.9405 | C22: =DCF!C10 -> 2128.6518 | D22: =DCF!D10 -> 2427.8748 | E22: =DCF!E10 -> 2752.2732 | F22: =DCF!F10 -> 3100.9599
A23: Cash interest — TLB (beginning) | B23: =-$D$15*$C$15 -> -948.24844 | C23: =-B29*$C$15 -> -894.18579 | D23: =-C29*$C$15 -> -816.43212 | E23: =-D29*$C$15 -> -711.68814 | F23: =-E29*$C$15 -> -576.48675
A24: Cash interest — notes | B24: =-$D$16*$C$16 -> -505.7325 | C24: =-$D$16*$C$16 -> -505.7325 | D24: =-$D$16*$C$16 -> -505.7325 | E24: =-$D$16*$C$16 -> -505.7325 | F24: =-$D$16*$C$16 -> -505.7325
A25: Interest tax shield | B25: =-(B23+B24)*Assumptions!$B$38 -> 319.87581 | C25: =-(C23+C24)*Assumptions!$B$38 -> 307.98202 | D25: =-(D23+D24)*Assumptions!$B$38 -> 290.87622 | E25: =-(E23+E24)*Assumptions!$B$38 -> 267.83254 | F25: =-(F23+F24)*Assumptions!$B$38 -> 238.08824
A26: Levered FCF for paydown | B26: =MAX(0,B22+B23+B24+B25) -> 720.83535 | C26: =MAX(0,C22+C23+C24+C25) -> 1036.7156 | D26: =MAX(0,D22+D23+D24+D25) -> 1396.5864 | E26: =MAX(0,E22+E23+E24+E25) -> 1802.6851 | F26: =MAX(0,F22+F23+F24+F25) -> 2256.8289
A27: TLB — beginning | B27: =$D$15 -> 12643.312 | C27: =B29 -> 11922.477 | D27: =C29 -> 10885.762 | E27: =D29 -> 9489.1751 | F27: =E29 -> 7686.49
A28: TLB — (paydown) | B28: =-MIN(B27,B26) -> -720.83535 | C28: =-MIN(C27,C26) -> -1036.7156 | D28: =-MIN(D27,D26) -> -1396.5864 | E28: =-MIN(E27,E26) -> -1802.6851 | F28: =-MIN(F27,F26) -> -2256.8289
A29: TLB — ending | B29: =B27+B28 -> 11922.477 | C29: =C27+C28 -> 10885.762 | D29: =D27+D28 -> 9489.1751 | E29: =E27+E28 -> 7686.49 | F29: =F27+F28 -> 5429.6611
A30: Notes — ending (bullet) | B30: =$D$16 -> 5619.25 | C30: =$D$16 -> 5619.25 | D30: =$D$16 -> 5619.25 | E30: =$D$16 -> 5619.25 | F30: =$D$16 -> 5619.25
A31: Total debt — ending | B31: =B29+B30 -> 17541.727 | C31: =C29+C30 -> 16505.012 | D31: =D29+D30 -> 15108.425 | E31: =E29+E30 -> 13305.74 | F31: =F29+F30 -> 11048.911
A33: EXIT & RETURNS
A34: FY2031E Adj. EBITDA | B34: =Model_3S!H22 -> 5164.7337
A35: Exit EV/EBITDA multiple | B35: 20
A36: Exit enterprise value | B36: =B34*B35 -> 103294.67
A37: Less: exit net debt | B37: =-F31 -> -11048.911
A38: Exit equity value | B38: =B36+B37 -> 92245.762
A39: MOIC | B39: =B38/B18 -> 0.97188321
A40: IRR (5-yr) | B40: =(B38/B18)^(1/5)-1 -> -0.0056876916
A42: MAXIMUM ENTRY PRICE AT TARGET IRR THRESHOLDS (exit equity constant — debt sized on EBITDA, not price)
A43: Target IRR | B43: Max sponsor equity | C43: Implied entry EV | D43: Implied price/share | E43: Prem/(disc) to market
A44: 0.15 | B44: =$B$38/(1+A44)^5 -> 45862.447 | C44: =(B44+$D$17)/(1+$B$11) -> 62867.656 | D44: =(C44-$B$9)/$B$7 -> 221.75379 | E44: =D44/Assumptions!$B$49-1 -> -0.3282224
A45: 0.2 | B45: =$B$38/(1+A45)^5 -> 37071.503 | C45: =(B45+$D$17)/(1+$B$11) -> 54249.084 | D45: =(C45-$B$9)/$B$7 -> 190.50443 | E45: =D45/Assumptions!$B$49-1 -> -0.42288873
A46: 0.25 | B46: =$B$38/(1+A46)^5 -> 30227.091 | C46: =(B46+$D$17)/(1+$B$11) -> 47538.876 | D46: =(C46-$B$9)/$B$7 -> 166.17445 | E46: =D46/Assumptions!$B$49-1 -> -0.49659359
A47: 0.3 | B47: =$B$38/(1+A47)^5 -> 24844.466 | C47: =(B47+$D$17)/(1+$B$11) -> 42261.792 | D47: =(C47-$B$9)/$B$7 -> 147.04072 | E47: =D47/Assumptions!$B$49-1 -> -0.55455704
A49: A CDNS LBO would be the largest tech buyout ever attempted (~$110B at a 20% premium, ~40x EBITDA entry) — the table is the theoretical LBO floor, far below market, as expected for a premier compounder.

Sheet Monte_Carlo
A1: MONTE CARLO SIMULATION — 500 LIVE TRIALS (press F9 / recalc to refresh draws)
A2: Compact DCF per trial calibrated to the DCF sheet at base inputs; equity = PV(TV) + PV(FCF) − net debt.
A4: Distribution parameters — Normal(mean, σ)
A5: Variable | B5: Mean (linked) | C5: σ (input)
A6: FY2027 revenue growth | B6: =Assumptions!E12 -> 0.13 | C6: 0.03
A7: Terminal Adj. EBITDA margin (FY35) | B7: =Assumptions!F17-Assumptions!F18 -> 0.5 | C7: 0.03
A8: WACC | B8: =WACC!B20 -> 0.09732295 | C8: 0.0075
A9: Exit EV/EBITDA multiple | B9: =Assumptions!B48 -> 20 | C9: 3
A11: Calibration statics (linked)
A12: Base FY2035 Adj. EBITDA | B12: =Model_3S!L22 -> 7576.1851
A13: Base PV of explicit FCF (DCF) | B13: =DCF!B15 -> 18038.088
A14: Net debt FY2026E | B14: =DCF!B31 -> 1707.9618
A15: Diluted shares (mm) | B15: =Assumptions!B37 -> 275.8
A16: Current share price | B16: =Assumptions!B49 -> 330.1
A17: FY2035 growth (selected) | B17: =Assumptions!E13 -> 0.08
A18: FY2026E revenue | B18: =Model_3S!C18 -> 6175
A20: Simulation results ($/share)
A21: Mean | B21: =AVERAGE($K$41:$K$540) -> 295.07707
A22: Median | B22: =MEDIAN($K$41:$K$540) -> 289.98405
A23: Standard deviation | B23: =STDEV($K$41:$K$540) -> 61.182128
A24: 5th percentile | B24: =PERCENTILE($K$41:$K$540,0.05) -> 209.85822
A25: 25th percentile | B25: =PERCENTILE($K$41:$K$540,0.25) -> 251.32034
A26: 75th percentile | B26: =PERCENTILE($K$41:$K$540,0.75) -> 328.63057
A27: 95th percentile | B27: =PERCENTILE($K$41:$K$540,0.95) -> 403.9716
A28: P(value > current price) | B28: =COUNTIF($K$41:$K$540,">"&B16)/500 -> 0.244
A30: Scenario probability-weighted value (compact DCF per scenario)
A31: Scenario | B31: Probability | C31: Value / share
A32: Base | B32: =Assumptions!B8 -> 0.5 | C32: =($B$13*($B$18*(1+(Assumptions!B12+Assumptions!B13)/2)^9*(Assumptions!C17-Assumptions!C18))/$B$12+Assumptions!$B$48*($B$18*(1+(Assumptions!B12+Assumptions!B13)/2)^9*(Assumptions!C17-Assumptions!C18))/(1+$B$8)^9-$B$14)/$B$15 -> 297.66559
A33: Bull | B33: =Assumptions!C8 -> 0.3 | C33: =($B$13*($B$18*(1+(Assumptions!C12+Assumptions!C13)/2)^9*(Assumptions!D17-Assumptions!D18))/$B$12+Assumptions!$B$48*($B$18*(1+(Assumptions!C12+Assumptions!C13)/2)^9*(Assumptions!D17-Assumptions!D18))/(1+$B$8)^9-$B$14)/$B$15 -> 432.31858
A34: Bear | B34: =Assumptions!D8 -> 0.2 | C34: =($B$13*($B$18*(1+(Assumptions!D12+Assumptions!D13)/2)^9*(Assumptions!E17-Assumptions!E18))/$B$12+Assumptions!$B$48*($B$18*(1+(Assumptions!D12+Assumptions!D13)/2)^9*(Assumptions!E17-Assumptions!E18))/(1+$B$8)^9-$B$14)/$B$15 -> 155.01786
A35: Probability-weighted value | C35: =SUMPRODUCT(B32:B34,C32:C34) -> 309.53194
A39: TRIALS
A40: # | B40: g FY27 | C40: Term margin | D40: WACC | E40: Exit x | F40: Rev FY35 | G40: EBITDA FY35 | H40: PV(TV) | I40: PV(FCF) | J40: Equity | K40: $ / share | N40: Bin ($/sh) | O40: low | P40: high | Q40: Count
A41: 1 | B41: =NORMINV(RAND(),$B$6,$C$6) -> 0.12423542 | C41: =MAX(0.25,NORMINV(RAND(),$B$7,$C$7)) -> 0.48994198 | D41: =MAX(0.07,NORMINV(RAND(),$B$8,$C$8)) -> 0.10432478 | E41: =MAX(8,NORMINV(RAND(),$B$9,$C$9)) -> 18.751467 | F41: =$B$18*(1+(B41+$B$17)/2)^9 -> 14814.561 | G41: =F41*C41 -> 7258.2755 | H41: =E41*G41/(1+D41)^9 -> 55718.237 | I41: =$B$13*G41/$B$12*((1+$B$8)/(1+D41))^4.5 -> 16793.56 | J41: =H41+I41-$B$14 -> 70803.835 | K41: =J41/$B$15 -> 256.72166 | N41: <125 | O41: 100 | P41: 125 | Q41: =COUNTIF($K$41:$K$540,"<"&P41) -> 0
A42: 2 | B42: =NORMINV(RAND(),$B$6,$C$6) -> 0.14333475 | C42: =MAX(0.25,NORMINV(RAND(),$B$7,$C$7)) -> 0.52287731 | D42: =MAX(0.07,NORMINV(RAND(),$B$8,$C$8)) -> 0.093204242 | E42: =MAX(8,NORMINV(RAND(),$B$9,$C$9)) -> 18.767401 | F42: =$B$18*(1+(B42+$B$17)/2)^9 -> 16010.714 | G42: =F42*C42 -> 8371.6391 | H42: =E42*G42/(1+D42)^9 -> 70453.546 | I42: =$B$13*G42/$B$12*((1+$B$8)/(1+D42))^4.5 -> 20272.141 | J42: =H42+I42-$B$14 -> 89017.724 | K42: =J42/$B$15 -> 322.76187 | N42: 125-150 | O42: 125 | P42: 150 | Q42: =COUNTIFS($K$41:$K$540,">="&O42,$K$41:$K$540,"<"&P42) -> 1
A43: 3 | B43: =NORMINV(RAND(),$B$6,$C$6) -> 0.11887506 | C43: =MAX(0.25,NORMINV(RAND(),$B$7,$C$7)) -> 0.51268571 | D43: =MAX(0.07,NORMINV(RAND(),$B$8,$C$8)) -> 0.096340537 | E43: =MAX(8,NORMINV(RAND(),$B$9,$C$9)) -> 17.883727 | F43: =$B$18*(1+(B43+$B$17)/2)^9 -> 14493.457 | G43: =F43*C43 -> 7430.5884 | H43: =E43*G43/(1+D43)^9 -> 58072.695 | I43: =$B$13*G43/$B$12*((1+$B$8)/(1+D43))^4.5 -> 17762.888 | J43: =H43+I43-$B$14 -> 74127.621 | K43: =J43/$B$15 -> 268.7731 | N43: 150-175 | O43: 150 | P43: 175 | Q43: =COUNTIFS($K$41:$K$540,">="&O43,$K$41:$K$540,"<"&P43) -> 2
A44: 4 | B44: =NORMINV(RAND(),$B$6,$C$6) -> 0.13143866 | C44: =MAX(0.25,NORMINV(RAND(),$B$7,$C$7)) -> 0.49417952 | D44: =MAX(0.07,NORMINV(RAND(),$B$8,$C$8)) -> 0.11272974 | E44: =MAX(8,NORMINV(RAND(),$B$9,$C$9)) -> 22.471805 | F44: =$B$18*(1+(B44+$B$17)/2)^9 -> 15256.014 | G44: =F44*C44 -> 7539.2095 | H44: =E44*G44/(1+D44)^9 -> 64782.32 | I44: =$B$13*G44/$B$12*((1+$B$8)/(1+D44))^4.5 -> 16858.432 | J44: =H44+I44-$B$14 -> 79932.79 | K44: =J44/$B$15 -> 289.82157 | N44: 175-200 | O44: 175 | P44: 200 | Q44: =COUNTIFS($K$41:$K$540,">="&O44,$K$41:$K$540,"<"&P44) -> 13
A45: 5 | B45: =NORMINV(RAND(),$B$6,$C$6) -> 0.1115909 | C45: =MAX(0.25,NORMINV(RAND(),$B$7,$C$7)) -> 0.51254878 | D45: =MAX(0.07,NORMINV(RAND(),$B$8,$C$8)) -> 0.09724733 | E45: =MAX(8,NORMINV(RAND(),$B$9,$C$9)) -> 15.227909 | F45: =$B$18*(1+(B45+$B$17)/2)^9 -> 14067.029 | G45: =F45*C45 -> 7210.0386 | H45: =E45*G45/(1+D45)^9 -> 47625.23 | I45: =$B$13*G45/$B$12*((1+$B$8)/(1+D45))^4.5 -> 17171.656 | J45: =H45+I45-$B$14 -> 63088.924 | K45: =J45/$B$15 -> 228.74882 | N45: 200-225 | O45: 200 | P45: 225 | Q45: =COUNTIFS($K$41:$K$540,">="&O45,$K$41:$K$540,"<"&P45) -> 38
A46: 6 | B46: =NORMINV(RAND(),$B$6,$C$6) -> 0.098106629 | C46: =MAX(0.25,NORMINV(RAND(),$B$7,$C$7)) -> 0.46808953 | D46: =MAX(0.07,NORMINV(RAND(),$B$8,$C$8)) -> 0.088661927 | E46: =MAX(8,NORMINV(RAND(),$B$9,$C$9)) -> 22.149681 | F46: =$B$18*(1+(B46+$B$17)/2)^9 -> 13306.972 | G46: =F46*C46 -> 6228.8541 | H46: =E46*G46/(1+D46)^9 -> 64230.059 | I46: =$B$13*G46/$B$12*((1+$B$8)/(1+D46))^4.5 -> 15368.607 | J46: =H46+I46-$B$14 -> 77890.704 | K46: =J46/$B$15 -> 282.41735 | N46: 225-250 | O46: 225 | P46: 250 | Q46: =COUNTIFS($K$41:$K$540,">="&O46,$K$41:$K$540,"<"&P46) -> 68
A47: 7 | B47: =NORMINV(RAND(),$B$6,$C$6) -> 0.12155337 | C47: =MAX(0.25,NORMINV(RAND(),$B$7,$C$7)) -> 0.53613145 | D47: =MAX(0.07,NORMINV(RAND(),$B$8,$C$8)) -> 0.10814294 | E47: =MAX(8,NORMINV(RAND(),$B$9,$C$9)) -> 14.9526 | F47: =$B$18*(1+(B47+$B$17)/2)^9 -> 14653.115 | G47: =F47*C47 -> 7855.9959 | H47: =E47*G47/(1+D47)^9 -> 46618.242 | I47: =$B$13*G47/$B$12*((1+$B$8)/(1+D47))^4.5 -> 17896.381 | J47: =H47+I47-$B$14 -> 62806.661 | K47: =J47/$B$15 -> 227.72538 | N47: 250-275 | O47: 250 | P47: 275 | Q47: =COUNTIFS($K$41:$K$540,">="&O47,$K$41:$K$540,"<"&P47) -> 76
A48: 8 | B48: =NORMINV(RAND(),$B$6,$C$6) -> 0.15120065 | C48: =MAX(0.25,NORMINV(RAND(),$B$7,$C$7)) -> 0.4539031 | D48: =MAX(0.07,NORMINV(RAND(),$B$8,$C$8)) -> 0.092560141 | E48: =MAX(8,NORMINV(RAND(),$B$9,$C$9)) -> 21.817516 | F48: =$B$18*(1+(B48+$B$17)/2)^9 -> 16527.785 | G48: =F48*C48 -> 7502.0127 | H48: =E48*G48/(1+D48)^9 -> 73786.162 | I48: =$B$13*G48/$B$12*((1+$B$8)/(1+D48))^4.5 -> 18214.561 | J48: =H48+I48-$B$14 -> 90292.761 | K48: =J48/$B$15 -> 327.38492 | N48: 275-300 | O48: 275 | P48: 300 | Q48: =COUNTIFS($K$41:$K$540,">="&O48,$K$41:$K$540,"<"&P48) -> 92
A49: 9 | B49: =NORMINV(RAND(),$B$6,$C$6) -> 0.21153068 | C49: =MAX(0.25,NORMINV(RAND(),$B$7,$C$7)) -> 0.48898166 | D49: =MAX(0.07,NORMINV(RAND(),$B$8,$C$8)) -> 0.099658196 | E49: =MAX(8,NORMINV(RAND(),$B$9,$C$9)) -> 21.830589 | F49: =$B$18*(1+(B49+$B$17)/2)^9 -> 21013.485 | G49: =F49*C49 -> 10275.209 | H49: =E49*G49/(1+D49)^9 -> 95397.43 | I49: =$B$13*G49/$B$12*((1+$B$8)/(1+D49))^4.5 -> 24231.256 | J49: =H49+I49-$B$14 -> 117920.72 | K49: =J49/$B$15 -> 427.55883 | N49: 300-325 | O49: 300 | P49: 325 | Q49: =COUNTIFS($K$41:$K$540,">="&O49,$K$41:$K$540,"<"&P49) -> 76
A50: 10 | B50: =NORMINV(RAND(),$B$6,$C$6) -> 0.13697865 | C50: =MAX(0.25,NORMINV(RAND(),$B$7,$C$7)) -> 0.49939956 | D50: =MAX(0.07,NORMINV(RAND(),$B$8,$C$8)) -> 0.098923622 | E50: =MAX(8,NORMINV(RAND(),$B$9,$C$9)) -> 25.966299 | F50: =$B$18*(1+(B50+$B$17)/2)^9 -> 15603.448 | G50: =F50*C50 -> 7792.3552 | H50: =E50*G50/(1+D50)^9 -> 86570.757 | I50: =$B$13*G50/$B$12*((1+$B$8)/(1+D50))^4.5 -> 18431.469 | J50: =H50+I50-$B$14 -> 103294.26 | K50: =J50/$B$15 -> 374.52598 | N50: 325-350 | O50: 325 | P50: 350 | Q50: =COUNTIFS($K$41:$K$540,">="&O50,$K$41:$K$540,"<"&P50) -> 45
A51: 11 | B51: =NORMINV(RAND(),$B$6,$C$6) -> 0.13428342 | C51: =MAX(0.25,NORMINV(RAND(),$B$7,$C$7)) -> 0.54161358 | D51: =MAX(0.07,NORMINV(RAND(),$B$8,$C$8)) -> 0.10598951 | E51: =MAX(8,NORMINV(RAND(),$B$9,$C$9)) -> 18.511658 | F51: =$B$18*(1+(B51+$B$17)/2)^9 -> 15433.552 | G51: =F51*C51 -> 8359.0212 | H51: =E51*G51/(1+D51)^9 -> 62494.481 | I51: =$B$13*G51/$B$12*((1+$B$8)/(1+D51))^4.5 -> 19209.713 | J51: =H51+I51-$B$14 -> 79996.232 | K51: =J51/$B$15 -> 290.0516 | N51: 350-375 | O51: 350 | P51: 375 | Q51: =COUNTIFS($K$41:$K$540,">="&O51,$K$41:$K$540,"<"&P51) -> 38
A52: 12 | B52: =NORMINV(RAND(),$B$6,$C$6) -> 0.11623703 | C52: =MAX(0.25,NORMINV(RAND(),$B$7,$C$7)) -> 0.49383363 | D52: =MAX(0.07,NORMINV(RAND(),$B$8,$C$8)) -> 0.099792007 | E52: =MAX(8,NORMINV(RAND(),$B$9,$C$9)) -> 21.621807 | F52: =$B$18*(1+(B52+$B$17)/2)^9 -> 14337.713 | G52: =F52*C52 -> 7080.4449 | H52: =E52*G52/(1+D52)^9 -> 65036.552 | I52: =$B$13*G52/$B$12*((1+$B$8)/(1+D52))^4.5 -> 16688.144 | J52: =H52+I52-$B$14 -> 80016.734 | K52: =J52/$B$15 -> 290.12594 | N52: 375-400 | O52: 375 | P52: 400 | Q52: =COUNTIFS($K$41:$K$540,">="&O52,$K$41:$K$540,"<"&P52) -> 23
A53: 13 | B53: =NORMINV(RAND(),$B$6,$C$6) -> 0.14771294 | C53: =MAX(0.25,NORMINV(RAND(),$B$7,$C$7)) -> 0.53444656 | D53: =MAX(0.07,NORMINV(RAND(),$B$8,$C$8)) -> 0.083039262 | E53: =MAX(8,NORMINV(RAND(),$B$9,$C$9)) -> 19.955212 | F53: =$B$18*(1+(B53+$B$17)/2)^9 -> 16296.714 | G53: =F53*C53 -> 8709.7229 | H53: =E53*G53/(1+D53)^9 -> 84774.039 | I53: =$B$13*G53/$B$12*((1+$B$8)/(1+D53))^4.5 -> 21996.34 | J53: =H53+I53-$B$14 -> 105062.42 | K53: =J53/$B$15 -> 380.93697 | N53: 400-425 | O53: 400 | P53: 425 | Q53: =COUNTIFS($K$41:$K$540,">="&O53,$K$41:$K$540,"<"&P53) -> 15
... A60: 20 | B60: =NORMINV(RAND(),$B$6,$C$6) -> 0.16088232 | C60: =MAX(0.25,NORMINV(RAND(),$B$7,$C$7)) -> 0.53624227 | D60: =MAX(0.07,NORMINV(RAND(),$B$8,$C$8)) -> 0.10407651 | E60: =MAX(8,NORMINV(RAND(),$B$9,$C$9)) -> 17.513869 | F60: =$B$18*(1+(B60+$B$17)/2)^9 -> 17184.561 | G60: =F60*C60 -> 9215.0881 | H60: =E60*G60/(1+D60)^9 -> 66204.736 | I60: =$B$13*G60/$B$12*((1+$B$8)/(1+D60))^4.5 -> 21342.644 | J60: =H60+I60-$B$14 -> 85839.419 | K60: =J60/$B$15 -> 311.23792 | N60: 575-600 | O60: 575 | P60: 600 | Q60: =COUNTIFS($K$41:$K$540,">="&O60,$K$41:$K$540,"<"&P60) -> 0
A61: 21 | B61: =NORMINV(RAND(),$B$6,$C$6) -> 0.14653008 | C61: =MAX(0.25,NORMINV(RAND(),$B$7,$C$7)) -> 0.52757127 | D61: =MAX(0.07,NORMINV(RAND(),$B$8,$C$8)) -> 0.092156064 | E61: =MAX(8,NORMINV(RAND(),$B$9,$C$9)) -> 20.081275 | F61: =$B$18*(1+(B61+$B$17)/2)^9 -> 16219.001 | G61: =F61*C61 -> 8556.6789 | H61: =E61*G61/(1+D61)^9 -> 77720.252 | I61: =$B$13*G61/$B$12*((1+$B$8)/(1+D61))^4.5 -> 20809.856 | J61: =H61+I61-$B$14 -> 96822.146 | K61: =J61/$B$15 -> 351.05927 | N61: 600+ | O61: 600 | P61: 625 | Q61: =COUNTIF($K$41:$K$540,">="&O61) -> 1
A62: 22 | B62: =NORMINV(RAND(),$B$6,$C$6) -> 0.18417822 | C62: =MAX(0.25,NORMINV(RAND(),$B$7,$C$7)) -> 0.49583341 | D62: =MAX(0.07,NORMINV(RAND(),$B$8,$C$8)) -> 0.098746429 | E62: =MAX(8,NORMINV(RAND(),$B$9,$C$9)) -> 22.484762 | F62: =$B$18*(1+(B62+$B$17)/2)^9 -> 18860.903 | G62: =F62*C62 -> 9351.866 | H62: =E62*G62/(1+D62)^9 -> 90096.784 | I62: =$B$13*G62/$B$12*((1+$B$8)/(1+D62))^4.5 -> 22136.279 | J62: =H62+I62-$B$14 -> 110525.1 | K62: =J62/$B$15 -> 400.74366
A63: 23 | B63: =NORMINV(RAND(),$B$6,$C$6) -> 0.14103775 | C63: =MAX(0.25,NORMINV(RAND(),$B$7,$C$7)) -> 0.56010576 | D63: =MAX(0.07,NORMINV(RAND(),$B$8,$C$8)) -> 0.10435652 | E63: =MAX(8,NORMINV(RAND(),$B$9,$C$9)) -> 12.628936 | F63: =$B$18*(1+(B63+$B$17)/2)^9 -> 15862.457 | G63: =F63*C63 -> 8884.6535 | H63: =E63*G63/(1+D63)^9 -> 45922.292 | I63: =$B$13*G63/$B$12*((1+$B$8)/(1+D63))^4.5 -> 20553.872 | J63: =H63+I63-$B$14 -> 64768.202 | K63: =J63/$B$15 -> 234.83757
A64: 24 | B64: =NORMINV(RAND(),$B$6,$C$6) -> 0.14203791 | C64: =MAX(0.25,NORMINV(RAND(),$B$7,$C$7)) -> 0.51368309 | D64: =MAX(0.07,NORMINV(RAND(),$B$8,$C$8)) -> 0.10062539 | E64: =MAX(8,NORMINV(RAND(),$B$9,$C$9)) -> 21.576205 | F64: =$B$18*(1+(B64+$B$17)/2)^9 -> 15926.861 | G64: =F64*C64 -> 8181.3589 | H64: =E64*G64/(1+D64)^9 -> 74480.874 | I64: =$B$13*G64/$B$12*((1+$B$8)/(1+D64))^4.5 -> 19217.309 | J64: =H64+I64-$B$14 -> 91990.222 | K64: =J64/$B$15 -> 333.5396
A65: 25 | B65: =NORMINV(RAND(),$B$6,$C$6) -> 0.066762694 | C65: =MAX(0.25,NORMINV(RAND(),$B$7,$C$7)) -> 0.46498314 | D65: =MAX(0.07,NORMINV(RAND(),$B$8,$C$8)) -> 0.09317449 | E65: =MAX(8,NORMINV(RAND(),$B$9,$C$9)) -> 25.710666 | F65: =$B$18*(1+(B65+$B$17)/2)^9 -> 11679.476 | G65: =F65*C65 -> 5430.7595 | H65: =E65*G65/(1+D65)^9 -> 62627.994 | I65: =$B$13*G65/$B$12*((1+$B$8)/(1+D65))^4.5 -> 13152.335 | J65: =H65+I65-$B$14 -> 74072.367 | K65: =J65/$B$15 -> 268.57276
A66: 26 | B66: =NORMINV(RAND(),$B$6,$C$6) -> 0.11029219 | C66: =MAX(0.25,NORMINV(RAND(),$B$7,$C$7)) -> 0.48092462 | D66: =MAX(0.07,NORMINV(RAND(),$B$8,$C$8)) -> 0.095377648 | E66: =MAX(8,NORMINV(RAND(),$B$9,$C$9)) -> 23.648612 | F66: =$B$18*(1+(B66+$B$17)/2)^9 -> 13992.184 | G66: =F66*C66 -> 6729.1856 | H66: =E66*G66/(1+D66)^9 -> 70096.009 | I66: =$B$13*G66/$B$12*((1+$B$8)/(1+D66))^4.5 -> 16149.909 | J66: =H66+I66-$B$14 -> 84537.955 | K66: =J66/$B$15 -> 306.51905
A67: 27 | B67: =NORMINV(RAND(),$B$6,$C$6) -> 0.098673086 | C67: =MAX(0.25,NORMINV(RAND(),$B$7,$C$7)) -> 0.48490139 | D67: =MAX(0.07,NORMINV(RAND(),$B$8,$C$8)) -> 0.11015675 | E67: =MAX(8,NORMINV(RAND(),$B$9,$C$9)) -> 22.015741 | F67: =$B$18*(1+(B67+$B$17)/2)^9 -> 13338.151 | G67: =F67*C67 -> 6467.6878 | H67: =E67*G67/(1+D67)^9 -> 55593.452 | I67: =$B$13*G67/$B$12*((1+$B$8)/(1+D67))^4.5 -> 14613.851 | J67: =H67+I67-$B$14 -> 68499.341 | K67: =J67/$B$15 -> 248.366
A68: 28 | B68: =NORMINV(RAND(),$B$6,$C$6) -> 0.15591967 | C68: =MAX(0.25,NORMINV(RAND(),$B$7,$C$7)) -> 0.50960313 | D68: =MAX(0.07,NORMINV(RAND(),$B$8,$C$8)) -> 0.09748444 | E68: =MAX(8,NORMINV(RAND(),$B$9,$C$9)) -> 20.967505 | F68: =$B$18*(1+(B68+$B$17)/2)^9 -> 16845.068 | G68: =F68*C68 -> 8584.2996 | H68: =E68*G68/(1+D68)^9 -> 77923.109 | I68: =$B$13*G68/$B$12*((1+$B$8)/(1+D68))^4.5 -> 20424.771 | J68: =H68+I68-$B$14 -> 96639.918 | K68: =J68/$B$15 -> 350.39854
A69: 29 | B69: =NORMINV(RAND(),$B$6,$C$6) -> 0.1041361 | C69: =MAX(0.25,NORMINV(RAND(),$B$7,$C$7)) -> 0.52948238 | D69: =MAX(0.07,NORMINV(RAND(),$B$8,$C$8)) -> 0.1066947 | E69: =MAX(8,NORMINV(RAND(),$B$9,$C$9)) -> 22.578158 | F69: =$B$18*(1+(B69+$B$17)/2)^9 -> 13642.196 | G69: =F69*C69 -> 7223.3021 | H69: =E69*G69/(1+D69)^9 -> 65489.82 | I69: =$B$13*G69/$B$12*((1+$B$8)/(1+D69))^4.5 -> 16552.193 | J69: =H69+I69-$B$14 -> 80334.051 | K69: =J69/$B$15 -> 291.27647
A70: 30 | B70: =NORMINV(RAND(),$B$6,$C$6) -> 0.098933928 | C70: =MAX(0.25,NORMINV(RAND(),$B$7,$C$7)) -> 0.46305697 | D70: =MAX(0.07,NORMINV(RAND(),$B$8,$C$8)) -> 0.1130724 | E70: =MAX(8,NORMINV(RAND(),$B$9,$C$9)) -> 20.901606 | F70: =$B$18*(1+(B70+$B$17)/2)^9 -> 13352.53 | G70: =F70*C70 -> 6182.9819 | H70: =E70*G70/(1+D70)^9 -> 49279.571 | I70: =$B$13*G70/$B$12*((1+$B$8)/(1+D70))^4.5 -> 13806.628 | J70: =H70+I70-$B$14 -> 61378.237 | K70: =J70/$B$15 -> 222.54618
A71: 31 | B71: =NORMINV(RAND(),$B$6,$C$6) -> 0.15567386 | C71: =MAX(0.25,NORMINV(RAND(),$B$7,$C$7)) -> 0.47135736 | D71: =MAX(0.07,NORMINV(RAND(),$B$8,$C$8)) -> 0.086790015 | E71: =MAX(8,NORMINV(RAND(),$B$9,$C$9)) -> 17.359615 | F71: =$B$18*(1+(B71+$B$17)/2)^9 -> 16828.408 | G71: =F71*C71 -> 7932.1941 | H71: =E71*G71/(1+D71)^9 -> 65106.246 | I71: =$B$13*G71/$B$12*((1+$B$8)/(1+D71))^4.5 -> 19723.453 | J71: =H71+I71-$B$14 -> 83121.737 | K71: =J71/$B$15 -> 301.38411
A72: 32 | B72: =NORMINV(RAND(),$B$6,$C$6) -> 0.1030855 | C72: =MAX(0.25,NORMINV(RAND(),$B$7,$C$7)) -> 0.50647151 | D72: =MAX(0.07,NORMINV(RAND(),$B$8,$C$8)) -> 0.091220902 | E72: =MAX(8,NORMINV(RAND(),$B$9,$C$9)) -> 17.200036 | F72: =$B$18*(1+(B72+$B$17)/2)^9 -> 13583.25 | G72: =F72*C72 -> 6879.5292 | H72: =E72*G72/(1+D72)^9 -> 53935.409 | I72: =$B$13*G72/$B$12*((1+$B$8)/(1+D72))^4.5 -> 16795.645 | J72: =H72+I72-$B$14 -> 69023.092 | K72: =J72/$B$15 -> 250.26502
A73: 33 | B73: =NORMINV(RAND(),$B$6,$C$6) -> 0.14870373 | C73: =MAX(0.25,NORMINV(RAND(),$B$7,$C$7)) -> 0.47642393 | D73: =MAX(0.07,NORMINV(RAND(),$B$8,$C$8)) -> 0.10034937 | E73: =MAX(8,NORMINV(RAND(),$B$9,$C$9)) -> 17.067797 | F73: =$B$18*(1+(B73+$B$17)/2)^9 -> 16362.063 | G73: =F73*C73 -> 7795.2783 | H73: =E73*G73/(1+D73)^9 -> 56264.4 | I73: =$B$13*G73/$B$12*((1+$B$8)/(1+D73))^4.5 -> 18331.117 | J73: =H73+I73-$B$14 -> 72887.555 | K73: =J73/$B$15 -> 264.27685
... A540: 500 | B540: =NORMINV(RAND(),$B$6,$C$6) -> 0.116377 | C540: =MAX(0.25,NORMINV(RAND(),$B$7,$C$7)) -> 0.46144779 | D540: =MAX(0.07,NORMINV(RAND(),$B$8,$C$8)) -> 0.10664278 | E540: =MAX(8,NORMINV(RAND(),$B$9,$C$9)) -> 17.173723 | F540: =$B$18*(1+(B540+$B$17)/2)^9 -> 14345.939 | G540: =F540*C540 -> 6619.902 | H540: =E540*G540/(1+D540)^9 -> 45671.881 | I540: =$B$13*G540/$B$12*((1+$B$8)/(1+D540))^4.5 -> 15172.705 | J540: =H540+I540-$B$14 -> 59136.624 | K540: =J540/$B$15 -> 214.41851

Sheet Football_Field
A1: FOOTBALL FIELD — VALUATION SUMMARY ($ per share)
A2: =CONCATENATE("Current price: $",TEXT(Assumptions!B49,"0.00")," · Scenario: ",CHOOSE(Assumptions!B4,"BASE","BULL","BEAR")," · Probability-weighted value: $",TEXT(Monte_Carlo!C35,"0.00")) -> Current price: $330.10 · Scenario: BASE · Probability-weighted value: $309.53
A4: Methodology | B4: Low | C4: High | D4: (base) | E4: (span) | F4: Midpoint
A5: 52-week trading range | B5: 262.75 | C5: 416.69 | D5: =B5 -> 262.75 | E5: =C5-B5 -> 153.94 | F5: =(B5+C5)/2 -> 339.72
A6: Analyst targets (avg $387, n=32; low e) | B6: 340 | C6: 432 | D6: =B6 -> 340 | E6: =C6-B6 -> 92 | F6: =(B6+C6)/2 -> 386
A7: DCF — Gordon growth (WACC ±0.5%, g 3.0–4.0%) | B7: =(SUMPRODUCT(DCF!$B$10:$J$10,(1+(WACC!$B$20+0.005))^-DCF!$B$11:$J$11)+DCF!$J$10*(1+0.03)/((WACC!$B$20+0.005)-0.03)/(1+(WACC!$B$20+0.005))^9-DCF!$B$31)/DCF!$B$32 -> 158.81377 | C7: =(SUMPRODUCT(DCF!$B$10:$J$10,(1+(WACC!$B$20-0.005))^-DCF!$B$11:$J$11)+DCF!$J$10*(1+0.04)/((WACC!$B$20-0.005)-0.04)/(1+(WACC!$B$20-0.005))^9-DCF!$B$31)/DCF!$B$32 -> 213.58189 | D7: =B7 -> 158.81377 | E7: =C7-B7 -> 54.768126 | F7: =(B7+C7)/2 -> 186.19783
A8: DCF — exit multiple (17.5–22.5x, WACC ±0.5%) | B8: =(SUMPRODUCT(DCF!$B$10:$J$10,(1+(WACC!$B$20+0.005))^-DCF!$B$11:$J$11)+17.5*Model_3S!$L$22/(1+(WACC!$B$20+0.005))^9-DCF!$B$31)/DCF!$B$32 -> 257.88444 | C8: =(SUMPRODUCT(DCF!$B$10:$J$10,(1+(WACC!$B$20-0.005))^-DCF!$B$11:$J$11)+22.5*Model_3S!$L$22/(1+(WACC!$B$20-0.005))^9-DCF!$B$31)/DCF!$B$32 -> 339.79604 | D8: =B8 -> 257.88444 | E8: =C8-B8 -> 81.911595 | F8: =(B8+C8)/2 -> 298.84024
A9: Trading comps — EV/EBITDA (25–35x FY26E) | B9: =Comps!E14 -> 248.48681 | C9: =Comps!F14 -> 350.35864 | D9: =B9 -> 248.48681 | E9: =C9-B9 -> 101.87183 | F9: =(B9+C9)/2 -> 299.42273
A10: Trading comps — P/E (35–45x FY26E non-GAAP EPS) | B10: =Comps!E15 -> 276.5 | C10: =Comps!F15 -> 355.5 | D10: =B10 -> 276.5 | E10: =C10-B10 -> 79 | F10: =(B10+C10)/2 -> 316
A11: Precedent transactions (10–15x FY26E revenue) | B11: =Precedents!B18 -> 217.70137 | C11: =Precedents!C18 -> 329.64843 | D11: =B11 -> 217.70137 | E11: =C11-B11 -> 111.94706 | F11: =(B11+C11)/2 -> 273.6749
A12: LBO capacity (25% → 15% IRR) | B12: =LBO!D46 -> 166.17445 | C12: =LBO!D44 -> 221.75379 | D12: =B12 -> 166.17445 | E12: =C12-B12 -> 55.579333 | F12: =(B12+C12)/2 -> 193.96412
A13: Monte Carlo P25–P75 (live) | B13: =Monte_Carlo!B25 -> 251.32034 | C13: =Monte_Carlo!B26 -> 328.63057 | D13: =B13 -> 251.32034 | E13: =C13-B13 -> 77.310232 | F13: =(B13+C13)/2 -> 289.97546
A14: Current price (marker) | B14: =Assumptions!B49-3 -> 327.1 | C14: =Assumptions!B49+3 -> 333.1 | D14: =B14 -> 327.1 | E14: =C14-B14 -> 6 | F14: =(B14+C14)/2 -> 330.1
A16: 52-wk range: macrotrends. Analyst target: 32-analyst avg $387, high $432 (Stifel); low end of band estimated. All other rows are live model outputs.
