Workbook

Sheet Summary
A1: DIVERSIFICATION CANDIDATES — TOP PICK PER SECTOR THAT FIXES YOUR AI CONCENTRATION
A2: Your account is ~95% AI-correlated. These three sit OUTSIDE that cluster. Each has its own scenario-DCF sheet. Prices 7/22-24/2026.
A4: Sector (your gap) | B4: Top pick | C4: Price | D4: Weighted value | E4: Weighted upside | F4: AI correlation | G4: Why this one
A5: Healthcare | B5: LLY | C5: =LLY_DCF!B5 -> 1165.98 | D5: =LLY_DCF!B38 -> 1040.9234 | E5: =LLY_DCF!B39 -> -0.10725447 | F5: Very low | G5: GLP-1 growth juggernaut; aging-demographic tailwind independent of AI capex. Premium price — buy for growth+de-correlation, not cheapness.
A6: Payments / Financials | B6: V | C6: =V_DCF!B5 -> 350.94 | D6: =V_DCF!B38 -> 335.4612 | E6: =V_DCF!B39 -> -0.044106675 | F6: Low | G6: The duopoly toll-booth you already understand from EDA — ~67% margins, grows with global commerce, different cycle entirely.
A7: Consumer defensive | B7: COST | C7: =COST_DCF!B5 -> 925 | D7: =COST_DCF!B38 -> 429.05691 | E7: =COST_DCF!B39 -> -0.53615469 | F7: Very low | G7: Membership moat, recession-resilient compounder. Chronically 'expensive' on DCF; the return is durability, not a discount.
A9: HOW TO USE THIS
A10: These are DIVERSIFIERS, not cheap-stock bets. Unlike SNPS (+19% because it's fear-discounted), premium compounders like LLY/V/COST usually read 'fairly-to-richly valued' on a DCF — you buy them to de-correlate a 95%-AI book and add a second growth engine, accepting a full-ish price for quality. The weighted-upside numbers will be modest by design.
A11: Fund them with NEW money, not by selling SNPS/VST. A clean way in: carve one lane out of your weekly $100 (e.g. add $20/wk to a healthcare or payments name), or route a future contribution bump. Start with ONE — probably V (fits your duopoly instinct) or LLY (biggest de-correlation) — not all three at once.
A12: The single highest-impact diversifier is still a broad index (VTI total-market or VXUS ex-US) — it fixes concentration AND the missing sectors in one ticket, and it's the honest answer to the BND question from before. A single stock diversifies the SECTOR; an index diversifies the SINGLE-STOCK RISK too.
A13: On your CURRENT holdings (see 'Add_To_Current' tab): the only strong add is SNPS, already covered by your DCA. So new capital is better spent widening the base than deepening the AI bet.

Sheet Add_To_Current
A1: WHAT TO ADD TO — YOUR 7 CURRENT HOLDINGS, RANKED BY ADD-PRIORITY (from the full models)
A4: Priority | B4: Holding | C4: Current weight | D4: Weighted value vs price | E4: Verdict | F4: Why
A5: ADD | B5: SNPS | C5: 0.11 | D5: 0.19 | E5: KEEP ADDING | F5: Best risk/reward you own — EDA duopoly at a fear discount, +19% weighted, near 52-wk low. Your $40/wk DCA already funds this. This is your #1 add, full stop.
A6: HOLD | B6: VST | C6: 0.06 | D6: 0.1 | E6: KEEP DCA, DON'T CHASE | F6: Re-rated $155→$166, now ~fair vs ~$180 model. Still your diversifier — keep the $40/wk, but it's accumulate-not-pounce.
A7: HOLD | B7: META | C7: 0.1 | D7: 0.05 | E7: SMALL DCA OK | F7: ~Fair value; best AI-bust floor (net cash + ads). Your $20/wk is fine. Not a conviction add at this price.
A8: WATCH | B8: NOW | C8: 0.15 | D8: 0.5 | E8: HOLD, DON'T ADD YET | F8: Screens +50-73% cheap AND near lows — tempting — but the bear case (agents eating seat-based SaaS) is STRUCTURAL. Solid Q2 says hold; wait 2 quarters of seat/renewal data before adding to a 15% position.
A9: TRIM | B9: GOOGL | C9: 0.26 | D9: 0.09 | E9: DON'T ADD — TRIM CANDIDATE | F9: Quality, but 26% of the account and part of the 53% block. Adding deepens concentration. Trim toward 25% at the annual check, don't add.
A10: TRIM | B10: NVDA | C10: 0.27 | D10: 0.11 | E10: DON'T ADD — TRIM CANDIDATE | F10: Highest-variance name at 27%. You're already maximally exposed. This is a trim-if->30% name, never an add.
A11: CASH | B11: SPAXX | C11: 0.05 | E11: EARMARKED | F11: Dry powder for the Nov/Dec SpaceX window. Leave it.
A13: Bottom line on adds: your ONLY strong add among current holdings is SNPS — which your DCA already covers. NOW is a 'watch, not add'. Everything else is hold or trim. That's WHY the real opportunity is new-sector diversification (next sheets), not piling more into a 95%-AI book.

Sheet LLY_DCF
A1: Eli Lilly (LLY) — SCENARIO DCF ($mm except per share)
A2: Rev35 = rev26×(1+avg(g27,g35))^9; FCF = EBITDA×0.79 − capex; interim = avg(FCF26,FCF35)×9-yr annuity; TV = avg(exit-multiple, Gordon), PV@9y; equity = EV + net cash. Same engine as the ranking/stress-test files.
A4: MARKET & COMPANY INPUTS
A5: Current share price | B5: 1165.98
A6: Diluted shares (mm) | B6: 941.74
A7: Net cash / (net debt) ($mm) | B7: -25000
A8: FY2026E revenue ($mm) | B8: 83500
A9: Beta | B9: 0.5
A10: Risk-free (10Y, 7/17/26) | B10: 0.0455
A11: Equity risk premium | B11: 0.0475
A12: Capex % of terminal revenue | B12: 0.08
A13: Cash tax rate | B13: 0.21
A14: Terminal growth g | B14: 0.03
A15: WACC (CAPM) | B15: =B10+B9*B11 -> 0.06925
A17: SCENARIOS
B18: Base | C18: Bull | D18: Bear
A19: FY2027 rev growth | B19: 0.16 | C19: 0.22 | D19: 0.08
A20: FY2035 rev growth | B20: 0.05 | C20: 0.08 | D20: 0
A21: Terminal EBITDA margin | B21: 0.42 | C21: 0.45 | D21: 0.35
A22: Exit EV/EBITDA | B22: 16 | C22: 19 | D22: 12
A23: Probability weight | B23: 0.45 | C23: 0.3 | D23: 0.25
A25: VALUATION (per scenario)
A26: FY2035 revenue | B26: =$B$8*(1+(B19+B20)/2)^9 -> 205091.18 | C26: =$B$8*(1+(C19+C20)/2)^9 -> 293742.67 | D26: =$B$8*(1+(D19+D20)/2)^9 -> 118846.54
A27: FY2035 EBITDA | B27: =B26*B21 -> 86138.294 | C27: =C26*C21 -> 132184.2 | D27: =D26*D21 -> 41596.288
A28: FY2035 FCF | B28: =B27*(1-$B$13)-B26*$B$12 -> 51641.958 | C28: =C27*(1-$B$13)-C26*$B$12 -> 80926.106 | D28: =D27*(1-$B$13)-D26*$B$12 -> 23353.344
A29: FY2026 FCF (approx) | B29: =$B$8*B21*0.67*(1-$B$13)-$B$8*$B$12 -> 11882.551 | C29: =$B$8*C21*0.67*(1-$B$13)-$B$8*$B$12 -> 13208.448 | D29: =$B$8*D21*0.67*(1-$B$13)-$B$8*$B$12 -> 8788.7925
A30: PV interim FCF | B30: =AVERAGE(B28:B29)*(1-(1+$B$15)^-9)/$B$15 -> 207600.32 | C30: =AVERAGE(C28:C29)*(1-(1+$B$15)^-9)/$B$15 -> 307635.01 | D30: =AVERAGE(D28:D29)*(1-(1+$B$15)^-9)/$B$15 -> 105041.63
A31: PV TV — exit mult | B31: =B22*B27/(1+$B$15)^9 -> 754402.16 | C31: =C22*C27/(1+$B$15)^9 -> 1374737.6 | D31: =D22*D27/(1+$B$15)^9 -> 273226.29
A32: PV TV — Gordon | B32: =B28*(1+$B$14)/($B$15-$B$14)/(1+$B$15)^9 -> 741800.18 | C32: =C28*(1+$B$14)/($B$15-$B$14)/(1+$B$15)^9 -> 1162446.2 | D32: =D28*(1+$B$14)/($B$15-$B$14)/(1+$B$15)^9 -> 335454.26
A33: Enterprise value | B33: =B30+AVERAGE(B31:B32) -> 955701.49 | C33: =C30+AVERAGE(C31:C32) -> 1576226.9 | D33: =D30+AVERAGE(D31:D32) -> 409381.91
A34: Equity value | B34: =B33+$B$7 -> 930701.49 | C34: =C33+$B$7 -> 1551226.9 | D34: =D33+$B$7 -> 384381.91
A35: Value per share | B35: =MAX(0,B34)/$B$6 -> 988.2786 | C35: =MAX(0,C34)/$B$6 -> 1647.1924 | D35: =MAX(0,D34)/$B$6 -> 408.16139
A36: Upside vs price | B36: =B35/$B$5-1 -> -0.15240519 | C36: =C35/$B$5-1 -> 0.41271066 | D36: =D35/$B$5-1 -> -0.64994135
A38: PROB-WEIGHTED VALUE / SHARE | B38: =SUMPRODUCT(B23:D23,B35:D35) -> 1040.9234
A39: Weighted upside / (downside) | B39: =B38/B5-1 -> -0.10725447
A41: HEALTHCARE. Q1-26 rev $19.8B (+56%); FY26 guide RAISED to $82-85B rev / $35.50-37 non-GAAP EPS. GLP-1 (Zepbound/Mounjaro) + oral orforglipron. Price $1,166 = ~32x fwd EPS — priced for continued dominance. Bear = patent cliff ~2030s + Novo/competition + obesity-drug pricing pressure. Net debt ~$25B(e), capex elevated on capacity buildout. Sources: investor.lilly.com Q1-26; companiesmarketcap.

Sheet V_DCF
A1: Visa (V) — SCENARIO DCF ($mm except per share)
A2: Rev35 = rev26×(1+avg(g27,g35))^9; FCF = EBITDA×0.79 − capex; interim = avg(FCF26,FCF35)×9-yr annuity; TV = avg(exit-multiple, Gordon), PV@9y; equity = EV + net cash. Same engine as the ranking/stress-test files.
A4: MARKET & COMPANY INPUTS
A5: Current share price | B5: 350.94
A6: Diluted shares (mm) | B6: 1880
A7: Net cash / (net debt) ($mm) | B7: -5000
A8: FY2026E revenue ($mm) | B8: 44000
A9: Beta | B9: 0.95
A10: Risk-free (10Y, 7/17/26) | B10: 0.0455
A11: Equity risk premium | B11: 0.0475
A12: Capex % of terminal revenue | B12: 0.04
A13: Cash tax rate | B13: 0.21
A14: Terminal growth g | B14: 0.03
A15: WACC (CAPM) | B15: =B10+B9*B11 -> 0.090625
A17: SCENARIOS
B18: Base | C18: Bull | D18: Bear
A19: FY2027 rev growth | B19: 0.1 | C19: 0.13 | D19: 0.06
A20: FY2035 rev growth | B20: 0.07 | C20: 0.09 | D20: 0.03
A21: Terminal EBITDA margin | B21: 0.7 | C21: 0.72 | D21: 0.66
A22: Exit EV/EBITDA | B22: 18 | C22: 21 | D22: 13
A23: Probability weight | B23: 0.55 | C23: 0.25 | D23: 0.2
A25: VALUATION (per scenario)
A26: FY2035 revenue | B26: =$B$8*(1+(B19+B20)/2)^9 -> 91689.651 | C26: =$B$8*(1+(C19+C20)/2)^9 -> 112553.62 | D26: =$B$8*(1+(D19+D20)/2)^9 -> 65388.186
A27: FY2035 EBITDA | B27: =B26*B21 -> 64182.756 | C27: =C26*C21 -> 81038.61 | D27: =D26*D21 -> 43156.203
A28: FY2035 FCF | B28: =B27*(1-$B$13)-B26*$B$12 -> 47036.791 | C28: =C27*(1-$B$13)-C26*$B$12 -> 59518.357 | D28: =D27*(1-$B$13)-D26*$B$12 -> 31477.873
A29: FY2026 FCF (approx) | B29: =$B$8*B21*0.67*(1-$B$13)-$B$8*$B$12 -> 14542.44 | C29: =$B$8*C21*0.67*(1-$B$13)-$B$8*$B$12 -> 15008.224 | D29: =$B$8*D21*0.67*(1-$B$13)-$B$8*$B$12 -> 13610.872
A30: PV interim FCF | B30: =AVERAGE(B28:B29)*(1-(1+$B$15)^-9)/$B$15 -> 184123.25 | C30: =AVERAGE(C28:C29)*(1-(1+$B$15)^-9)/$B$15 -> 222836.11 | D30: =AVERAGE(D28:D29)*(1-(1+$B$15)^-9)/$B$15 -> 134816.34
A31: PV TV — exit mult | B31: =B22*B27/(1+$B$15)^9 -> 529190.24 | C31: =C22*C27/(1+$B$15)^9 -> 779528.93 | D31: =D22*D27/(1+$B$15)^9 -> 256984.86
A32: PV TV — Gordon | B32: =B28*(1+$B$14)/($B$15-$B$14)/(1+$B$15)^9 -> 366053.13 | C32: =C28*(1+$B$14)/($B$15-$B$14)/(1+$B$15)^9 -> 463188.07 | D32: =D28*(1+$B$14)/($B$15-$B$14)/(1+$B$15)^9 -> 244969.38
A33: Enterprise value | B33: =B30+AVERAGE(B31:B32) -> 631744.94 | C33: =C30+AVERAGE(C31:C32) -> 844194.62 | D33: =D30+AVERAGE(D31:D32) -> 385793.46
A34: Equity value | B34: =B33+$B$7 -> 626744.94 | C34: =C33+$B$7 -> 839194.62 | D34: =D33+$B$7 -> 380793.46
A35: Value per share | B35: =MAX(0,B34)/$B$6 -> 333.37497 | C35: =MAX(0,C34)/$B$6 -> 446.38012 | D35: =MAX(0,D34)/$B$6 -> 202.54971
A36: Upside vs price | B36: =B35/$B$5-1 -> -0.050051384 | C36: =C35/$B$5-1 -> 0.27195565 | D36: =D35/$B$5-1 -> -0.42283663
A38: PROB-WEIGHTED VALUE / SHARE | B38: =SUMPRODUCT(B23:D23,B35:D35) -> 335.4612
A39: Weighted upside / (downside) | B39: =B38/B5-1 -> -0.044106675
A41: PAYMENTS. The EDA-style duopoly (V+MA) — toll booth on global commerce, ~67% operating margin. FY25 rev $40B (+11%); FY26E ~$44B; reports FQ3 7/28/26. Bear = interchange/regulation + stablecoin/real-time-rails disruption of card networks. Net debt ~$5B(e). Price $351. Sources: stockanalysis/companiesmarketcap 7/2026.

Sheet COST_DCF
A1: Costco (COST) — SCENARIO DCF ($mm except per share)
A2: Rev35 = rev26×(1+avg(g27,g35))^9; FCF = EBITDA×0.79 − capex; interim = avg(FCF26,FCF35)×9-yr annuity; TV = avg(exit-multiple, Gordon), PV@9y; equity = EV + net cash. Same engine as the ranking/stress-test files.
A4: MARKET & COMPANY INPUTS
A5: Current share price | B5: 925
A6: Diluted shares (mm) | B6: 443
A7: Net cash / (net debt) ($mm) | B7: 5000
A8: FY2026E revenue ($mm) | B8: 295000
A9: Beta | B9: 0.8
A10: Risk-free (10Y, 7/17/26) | B10: 0.0455
A11: Equity risk premium | B11: 0.0475
A12: Capex % of terminal revenue | B12: 0.025
A13: Cash tax rate | B13: 0.21
A14: Terminal growth g | B14: 0.03
A15: WACC (CAPM) | B15: =B10+B9*B11 -> 0.0835
A17: SCENARIOS
B18: Base | C18: Bull | D18: Bear
A19: FY2027 rev growth | B19: 0.08 | C19: 0.1 | D19: 0.05
A20: FY2035 rev growth | B20: 0.04 | C20: 0.05 | D20: 0.02
A21: Terminal EBITDA margin | B21: 0.05 | C21: 0.055 | D21: 0.045
A22: Exit EV/EBITDA | B22: 22 | C22: 25 | D22: 16
A23: Probability weight | B23: 0.55 | C23: 0.2 | D23: 0.25
A25: VALUATION (per scenario)
A26: FY2035 revenue | B26: =$B$8*(1+(B19+B20)/2)^9 -> 498396.29 | C26: =$B$8*(1+(C19+C20)/2)^9 -> 565585.41 | D26: =$B$8*(1+(D19+D20)/2)^9 -> 402054.72
A27: FY2035 EBITDA | B27: =B26*B21 -> 24919.815 | C27: =C26*C21 -> 31107.197 | D27: =D26*D21 -> 18092.462
A28: FY2035 FCF | B28: =B27*(1-$B$13)-B26*$B$12 -> 7226.7462 | C28: =C27*(1-$B$13)-C26*$B$12 -> 10435.051 | D28: =D27*(1-$B$13)-D26*$B$12 -> 4241.6773
A29: FY2026 FCF (approx) | B29: =$B$8*B21*0.67*(1-$B$13)-$B$8*$B$12 -> 432.175 | C29: =$B$8*C21*0.67*(1-$B$13)-$B$8*$B$12 -> 1212.8925 | D29: =$B$8*D21*0.67*(1-$B$13)-$B$8*$B$12 -> -348.5425
A30: PV interim FCF | B30: =AVERAGE(B28:B29)*(1-(1+$B$15)^-9)/$B$15 -> 23577.92 | C30: =AVERAGE(C28:C29)*(1-(1+$B$15)^-9)/$B$15 -> 35858.088 | D30: =AVERAGE(D28:D29)*(1-(1+$B$15)^-9)/$B$15 -> 11984.98
A31: PV TV — exit mult | B31: =B22*B27/(1+$B$15)^9 -> 266383.46 | C31: =C22*C27/(1+$B$15)^9 -> 377868.47 | D31: =D22*D27/(1+$B$15)^9 -> 140655.73
A32: PV TV — Gordon | B32: =B28*(1+$B$14)/($B$15-$B$14)/(1+$B$15)^9 -> 67603.006 | C32: =C28*(1+$B$14)/($B$15-$B$14)/(1+$B$15)^9 -> 97615.271 | D32: =D28*(1+$B$14)/($B$15-$B$14)/(1+$B$15)^9 -> 39679.01
A33: Enterprise value | B33: =B30+AVERAGE(B31:B32) -> 190571.15 | C33: =C30+AVERAGE(C31:C32) -> 273599.96 | D33: =D30+AVERAGE(D31:D32) -> 102152.35
A34: Equity value | B34: =B33+$B$7 -> 195571.15 | C34: =C33+$B$7 -> 278599.96 | D34: =D33+$B$7 -> 107152.35
A35: Value per share | B35: =MAX(0,B34)/$B$6 -> 441.46987 | C35: =MAX(0,C34)/$B$6 -> 628.89381 | D35: =MAX(0,D34)/$B$6 -> 241.87889
A36: Upside vs price | B36: =B35/$B$5-1 -> -0.52273528 | C36: =C35/$B$5-1 -> -0.3201148 | D36: =D35/$B$5-1 -> -0.73850931
A38: PROB-WEIGHTED VALUE / SHARE | B38: =SUMPRODUCT(B23:D23,B35:D35) -> 429.05691
A39: Weighted upside / (downside) | B39: =B38/B5-1 -> -0.53615469
A41: CONSUMER DEFENSIVE. Membership moat, recession-resilient, ~9% comp-sales growth. FY25 rev $275B, TTM $286B; Q2-26 EPS $4.58 (+14%). THIN margins (~5% EBITDA) but durable; ALWAYS trades premium (~22x EV/EBITDA) — the DCF will read 'richly valued', which is the point: you buy COST for compounding + de-correlation, not cheapness. Net cash ~$5B. Price ~$925 (mkt cap $411B). Sources: investor.costco.com Q2-26; gurufocus.
