Workbook

Sheet Risks
A1: RISK FLAGS & CORRECTIONS (July 24, 2026)
A4: 1. CONCENTRATION CREPT BACK TO ~53%
A5: NVDA (~27%) + GOOGL (~26%) are back to half the account despite the July trim — winners re-ran, then gave some back today. Both sit just under the 30% tripwire. ACTION: at the annual rebalance (or if either crosses 30%), trim to 25% and route to whatever's furthest below target. In a Roth this is free.
A7: 2. ~95% OF EQUITY IS ONE AI BET
A8: NVDA, GOOGL, NOW, SNPS, META all rise and fall on AI capex/adoption — the AI stress test showed them dropping together. VST is the only partial diversifier, and even it has AI-demand exposure. There is ZERO non-tech, non-US, non-AI ballast. Defensible at 22 (long horizon, high risk capacity) but it must be a CONSCIOUS choice, not an accident. Today's GOOGL −7% is a preview of a correlated down-day.
A10: 3. NO INDEX / DIVERSIFIER CORE
A11: 100% single stocks. One blow-up (accounting fraud, disruption, a bad NVDA cycle) hits with full force and can't be diversified away. Optional fix: route a slice of new contributions to a low-cost total-market or ex-US index fund as ballast. Not required — but the honest counterweight to a 7-stock book.
A13: 4. SpaceX WOULD DEEPEN, NOT DIVERSIFY
A14: SpaceX (~45x sales, ~90% terminal optionality) is another hot-narrative growth name — adding it increases the portfolio's tilt toward the exact factor it already over-owns. Fine as a small TICKET from the $839 cash; do NOT let it grow into a core position or fund it by raiding SNPS/VST. Lockup mechanics: standard 180-day from the 6/12 IPO ≈ mid-Dec; a November partial release is possible — verify before committing.
A16: 5. NOW IS THE ONE TO WATCH
A17: Near 52-wk low and down again today. Its bear case (agentic AI commoditizing seat-based SaaS) is STRUCTURAL, not cyclical — the one holding where cheap could mean broken. It reported a solid Q2 (rev $3.99B, raised guidance), which argues for holding — but do not ADD until two more quarters show seats/renewals holding. It's 15.5% of the account; that's a lot riding on an open question.
A19: 6. VST HAS RE-RATED
... A23: Roth wrapper (tax-free 40-yr compounding), automatic $100/wk, five industries, positions you can each explain, and every recent add bought at a discount. The structure is genuinely good — these flags are refinements, not a teardown.

Sheet Holdings
A1: PORTFOLIO — HOLDINGS & PER-STOCK 5-10 YEAR RETURN ASSUMPTIONS (prices 7/22-24/2026)
A2: Blue = inputs (edit prices & return assumptions). Value/weight are formulas. Per-stock returns are expected ANNUAL total return over 5-10 yrs — judgments grounded in this session's DCFs, not guarantees.
A4: Ticker | B4: Shares | C4: Price | D4: Value | E4: Weight | F4: Bear %/yr | G4: Base %/yr | H4: Bull %/yr | I4: 5-10yr thesis
A5: NVDA | B5: 23.957 | C5: 208.76 | D5: =B5*C5 -> 5001.2633 | E5: =D5/$D$12 -> 0.26989335 | F5: -0.03 | G5: 0.11 | H5: 0.2 | I5: AI compute king; highest variance. Moat=CUDA, but customer concentration (top buyers building own silicon) + efficiency shocks (DeepSeek/K3) cap the base. Cyclical.
A6: GOOGL | B6: 14.257 | C6: 342 | D6: =B6*C6 -> 4875.894 | E6: =D6/$D$12 -> 0.2631278 | F6: 0.02 | G6: 0.09 | H6: 0.14 | I6: Search/Cloud/YouTube cash machine + Gemini. Live risk: AI-native search eroding the core (−7% today on exactly this fear). Quality compounder, real disruption tail.
A7: NOW | B7: 30.067 | C7: 95.46 | D7: =B7*C7 -> 2870.1958 | E7: =D7/$D$12 -> 0.15489022 | F7: 0 | G7: 0.12 | H7: 0.18 | I7: Agentic SaaS; near 52-wk low. Biggest modeled upside BUT worst AI-commoditization score — agents may erode seat-based pricing. Deep value or value trap.
A8: SNPS | B8: 5.446 | C8: 372.99 | D8: =B8*C8 -> 2031.3035 | E8: =D8/$D$12 -> 0.10961937 | F8: 0.03 | G8: 0.12 | H8: 0.17 | I8: EDA duopoly at a fear discount (K3/China). +19% weighted upside, best risk/reward in the book. ~8% rev CAGR + margin expansion + re-rating optionality.
A9: META | B9: 2.567 | C9: 710 | D9: =B9*C9 -> 1822.57 | E9: =D9/$D$12 -> 0.098355056 | F9: 0.02 | G9: 0.1 | H9: 0.15 | I9: AI monetization + best bust-floor (net cash, ad demand exists without the narrative). Overhang: $125-145B/yr capex must earn its return. Price est — verify.
A10: VST | B10: 6.562 | C10: 166.21 | D10: =B10*C10 -> 1090.67 | E10: =D10/$D$12 -> 0.058858047 | F10: 0 | G10: 0.08 | H10: 0.13 | I10: Power = surest demand trend of the era. Ran from $155; now ~fair vs model. The one partial non-AI diversifier. Commodity ceiling caps the base.
A11: SPAXX (cash→SpaceX) | B11: 838.62 | C11: 1 | D11: =B11*C11 -> 838.62 | E11: =D11/$D$12 -> 0.045256158 | F11: 0.04 | G11: 0.04 | H11: 0.04 | I11: Dry powder for a Nov SpaceX entry. Modeled as money-market until deployed. SpaceX itself would be a ~45x-sales TICKET, not a core — huge variance, sized small.
A12: TOTAL | D12: =SUM(D5:D11) -> 18530.517 | E12: =SUM(E5:E11) -> 1
F13: Bear | G13: Base | H13: Bull
A14: Blended portfolio return (weighted): | F14: =SUMPRODUCT($E5:$E11,F5:F11) -> 0.0042316838 | G14: =SUMPRODUCT($E5:$E11,G5:G11) -> 0.10146532 | H14: =SUMPRODUCT($E5:$E11,H5:H11) -> 0.16154715
A16: Two-stock block (NVDA+GOOGL): | D16: =D5+D6 -> 9877.1573 | E16: =E5+E6 -> 0.53302115

Sheet Projection
A1: PROJECTED PORTFOLIO GROWTH — 10 YEARS (starting value + $100/wk contributions, three blended-return scenarios)
A2: Year-by-year: Value(next) = Value(now) × (1 + blended return) + annual contribution. Returns link from Holdings; contribution is an input. These are COMPOUNDING SCENARIOS, not forecasts.
A4: Starting value (from Holdings) | B4: =Holdings!D12 -> 18530.517
A5: Annual contribution ($100/wk × 52) | B5: 5200
A6: (Roth max is ~$7,000/yr — headroom of ~$1,800)
A8: Year | B8: Bear | C8: Base | D8: Bull | E8: Contributions to date | F8: Principal (start+contrib)
A9: 0 | B9: =$B$4 -> 18530.517 | C9: =$B$4 -> 18530.517 | D9: =$B$4 -> 18530.517 | E9: 0 | F9: =$B$4 -> 18530.517
A10: 1 | B10: =B9*(1+Holdings!$F$14)+$B$5 -> 23808.932 | C10: =C9*(1+Holdings!$G$14)+$B$5 -> 25610.721 | D10: =D9*(1+Holdings!$H$14)+$B$5 -> 26724.069 | E10: =E9+$B$5 -> 5200 | F10: =$B$4+E10 -> 23730.517
A11: 2 | B11: =B10*(1+Holdings!$F$14)+$B$5 -> 29109.684 | C11: =C10*(1+Holdings!$G$14)+$B$5 -> 33409.321 | D11: =D10*(1+Holdings!$H$14)+$B$5 -> 36241.266 | E11: =E10+$B$5 -> 10400 | F11: =$B$4+E11 -> 28930.517
A12: 3 | B12: =B11*(1+Holdings!$F$14)+$B$5 -> 34432.867 | C12: =C11*(1+Holdings!$G$14)+$B$5 -> 41999.209 | D12: =D11*(1+Holdings!$H$14)+$B$5 -> 47295.939 | E12: =E11+$B$5 -> 15600 | F12: =$B$4+E12 -> 34130.517
A13: 4 | B13: =B12*(1+Holdings!$F$14)+$B$5 -> 39778.576 | C13: =C12*(1+Holdings!$G$14)+$B$5 -> 51460.672 | D13: =D12*(1+Holdings!$H$14)+$B$5 -> 60136.463 | E13: =E12+$B$5 -> 20800 | F13: =$B$4+E13 -> 39330.517
A14: 5 | B14: =B13*(1+Holdings!$F$14)+$B$5 -> 45146.906 | C14: =C13*(1+Holdings!$G$14)+$B$5 -> 61882.145 | D14: =D13*(1+Holdings!$H$14)+$B$5 -> 75051.337 | E14: =E13+$B$5 -> 26000 | F14: =$B$4+E14 -> 44530.517
A15: 6 | B15: =B14*(1+Holdings!$F$14)+$B$5 -> 50537.954 | C15: =C14*(1+Holdings!$G$14)+$B$5 -> 73361.037 | D15: =D14*(1+Holdings!$H$14)+$B$5 -> 92375.666 | E15: =E14+$B$5 -> 31200 | F15: =$B$4+E15 -> 49730.517
A16: 7 | B16: =B15*(1+Holdings!$F$14)+$B$5 -> 55951.814 | C16: =C15*(1+Holdings!$G$14)+$B$5 -> 86004.638 | D16: =D15*(1+Holdings!$H$14)+$B$5 -> 112498.69 | E16: =E15+$B$5 -> 36400 | F16: =$B$4+E16 -> 54930.517
A17: 8 | B17: =B16*(1+Holdings!$F$14)+$B$5 -> 61388.585 | C17: =C16*(1+Holdings!$G$14)+$B$5 -> 99931.125 | D17: =D16*(1+Holdings!$H$14)+$B$5 -> 135872.53 | E17: =E16+$B$5 -> 41600 | F17: =$B$4+E17 -> 60130.517
A18: 9 | B18: =B17*(1+Holdings!$F$14)+$B$5 -> 66848.362 | C18: =C17*(1+Holdings!$G$14)+$B$5 -> 115270.67 | D18: =D17*(1+Holdings!$H$14)+$B$5 -> 163022.35 | E18: =E17+$B$5 -> 46800 | F18: =$B$4+E18 -> 65330.517
A19: 10 | B19: =B18*(1+Holdings!$F$14)+$B$5 -> 72331.243 | C19: =C18*(1+Holdings!$G$14)+$B$5 -> 132166.64 | D19: =D18*(1+Holdings!$H$14)+$B$5 -> 194558.15 | E19: =E18+$B$5 -> 52000 | F19: =$B$4+E19 -> 70530.517
A21: 5-year and 10-year values are highlighted. 'Principal' = what you put in — the gap above it is investment growth.
