Workbook

Sheet Cover
A1: T1 ENERGY INC. (NYSE: TE) — DCF VALUATION & 3-STATEMENT OPERATING MODEL
A2: Prepared August 2026 · $ millions except per-share · Calendar fiscal year · Formerly FREYR Battery; pivoted to US solar manufacturing
A4: READ THIS FIRST — THE CRUX
C5: T1's profit engine is the Section 45X Advanced Manufacturing Production Credit (~$0.07/W modules, ~$0.04/W cells), NOT its operating margin. Module assembly against Chinese competition earns a thin-to-negative gross margin on its own; the credits are what make the P&L work. 45X is scheduled to STEP DOWN (100% through 2029, then 75%/50%/25%/0% in 2030-33). So the entire investment question is: can T1 reach standalone profitability BEFORE the credits disappear? This model makes that explicit — see the '45X phase-out factor' row on Model_3S and the Bear scenario.
A7: CONTENTS
A8: Assumptions | C8: Scenario switch & levers (edit yellow cells)
A9: Historicals | C9: FY2024–FY2025 actuals, Q2-2026 preliminary, FY2026E build
A10: Model_3S | C10: Linked IS/BS/CF FY2026E–FY2035E with explicit 45X credit line and phase-out schedule
A11: WACC | C11: CAPM — high beta small-cap with policy risk
A12: DCF | C12: Unlevered FCF, Gordon + exit-multiple TV, sensitivities
A13: Comps | C13: US/global solar manufacturing peers (FSLR primary)
A14: Precedents | C14: Solar manufacturing M&A — incl. T1's own Trina-US and KORE deals
A15: LBO | C15: Illustrative — negative EBITDA means conventional debt capacity is ~zero
A16: Monte_Carlo | C16: 500 live trials + scenario probability weights
A17: Football_Field | C17: Valuation summary chart vs. current price
A19: LEGEND
A20: Blue font / yellow fill | C20: Hardcoded input or scenario lever — edit these
A21: Black font | C21: Formula — do not overwrite
A22: Green font | C22: Link to another sheet
A23: 'e' | C23: Estimated figure — see notes
A25: KEY MODELING NOTES
A26: 1. | C26: Q2-2026 preliminary: revenue $245-255mm on 835 MW shipped, net loss from continuing ops $34-37mm, NEGATIVE adjusted EBITDA, cash + restricted cash $156.4mm at 6/30/26.
A27: 2. | C27: G2_Austin (solar CELL plant) Phase 1 capex RAISED to $510mm from $425mm; first cell production DELAYED to Q1-2027. Cells are what stack the 45X credit and lift domestic content — the delay pushes the profitability inflection right.
A28: 3. | C28: 2026 actions: bought Evervolt solar patents ($135mm), monetized 2025 45X credits for $39.1mm, closed KORE Power acquisition (energy storage / AI data-center infrastructure, 'T1 NRI' brand), raised $120mm convertible notes (late July).
A29: 4. | C29: Liquidity is the live risk: ~$150mm cash against a $510mm Phase 1 program and ~$670mm debt. The model's revolver-draw row is a FUNDING-GAP INDICATOR — draws mean an equity raise in practice (dilution not modeled).
A30: 5. | C30: Share-count/market-cap sources conflict (279.27mm shares × $6.81 ≈ $1.90B vs. a $1.37B market cap quoted 7/28/26) — likely convertible/timing differences. Both are editable inputs; verify before relying on per-share output.
A32: KEY SOURCES
A33: Q2-2026 preliminary results (July 2026) | C33: stocktitan/Globe & Mail/Benzinga: rev $245-255mm, 835 MW, net loss $34-37mm, cash $156.4mm; G2 capex $510mm, first cells Q1-2027; Evervolt patents $135mm; 45X monetization $39.1mm
A34: Market data (Aug 2026) | C34: stockanalysis/etoro/CNN: price ~$6.81, 279.27mm shares, cash $46.37mm & debt $549.78mm (as reported; pre-convert), analyst avg target ~$10.07 'Strong Buy'; Alliance Global cut to $7
A35: 45X credit mechanics | C35: IRA Section 45X: ~$0.07/W modules, ~$0.04/W cells; statutory step-down 2030-2032. Treat the phase-out row as an ASSUMPTION — subsequent legislation may alter it.
A36: 10Y UST 4.55% | C36: tradingeconomics / FRED DGS10
A38: DISCLAIMER | C38: Educational model, not investment advice. TE is a small-cap, levered, policy-dependent manufacturer — outcomes are wide and the equity is speculative. Verify all figures against T1 filings.

Sheet Assumptions
A1: ASSUMPTIONS & SCENARIO LEVERS — T1 ENERGY
A2: Edit yellow cells. Switch drives Model_3S, DCF, LBO, Monte Carlo.
A4: SCENARIO SWITCH (1 = Base, 2 = Bull, 3 = Bear) | B4: 1 | C4: =CHOOSE($B$4,"BASE — G2 cells ramp, margins improve before 45X fades","BULL — full domestic stack + storage/AI datacenter scale","BEAR — thin margins persist, 45X fades, funding squeeze") -> BASE — G2 cells ramp, margins improve before 45X fades
A6: Scenario probability weights
B7: Base | C7: Bull | D7: Bear | E7: Total
A8: Probability | B8: 0.4 | C8: 0.2 | D8: 0.4 | E8: =SUM(B8:D8) -> 1 | F8: Heavy 40% bear weight: policy dependence + funding gap + commodity competition are all live
A10: Revenue growth — decays linearly FY2027 → FY2035
B11: Base | C11: Bull | D11: Bear | E11: Selected
A12: FY2027 revenue growth | B12: 0.35 | C12: 0.55 | D12: 0.1 | E12: =CHOOSE($B$4,B12,C12,D12) -> 0.35
A13: FY2035 revenue growth (terminal-year) | B13: 0.04 | C13: 0.07 | D13: 0 | E13: =CHOOSE($B$4,B13,C13,D13) -> 0.04
A14: FY27 growth = G2_Austin cells coming online (Q1-27) + KORE storage. Bear assumes the ramp slips and pricing stays brutal.
A15: Operating drivers — FY2026 start ramps linearly to FY2035 target
A16: Driver | B16: FY26 start | C16: Base target | D16: Bull target | E16: Bear target | F16: Selected
A17: Gross margin EXCLUDING 45X credits | B17: 0.03 | C17: 0.14 | D17: 0.2 | E17: 0.03 | F17: =CHOOSE($B$4,C17,D17,E17) -> 0.14
A18: 45X credits as % of revenue (pre-phase-out) | B18: 0.23 | C18: 0.28 | D18: 0.3 | E18: 0.2 | F18: =CHOOSE($B$4,C18,D18,E18) -> 0.28
A19: Cash opex — SG&A + R&D (% revenue) | B19: 0.11 | C19: 0.065 | D19: 0.055 | E19: 0.09 | F19: =CHOOSE($B$4,C19,D19,E19) -> 0.065
A20: Stock-based compensation (% revenue) | B20: 0.02 | C20: 0.012 | D20: 0.012 | E20: 0.018 | F20: =CHOOSE($B$4,C20,D20,E20) -> 0.012
A21: D&A (% revenue) | B21: 0.055 | C21: 0.05 | D21: 0.045 | E21: 0.06 | F21: =CHOOSE($B$4,C21,D21,E21) -> 0.05
A22: Cash tax rate (large NOLs early) | B22: 0 | C22: 0.18 | D22: 0.18 | E22: 0 | F22: =CHOOSE($B$4,C22,D22,E22) -> 0.18
A23: Other current assets (% revenue) | B23: 0.08 | C23: 0.08 | D23: 0.08 | E23: 0.08 | F23: =CHOOSE($B$4,C23,D23,E23) -> 0.08
A24: Customer deposits / deferred revenue (% rev) | B24: 0.05 | C24: 0.05 | D24: 0.06 | E24: 0.04 | F24: =CHOOSE($B$4,C24,D24,E24) -> 0.05
A25: THE WHOLE THESIS IS ROW 17: ex-credit gross margin. Base says domestic cells lift it 3% → 14% by FY35. Bear says it never improves — and when 45X fades, EBITDA goes structurally negative.
A26: Working capital (held constant)
A27: Days sales outstanding (DSO) | B27: 45
A28: Days inventory (DIO, on COGS) | B28: 75
A29: Days payable (DPO, on COGS + cash opex) | B29: 60
A33: Capital, capex program & financing
A34: Interest earned on cash | B34: 0.035
A35: Revolver / gap-funding rate | B35: 0.1
A36: Minimum cash balance ($mm) | B36: 100
A37: Diluted shares outstanding (mm) | B37: 279.3
A38: Marginal tax rate (valuation) | B38: 0.21
A39: Average rate on existing debt | B39: 0.085
A40: G2_Austin Phase 1 capex — FY2026 ($mm) | B40: 300 | C40: Phase 1 total $510mm split across FY26/27; first cells Q1-2027
A41: G2_Austin Phase 1 capex — FY2027 ($mm) | B41: 210
A42: Maintenance capex thereafter (% revenue) | B42: 0.03
A43: Acquisitions FY2026 (Evervolt patents etc., $mm) | B43: 135
A44: Equity issuance FY2026 ($mm) | B44: 0
A46: Terminal value & market inputs
A47: Terminal (perpetuity) growth rate g | B47: 0.02
A48: Exit EV / Adj. EBITDA multiple (FY2035) | B48: 7
A49: Current share price (Aug 2026) | B49: 6.81
A51: Exit 7x reflects commodity-manufacturing economics (FSLR-type range 6-10x), not a software/toll-booth multiple.

Sheet Historicals
A1: HISTORICAL FINANCIALS ($mm)
B4: FY2024A | C4: FY2025A e | E4: Q1-26A e | F4: Q2-26A prelim | H4: FY2026E
A5: Revenue | B5: 0 | C5: 340 | E5: 190 | F5: 250 | H5: 1050 | I5: FY26E ~$1.05B: ~3.5 GW at ~$0.30/W ASP (G1_Dallas target 3.1-4.2 GW, guided to upper end)
A6: Module shipments (MW) | F6: 835 | H6: 3500
A7: Net income (loss) from continuing ops | C7: -180 | F7: -35
A8: Adjusted EBITDA | F8: -15 | G8: NEGATIVE in Q2-26 — the company is not yet EBITDA-profitable
A9: Cash + restricted cash (period end) | F9: 156.4
A11: Business | B11: US solar manufacturing. G1_Dallas (5 GW module plant, ex-Trina) operating; G2_Austin (cells) Phase 1 $510mm, first output Q1-2027.
A12: Profit engine | B12: Section 45X credits (~$0.07/W modules, ~$0.04/W cells). Monetized $39.1mm of 2025 credits in 2026.
A13: 2026 corporate actions | B13: Evervolt solar patents $135mm · KORE Power acquired (storage + AI data-center infra, 'T1 NRI') · $120mm convertible notes raised late July
A14: Capital structure | B14: ~$550mm debt reported + ~$120mm new converts ≈ $670mm; cash ~$150mm → net debt ~$520mm vs ~$1.9B market cap
A15: Analyst view | B15: Avg target ~$10.07, 'Strong Buy' consensus; but Alliance Global cut to $7 — wide dispersion is itself a signal
A16: Risk file | B16: 45X phase-out (2030-33) · Chinese module pricing · G2 execution/delay · funding gap vs $510mm program · tariff/policy swings
A19: Opening balance sheet, 12/31/2025 (estimated):
A20: Cash + restricted e | B20: 200
A21: Receivables e | B21: 120
A22: Inventory e | B22: 180
A23: Other current assets e | B23: 90
A24: PP&E net e | B24: 900
A25: Goodwill + intangibles + other LT e | B25: 300
A26: AP + accrued e | B26: 160
A27: Customer deposits / deferred e | B27: 50
A28: Total debt e | B28: 550
A29: Other LT liabilities e | B29: 120
A31: Balance sheet substantially ESTIMATED (post-pivot reporting is discontinuous — FREYR→T1 with asset acquisitions and a discontinued battery segment). Equity is the plug. Verify against the 10-Q before relying on it.

Sheet Model_3S
A1: 3-STATEMENT OPERATING MODEL — FY2026E–FY2035E ($mm; 45X credits shown explicitly)
A2: =CONCATENATE("Active scenario: ",CHOOSE(Assumptions!$B$4,"BASE","BULL","BEAR")) -> Active scenario: BASE
B4: FY2025A | C4: FY2026E | D4: FY2027E | E4: FY2028E | F4: FY2029E | G4: FY2030E | H4: FY2031E | I4: FY2032E | J4: FY2033E | K4: FY2034E | L4: FY2035E
A6: DRIVERS
A7: Revenue growth % | C7: =C19/B19-1 -> 2.0882353 | D7: =Assumptions!$E$12+(Assumptions!$E$13-Assumptions!$E$12)*0/8 -> 0.35 | E7: =Assumptions!$E$12+(Assumptions!$E$13-Assumptions!$E$12)*1/8 -> 0.31125 | F7: =Assumptions!$E$12+(Assumptions!$E$13-Assumptions!$E$12)*2/8 -> 0.2725 | G7: =Assumptions!$E$12+(Assumptions!$E$13-Assumptions!$E$12)*3/8 -> 0.23375 | H7: =Assumptions!$E$12+(Assumptions!$E$13-Assumptions!$E$12)*4/8 -> 0.195 | I7: =Assumptions!$E$12+(Assumptions!$E$13-Assumptions!$E$12)*5/8 -> 0.15625 | J7: =Assumptions!$E$12+(Assumptions!$E$13-Assumptions!$E$12)*6/8 -> 0.1175 | K7: =Assumptions!$E$12+(Assumptions!$E$13-Assumptions!$E$12)*7/8 -> 0.07875 | L7: =Assumptions!$E$12+(Assumptions!$E$13-Assumptions!$E$12)*8/8 -> 0.04
A8: Gross margin ex-45X % | C8: =Assumptions!$B$17 -> 0.03 | D8: =Assumptions!$B$17+(Assumptions!$F$17-Assumptions!$B$17)*1/9 -> 0.042222222 | E8: =Assumptions!$B$17+(Assumptions!$F$17-Assumptions!$B$17)*2/9 -> 0.054444444 | F8: =Assumptions!$B$17+(Assumptions!$F$17-Assumptions!$B$17)*3/9 -> 0.066666667 | G8: =Assumptions!$B$17+(Assumptions!$F$17-Assumptions!$B$17)*4/9 -> 0.078888889 | H8: =Assumptions!$B$17+(Assumptions!$F$17-Assumptions!$B$17)*5/9 -> 0.091111111 | I8: =Assumptions!$B$17+(Assumptions!$F$17-Assumptions!$B$17)*6/9 -> 0.10333333 | J8: =Assumptions!$B$17+(Assumptions!$F$17-Assumptions!$B$17)*7/9 -> 0.11555556 | K8: =Assumptions!$B$17+(Assumptions!$F$17-Assumptions!$B$17)*8/9 -> 0.12777778 | L8: =Assumptions!$B$17+(Assumptions!$F$17-Assumptions!$B$17)*9/9 -> 0.14
A9: 45X credit % of revenue (pre-phase-out) | C9: =Assumptions!$B$18 -> 0.23 | D9: =Assumptions!$B$18+(Assumptions!$F$18-Assumptions!$B$18)*1/9 -> 0.23555556 | E9: =Assumptions!$B$18+(Assumptions!$F$18-Assumptions!$B$18)*2/9 -> 0.24111111 | F9: =Assumptions!$B$18+(Assumptions!$F$18-Assumptions!$B$18)*3/9 -> 0.24666667 | G9: =Assumptions!$B$18+(Assumptions!$F$18-Assumptions!$B$18)*4/9 -> 0.25222222 | H9: =Assumptions!$B$18+(Assumptions!$F$18-Assumptions!$B$18)*5/9 -> 0.25777778 | I9: =Assumptions!$B$18+(Assumptions!$F$18-Assumptions!$B$18)*6/9 -> 0.26333333 | J9: =Assumptions!$B$18+(Assumptions!$F$18-Assumptions!$B$18)*7/9 -> 0.26888889 | K9: =Assumptions!$B$18+(Assumptions!$F$18-Assumptions!$B$18)*8/9 -> 0.27444444 | L9: =Assumptions!$B$18+(Assumptions!$F$18-Assumptions!$B$18)*9/9 -> 0.28
A10: Cash opex % rev | C10: =Assumptions!$B$19 -> 0.11 | D10: =Assumptions!$B$19+(Assumptions!$F$19-Assumptions!$B$19)*1/9 -> 0.105 | E10: =Assumptions!$B$19+(Assumptions!$F$19-Assumptions!$B$19)*2/9 -> 0.1 | F10: =Assumptions!$B$19+(Assumptions!$F$19-Assumptions!$B$19)*3/9 -> 0.095 | G10: =Assumptions!$B$19+(Assumptions!$F$19-Assumptions!$B$19)*4/9 -> 0.09 | H10: =Assumptions!$B$19+(Assumptions!$F$19-Assumptions!$B$19)*5/9 -> 0.085 | I10: =Assumptions!$B$19+(Assumptions!$F$19-Assumptions!$B$19)*6/9 -> 0.08 | J10: =Assumptions!$B$19+(Assumptions!$F$19-Assumptions!$B$19)*7/9 -> 0.075 | K10: =Assumptions!$B$19+(Assumptions!$F$19-Assumptions!$B$19)*8/9 -> 0.07 | L10: =Assumptions!$B$19+(Assumptions!$F$19-Assumptions!$B$19)*9/9 -> 0.065
A11: SBC % rev | C11: =Assumptions!$B$20 -> 0.02 | D11: =Assumptions!$B$20+(Assumptions!$F$20-Assumptions!$B$20)*1/9 -> 0.019111111 | E11: =Assumptions!$B$20+(Assumptions!$F$20-Assumptions!$B$20)*2/9 -> 0.018222222 | F11: =Assumptions!$B$20+(Assumptions!$F$20-Assumptions!$B$20)*3/9 -> 0.017333333 | G11: =Assumptions!$B$20+(Assumptions!$F$20-Assumptions!$B$20)*4/9 -> 0.016444444 | H11: =Assumptions!$B$20+(Assumptions!$F$20-Assumptions!$B$20)*5/9 -> 0.015555556 | I11: =Assumptions!$B$20+(Assumptions!$F$20-Assumptions!$B$20)*6/9 -> 0.014666667 | J11: =Assumptions!$B$20+(Assumptions!$F$20-Assumptions!$B$20)*7/9 -> 0.013777778 | K11: =Assumptions!$B$20+(Assumptions!$F$20-Assumptions!$B$20)*8/9 -> 0.012888889 | L11: =Assumptions!$B$20+(Assumptions!$F$20-Assumptions!$B$20)*9/9 -> 0.012
A12: D&A % rev | C12: =Assumptions!$B$21 -> 0.055 | D12: =Assumptions!$B$21+(Assumptions!$F$21-Assumptions!$B$21)*1/9 -> 0.054444444 | E12: =Assumptions!$B$21+(Assumptions!$F$21-Assumptions!$B$21)*2/9 -> 0.053888889 | F12: =Assumptions!$B$21+(Assumptions!$F$21-Assumptions!$B$21)*3/9 -> 0.053333333 | G12: =Assumptions!$B$21+(Assumptions!$F$21-Assumptions!$B$21)*4/9 -> 0.052777778 | H12: =Assumptions!$B$21+(Assumptions!$F$21-Assumptions!$B$21)*5/9 -> 0.052222222 | I12: =Assumptions!$B$21+(Assumptions!$F$21-Assumptions!$B$21)*6/9 -> 0.051666667 | J12: =Assumptions!$B$21+(Assumptions!$F$21-Assumptions!$B$21)*7/9 -> 0.051111111 | K12: =Assumptions!$B$21+(Assumptions!$F$21-Assumptions!$B$21)*8/9 -> 0.050555556 | L12: =Assumptions!$B$21+(Assumptions!$F$21-Assumptions!$B$21)*9/9 -> 0.05
A13: Cash tax rate % | C13: =Assumptions!$B$22 -> 0 | D13: =Assumptions!$B$22+(Assumptions!$F$22-Assumptions!$B$22)*1/9 -> 0.02 | E13: =Assumptions!$B$22+(Assumptions!$F$22-Assumptions!$B$22)*2/9 -> 0.04 | F13: =Assumptions!$B$22+(Assumptions!$F$22-Assumptions!$B$22)*3/9 -> 0.06 | G13: =Assumptions!$B$22+(Assumptions!$F$22-Assumptions!$B$22)*4/9 -> 0.08 | H13: =Assumptions!$B$22+(Assumptions!$F$22-Assumptions!$B$22)*5/9 -> 0.1 | I13: =Assumptions!$B$22+(Assumptions!$F$22-Assumptions!$B$22)*6/9 -> 0.12 | J13: =Assumptions!$B$22+(Assumptions!$F$22-Assumptions!$B$22)*7/9 -> 0.14 | K13: =Assumptions!$B$22+(Assumptions!$F$22-Assumptions!$B$22)*8/9 -> 0.16 | L13: =Assumptions!$B$22+(Assumptions!$F$22-Assumptions!$B$22)*9/9 -> 0.18
A14: Other current assets % rev | C14: =Assumptions!$B$23 -> 0.08 | D14: =Assumptions!$B$23+(Assumptions!$F$23-Assumptions!$B$23)*1/9 -> 0.08 | E14: =Assumptions!$B$23+(Assumptions!$F$23-Assumptions!$B$23)*2/9 -> 0.08 | F14: =Assumptions!$B$23+(Assumptions!$F$23-Assumptions!$B$23)*3/9 -> 0.08 | G14: =Assumptions!$B$23+(Assumptions!$F$23-Assumptions!$B$23)*4/9 -> 0.08 | H14: =Assumptions!$B$23+(Assumptions!$F$23-Assumptions!$B$23)*5/9 -> 0.08 | I14: =Assumptions!$B$23+(Assumptions!$F$23-Assumptions!$B$23)*6/9 -> 0.08 | J14: =Assumptions!$B$23+(Assumptions!$F$23-Assumptions!$B$23)*7/9 -> 0.08 | K14: =Assumptions!$B$23+(Assumptions!$F$23-Assumptions!$B$23)*8/9 -> 0.08 | L14: =Assumptions!$B$23+(Assumptions!$F$23-Assumptions!$B$23)*9/9 -> 0.08
A15: Deferred revenue % rev | C15: =Assumptions!$B$24 -> 0.05 | D15: =Assumptions!$B$24+(Assumptions!$F$24-Assumptions!$B$24)*1/9 -> 0.05 | E15: =Assumptions!$B$24+(Assumptions!$F$24-Assumptions!$B$24)*2/9 -> 0.05 | F15: =Assumptions!$B$24+(Assumptions!$F$24-Assumptions!$B$24)*3/9 -> 0.05 | G15: =Assumptions!$B$24+(Assumptions!$F$24-Assumptions!$B$24)*4/9 -> 0.05 | H15: =Assumptions!$B$24+(Assumptions!$F$24-Assumptions!$B$24)*5/9 -> 0.05 | I15: =Assumptions!$B$24+(Assumptions!$F$24-Assumptions!$B$24)*6/9 -> 0.05 | J15: =Assumptions!$B$24+(Assumptions!$F$24-Assumptions!$B$24)*7/9 -> 0.05 | K15: =Assumptions!$B$24+(Assumptions!$F$24-Assumptions!$B$24)*8/9 -> 0.05 | L15: =Assumptions!$B$24+(Assumptions!$F$24-Assumptions!$B$24)*9/9 -> 0.05
A16: 45X PHASE-OUT FACTOR (statutory step-down — editable) | C16: 1 | D16: 1 | E16: 1 | F16: 1 | G16: 0.75 | H16: 0.5 | I16: 0.25 | J16: 0 | K16: 0 | L16: 0 | M16: IRA 45X: 100% through 2029, then 75%/50%/25%/0% for 2030-2032, zero thereafter. THE key policy assumption.
A18: INCOME STATEMENT
A19: Revenue | B19: =Historicals!C5 -> 340 | C19: =Historicals!H5 -> 1050 | D19: =C19*(1+D7) -> 1417.5 | E19: =D19*(1+E7) -> 1858.6969 | F19: =E19*(1+F7) -> 2365.1918 | G19: =F19*(1+G7) -> 2918.0554 | H19: =G19*(1+H7) -> 3487.0761 | I19: =H19*(1+I7) -> 4031.9318 | J19: =I19*(1+J7) -> 4505.6838 | K19: =J19*(1+K7) -> 4860.5064 | L19: =K19*(1+L7) -> 5054.9266
A20: Cost of revenue (excl. D&A) | C20: =-C19*(1-C8) -> -1018.5 | D20: =-D19*(1-D8) -> -1357.65 | E20: =-E19*(1-E8) -> -1757.5012 | F20: =-F19*(1-F8) -> -2207.5123 | G20: =-G19*(1-G8) -> -2687.8532 | H20: =-H19*(1-H8) -> -3169.3648 | I20: =-I19*(1-I8) -> -3615.2988 | J20: =-J19*(1-J8) -> -3985.027 | ... L20: =-L19*(1-L8) -> -4347.2369
A21: Gross profit EXCLUDING 45X credits | C21: =C19+C20 -> 31.5 | D21: =D19+D20 -> 59.85 | E21: =E19+E20 -> 101.19572 | F21: =F19+F20 -> 157.67945 | G21: =G19+G20 -> 230.20214 | H21: =H19+H20 -> 317.71138 | I21: =I19+I20 -> 416.63295 | J21: =J19+J20 -> 520.65679 | ... L21: =L19+L20 -> 707.68973 | M21: If this row is negative, the business loses money on every panel BEFORE credits
A22: 45X production tax credits | C22: =C19*C9*C16 -> 241.5 | D22: =D19*D9*D16 -> 333.9 | E22: =E19*E9*E16 -> 448.15247 | F22: =F19*F9*F16 -> 583.41397 | G22: =G19*G9*G16 -> 551.9988 | H22: =H19*H9*H16 -> 449.44537 | I22: =I19*I9*I16 -> 265.43551 | J22: =J19*J9*J16 -> 0 | ... L22: =L19*L9*L16 -> 0
A23: Gross profit including credits | C23: =C21+C22 -> 273 | D23: =D21+D22 -> 393.75 | E23: =E21+E22 -> 549.34819 | F23: =F21+F22 -> 741.09342 | G23: =G21+G22 -> 782.20095 | H23: =H21+H22 -> 767.15675 | I23: =I21+I22 -> 682.06846 | J23: =J21+J22 -> 520.65679 | ... L23: =L21+L22 -> 707.68973
A24: Cash opex (SG&A + R&D) | C24: =-C19*C10 -> -115.5 | D24: =-D19*D10 -> -148.8375 | E24: =-E19*E10 -> -185.86969 | F24: =-F19*F10 -> -224.69322 | G24: =-G19*G10 -> -262.62498 | H24: =-H19*H10 -> -296.40147 | I24: =-I19*I10 -> -322.55454 | J24: =-J19*J10 -> -337.92628 | ... L24: =-L19*L10 -> -328.57023
A25: Adjusted EBITDA | C25: =C23+C24 -> 157.5 | D25: =D23+D24 -> 244.9125 | E25: =E23+E24 -> 363.4785 | F25: =F23+F24 -> 516.4002 | G25: =G23+G24 -> 519.57597 | H25: =H23+H24 -> 470.75528 | I25: =I23+I24 -> 359.51392 | J25: =J23+J24 -> 182.73051 | ... L25: =L23+L24 -> 379.1195
A26: Stock-based compensation | C26: =-C19*C11 -> -21 | D26: =-D19*D11 -> -27.09 | E26: =-E19*E11 -> -33.869588 | F26: =-F19*F11 -> -40.996657 | G26: =-G19*G11 -> -47.985799 | H26: =-H19*H11 -> -54.243407 | I26: =-I19*I11 -> -59.135 | J26: =-J19*J11 -> -62.07831 | ... L26: =-L19*L11 -> -60.65912
A27: D&A | C27: =-C19*C12 -> -57.75 | D27: =-D19*D12 -> -77.175 | E27: =-E19*E12 -> -100.16311 | F27: =-F19*F12 -> -126.14356 | G27: =-G19*G12 -> -154.00848 | H27: =-H19*H12 -> -182.10287 | I27: =-I19*I12 -> -208.31648 | J27: =-J19*J12 -> -230.2905 | ... L27: =-L19*L12 -> -252.74633
A28: EBIT | C28: =C25+C26+C27 -> 78.75 | D28: =D25+D26+D27 -> 140.6475 | E28: =E25+E26+E27 -> 229.4458 | F28: =F25+F26+F27 -> 349.25999 | G28: =G25+G26+G27 -> 317.58169 | H28: =H25+H26+H27 -> 234.40901 | I28: =I25+I26+I27 -> 92.062443 | J28: =J25+J26+J27 -> -109.63831 | ... L28: =L25+L26+L27 -> 65.714046
A29: Interest income (on beginning cash) | C29: =B72*Assumptions!$B$34 -> 7 | D29: =C72*Assumptions!$B$34 -> 3.5 | E29: =D72*Assumptions!$B$34 -> 3.5 | F29: =E72*Assumptions!$B$34 -> 3.5 | G29: =F72*Assumptions!$B$34 -> 11.710645 | H29: =G72*Assumptions!$B$34 -> 21.047095 | I29: =H72*Assumptions!$B$34 -> 28.359637 | J29: =I72*Assumptions!$B$34 -> 32.02772 | ... L29: =K72*Assumptions!$B$34 -> 31.355132
A30: Interest expense (beginning debt) | C30: =-(B52*Assumptions!$B$39+B56*Assumptions!$B$35) -> -46.75 | D30: =-(C52*Assumptions!$B$39+C56*Assumptions!$B$35) -> -67.057192 | E30: =-(D52*Assumptions!$B$39+D56*Assumptions!$B$35) -> -76.554917 | F30: =-(E52*Assumptions!$B$39+E56*Assumptions!$B$35) -> -61.511693 | G30: =-(F52*Assumptions!$B$39+F56*Assumptions!$B$35) -> -56.95 | H30: =-(G52*Assumptions!$B$39+G56*Assumptions!$B$35) -> -56.95 | I30: =-(H52*Assumptions!$B$39+H56*Assumptions!$B$35) -> -56.95 | J30: =-(I52*Assumptions!$B$39+I56*Assumptions!$B$35) -> -56.95 | ... L30: =-(K52*Assumptions!$B$39+K56*Assumptions!$B$35) -> -56.95
A31: Pre-tax income | C31: =C28+C29+C30 -> 39 | D31: =D28+D29+D30 -> 77.090308 | E31: =E28+E29+E30 -> 156.39089 | F31: =F28+F29+F30 -> 291.24829 | G31: =G28+G29+G30 -> 272.34234 | H31: =H28+H29+H30 -> 198.5061 | I31: =I28+I29+I30 -> 63.472079 | J31: =J28+J29+J30 -> -134.56059 | ... L31: =L28+L29+L30 -> 40.119179
A32: Taxes (NOL-shielded early) | C32: =-MAX(0,C31)*C13 -> 0 | D32: =-MAX(0,D31)*D13 -> -1.5418062 | E32: =-MAX(0,E31)*E13 -> -6.2556354 | F32: =-MAX(0,F31)*F13 -> -17.474898 | G32: =-MAX(0,G31)*G13 -> -21.787387 | H32: =-MAX(0,H31)*H13 -> -19.85061 | I32: =-MAX(0,I31)*I13 -> -7.6166495 | J32: =-MAX(0,J31)*J13 -> 0 | ... L32: =-MAX(0,L31)*L13 -> -7.2214522
A33: Net income (loss) | C33: =C31+C32 -> 39 | D33: =D31+D32 -> 75.548502 | E33: =E31+E32 -> 150.13525 | F33: =F31+F32 -> 273.7734 | G33: =G31+G32 -> 250.55495 | H33: =H31+H32 -> 178.65549 | I33: =I31+I32 -> 55.85543 | J33: =J31+J32 -> -134.56059 | ... L33: =L31+L32 -> 32.897727
A34: Adj. EBITDA margin % | C34: =C25/C19 -> 0.15 | D34: =D25/D19 -> 0.17277778 | E34: =E25/E19 -> 0.19555556 | F34: =F25/F19 -> 0.21833333 | G34: =G25/G19 -> 0.17805556 | H34: =H25/H19 -> 0.135 | I34: =I25/I19 -> 0.089166667 | J34: =J25/J19 -> 0.040555556 | ... L34: =L25/L19 -> 0.075
A36: WORKING CAPITAL
A37: Accounts receivable | B37: 120 | C37: =C19*Assumptions!$B$27/365 -> 129.45205 | D37: =D19*Assumptions!$B$27/365 -> 174.76027 | E37: =E19*Assumptions!$B$27/365 -> 229.15441 | F37: =F19*Assumptions!$B$27/365 -> 291.59899 | G37: =G19*Assumptions!$B$27/365 -> 359.76025 | H37: =H19*Assumptions!$B$27/365 -> 429.9135 | I37: =I19*Assumptions!$B$27/365 -> 497.08748 | J37: =J19*Assumptions!$B$27/365 -> 555.49526 | ... L37: =L19*Assumptions!$B$27/365 -> 623.21013
A38: Inventory (panels, cells, polysilicon) | B38: 180 | C38: =-C20*Assumptions!$B$28/365 -> 209.28082 | D38: =-D20*Assumptions!$B$28/365 -> 278.96918 | E38: =-E20*Assumptions!$B$28/365 -> 361.13037 | F38: =-F20*Assumptions!$B$28/365 -> 453.59842 | G38: =-G20*Assumptions!$B$28/365 -> 552.2986 | H38: =-H20*Assumptions!$B$28/365 -> 651.23933 | I38: =-I20*Assumptions!$B$28/365 -> 742.86962 | J38: =-J20*Assumptions!$B$28/365 -> 818.84116 | ... L38: =-L20*Assumptions!$B$28/365 -> 893.26786
A39: Other current assets (incl. 45X receivable) | B39: 90 | C39: =C19*C14 -> 84 | D39: =D19*D14 -> 113.4 | E39: =E19*E14 -> 148.69575 | F39: =F19*F14 -> 189.21534 | G39: =G19*G14 -> 233.44443 | H39: =H19*H14 -> 278.96609 | I39: =I19*I14 -> 322.55454 | J39: =J19*J14 -> 360.4547 | ... L39: =L19*L14 -> 404.39413
A40: AP + accrued | B40: -160 | C40: =(C20+C24)*Assumptions!$B$29/365 -> -186.41096 | D40: =(D20+D24)*Assumptions!$B$29/365 -> -247.64178 | E40: =(E20+E24)*Assumptions!$B$29/365 -> -319.45822 | F40: =(F20+F24)*Assumptions!$B$29/365 -> -399.81461 | G40: =(G20+G24)*Assumptions!$B$29/365 -> -485.01011 | H40: =(H20+H24)*Assumptions!$B$29/365 -> -569.715 | I40: =(I20+I24)*Assumptions!$B$29/365 -> -647.31836 | J40: =(J20+J24)*Assumptions!$B$29/365 -> -710.62246 | ... L40: =(L20+L24)*Assumptions!$B$29/365 -> -768.62583
A41: Customer deposits / deferred revenue | B41: -50 | C41: =-C19*C15 -> -52.5 | D41: =-D19*D15 -> -70.875 | E41: =-E19*E15 -> -92.934844 | F41: =-F19*F15 -> -118.25959 | G41: =-G19*G15 -> -145.90277 | H41: =-H19*H15 -> -174.35381 | I41: =-I19*I15 -> -201.59659 | J41: =-J19*J15 -> -225.28419 | ... L41: =-L19*L15 -> -252.74633
A42: Net working capital | B42: =SUM(B37:B41) -> 180 | C42: =SUM(C37:C41) -> 183.82192 | D42: =SUM(D37:D41) -> 248.61267 | E42: =SUM(E37:E41) -> 326.58747 | F42: =SUM(F37:F41) -> 416.33855 | G42: =SUM(G37:G41) -> 514.5904 | H42: =SUM(H37:H41) -> 616.05012 | I42: =SUM(I37:I41) -> 713.5967 | ... L42: =SUM(L37:L41) -> 899.49996
A43: (Increase) / decrease in NWC — cash impact | C43: =-(C42-B42) -> -3.8219178 | D43: =-(D42-C42) -> -64.790753 | E43: =-(E42-D42) -> -77.974798 | F43: =-(F42-E42) -> -89.751083 | G43: =-(G42-F42) -> -98.251848 | H43: =-(H42-G42) -> -101.45972 | I43: =-(I42-H42) -> -97.546576 | J43: =-(J42-I42) -> -85.287785 | ... L43: =-(L42-K42) -> -36.149739
A45: CAPEX & PP&E (G2_Austin Phase 1 program, then maintenance)
A46: Capex | C46: =Assumptions!$B$40 -> 300 | D46: =Assumptions!$B$41 -> 210 | E46: =E19*Assumptions!$B$42 -> 55.760906 | F46: =F19*Assumptions!$B$42 -> 70.955753 | G46: =G19*Assumptions!$B$42 -> 87.541661 | H46: =H19*Assumptions!$B$42 -> 104.61228 | I46: =I19*Assumptions!$B$42 -> 120.95795 | J46: =J19*Assumptions!$B$42 -> 135.17051 | K46: =K19*Assumptions!$B$42 -> 145.81519 | L46: =L19*Assumptions!$B$42 -> 151.6478 | M46: FY26/27 = G2_Austin Phase 1 ($510mm total). 90% of D&A depreciates PP&E, 10% amortizes intangibles.
A47: PP&E, net | B47: 900 | C47: =B47+C46+C27*0.9 -> 1148.025 | D47: =C47+D46+D27*0.9 -> 1288.5675 | E47: =D47+E46+E27*0.9 -> 1254.1816 | F47: =E47+F46+F27*0.9 -> 1211.6082 | G47: =F47+G46+G27*0.9 -> 1160.5422 | H47: =G47+H46+H27*0.9 -> 1101.2619 | I47: =H47+I46+I27*0.9 -> 1034.735 | J47: =I47+J46+J27*0.9 -> 962.64408 | ... L47: =K47+L46+L27*0.9 -> 811.48233
A49: DEBT SCHEDULE (converts + project debt; revolver row = FUNDING GAP indicator)
A50: Term debt & converts — beginning | C50: =B52 -> 550 | D50: =C52 -> 670 | E50: =D52 -> 670 | F50: =E52 -> 670 | G50: =F52 -> 670 | H50: =G52 -> 670 | I50: =H52 -> 670 | J50: =I52 -> 670 | ... L50: =K52 -> 670
A51: Net issuance / (repayment) — input | C51: 120 | D51: 0 | E51: 0 | F51: 0 | G51: 0 | H51: 0 | I51: 0 | J51: 0 | K51: 0 | L51: 0
A52: Term debt & converts — ending | B52: 550 | C52: =MAX(0,C50+C51) -> 670 | D52: =MAX(0,D50+D51) -> 670 | E52: =MAX(0,E50+E51) -> 670 | F52: =MAX(0,F50+F51) -> 670 | G52: =MAX(0,G50+G51) -> 670 | H52: =MAX(0,H50+H51) -> 670 | I52: =MAX(0,I50+I51) -> 670 | J52: =MAX(0,J50+J51) -> 670 | ... L52: =MAX(0,L50+L51) -> 670
A53: Gap funding — beginning | C53: =B56 -> 0 | D53: =C56 -> 101.07192 | E53: =D56 -> 196.04917 | F53: =E56 -> 45.616926 | G53: =F56 -> 0 | H53: =G56 -> 0 | I53: =H56 -> 0 | J53: =I56 -> 0 | ... L53: =K56 -> 0
A54: Draw (if cash < minimum) = EQUITY RAISE NEEDED | C54: =MAX(0,Assumptions!$B$36-(B72+C33-C26-C27+C43-C46+C67+C68+C51)) -> 101.07192 | D54: =MAX(0,Assumptions!$B$36-(C72+D33-D26-D27+D43-D46+D67+D68+D51)) -> 94.977251 | E54: =MAX(0,Assumptions!$B$36-(D72+E33-E26-E27+E43-E46+E67+E68+E51)) -> 0 | F54: =MAX(0,Assumptions!$B$36-(E72+F33-F26-F27+F43-F46+F67+F68+F51)) -> 0 | G54: =MAX(0,Assumptions!$B$36-(F72+G33-G26-G27+G43-G46+G67+G68+G51)) -> 0 | H54: =MAX(0,Assumptions!$B$36-(G72+H33-H26-H27+H43-H46+H67+H68+H51)) -> 0 | I54: =MAX(0,Assumptions!$B$36-(H72+I33-I26-I27+I43-I46+I67+I68+I51)) -> 0 | J54: =MAX(0,Assumptions!$B$36-(I72+J33-J26-J27+J43-J46+J67+J68+J51)) -> 0 | ... L54: =MAX(0,Assumptions!$B$36-(K72+L33-L26-L27+L43-L46+L67+L68+L51)) -> 0 | M54: Non-zero draws = external funding need. In reality this is dilutive equity, NOT cheap debt — dilution is not modeled.
A55: (Repayment) | C55: =-MIN(C53,MAX(0,(B72+C33-C26-C27+C43-C46+C67+C68+C51)-Assumptions!$B$36)) -> 0 | D55: =-MIN(D53,MAX(0,(C72+D33-D26-D27+D43-D46+D67+D68+D51)-Assumptions!$B$36)) -> 0 | E55: =-MIN(E53,MAX(0,(D72+E33-E26-E27+E43-E46+E67+E68+E51)-Assumptions!$B$36)) -> -150.43224 | F55: =-MIN(F53,MAX(0,(E72+F33-F26-F27+F43-F46+F67+F68+F51)-Assumptions!$B$36)) -> -45.616926 | G55: =-MIN(G53,MAX(0,(F72+G33-G26-G27+G43-G46+G67+G68+G51)-Assumptions!$B$36)) -> 0 | H55: =-MIN(H53,MAX(0,(G72+H33-H26-H27+H43-H46+H67+H68+H51)-Assumptions!$B$36)) -> 0 | I55: =-MIN(I53,MAX(0,(H72+I33-I26-I27+I43-I46+I67+I68+I51)-Assumptions!$B$36)) -> 0 | J55: =-MIN(J53,MAX(0,(I72+J33-J26-J27+J43-J46+J67+J68+J51)-Assumptions!$B$36)) -> 0 | ... L55: =-MIN(L53,MAX(0,(K72+L33-L26-L27+L43-L46+L67+L68+L51)-Assumptions!$B$36)) -> 0
A56: Gap funding — ending | B56: 0 | C56: =C53+C54+C55 -> 101.07192 | D56: =D53+D54+D55 -> 196.04917 | E56: =E53+E54+E55 -> 45.616926 | F56: =F53+F54+F55 -> 0 | G56: =G53+G54+G55 -> 0 | H56: =H53+H54+H55 -> 0 | I56: =I53+I54+I55 -> 0 | J56: =J53+J54+J55 -> 0 | ... L56: =L53+L54+L55 -> 0
A57: Total debt — ending | B57: =B52+B56 -> 550 | C57: =C52+C56 -> 771.07192 | D57: =D52+D56 -> 866.04917 | E57: =E52+E56 -> 715.61693 | F57: =F52+F56 -> 670 | G57: =G52+G56 -> 670 | H57: =H52+H56 -> 670 | I57: =I52+I56 -> 670 | ... L57: =L52+L56 -> 670
A59: CASH FLOW STATEMENT
A60: Net income (loss) | C60: =C33 -> 39 | D60: =D33 -> 75.548502 | E60: =E33 -> 150.13525 | F60: =F33 -> 273.7734 | G60: =G33 -> 250.55495 | H60: =H33 -> 178.65549 | I60: =I33 -> 55.85543 | J60: =J33 -> -134.56059 | ... L60: =L33 -> 32.897727
A61: + D&A | C61: =-C27 -> 57.75 | D61: =-D27 -> 77.175 | E61: =-E27 -> 100.16311 | F61: =-F27 -> 126.14356 | G61: =-G27 -> 154.00848 | H61: =-H27 -> 182.10287 | I61: =-I27 -> 208.31648 | J61: =-J27 -> 230.2905 | ... L61: =-L27 -> 252.74633
A62: + Stock-based compensation | C62: =-C26 -> 21 | D62: =-D26 -> 27.09 | E62: =-E26 -> 33.869588 | F62: =-F26 -> 40.996657 | G62: =-G26 -> 47.985799 | H62: =-H26 -> 54.243407 | I62: =-I26 -> 59.135 | J62: =-J26 -> 62.07831 | ... L62: =-L26 -> 60.65912
A63: +/- Change in NWC | C63: =C43 -> -3.8219178 | D63: =D43 -> -64.790753 | E63: =E43 -> -77.974798 | F63: =F43 -> -89.751083 | G63: =G43 -> -98.251848 | H63: =H43 -> -101.45972 | I63: =I43 -> -97.546576 | J63: =J43 -> -85.287785 | ... L63: =L43 -> -36.149739
A64: Cash from operations | C64: =SUM(C60:C63) -> 113.92808 | D64: =SUM(D60:D63) -> 115.02275 | E64: =SUM(E60:E63) -> 206.19315 | F64: =SUM(F60:F63) -> 351.16253 | G64: =SUM(G60:G63) -> 354.29738 | H64: =SUM(H60:H63) -> 313.54205 | I64: =SUM(I60:I63) -> 225.76033 | J64: =SUM(J60:J63) -> 72.520444 | ... L64: =SUM(L60:L63) -> 310.15344
A65: - Capex | C65: =-C46 -> -300 | D65: =-D46 -> -210 | E65: =-E46 -> -55.760906 | F65: =-F46 -> -70.955753 | G65: =-G46 -> -87.541661 | H65: =-H46 -> -104.61228 | I65: =-I46 -> -120.95795 | J65: =-J46 -> -135.17051 | ... L65: =-L46 -> -151.6478
A66: Free cash flow | C66: =C64+C65 -> -186.07192 | D66: =D64+D65 -> -94.977251 | E66: =E64+E65 -> 150.43224 | F66: =F64+F65 -> 280.20678 | G66: =G64+G65 -> 266.75572 | H66: =H64+H65 -> 208.92976 | I66: =I64+I65 -> 104.80237 | J66: =J64+J65 -> -62.65007 | ... L66: =L64+L65 -> 158.50564
A67: - Acquisitions (Evervolt patents, KORE) | C67: =-Assumptions!$B$43 -> -135 | D67: 0 | E67: 0 | F67: 0 | G67: 0 | H67: 0 | I67: 0 | J67: 0 | K67: 0 | L67: 0
A68: + Equity issuance | C68: =Assumptions!$B$44 -> 0 | D68: 0 | E68: 0 | F68: 0 | G68: 0 | H68: 0 | I68: 0 | J68: 0 | K68: 0 | L68: 0
A69: + Debt draws / (repayments) | C69: =C51+C54+C55 -> 221.07192 | D69: =D51+D54+D55 -> 94.977251 | E69: =E51+E54+E55 -> -150.43224 | F69: =F51+F54+F55 -> -45.616926 | G69: =G51+G54+G55 -> 0 | H69: =H51+H54+H55 -> 0 | I69: =I51+I54+I55 -> 0 | J69: =J51+J54+J55 -> 0 | ... L69: =L51+L54+L55 -> 0
A70: Net change in cash | C70: =C66+C67+C68+C69 -> -100 | D70: =D66+D67+D68+D69 -> 0 | E70: =E66+E67+E68+E69 -> 0 | F70: =F66+F67+F68+F69 -> 234.58985 | G70: =G66+G67+G68+G69 -> 266.75572 | H70: =H66+H67+H68+H69 -> 208.92976 | I70: =I66+I67+I68+I69 -> 104.80237 | J70: =J66+J67+J68+J69 -> -62.65007 | ... L70: =L66+L67+L68+L69 -> 158.50564
A71: Cash — beginning | C71: =B72 -> 200 | D71: =C72 -> 100 | E71: =D72 -> 100 | F71: =E72 -> 100 | G71: =F72 -> 334.58985 | H71: =G72 -> 601.34557 | I71: =H72 -> 810.27533 | J71: =I72 -> 915.0777 | ... L71: =K72 -> 895.86093
A72: Cash — ending | B72: 200 | C72: =C71+C70 -> 100 | D72: =D71+D70 -> 100 | E72: =E71+E70 -> 100 | F72: =F71+F70 -> 334.58985 | G72: =G71+G70 -> 601.34557 | H72: =H71+H70 -> 810.27533 | I72: =I71+I70 -> 915.0777 | J72: =J71+J70 -> 852.42763 | ... L72: =L71+L70 -> 1054.3666
A74: BALANCE SHEET
A75: Cash + restricted | B75: =B72 -> 200 | C75: =C72 -> 100 | D75: =D72 -> 100 | E75: =E72 -> 100 | F75: =F72 -> 334.58985 | G75: =G72 -> 601.34557 | H75: =H72 -> 810.27533 | I75: =I72 -> 915.0777 | ... L75: =L72 -> 1054.3666
A76: Accounts receivable | B76: =B37 -> 120 | C76: =C37 -> 129.45205 | D76: =D37 -> 174.76027 | E76: =E37 -> 229.15441 | F76: =F37 -> 291.59899 | G76: =G37 -> 359.76025 | H76: =H37 -> 429.9135 | I76: =I37 -> 497.08748 | ... L76: =L37 -> 623.21013
A77: Inventory | B77: =B38 -> 180 | C77: =C38 -> 209.28082 | D77: =D38 -> 278.96918 | E77: =E38 -> 361.13037 | F77: =F38 -> 453.59842 | G77: =G38 -> 552.2986 | H77: =H38 -> 651.23933 | I77: =I38 -> 742.86962 | ... L77: =L38 -> 893.26786
A78: Other current assets | B78: =B39 -> 90 | C78: =C39 -> 84 | D78: =D39 -> 113.4 | E78: =E39 -> 148.69575 | F78: =F39 -> 189.21534 | G78: =G39 -> 233.44443 | H78: =H39 -> 278.96609 | I78: =I39 -> 322.55454 | ... L78: =L39 -> 404.39413
A79: PP&E, net | B79: =B47 -> 900 | C79: =C47 -> 1148.025 | D79: =D47 -> 1288.5675 | E79: =E47 -> 1254.1816 | F79: =F47 -> 1211.6082 | G79: =G47 -> 1160.5422 | H79: =H47 -> 1101.2619 | I79: =I47 -> 1034.735 | ... L79: =L47 -> 811.48233
A80: Goodwill + intangibles + other LT | B80: 300 | C80: =B80-C67+C27*0.1 -> 429.225 | D80: =C80-D67+D27*0.1 -> 421.5075 | E80: =D80-E67+E27*0.1 -> 411.49119 | F80: =E80-F67+F27*0.1 -> 398.87683 | G80: =F80-G67+G27*0.1 -> 383.47599 | H80: =G80-H67+H27*0.1 -> 365.2657 | I80: =H80-I67+I27*0.1 -> 344.43405 | J80: =I80-J67+J27*0.1 -> 321.405 | ... L80: =K80-L67+L27*0.1 -> 271.55781
A81: TOTAL ASSETS | B81: =SUM(B75:B80) -> 1790 | C81: =SUM(C75:C80) -> 2099.9829 | D81: =SUM(D75:D80) -> 2377.2045 | E81: =SUM(E75:E80) -> 2504.6533 | F81: =SUM(F75:F80) -> 2879.4876 | G81: =SUM(G75:G80) -> 3290.867 | H81: =SUM(H75:H80) -> 3636.9218 | I81: =SUM(I75:I80) -> 3856.7584 | ... L81: =SUM(L75:L80) -> 4058.2788
A82: AP + accrued | B82: =-B40 -> 160 | C82: =-C40 -> 186.41096 | D82: =-D40 -> 247.64178 | E82: =-E40 -> 319.45822 | F82: =-F40 -> 399.81461 | G82: =-G40 -> 485.01011 | H82: =-H40 -> 569.715 | I82: =-I40 -> 647.31836 | ... L82: =-L40 -> 768.62583
A83: Customer deposits / deferred | B83: =-B41 -> 50 | C83: =-C41 -> 52.5 | D83: =-D41 -> 70.875 | E83: =-E41 -> 92.934844 | F83: =-F41 -> 118.25959 | G83: =-G41 -> 145.90277 | H83: =-H41 -> 174.35381 | I83: =-I41 -> 201.59659 | ... L83: =-L41 -> 252.74633
A84: Total debt | B84: =B57 -> 550 | C84: =C57 -> 771.07192 | D84: =D57 -> 866.04917 | E84: =E57 -> 715.61693 | F84: =F57 -> 670 | G84: =G57 -> 670 | H84: =H57 -> 670 | I84: =I57 -> 670 | ... L84: =L57 -> 670
A85: Other LT liabilities | B85: 120 | C85: =B85 -> 120 | D85: =B85 -> 120 | E85: =B85 -> 120 | F85: =B85 -> 120 | G85: =B85 -> 120 | H85: =B85 -> 120 | I85: =B85 -> 120 | J85: =B85 -> 120 | K85: =B85 -> 120 | L85: =B85 -> 120
A86: TOTAL LIABILITIES | B86: =SUM(B82:B85) -> 880 | C86: =SUM(C82:C85) -> 1129.9829 | D86: =SUM(D82:D85) -> 1304.5659 | E86: =SUM(E82:E85) -> 1248.01 | F86: =SUM(F82:F85) -> 1308.0742 | G86: =SUM(G82:G85) -> 1420.9129 | H86: =SUM(H82:H85) -> 1534.0688 | I86: =SUM(I82:I85) -> 1638.915 | ... L86: =SUM(L82:L85) -> 1811.3722
A87: Total equity (opening = plug; rolls with NI + SBC + issuance) | B87: =B81-B86 -> 910 | C87: =B87+C33-C26+C68 -> 970 | D87: =C87+D33-D26+D68 -> 1072.6385 | E87: =D87+E33-E26+E68 -> 1256.6433 | F87: =E87+F33-F26+F68 -> 1571.4134 | G87: =F87+G33-G26+G68 -> 1869.9541 | H87: =G87+H33-H26+H68 -> 2102.853 | I87: =H87+I33-I26+I68 -> 2217.8435 | J87: =I87+J33-J26+J68 -> 2145.3612 | ... L87: =K87+L33-L26+L68 -> 2246.9067
A88: TOTAL LIABILITIES + EQUITY | B88: =B86+B87 -> 1790 | C88: =C86+C87 -> 2099.9829 | D88: =D86+D87 -> 2377.2045 | E88: =E86+E87 -> 2504.6533 | F88: =F86+F87 -> 2879.4876 | G88: =G86+G87 -> 3290.867 | H88: =H86+H87 -> 3636.9218 | I88: =I86+I87 -> 3856.7584 | ... L88: =L86+L87 -> 4058.2788
A89: Balance check (must be 0) | B89: =B81-B88 -> 0 | C89: =C81-C88 -> 0 | D89: =D81-D88 -> 0 | E89: =E81-E88 -> 0 | F89: =F81-F88 -> 0 | G89: =G81-G88 -> 0 | H89: =H81-H88 -> 0 | I89: =I81-I88 -> 0 | ... L89: =L81-L88 -> 0

Sheet WACC
A1: WEIGHTED AVERAGE COST OF CAPITAL — AUGUST 2026
A4: COST OF EQUITY (CAPM)
A5: Risk-free rate — 10Y UST | B5: 0.0455 | C5: tradingeconomics / FRED DGS10
A6: Levered beta | B6: 2.2 | C6: Small-cap solar manufacturer; post-pivot history is short — proxied high (e)
A7: Equity risk premium | B7: 0.0475 | C7: Damodaran implied ERP, mid-2026
A8: Company-specific premium | B8: 0.02 | C8: Added for policy dependence (45X), funding gap, single-plant concentration, short operating history
A9: Cost of equity | B9: =B5+B6*B7+B8 -> 0.17
A11: COST OF DEBT
A12: Pre-tax cost of debt | B12: 0.085 | C12: Convertible + project debt; high-yield territory
A13: Tax rate | B13: =Assumptions!B38 -> 0.21
A14: After-tax cost of debt | B14: =B12*(1-B13) -> 0.06715 | C14: Note: NOLs mean little near-term tax shield in practice
A16: CAPITAL STRUCTURE (market weights)
A17: Debt / total capitalization | B17: 0.26 | C17: ~$670mm debt vs ~$1.9B market cap
A18: Equity / total capitalization | B18: =1-B17 -> 0.74
A20: WACC | B20: =B18*B9+B17*B14 -> 0.143259
A22: WACC ≈ 13.5%. Sensitivity range in DCF: 11.5% – 15.5%. For a policy-dependent small-cap the discount rate is highly contestable — flex it.

Sheet DCF
A1: DISCOUNTED CASH FLOW — UNLEVERED FCF ($mm; valuation as of FY2026 year-end, mid-year convention)
B4: FY2027E | C4: FY2028E | D4: FY2029E | E4: FY2030E | F4: FY2031E | G4: FY2032E | H4: FY2033E | I4: FY2034E | J4: FY2035E
A5: EBIT | B5: =Model_3S!D28 -> 140.6475 | C5: =Model_3S!E28 -> 229.4458 | D5: =Model_3S!F28 -> 349.25999 | E5: =Model_3S!G28 -> 317.58169 | F5: =Model_3S!H28 -> 234.40901 | G5: =Model_3S!I28 -> 92.062443 | H5: =Model_3S!J28 -> -109.63831 | I5: =Model_3S!K28 -> -27.542869 | J5: =Model_3S!L28 -> 65.714046
A6: Cash taxes on EBIT | B6: =-MAX(0,B5)*Model_3S!D13 -> -2.81295 | C6: =-MAX(0,C5)*Model_3S!E13 -> -9.1778321 | D6: =-MAX(0,D5)*Model_3S!F13 -> -20.955599 | E6: =-MAX(0,E5)*Model_3S!G13 -> -25.406535 | F6: =-MAX(0,F5)*Model_3S!H13 -> -23.440901 | G6: =-MAX(0,G5)*Model_3S!I13 -> -11.047493 | H6: =-MAX(0,H5)*Model_3S!J13 -> 0 | I6: =-MAX(0,I5)*Model_3S!K13 -> 0 | J6: =-MAX(0,J5)*Model_3S!L13 -> -11.828528
A7: + D&A | B7: =-Model_3S!D27 -> 77.175 | C7: =-Model_3S!E27 -> 100.16311 | D7: =-Model_3S!F27 -> 126.14356 | E7: =-Model_3S!G27 -> 154.00848 | F7: =-Model_3S!H27 -> 182.10287 | G7: =-Model_3S!I27 -> 208.31648 | H7: =-Model_3S!J27 -> 230.2905 | I7: =-Model_3S!K27 -> 245.7256 | J7: =-Model_3S!L27 -> 252.74633
A8: − Capex | B8: =-Model_3S!D46 -> -210 | C8: =-Model_3S!E46 -> -55.760906 | D8: =-Model_3S!F46 -> -70.955753 | E8: =-Model_3S!G46 -> -87.541661 | F8: =-Model_3S!H46 -> -104.61228 | G8: =-Model_3S!I46 -> -120.95795 | H8: =-Model_3S!J46 -> -135.17051 | I8: =-Model_3S!K46 -> -145.81519 | J8: =-Model_3S!L46 -> -151.6478
A9: +/− Change in NWC | B9: =Model_3S!D43 -> -64.790753 | C9: =Model_3S!E43 -> -77.974798 | D9: =Model_3S!F43 -> -89.751083 | E9: =Model_3S!G43 -> -98.251848 | F9: =Model_3S!H43 -> -101.45972 | G9: =Model_3S!I43 -> -97.546576 | H9: =Model_3S!J43 -> -85.287785 | I9: =Model_3S!K43 -> -64.465739 | J9: =Model_3S!L43 -> -36.149739
A10: Unlevered free cash flow | B10: =SUM(B5:B9) -> -59.781203 | C10: =SUM(C5:C9) -> 186.69538 | D10: =SUM(D5:D9) -> 293.74111 | E10: =SUM(E5:E9) -> 260.39012 | F10: =SUM(F5:F9) -> 186.99897 | G10: =SUM(G5:G9) -> 70.826895 | H10: =SUM(H5:H9) -> -99.806099 | I10: =SUM(I5:I9) -> 7.9018001 | J10: =SUM(J5:J9) -> 118.83431
A11: Discount period (mid-year) | B11: 0.5 | C11: 1.5 | D11: 2.5 | E11: 3.5 | F11: 4.5 | G11: 5.5 | H11: 6.5 | I11: 7.5 | J11: 8.5
A12: Discount factor @ WACC | B12: =(1+$B$16)^-B11 -> 0.93524993 | C12: =(1+$B$16)^-C11 -> 0.81805604 | D12: =(1+$B$16)^-D11 -> 0.71554743 | E12: =(1+$B$16)^-E11 -> 0.62588393 | F12: =(1+$B$16)^-F11 -> 0.54745594 | G12: =(1+$B$16)^-G11 -> 0.47885557 | H12: =(1+$B$16)^-H11 -> 0.41885134 | I12: =(1+$B$16)^-I11 -> 0.3663661 | J12: =(1+$B$16)^-J11 -> 0.32045766
A13: PV of FCF | B13: =B10*B12 -> -55.910366 | C13: =C10*C12 -> 152.72728 | D13: =D10*D12 -> 210.1857 | E13: =E10*E12 -> 162.97399 | F13: =F10*F12 -> 102.3737 | G13: =G10*G12 -> 33.915853 | H13: =H10*H12 -> -41.803919 | I13: =I10*I12 -> 2.8949517 | J13: =J10*J12 -> 38.081365
A14: Watch the FY2030-33 columns: that's where the 45X step-down bites. If FCF turns negative there, the business never reached standalone viability.
A15: Sum of PV of explicit FCF (FY27–35) | B15: =SUM(B13:J13) -> 605.43855
A16: WACC | B16: =WACC!B20 -> 0.143259
A18: TERMINAL VALUE — METHOD 1: GORDON GROWTH
A19: Terminal growth g | B19: =Assumptions!B47 -> 0.02
A20: Terminal value | B20: =MAX(0,J10)*(1+B19)/(B16-B19) -> 983.38456 | C20: Floored at zero — a negative terminal FCF would imply a worthless (or liability) terminal business
A21: PV of terminal value (9.0 yrs) | B21: =B20/(1+B16)^9 -> 294.72822
A22: Implied exit EV/EBITDA | B22: =IFERROR(B20/Model_3S!L25,0) -> 2.5938644
A24: TERMINAL VALUE — METHOD 2: EXIT MULTIPLE
A25: Exit EV/Adj. EBITDA multiple | B25: =Assumptions!B48 -> 7
A26: Terminal value | B26: =MAX(0,B25*Model_3S!L25) -> 2653.8365
A27: PV of terminal value | B27: =B26/(1+B16)^9 -> 795.37603
A28: Implied perpetuity growth | B28: =IFERROR((B16*B26-J10)/(B26+J10),0) -> 0.094259892
A30: ENTERPRISE → EQUITY VALUE BRIDGE
A31: Net debt, FY2026E year-end (debt − cash) | B31: =Model_3S!C57-Model_3S!C72 -> 671.07192
A32: Diluted shares (mm) | B32: =Assumptions!B37 -> 279.3
B33: Gordon growth | C33: Exit multiple | D33: Average
A34: Enterprise value | B34: =B15+B21 -> 900.16678 | C34: =B15+B27 -> 1400.8146 | D34: =AVERAGE(B34:C34) -> 1150.4907
A35: − Net debt | B35: =-$B$31 -> -671.07192 | C35: =-$B$31 -> -671.07192 | D35: =-$B$31 -> -671.07192
A36: Equity value | B36: =B34+B35 -> 229.09486 | C36: =C34+C35 -> 729.74267 | D36: =D34+D35 -> 479.41876
A37: Implied value per share | B37: =MAX(0,B36)/$B$32 -> 0.82024654 | C37: =MAX(0,C36)/$B$32 -> 2.6127557 | D37: =MAX(0,D36)/$B$32 -> 1.7165011
A38: Upside / (downside) vs current price | B38: =B37/Assumptions!$B$49-1 -> -0.87955264 | C38: =C37/Assumptions!$B$49-1 -> -0.61633543 | D38: =D37/Assumptions!$B$49-1 -> -0.74794404
A40: Equity floored at zero: with ~$520mm net debt, a weak enough operating case wipes out the equity before the enterprise. That IS the bear case for a levered manufacturer.
A42: SENSITIVITY — VALUE PER SHARE: WACC × TERMINAL GROWTH (Gordon)
B43: WACC \ g | C43: 0.01 | D43: 0.015 | E43: 0.02 | F43: 0.025 | G43: 0.03
B44: 0.115 | C44: =MAX(0,SUMPRODUCT($B$10:$J$10,(1+$B$44)^-($B$11:$J$11))+MAX(0,$J$10)*(1+C$43)/($B$44-C$43)/(1+$B$44)^9-$B$31)/$B$32 -> 1.4915465 | D44: =MAX(0,SUMPRODUCT($B$10:$J$10,(1+$B$44)^-($B$11:$J$11))+MAX(0,$J$10)*(1+D$43)/($B$44-D$43)/(1+$B$44)^9-$B$31)/$B$32 -> 1.5763576 | E44: =MAX(0,SUMPRODUCT($B$10:$J$10,(1+$B$44)^-($B$11:$J$11))+MAX(0,$J$10)*(1+E$43)/($B$44-E$43)/(1+$B$44)^9-$B$31)/$B$32 -> 1.6700961 | F44: =MAX(0,SUMPRODUCT($B$10:$J$10,(1+$B$44)^-($B$11:$J$11))+MAX(0,$J$10)*(1+F$43)/($B$44-F$43)/(1+$B$44)^9-$B$31)/$B$32 -> 1.7742501 | G44: =MAX(0,SUMPRODUCT($B$10:$J$10,(1+$B$44)^-($B$11:$J$11))+MAX(0,$J$10)*(1+G$43)/($B$44-G$43)/(1+$B$44)^9-$B$31)/$B$32 -> 1.8906575
B45: 0.125 | C45: =MAX(0,SUMPRODUCT($B$10:$J$10,(1+$B$45)^-($B$11:$J$11))+MAX(0,$J$10)*(1+C$43)/($B$45-C$43)/(1+$B$45)^9-$B$31)/$B$32 -> 1.1796452 | D45: =MAX(0,SUMPRODUCT($B$10:$J$10,(1+$B$45)^-($B$11:$J$11))+MAX(0,$J$10)*(1+D$43)/($B$45-D$43)/(1+$B$45)^9-$B$31)/$B$32 -> 1.2451887 | E45: =MAX(0,SUMPRODUCT($B$10:$J$10,(1+$B$45)^-($B$11:$J$11))+MAX(0,$J$10)*(1+E$43)/($B$45-E$43)/(1+$B$45)^9-$B$31)/$B$32 -> 1.3169746 | F45: =MAX(0,SUMPRODUCT($B$10:$J$10,(1+$B$45)^-($B$11:$J$11))+MAX(0,$J$10)*(1+F$43)/($B$45-F$43)/(1+$B$45)^9-$B$31)/$B$32 -> 1.395939 | G45: =MAX(0,SUMPRODUCT($B$10:$J$10,(1+$B$45)^-($B$11:$J$11))+MAX(0,$J$10)*(1+G$43)/($B$45-G$43)/(1+$B$45)^9-$B$31)/$B$32 -> 1.4832155
B46: 0.135 | C46: =MAX(0,SUMPRODUCT($B$10:$J$10,(1+$B$46)^-($B$11:$J$11))+MAX(0,$J$10)*(1+C$43)/($B$46-C$43)/(1+$B$46)^9-$B$31)/$B$32 -> 0.91795599 | D46: =MAX(0,SUMPRODUCT($B$10:$J$10,(1+$B$46)^-($B$11:$J$11))+MAX(0,$J$10)*(1+D$43)/($B$46-D$43)/(1+$B$46)^9-$B$31)/$B$32 -> 0.96945309 | E46: =MAX(0,SUMPRODUCT($B$10:$J$10,(1+$B$46)^-($B$11:$J$11))+MAX(0,$J$10)*(1+E$43)/($B$46-E$43)/(1+$B$46)^9-$B$31)/$B$32 -> 1.0254282 | F46: =MAX(0,SUMPRODUCT($B$10:$J$10,(1+$B$46)^-($B$11:$J$11))+MAX(0,$J$10)*(1+F$43)/($B$46-F$43)/(1+$B$46)^9-$B$31)/$B$32 -> 1.086492 | G46: =MAX(0,SUMPRODUCT($B$10:$J$10,(1+$B$46)^-($B$11:$J$11))+MAX(0,$J$10)*(1+G$43)/($B$46-G$43)/(1+$B$46)^9-$B$31)/$B$32 -> 1.1533713
B47: 0.145 | C47: =MAX(0,SUMPRODUCT($B$10:$J$10,(1+$B$47)^-($B$11:$J$11))+MAX(0,$J$10)*(1+C$43)/($B$47-C$43)/(1+$B$47)^9-$B$31)/$B$32 -> 0.6950886 | D47: =MAX(0,SUMPRODUCT($B$10:$J$10,(1+$B$47)^-($B$11:$J$11))+MAX(0,$J$10)*(1+D$43)/($B$47-D$43)/(1+$B$47)^9-$B$31)/$B$32 -> 0.73612034 | E47: =MAX(0,SUMPRODUCT($B$10:$J$10,(1+$B$47)^-($B$11:$J$11))+MAX(0,$J$10)*(1+E$43)/($B$47-E$43)/(1+$B$47)^9-$B$31)/$B$32 -> 0.78043462 | F47: =MAX(0,SUMPRODUCT($B$10:$J$10,(1+$B$47)^-($B$11:$J$11))+MAX(0,$J$10)*(1+F$43)/($B$47-F$43)/(1+$B$47)^9-$B$31)/$B$32 -> 0.82844175 | G47: =MAX(0,SUMPRODUCT($B$10:$J$10,(1+$B$47)^-($B$11:$J$11))+MAX(0,$J$10)*(1+G$43)/($B$47-G$43)/(1+$B$47)^9-$B$31)/$B$32 -> 0.88062342
B48: 0.155 | C48: =MAX(0,SUMPRODUCT($B$10:$J$10,(1+$B$48)^-($B$11:$J$11))+MAX(0,$J$10)*(1+C$43)/($B$48-C$43)/(1+$B$48)^9-$B$31)/$B$32 -> 0.50282709 | D48: =MAX(0,SUMPRODUCT($B$10:$J$10,(1+$B$48)^-($B$11:$J$11))+MAX(0,$J$10)*(1+D$43)/($B$48-D$43)/(1+$B$48)^9-$B$31)/$B$32 -> 0.5359165 | E48: =MAX(0,SUMPRODUCT($B$10:$J$10,(1+$B$48)^-($B$11:$J$11))+MAX(0,$J$10)*(1+E$43)/($B$48-E$43)/(1+$B$48)^9-$B$31)/$B$32 -> 0.57145697 | F48: =MAX(0,SUMPRODUCT($B$10:$J$10,(1+$B$48)^-($B$11:$J$11))+MAX(0,$J$10)*(1+F$43)/($B$48-F$43)/(1+$B$48)^9-$B$31)/$B$32 -> 0.60973133 | G48: =MAX(0,SUMPRODUCT($B$10:$J$10,(1+$B$48)^-($B$11:$J$11))+MAX(0,$J$10)*(1+G$43)/($B$48-G$43)/(1+$B$48)^9-$B$31)/$B$32 -> 0.65106764
A50: SENSITIVITY — VALUE PER SHARE: WACC × EXIT EV/EBITDA MULTIPLE
B51: WACC \ x | C51: 4 | D51: 5.5 | E51: 7 | F51: 8.5 | G51: 10
B52: 0.115 | C52: =MAX(0,SUMPRODUCT($B$10:$J$10,(1+$B$52)^-($B$11:$J$11))+MAX(0,C$51*Model_3S!$L$25)/(1+$B$52)^9-$B$31)/$B$32 -> 1.9934676 | D52: =MAX(0,SUMPRODUCT($B$10:$J$10,(1+$B$52)^-($B$11:$J$11))+MAX(0,D$51*Model_3S!$L$25)/(1+$B$52)^9-$B$31)/$B$32 -> 2.757871 | E52: =MAX(0,SUMPRODUCT($B$10:$J$10,(1+$B$52)^-($B$11:$J$11))+MAX(0,E$51*Model_3S!$L$25)/(1+$B$52)^9-$B$31)/$B$32 -> 3.5222745 | F52: =MAX(0,SUMPRODUCT($B$10:$J$10,(1+$B$52)^-($B$11:$J$11))+MAX(0,F$51*Model_3S!$L$25)/(1+$B$52)^9-$B$31)/$B$32 -> 4.2866779 | G52: =MAX(0,SUMPRODUCT($B$10:$J$10,(1+$B$52)^-($B$11:$J$11))+MAX(0,G$51*Model_3S!$L$25)/(1+$B$52)^9-$B$31)/$B$32 -> 5.0510814
B53: 0.125 | C53: =MAX(0,SUMPRODUCT($B$10:$J$10,(1+$B$53)^-($B$11:$J$11))+MAX(0,C$51*Model_3S!$L$25)/(1+$B$53)^9-$B$31)/$B$32 -> 1.7661024 | D53: =MAX(0,SUMPRODUCT($B$10:$J$10,(1+$B$53)^-($B$11:$J$11))+MAX(0,D$51*Model_3S!$L$25)/(1+$B$53)^9-$B$31)/$B$32 -> 2.4714834 | E53: =MAX(0,SUMPRODUCT($B$10:$J$10,(1+$B$53)^-($B$11:$J$11))+MAX(0,E$51*Model_3S!$L$25)/(1+$B$53)^9-$B$31)/$B$32 -> 3.1768643 | F53: =MAX(0,SUMPRODUCT($B$10:$J$10,(1+$B$53)^-($B$11:$J$11))+MAX(0,F$51*Model_3S!$L$25)/(1+$B$53)^9-$B$31)/$B$32 -> 3.8822453 | G53: =MAX(0,SUMPRODUCT($B$10:$J$10,(1+$B$53)^-($B$11:$J$11))+MAX(0,G$51*Model_3S!$L$25)/(1+$B$53)^9-$B$31)/$B$32 -> 4.5876263
B54: 0.135 | C54: =MAX(0,SUMPRODUCT($B$10:$J$10,(1+$B$54)^-($B$11:$J$11))+MAX(0,C$51*Model_3S!$L$25)/(1+$B$54)^9-$B$31)/$B$32 -> 1.5551517 | D54: =MAX(0,SUMPRODUCT($B$10:$J$10,(1+$B$54)^-($B$11:$J$11))+MAX(0,D$51*Model_3S!$L$25)/(1+$B$54)^9-$B$31)/$B$32 -> 2.2065306 | E54: =MAX(0,SUMPRODUCT($B$10:$J$10,(1+$B$54)^-($B$11:$J$11))+MAX(0,E$51*Model_3S!$L$25)/(1+$B$54)^9-$B$31)/$B$32 -> 2.8579095 | F54: =MAX(0,SUMPRODUCT($B$10:$J$10,(1+$B$54)^-($B$11:$J$11))+MAX(0,F$51*Model_3S!$L$25)/(1+$B$54)^9-$B$31)/$B$32 -> 3.5092884 | G54: =MAX(0,SUMPRODUCT($B$10:$J$10,(1+$B$54)^-($B$11:$J$11))+MAX(0,G$51*Model_3S!$L$25)/(1+$B$54)^9-$B$31)/$B$32 -> 4.1606673
B55: 0.145 | C55: =MAX(0,SUMPRODUCT($B$10:$J$10,(1+$B$55)^-($B$11:$J$11))+MAX(0,C$51*Model_3S!$L$25)/(1+$B$55)^9-$B$31)/$B$32 -> 1.3591969 | D55: =MAX(0,SUMPRODUCT($B$10:$J$10,(1+$B$55)^-($B$11:$J$11))+MAX(0,D$51*Model_3S!$L$25)/(1+$B$55)^9-$B$31)/$B$32 -> 1.9611284 | E55: =MAX(0,SUMPRODUCT($B$10:$J$10,(1+$B$55)^-($B$11:$J$11))+MAX(0,E$51*Model_3S!$L$25)/(1+$B$55)^9-$B$31)/$B$32 -> 2.5630599 | F55: =MAX(0,SUMPRODUCT($B$10:$J$10,(1+$B$55)^-($B$11:$J$11))+MAX(0,F$51*Model_3S!$L$25)/(1+$B$55)^9-$B$31)/$B$32 -> 3.1649914 | G55: =MAX(0,SUMPRODUCT($B$10:$J$10,(1+$B$55)^-($B$11:$J$11))+MAX(0,G$51*Model_3S!$L$25)/(1+$B$55)^9-$B$31)/$B$32 -> 3.7669229
B56: 0.155 | C56: =MAX(0,SUMPRODUCT($B$10:$J$10,(1+$B$56)^-($B$11:$J$11))+MAX(0,C$51*Model_3S!$L$25)/(1+$B$56)^9-$B$31)/$B$32 -> 1.1769572 | D56: =MAX(0,SUMPRODUCT($B$10:$J$10,(1+$B$56)^-($B$11:$J$11))+MAX(0,D$51*Model_3S!$L$25)/(1+$B$56)^9-$B$31)/$B$32 -> 1.7335769 | E56: =MAX(0,SUMPRODUCT($B$10:$J$10,(1+$B$56)^-($B$11:$J$11))+MAX(0,E$51*Model_3S!$L$25)/(1+$B$56)^9-$B$31)/$B$32 -> 2.2901966 | F56: =MAX(0,SUMPRODUCT($B$10:$J$10,(1+$B$56)^-($B$11:$J$11))+MAX(0,F$51*Model_3S!$L$25)/(1+$B$56)^9-$B$31)/$B$32 -> 2.8468163 | G56: =MAX(0,SUMPRODUCT($B$10:$J$10,(1+$B$56)^-($B$11:$J$11))+MAX(0,G$51*Model_3S!$L$25)/(1+$B$56)^9-$B$31)/$B$32 -> 3.403436
A58: SENSITIVITY — THE ONE THAT MATTERS: TERMINAL EX-45X GROSS MARGIN × 45X SURVIVAL
A59: Rev35 ≈ FY26E rev × (1+avg growth)^9. EBITDA35 = Rev35 × (ex-credit GM − opex% + credit%×survival factor). 'Survival' = share of 45X still in force at FY35 (0 = full statutory phase-out, 1 = credits extended indefinitely). Exit-multiple TV.
B60: term GM \ 45X survival | C60: 0 | D60: 0.25 | E60: 0.5 | F60: 0.75 | G60: 1
B61: 0.03 | C61: =MAX(0,$B$15+MAX(0,$B$25*((Model_3S!$C$19*(1+(Assumptions!$E$12+Assumptions!$E$13)/2)^9)*($B$61-Assumptions!$F$19+Assumptions!$F$18*C$60)))/(1+$B$16)^9-$B$31)/$B$32 -> 0 | D61: =MAX(0,$B$15+MAX(0,$B$25*((Model_3S!$C$19*(1+(Assumptions!$E$12+Assumptions!$E$13)/2)^9)*($B$61-Assumptions!$F$19+Assumptions!$F$18*D$60)))/(1+$B$16)^9-$B$31)/$B$32 -> 1.1368175 | E61: =MAX(0,$B$15+MAX(0,$B$25*((Model_3S!$C$19*(1+(Assumptions!$E$12+Assumptions!$E$13)/2)^9)*($B$61-Assumptions!$F$19+Assumptions!$F$18*E$60)))/(1+$B$16)^9-$B$31)/$B$32 -> 3.8804374 | F61: =MAX(0,$B$15+MAX(0,$B$25*((Model_3S!$C$19*(1+(Assumptions!$E$12+Assumptions!$E$13)/2)^9)*($B$61-Assumptions!$F$19+Assumptions!$F$18*F$60)))/(1+$B$16)^9-$B$31)/$B$32 -> 6.6240572 | G61: =MAX(0,$B$15+MAX(0,$B$25*((Model_3S!$C$19*(1+(Assumptions!$E$12+Assumptions!$E$13)/2)^9)*($B$61-Assumptions!$F$19+Assumptions!$F$18*G$60)))/(1+$B$16)^9-$B$31)/$B$32 -> 9.367677
B62: 0.08 | C62: =MAX(0,$B$15+MAX(0,$B$25*((Model_3S!$C$19*(1+(Assumptions!$E$12+Assumptions!$E$13)/2)^9)*($B$62-Assumptions!$F$19+Assumptions!$F$18*C$60)))/(1+$B$16)^9-$B$31)/$B$32 -> 0.35292617 | D62: =MAX(0,$B$15+MAX(0,$B$25*((Model_3S!$C$19*(1+(Assumptions!$E$12+Assumptions!$E$13)/2)^9)*($B$62-Assumptions!$F$19+Assumptions!$F$18*D$60)))/(1+$B$16)^9-$B$31)/$B$32 -> 3.096546 | E62: =MAX(0,$B$15+MAX(0,$B$25*((Model_3S!$C$19*(1+(Assumptions!$E$12+Assumptions!$E$13)/2)^9)*($B$62-Assumptions!$F$19+Assumptions!$F$18*E$60)))/(1+$B$16)^9-$B$31)/$B$32 -> 5.8401658 | F62: =MAX(0,$B$15+MAX(0,$B$25*((Model_3S!$C$19*(1+(Assumptions!$E$12+Assumptions!$E$13)/2)^9)*($B$62-Assumptions!$F$19+Assumptions!$F$18*F$60)))/(1+$B$16)^9-$B$31)/$B$32 -> 8.5837856 | G62: =MAX(0,$B$15+MAX(0,$B$25*((Model_3S!$C$19*(1+(Assumptions!$E$12+Assumptions!$E$13)/2)^9)*($B$62-Assumptions!$F$19+Assumptions!$F$18*G$60)))/(1+$B$16)^9-$B$31)/$B$32 -> 11.327405
B63: 0.14 | C63: =MAX(0,$B$15+MAX(0,$B$25*((Model_3S!$C$19*(1+(Assumptions!$E$12+Assumptions!$E$13)/2)^9)*($B$63-Assumptions!$F$19+Assumptions!$F$18*C$60)))/(1+$B$16)^9-$B$31)/$B$32 -> 2.7046003 | D63: =MAX(0,$B$15+MAX(0,$B$25*((Model_3S!$C$19*(1+(Assumptions!$E$12+Assumptions!$E$13)/2)^9)*($B$63-Assumptions!$F$19+Assumptions!$F$18*D$60)))/(1+$B$16)^9-$B$31)/$B$32 -> 5.4482201 | E63: =MAX(0,$B$15+MAX(0,$B$25*((Model_3S!$C$19*(1+(Assumptions!$E$12+Assumptions!$E$13)/2)^9)*($B$63-Assumptions!$F$19+Assumptions!$F$18*E$60)))/(1+$B$16)^9-$B$31)/$B$32 -> 8.1918399 | F63: =MAX(0,$B$15+MAX(0,$B$25*((Model_3S!$C$19*(1+(Assumptions!$E$12+Assumptions!$E$13)/2)^9)*($B$63-Assumptions!$F$19+Assumptions!$F$18*F$60)))/(1+$B$16)^9-$B$31)/$B$32 -> 10.93546 | G63: =MAX(0,$B$15+MAX(0,$B$25*((Model_3S!$C$19*(1+(Assumptions!$E$12+Assumptions!$E$13)/2)^9)*($B$63-Assumptions!$F$19+Assumptions!$F$18*G$60)))/(1+$B$16)^9-$B$31)/$B$32 -> 13.67908
B64: 0.18 | C64: =MAX(0,$B$15+MAX(0,$B$25*((Model_3S!$C$19*(1+(Assumptions!$E$12+Assumptions!$E$13)/2)^9)*($B$64-Assumptions!$F$19+Assumptions!$F$18*C$60)))/(1+$B$16)^9-$B$31)/$B$32 -> 4.2723831 | D64: =MAX(0,$B$15+MAX(0,$B$25*((Model_3S!$C$19*(1+(Assumptions!$E$12+Assumptions!$E$13)/2)^9)*($B$64-Assumptions!$F$19+Assumptions!$F$18*D$60)))/(1+$B$16)^9-$B$31)/$B$32 -> 7.0160029 | E64: =MAX(0,$B$15+MAX(0,$B$25*((Model_3S!$C$19*(1+(Assumptions!$E$12+Assumptions!$E$13)/2)^9)*($B$64-Assumptions!$F$19+Assumptions!$F$18*E$60)))/(1+$B$16)^9-$B$31)/$B$32 -> 9.7596227 | F64: =MAX(0,$B$15+MAX(0,$B$25*((Model_3S!$C$19*(1+(Assumptions!$E$12+Assumptions!$E$13)/2)^9)*($B$64-Assumptions!$F$19+Assumptions!$F$18*F$60)))/(1+$B$16)^9-$B$31)/$B$32 -> 12.503242 | G64: =MAX(0,$B$15+MAX(0,$B$25*((Model_3S!$C$19*(1+(Assumptions!$E$12+Assumptions!$E$13)/2)^9)*($B$64-Assumptions!$F$19+Assumptions!$F$18*G$60)))/(1+$B$16)^9-$B$31)/$B$32 -> 15.246862
B65: 0.22 | C65: =MAX(0,$B$15+MAX(0,$B$25*((Model_3S!$C$19*(1+(Assumptions!$E$12+Assumptions!$E$13)/2)^9)*($B$65-Assumptions!$F$19+Assumptions!$F$18*C$60)))/(1+$B$16)^9-$B$31)/$B$32 -> 5.8401658 | D65: =MAX(0,$B$15+MAX(0,$B$25*((Model_3S!$C$19*(1+(Assumptions!$E$12+Assumptions!$E$13)/2)^9)*($B$65-Assumptions!$F$19+Assumptions!$F$18*D$60)))/(1+$B$16)^9-$B$31)/$B$32 -> 8.5837856 | E65: =MAX(0,$B$15+MAX(0,$B$25*((Model_3S!$C$19*(1+(Assumptions!$E$12+Assumptions!$E$13)/2)^9)*($B$65-Assumptions!$F$19+Assumptions!$F$18*E$60)))/(1+$B$16)^9-$B$31)/$B$32 -> 11.327405 | F65: =MAX(0,$B$15+MAX(0,$B$25*((Model_3S!$C$19*(1+(Assumptions!$E$12+Assumptions!$E$13)/2)^9)*($B$65-Assumptions!$F$19+Assumptions!$F$18*F$60)))/(1+$B$16)^9-$B$31)/$B$32 -> 14.071025 | G65: =MAX(0,$B$15+MAX(0,$B$25*((Model_3S!$C$19*(1+(Assumptions!$E$12+Assumptions!$E$13)/2)^9)*($B$65-Assumptions!$F$19+Assumptions!$F$18*G$60)))/(1+$B$16)^9-$B$31)/$B$32 -> 16.814645

Sheet Comps
A1: TRADING COMPARABLES — SOLAR MANUFACTURING (Aug 2026; peer multiples estimated)
A4: Company | B4: Ticker | C4: EV/Revenue | D4: EV/EBITDA | E4: Note
A5: First Solar | B5: FSLR | C5: 3 | D5: 8 | E5: e — the US-manufacturing benchmark; thin-film, 45X beneficiary, profitable
A6: Canadian Solar | B6: CSIQ | C6: 0.4 | D6: 6 | E6: e — global module maker; commodity economics
A7: JinkoSolar | B7: JKS | C7: 0.3 | D7: 5 | E7: e — Chinese scale player; the pricing pressure source
A8: Array Technologies | B8: ARRY | C8: 1.2 | D8: 8 | E8: e — US solar equipment (trackers)
A9: T1 Energy (self) | B9: TE | C9: =(Assumptions!B49*Assumptions!B37+DCF!B31)/Model_3S!C19 -> 2.4505761 | D9: =IFERROR((Assumptions!B49*Assumptions!B37+DCF!B31)/Model_3S!C25,0) -> 16.337174 | E9: EV/EBITDA is meaningless while FY26E EBITDA is ~zero/negative — use EV/Revenue
A10: Peer median (ex-TE) | C10: =MEDIAN(C5:C8) -> 0.8 | D10: =MEDIAN(D5:D8) -> 7
A11: Solar manufacturing is a COMMODITY industry — module makers trade at fractions of revenue. Only FSLR earns a premium (differentiated thin-film + scale + credits). TE's valuation case rests on becoming FSLR-like, not CSIQ-like.
A13: IMPLIED VALUE PER SHARE
A14: Method | B14: Low x | C14: High x | D14: Metric | E14: $/sh low | F14: $/sh high
A15: EV/Revenue × FY2026E revenue | B15: 0.8 | C15: 2 | D15: =Model_3S!C19 -> 1050 | E15: =MAX(0,B15*D15-DCF!$B$31)/Assumptions!$B$37 -> 0.60482665 | F15: =MAX(0,C15*D15-DCF!$B$31)/Assumptions!$B$37 -> 5.1161048
A16: EV/EBITDA × FY2029E (post-ramp, pre-phase-out) | B16: 5 | C16: 8 | D16: =Model_3S!F25 -> 516.4002 | E16: =MAX(0,B16*D16-DCF!$B$31)/Assumptions!$B$37 -> 6.8418514 | F16: =MAX(0,C16*D16-DCF!$B$31)/Assumptions!$B$37 -> 12.388578
A18: FY2029E is used for the EBITDA method: it's the last year of full 45X before the step-down, i.e. peak reported profitability.

Sheet Precedents
A1: PRECEDENT TRANSACTIONS — SOLAR / CLEAN-ENERGY MANUFACTURING
A4: Date | B4: Acquirer | C4: Target | D4: EV ($mm) | E4: Basis | F4: Note
A5: Nov-2024 | B5: T1 Energy (FREYR) | C5: Trina Solar US assets (G1_Dallas) | D5: 340 | E5: ~$0.07/W capacity | F5: T1's own founding deal — 5 GW module plant
A6: 2026 | B6: T1 Energy | C6: KORE Power | E6: n/d | F6: Storage + AI data-center infrastructure ('T1 NRI')
A7: 2026 | B7: T1 Energy | C7: Evervolt solar patents | D7: 135 | E7: IP | F7: Foundational solar patents
A8: 2023-25 | B8: Qcells / Hanwha | C8: US manufacturing buildout | D8: 2500 | E8: capacity investment | F8: e — Georgia integrated plant; not an M&A comp but a capacity benchmark
A9: 2022 | B9: SK / others | C9: US cell capacity investments | E9: n/d | F9: Policy-driven capacity announcements post-IRA
A11: There is no clean M&A comp set for a sub-scale US solar manufacturer — most transactions are capacity investments or distressed asset purchases, and several US module ventures have failed outright. The band below is a CAPACITY-BASED framework ($/W of installed nameplate), which is how these assets actually change hands.
A13: APPLIED RANGE — $/W OF NAMEPLATE CAPACITY
B14: Low | C14: High
A15: Nameplate capacity (GW) — G1 modules (+G2 cells from 2027) | B15: 5 | C15: 8
A16: EV per watt ($/W) | B16: 0.07 | C16: 0.15
A17: Implied EV ($mm) | B17: =B15*1000*B16 -> 350 | C17: =C15*1000*C16 -> 1200
A18: Implied value per share | B18: =MAX(0,B17-DCF!$B$31)/Assumptions!$B$37 -> 0 | C18: =MAX(0,C17-DCF!$B$31)/Assumptions!$B$37 -> 1.8937633
A20: $0.07/W ≈ what T1 paid for Trina's G1 assets. $0.15/W reflects a strategic premium for a de-risked, credit-qualified US line. Note how sensitive the per-share result is to net debt — that's the leverage at work.

Sheet LBO
A1: LBO / CONTROL-BUYOUT ANALYSIS — 5-YEAR HOLD (ENTRY END-FY2026, EXIT END-FY2031) ($mm)
A2: A conventional LBO is NOT viable here: FY2026E EBITDA is ~zero/negative and the company already carries ~$670mm of debt against a $510mm capex program. Debt capacity is sized off FY2029E EBITDA (peak-45X) and the sponsor must FUND the buildout — this is a growth-equity / distressed-control structure, not a classic buyout.
A5: ENTRY & FINANCING
A6: Entry premium to current price | B6: 0.3
A7: Entry price per share | B7: =Assumptions!B49*(1+B6) -> 8.853
A8: Diluted shares (mm) | B8: =Assumptions!B37 -> 279.3
A9: Equity purchase price | B9: =B7*B8 -> 2472.6429
A10: Plus: net debt assumed/refinanced | B10: =DCF!B31 -> 671.07192
A11: Entry enterprise value | B11: =B9+B10 -> 3143.7148
A12: Transaction fees (% of EV) | B12: 0.02
A13: FY2029E Adj. EBITDA (debt-sizing basis, peak 45X) | B13: =Model_3S!F25 -> 516.4002
A14: Entry EV / FY2029E EBITDA | B14: =IFERROR(B11/B13,0) -> 6.087749
A15: Debt tranche | B15: Multiple (on FY29E) | C15: Rate | D15: Amount
A16: Term Loan B | B16: 3 | C16: 0.095 | D16: =MAX(0,B16*$B$13) -> 1549.2006
A17: Senior notes | B17: 1 | C17: 0.115 | D17: =MAX(0,B17*$B$13) -> 516.4002
A18: Total new debt | B18: =B16+B17 -> 4 | D18: =D16+D17 -> 2065.6008
A19: Sponsor equity = EV×(1+fees) − debt | B19: =B11*(1+B12)-D18 -> 1140.9883
A20: Plus: capex/burn funding during hold (negative FCF) | B20: =-SUMIF(DCF!B10:F10,"<0") -> 59.781203
A21: TOTAL SPONSOR COMMITMENT | B21: =B19+B20 -> 1200.7695
A23: DEBT PAYDOWN — 100% FCF SWEEP (post-funding)
B24: FY2027E | C24: FY2028E | D24: FY2029E | E24: FY2030E | F24: FY2031E
A25: Unlevered FCF (DCF sheet) | B25: =DCF!B10 -> -59.781203 | C25: =DCF!C10 -> 186.69538 | D25: =DCF!D10 -> 293.74111 | E25: =DCF!E10 -> 260.39012 | F25: =DCF!F10 -> 186.99897
A26: Cash interest — TLB (beginning) | B26: =-$D$16*$C$16 -> -147.17406 | C26: =-B32*$C$16 -> -147.17406 | D26: =-C32*$C$16 -> -144.94033 | E26: =-D32*$C$16 -> -132.36962 | F26: =-E32*$C$16 -> -122.02382
A27: Cash interest — notes | B27: =-$D$17*$C$17 -> -59.386023 | C27: =-$D$17*$C$17 -> -59.386023 | D27: =-$D$17*$C$17 -> -59.386023 | E27: =-$D$17*$C$17 -> -59.386023 | F27: =-$D$17*$C$17 -> -59.386023
A28: Interest tax shield | B28: =-(B26+B27)*Assumptions!$B$38 -> 43.377617 | C28: =-(C26+C27)*Assumptions!$B$38 -> 43.377617 | D28: =-(D26+D27)*Assumptions!$B$38 -> 42.908535 | E28: =-(E26+E27)*Assumptions!$B$38 -> 40.268685 | F28: =-(F26+F27)*Assumptions!$B$38 -> 38.096067
A29: Levered FCF for paydown | B29: =MAX(0,B25+B26+B27+B28) -> 0 | C29: =MAX(0,C25+C26+C27+C28) -> 23.512912 | D29: =MAX(0,D25+D26+D27+D28) -> 132.32329 | E29: =MAX(0,E25+E26+E27+E28) -> 108.90317 | F29: =MAX(0,F25+F26+F27+F28) -> 43.685194
A30: TLB — beginning | B30: =$D$16 -> 1549.2006 | C30: =B32 -> 1549.2006 | D30: =C32 -> 1525.6877 | E30: =D32 -> 1393.3644 | F30: =E32 -> 1284.4612
A31: TLB — (paydown) | B31: =-MIN(B30,B29) -> 0 | C31: =-MIN(C30,C29) -> -23.512912 | D31: =-MIN(D30,D29) -> -132.32329 | E31: =-MIN(E30,E29) -> -108.90317 | F31: =-MIN(F30,F29) -> -43.685194
A32: TLB — ending | B32: =B30+B31 -> 1549.2006 | C32: =C30+C31 -> 1525.6877 | D32: =D30+D31 -> 1393.3644 | E32: =E30+E31 -> 1284.4612 | F32: =F30+F31 -> 1240.776
A33: Notes — ending (bullet) | B33: =$D$17 -> 516.4002 | C33: =$D$17 -> 516.4002 | D33: =$D$17 -> 516.4002 | E33: =$D$17 -> 516.4002 | F33: =$D$17 -> 516.4002
A34: Total debt — ending | B34: =B32+B33 -> 2065.6008 | C34: =C32+C33 -> 2042.0879 | D34: =D32+D33 -> 1909.7646 | E34: =E32+E33 -> 1800.8614 | F34: =F32+F33 -> 1757.1763
A36: EXIT & RETURNS
A37: FY2031E Adj. EBITDA | B37: =Model_3S!H25 -> 470.75528
A38: Exit EV/EBITDA multiple | B38: 7
A39: Exit enterprise value | B39: =MAX(0,B37*B38) -> 3295.287
A40: Less: exit net debt | B40: =-F34 -> -1757.1763
A41: Exit equity value | B41: =MAX(0,B39+B40) -> 1538.1107
A42: MOIC | B42: =IFERROR(B41/B21,0) -> 1.2809375
A43: IRR (5-yr) | B43: =IFERROR(MAX(-0.99,(B42)^(1/5)-1),-0.99) -> 0.050764977 | C43: Note FY2031 sits INSIDE the 45X step-down — a sponsor exiting then sells a business whose credits are already fading
A45: MAXIMUM ENTRY PRICE AT TARGET IRR THRESHOLDS
A46: Target IRR | B46: Max total commitment | C46: Max equity purchase | D46: Implied price/share | E46: Prem/(disc) to market
A47: 0.15 | B47: =$B$41/(1+A47)^5 -> 764.71286 | C47: =B47-$B$20 -> 704.93165 | D47: =MAX(0,C47-$B$10)/$B$8 -> 0.12123071 | E47: =D47/Assumptions!$B$49-1 -> -0.98219813
A48: 0.2 | B48: =$B$41/(1+A48)^5 -> 618.1322 | C48: =B48-$B$20 -> 558.35099 | D48: =MAX(0,C48-$B$10)/$B$8 -> 0 | E48: =D48/Assumptions!$B$49-1 -> -1
A49: 0.25 | B49: =$B$41/(1+A49)^5 -> 504.00812 | C49: =B49-$B$20 -> 444.22691 | D49: =MAX(0,C49-$B$10)/$B$8 -> 0 | E49: =D49/Assumptions!$B$49-1 -> -1
A50: 0.3 | B50: =$B$41/(1+A50)^5 -> 414.25793 | C50: =B50-$B$20 -> 354.47673 | D50: =MAX(0,C50-$B$10)/$B$8 -> 0 | E50: =D50/Assumptions!$B$49-1 -> -1
A52: If these implied prices land near or below zero, it means a financial buyer cannot underwrite the equity at ANY price on these assumptions — the buildout funding plus existing leverage consumes the whole return.

Sheet Monte_Carlo
A1: MONTE CARLO SIMULATION — 500 LIVE TRIALS (press F9 / recalc to refresh)
A2: Four random variables including 45X SURVIVAL — the policy variable that dominates this equity. Value floored at zero (levered small-cap: the equity can go to zero while the plant still exists).
A4: Distribution parameters
A5: Variable | B5: Mean (linked) | C5: σ (input)
A6: FY2027 revenue growth | B6: =Assumptions!E12 -> 0.35 | C6: 0.15
A7: Terminal ex-45X gross margin | B7: =Assumptions!F17 -> 0.14 | C7: 0.05
A8: WACC | B8: =WACC!B20 -> 0.143259 | C8: 0.02
A9: 45X survival factor at FY2035 (0=full phase-out, 1=extended) | B9: 0.25 | C9: 0.25
A11: Calibration statics (linked)
A12: FY2026E revenue | B12: =Model_3S!C19 -> 1050
A13: Base PV of explicit FCF (DCF) | B13: =DCF!B15 -> 605.43855
A14: Net debt FY2026E | B14: =DCF!B31 -> 671.07192
A15: Diluted shares (mm) | B15: =Assumptions!B37 -> 279.3
A16: Current share price | B16: =Assumptions!B49 -> 6.81
A17: FY2035 growth (selected) | B17: =Assumptions!E13 -> 0.04
A18: Terminal opex % revenue | B18: =Assumptions!F19 -> 0.065
A19: 45X credit rate % revenue | B19: =Assumptions!F18 -> 0.28
A20: Exit multiple | B20: =Assumptions!B48 -> 7
A22: Simulation results ($/share)
A23: Mean | B23: =AVERAGE($K$41:$K$540) -> 6.8673325
A24: Median | B24: =MEDIAN($K$41:$K$540) -> 5.1265554
A25: Standard deviation | B25: =STDEV($K$41:$K$540) -> 6.2331412
A26: 5th percentile | B26: =PERCENTILE($K$41:$K$540,0.05) -> 0.39732199
A27: 25th percentile | B27: =PERCENTILE($K$41:$K$540,0.25) -> 2.7557878
A28: 75th percentile | B28: =PERCENTILE($K$41:$K$540,0.75) -> 9.303632
A29: 95th percentile | B29: =PERCENTILE($K$41:$K$540,0.95) -> 18.674883
A30: P(value > current price) | B30: =COUNTIF($K$41:$K$540,">"&B16)/500 -> 0.388
A31: P(equity ≈ zero) | B31: =COUNTIF($K$41:$K$540,"<0.5")/500 -> 0.056 | C31: The wipeout probability — the number that matters most for a levered, policy-dependent equity
A33: Scenario probability-weighted value
A34: Scenario | B34: Probability | C34: Value / share
A35: Base | B35: =Assumptions!B8 -> 0.4 | C35: =MAX(0,$B$13+MAX(0,$B$20*(($B$12*(1+(Assumptions!B12+Assumptions!B13)/2)^9)*(Assumptions!C17-Assumptions!C19+$B$19*0.25)))/(1+$B$8)^9-$B$14)/$B$15 -> 5.4482201
A36: Bull | B36: =Assumptions!C8 -> 0.2 | C36: =MAX(0,$B$13+MAX(0,$B$20*(($B$12*(1+(Assumptions!C12+Assumptions!C13)/2)^9)*(Assumptions!D17-Assumptions!D19+$B$19*0.6)))/(1+$B$8)^9-$B$14)/$B$15 -> 27.812933
A37: Bear | B37: =Assumptions!D8 -> 0.4 | C37: =MAX(0,$B$13+MAX(0,$B$20*(($B$12*(1+(Assumptions!D12+Assumptions!D13)/2)^9)*(Assumptions!E17-Assumptions!E19+$B$19*0)))/(1+$B$8)^9-$B$14)/$B$15 -> 0
A38: Probability-weighted value | C38: =SUMPRODUCT(B35:B37,C35:C37) -> 7.7418746
A39: Bear assumes ZERO 45X survival at FY35 with unimproved margins — the structural-unviability case.
A40: # | B40: g FY27 | C40: Term GM | D40: WACC | E40: 45X surv | F40: Rev FY35 | G40: EBITDA FY35 | H40: PV(TV) | I40: PV(FCF) | J40: Equity | K40: $ / share | N40: Bin ($/sh) | O40: low | P40: high | Q40: Count
A41: 1 | B41: =NORMINV(RAND(),$B$6,$C$6) -> 0.49740921 | C41: =MAX(-0.05,NORMINV(RAND(),$B$7,$C$7)) -> 0.17484364 | D41: =MAX(0.08,NORMINV(RAND(),$B$8,$C$8)) -> 0.11468295 | E41: =MEDIAN(0,NORMINV(RAND(),$B$9,$C$9),1) -> 0.53652888 | F41: =$B$12*(1+(B41+$B$17)/2)^9 -> 8941.9851 | G41: =F41*(C41-$B$18+$B$19*E41) -> 2325.5575 | H41: =MAX(0,$B$20*G41)/(1+D41)^9 -> 6127.2118 | I41: =$B$13*((1+$B$8)/(1+D41))^4.5 -> 678.48428 | J41: =H41+I41-$B$14 -> 6134.6242 | K41: =MAX(0,J41)/$B$15 -> 21.964283 | N41: 0-1 | O41: 0 | P41: 1 | Q41: =COUNTIFS($K$41:$K$540,">="&O41,$K$41:$K$540,"<"&P41) -> 43
A42: 2 | B42: =NORMINV(RAND(),$B$6,$C$6) -> 0.36159955 | C42: =MAX(-0.05,NORMINV(RAND(),$B$7,$C$7)) -> 0.10317627 | D42: =MAX(0.08,NORMINV(RAND(),$B$8,$C$8)) -> 0.12743126 | E42: =MEDIAN(0,NORMINV(RAND(),$B$9,$C$9),1) -> 0 | F42: =$B$12*(1+(B42+$B$17)/2)^9 -> 5450.3536 | G42: =F42*(C42-$B$18+$B$19*E42) -> 208.07418 | H42: =MAX(0,$B$20*G42)/(1+D42)^9 -> 494.88647 | I42: =$B$13*((1+$B$8)/(1+D42))^4.5 -> 644.63751 | J42: =H42+I42-$B$14 -> 468.45206 | K42: =MAX(0,J42)/$B$15 -> 1.6772362 | N42: 1-2 | O42: 1 | P42: 2 | Q42: =COUNTIFS($K$41:$K$540,">="&O42,$K$41:$K$540,"<"&P42) -> 45
A43: 3 | B43: =NORMINV(RAND(),$B$6,$C$6) -> 0.38820571 | C43: =MAX(-0.05,NORMINV(RAND(),$B$7,$C$7)) -> 0.15321545 | D43: =MAX(0.08,NORMINV(RAND(),$B$8,$C$8)) -> 0.12844315 | E43: =MEDIAN(0,NORMINV(RAND(),$B$9,$C$9),1) -> 0.3671748 | F43: =$B$12*(1+(B43+$B$17)/2)^9 -> 6018.505 | G43: =F43*(C43-$B$18+$B$19*E43) -> 1149.6812 | H43: =MAX(0,$B$20*G43)/(1+D43)^9 -> 2712.4287 | I43: =$B$13*((1+$B$8)/(1+D43))^4.5 -> 642.04035 | J43: =H43+I43-$B$14 -> 2683.3971 | K43: =MAX(0,J43)/$B$15 -> 9.60758 | N43: 2-3 | O43: 2 | P43: 3 | Q43: =COUNTIFS($K$41:$K$540,">="&O43,$K$41:$K$540,"<"&P43) -> 47
A44: 4 | B44: =NORMINV(RAND(),$B$6,$C$6) -> 0.36099193 | C44: =MAX(-0.05,NORMINV(RAND(),$B$7,$C$7)) -> 0.13756578 | D44: =MAX(0.08,NORMINV(RAND(),$B$8,$C$8)) -> 0.14555265 | E44: =MEDIAN(0,NORMINV(RAND(),$B$9,$C$9),1) -> 0.51060296 | F44: =$B$12*(1+(B44+$B$17)/2)^9 -> 5437.9555 | G44: =F44*(C44-$B$18+$B$19*E44) -> 1172.0676 | H44: =MAX(0,$B$20*G44)/(1+D44)^9 -> 2414.9892 | I44: =$B$13*((1+$B$8)/(1+D44))^4.5 -> 600.00262 | J44: =H44+I44-$B$14 -> 2343.9199 | K44: =MAX(0,J44)/$B$15 -> 8.3921227 | N44: 3-4 | O44: 3 | P44: 4 | Q44: =COUNTIFS($K$41:$K$540,">="&O44,$K$41:$K$540,"<"&P44) -> 56
A45: 5 | B45: =NORMINV(RAND(),$B$6,$C$6) -> 0.26428562 | C45: =MAX(-0.05,NORMINV(RAND(),$B$7,$C$7)) -> 0.13767355 | D45: =MAX(0.08,NORMINV(RAND(),$B$8,$C$8)) -> 0.14087409 | E45: =MEDIAN(0,NORMINV(RAND(),$B$9,$C$9),1) -> 0.35053603 | F45: =$B$12*(1+(B45+$B$17)/2)^9 -> 3756.1776 | G45: =F45*(C45-$B$18+$B$19*E45) -> 641.64392 | H45: =MAX(0,$B$20*G45)/(1+D45)^9 -> 1371.6796 | I45: =$B$13*((1+$B$8)/(1+D45))^4.5 -> 611.15473 | J45: =H45+I45-$B$14 -> 1311.7624 | K45: =MAX(0,J45)/$B$15 -> 4.6966073 | N45: 4-5 | O45: 4 | P45: 5 | Q45: =COUNTIFS($K$41:$K$540,">="&O45,$K$41:$K$540,"<"&P45) -> 53
A46: 6 | B46: =NORMINV(RAND(),$B$6,$C$6) -> 0.24538283 | C46: =MAX(-0.05,NORMINV(RAND(),$B$7,$C$7)) -> 0.090956789 | D46: =MAX(0.08,NORMINV(RAND(),$B$8,$C$8)) -> 0.11950725 | E46: =MEDIAN(0,NORMINV(RAND(),$B$9,$C$9),1) -> 0.11737287 | F46: =$B$12*(1+(B46+$B$17)/2)^9 -> 3487.7871 | G46: =F46*(C46-$B$18+$B$19*E46) -> 205.1558 | H46: =MAX(0,$B$20*G46)/(1+D46)^9 -> 519.92373 | I46: =$B$13*((1+$B$8)/(1+D46))^4.5 -> 665.42606 | J46: =H46+I46-$B$14 -> 514.27787 | K46: =MAX(0,J46)/$B$15 -> 1.84131 | N46: 5-6 | O46: 5 | P46: 6 | Q46: =COUNTIFS($K$41:$K$540,">="&O46,$K$41:$K$540,"<"&P46) -> 40
A47: 7 | B47: =NORMINV(RAND(),$B$6,$C$6) -> 0.14036026 | C47: =MAX(-0.05,NORMINV(RAND(),$B$7,$C$7)) -> 0.14440006 | D47: =MAX(0.08,NORMINV(RAND(),$B$8,$C$8)) -> 0.13484896 | E47: =MEDIAN(0,NORMINV(RAND(),$B$9,$C$9),1) -> 0.73372901 | F47: =$B$12*(1+(B47+$B$17)/2)^9 -> 2283.882 | G47: =F47*(C47-$B$18+$B$19*E47) -> 650.5505 | H47: =MAX(0,$B$20*G47)/(1+D47)^9 -> 1458.601 | I47: =$B$13*((1+$B$8)/(1+D47))^4.5 -> 625.89232 | J47: =H47+I47-$B$14 -> 1413.4214 | K47: =MAX(0,J47)/$B$15 -> 5.0605849 | N47: 6-7 | O47: 6 | P47: 7 | Q47: =COUNTIFS($K$41:$K$540,">="&O47,$K$41:$K$540,"<"&P47) -> 27
A48: 8 | B48: =NORMINV(RAND(),$B$6,$C$6) -> 0.36386521 | C48: =MAX(-0.05,NORMINV(RAND(),$B$7,$C$7)) -> 0.10217958 | D48: =MAX(0.08,NORMINV(RAND(),$B$8,$C$8)) -> 0.11711701 | E48: =MEDIAN(0,NORMINV(RAND(),$B$9,$C$9),1) -> 0.18553112 | F48: =$B$12*(1+(B48+$B$17)/2)^9 -> 5496.8052 | G48: =F48*(C48-$B$18+$B$19*E48) -> 489.92087 | H48: =MAX(0,$B$20*G48)/(1+D48)^9 -> 1265.7153 | I48: =$B$13*((1+$B$8)/(1+D48))^4.5 -> 671.85711 | J48: =H48+I48-$B$14 -> 1266.5004 | K48: =MAX(0,J48)/$B$15 -> 4.5345523 | N48: 7-8 | O48: 7 | P48: 8 | Q48: =COUNTIFS($K$41:$K$540,">="&O48,$K$41:$K$540,"<"&P48) -> 31
A49: 9 | B49: =NORMINV(RAND(),$B$6,$C$6) -> 0.46797897 | C49: =MAX(-0.05,NORMINV(RAND(),$B$7,$C$7)) -> 0.15013627 | D49: =MAX(0.08,NORMINV(RAND(),$B$8,$C$8)) -> 0.15094866 | E49: =MEDIAN(0,NORMINV(RAND(),$B$9,$C$9),1) -> 0.27608419 | F49: =$B$12*(1+(B49+$B$17)/2)^9 -> 8050.7132 | G49: =F49*(C49-$B$18+$B$19*E49) -> 1307.7566 | H49: =MAX(0,$B$20*G49)/(1+D49)^9 -> 2582.9822 | I49: =$B$13*((1+$B$8)/(1+D49))^4.5 -> 587.44759 | J49: =H49+I49-$B$14 -> 2499.3578 | K49: =MAX(0,J49)/$B$15 -> 8.9486496 | N49: 8-10 | O49: 8 | P49: 10 | Q49: =COUNTIFS($K$41:$K$540,">="&O49,$K$41:$K$540,"<"&P49) -> 53
A50: 10 | B50: =NORMINV(RAND(),$B$6,$C$6) -> 0.26793775 | C50: =MAX(-0.05,NORMINV(RAND(),$B$7,$C$7)) -> 0.0083656351 | D50: =MAX(0.08,NORMINV(RAND(),$B$8,$C$8)) -> 0.13264217 | E50: =MEDIAN(0,NORMINV(RAND(),$B$9,$C$9),1) -> 0.23153462 | F50: =$B$12*(1+(B50+$B$17)/2)^9 -> 3810.098 | G50: =F50*(C50-$B$18+$B$19*E50) -> 31.225 | H50: =MAX(0,$B$20*G50)/(1+D50)^9 -> 71.246895 | I50: =$B$13*((1+$B$8)/(1+D50))^4.5 -> 631.39862 | J50: =H50+I50-$B$14 -> 31.573597 | K50: =MAX(0,J50)/$B$15 -> 0.11304546 | N50: 10-12 | O50: 10 | P50: 12 | Q50: =COUNTIFS($K$41:$K$540,">="&O50,$K$41:$K$540,"<"&P50) -> 32
A51: 11 | B51: =NORMINV(RAND(),$B$6,$C$6) -> 0.39841688 | C51: =MAX(-0.05,NORMINV(RAND(),$B$7,$C$7)) -> 0.16407271 | D51: =MAX(0.08,NORMINV(RAND(),$B$8,$C$8)) -> 0.10621035 | E51: =MEDIAN(0,NORMINV(RAND(),$B$9,$C$9),1) -> 0 | F51: =$B$12*(1+(B51+$B$17)/2)^9 -> 6250.1572 | G51: =F51*(C51-$B$18+$B$19*E51) -> 619.22001 | H51: =MAX(0,$B$20*G51)/(1+D51)^9 -> 1747.4452 | I51: =$B$13*((1+$B$8)/(1+D51))^4.5 -> 702.18439 | J51: =H51+I51-$B$14 -> 1778.5576 | K51: =MAX(0,J51)/$B$15 -> 6.3679113 | N51: 12-14 | O51: 12 | P51: 14 | Q51: =COUNTIFS($K$41:$K$540,">="&O51,$K$41:$K$540,"<"&P51) -> 23
A52: 12 | B52: =NORMINV(RAND(),$B$6,$C$6) -> 0.47577082 | C52: =MAX(-0.05,NORMINV(RAND(),$B$7,$C$7)) -> 0.11569603 | D52: =MAX(0.08,NORMINV(RAND(),$B$8,$C$8)) -> 0.15675089 | E52: =MEDIAN(0,NORMINV(RAND(),$B$9,$C$9),1) -> 0.20740544 | F52: =$B$12*(1+(B52+$B$17)/2)^9 -> 8278.6405 | G52: =F52*(C52-$B$18+$B$19*E52) -> 900.464 | H52: =MAX(0,$B$20*G52)/(1+D52)^9 -> 1699.8312 | I52: =$B$13*((1+$B$8)/(1+D52))^4.5 -> 574.30369 | J52: =H52+I52-$B$14 -> 1603.063 | K52: =MAX(0,J52)/$B$15 -> 5.7395738 | N52: 14-16 | O52: 14 | P52: 16 | Q52: =COUNTIFS($K$41:$K$540,">="&O52,$K$41:$K$540,"<"&P52) -> 10
... A57: 17 | B57: =NORMINV(RAND(),$B$6,$C$6) -> 0.30440328 | C57: =MAX(-0.05,NORMINV(RAND(),$B$7,$C$7)) -> 0.13054614 | D57: =MAX(0.08,NORMINV(RAND(),$B$8,$C$8)) -> 0.11192884 | E57: =MEDIAN(0,NORMINV(RAND(),$B$9,$C$9),1) -> 0.20921058 | F57: =$B$12*(1+(B57+$B$17)/2)^9 -> 4387.4302 | G57: =F57*(C57-$B$18+$B$19*E57) -> 544.59022 | H57: =MAX(0,$B$20*G57)/(1+D57)^9 -> 1467.1514 | I57: =$B$13*((1+$B$8)/(1+D57))^4.5 -> 686.07947 | J57: =H57+I57-$B$14 -> 1482.1589 | K57: =MAX(0,J57)/$B$15 -> 5.3066915 | N57: 30-40 | O57: 30 | P57: 40 | Q57: =COUNTIFS($K$41:$K$540,">="&O57,$K$41:$K$540,"<"&P57) -> 2
A58: 18 | B58: =NORMINV(RAND(),$B$6,$C$6) -> 0.46016535 | C58: =MAX(-0.05,NORMINV(RAND(),$B$7,$C$7)) -> 0.22579394 | D58: =MAX(0.08,NORMINV(RAND(),$B$8,$C$8)) -> 0.10831664 | E58: =MEDIAN(0,NORMINV(RAND(),$B$9,$C$9),1) -> 0.23739334 | F58: =$B$12*(1+(B58+$B$17)/2)^9 -> 7827.7676 | G58: =F58*(C58-$B$18+$B$19*E58) -> 1778.9704 | H58: =MAX(0,$B$20*G58)/(1+D58)^9 -> 4935.0559 | I58: =$B$13*((1+$B$8)/(1+D58))^4.5 -> 696.19927 | J58: =H58+I58-$B$14 -> 4960.1833 | K58: =MAX(0,J58)/$B$15 -> 17.759339 | N58: 40+ | O58: 40 | P58: 60 | Q58: =COUNTIF($K$41:$K$540,">="&O58) -> 3
A59: 19 | B59: =NORMINV(RAND(),$B$6,$C$6) -> 0.44026185 | C59: =MAX(-0.05,NORMINV(RAND(),$B$7,$C$7)) -> 0.20785786 | D59: =MAX(0.08,NORMINV(RAND(),$B$8,$C$8)) -> 0.13269893 | E59: =MEDIAN(0,NORMINV(RAND(),$B$9,$C$9),1) -> 0.35407514 | F59: =$B$12*(1+(B59+$B$17)/2)^9 -> 7284.4561 | G59: =F59*(C59-$B$18+$B$19*E59) -> 1762.8303 | H59: =MAX(0,$B$20*G59)/(1+D59)^9 -> 4020.4822 | I59: =$B$13*((1+$B$8)/(1+D59))^4.5 -> 631.25625 | J59: =H59+I59-$B$14 -> 3980.6665 | K59: =MAX(0,J59)/$B$15 -> 14.252297
A60: 20 | B60: =NORMINV(RAND(),$B$6,$C$6) -> 0.54097965 | C60: =MAX(-0.05,NORMINV(RAND(),$B$7,$C$7)) -> 0.11506573 | D60: =MAX(0.08,NORMINV(RAND(),$B$8,$C$8)) -> 0.11055137 | E60: =MEDIAN(0,NORMINV(RAND(),$B$9,$C$9),1) -> 0 | F60: =$B$12*(1+(B60+$B$17)/2)^9 -> 10422.708 | G60: =F60*(C60-$B$18+$B$19*E60) -> 521.82042 | H60: =MAX(0,$B$20*G60)/(1+D60)^9 -> 1421.5798 | I60: =$B$13*((1+$B$8)/(1+D60))^4.5 -> 689.9172 | J60: =H60+I60-$B$14 -> 1440.4251 | K60: =MAX(0,J60)/$B$15 -> 5.1572686
A61: 21 | B61: =NORMINV(RAND(),$B$6,$C$6) -> 0.35980746 | C61: =MAX(-0.05,NORMINV(RAND(),$B$7,$C$7)) -> 0.018505547 | D61: =MAX(0.08,NORMINV(RAND(),$B$8,$C$8)) -> 0.135948 | E61: =MEDIAN(0,NORMINV(RAND(),$B$9,$C$9),1) -> 0.18480901 | F61: =$B$12*(1+(B61+$B$17)/2)^9 -> 5413.859 | G61: =F61*(C61-$B$18+$B$19*E61) -> 28.433974 | H61: =MAX(0,$B$20*G61)/(1+D61)^9 -> 63.198902 | I61: =$B$13*((1+$B$8)/(1+D61))^4.5 -> 623.17191 | J61: =H61+I61-$B$14 -> 15.298894 | K61: =MAX(0,J61)/$B$15 -> 0.054775848
A62: 22 | B62: =NORMINV(RAND(),$B$6,$C$6) -> 0.1490775 | C62: =MAX(-0.05,NORMINV(RAND(),$B$7,$C$7)) -> 0.15428103 | D62: =MAX(0.08,NORMINV(RAND(),$B$8,$C$8)) -> 0.16225967 | E62: =MEDIAN(0,NORMINV(RAND(),$B$9,$C$9),1) -> 0.41539242 | F62: =$B$12*(1+(B62+$B$17)/2)^9 -> 2367.3887 | G62: =F62*(C62-$B$18+$B$19*E62) -> 486.7136 | H62: =MAX(0,$B$20*G62)/(1+D62)^9 -> 880.32494 | I62: =$B$13*((1+$B$8)/(1+D62))^4.5 -> 562.15573 | J62: =H62+I62-$B$14 -> 771.40875 | K62: =MAX(0,J62)/$B$15 -> 2.7619361
A63: 23 | B63: =NORMINV(RAND(),$B$6,$C$6) -> 0.40641951 | C63: =MAX(-0.05,NORMINV(RAND(),$B$7,$C$7)) -> 0.1172917 | D63: =MAX(0.08,NORMINV(RAND(),$B$8,$C$8)) -> 0.10882139 | E63: =MEDIAN(0,NORMINV(RAND(),$B$9,$C$9),1) -> 0.49405465 | F63: =$B$12*(1+(B63+$B$17)/2)^9 -> 6437.2106 | G63: =F63*(C63-$B$18+$B$19*E63) -> 1227.1062 | H63: =MAX(0,$B$20*G63)/(1+D63)^9 -> 3390.2038 | I63: =$B$13*((1+$B$8)/(1+D63))^4.5 -> 694.77426 | J63: =H63+I63-$B$14 -> 3413.9061 | K63: =MAX(0,J63)/$B$15 -> 12.22308
A64: 24 | B64: =NORMINV(RAND(),$B$6,$C$6) -> 0.4944046 | C64: =MAX(-0.05,NORMINV(RAND(),$B$7,$C$7)) -> 0.21050502 | D64: =MAX(0.08,NORMINV(RAND(),$B$8,$C$8)) -> 0.12589138 | E64: =MEDIAN(0,NORMINV(RAND(),$B$9,$C$9),1) -> 0.36806713 | F64: =$B$12*(1+(B64+$B$17)/2)^9 -> 8847.1393 | G64: =F64*(C64-$B$18+$B$19*E64) -> 2199.0787 | H64: =MAX(0,$B$20*G64)/(1+D64)^9 -> 5295.0538 | I64: =$B$13*((1+$B$8)/(1+D64))^4.5 -> 648.61455 | J64: =H64+I64-$B$14 -> 5272.5964 | K64: =MAX(0,J64)/$B$15 -> 18.877896
A65: 25 | B65: =NORMINV(RAND(),$B$6,$C$6) -> 0.30548349 | C65: =MAX(-0.05,NORMINV(RAND(),$B$7,$C$7)) -> 0.079822184 | D65: =MAX(0.08,NORMINV(RAND(),$B$8,$C$8)) -> 0.18791368 | E65: =MEDIAN(0,NORMINV(RAND(),$B$9,$C$9),1) -> 0 | F65: =$B$12*(1+(B65+$B$17)/2)^9 -> 4405.6578 | G65: =F65*(C65-$B$18+$B$19*E65) -> 65.30147 | H65: =MAX(0,$B$20*G65)/(1+D65)^9 -> 97.041401 | I65: =$B$13*((1+$B$8)/(1+D65))^4.5 -> 509.55249 | J65: =H65+I65-$B$14 -> -64.478026 | K65: =MAX(0,J65)/$B$15 -> 0
A66: 26 | B66: =NORMINV(RAND(),$B$6,$C$6) -> 0.44336606 | C66: =MAX(-0.05,NORMINV(RAND(),$B$7,$C$7)) -> 0.050944974 | D66: =MAX(0.08,NORMINV(RAND(),$B$8,$C$8)) -> 0.14224908 | E66: =MEDIAN(0,NORMINV(RAND(),$B$9,$C$9),1) -> 0 | F66: =$B$12*(1+(B66+$B$17)/2)^9 -> 7366.9209 | G66: =F66*(C66-$B$18+$B$19*E66) -> -103.54227 | H66: =MAX(0,$B$20*G66)/(1+D66)^9 -> 0 | I66: =$B$13*((1+$B$8)/(1+D66))^4.5 -> 607.85112 | J66: =H66+I66-$B$14 -> -63.220794 | K66: =MAX(0,J66)/$B$15 -> 0
A67: 27 | B67: =NORMINV(RAND(),$B$6,$C$6) -> 0.38204098 | C67: =MAX(-0.05,NORMINV(RAND(),$B$7,$C$7)) -> 0.12186023 | D67: =MAX(0.08,NORMINV(RAND(),$B$8,$C$8)) -> 0.14799519 | E67: =MEDIAN(0,NORMINV(RAND(),$B$9,$C$9),1) -> 0.3909007 | F67: =$B$12*(1+(B67+$B$17)/2)^9 -> 5882.3752 | G67: =F67*(C67-$B$18+$B$19*E67) -> 978.3121 | H67: =MAX(0,$B$20*G67)/(1+D67)^9 -> 1977.4925 | I67: =$B$13*((1+$B$8)/(1+D67))^4.5 -> 594.27929 | J67: =H67+I67-$B$14 -> 1900.6999 | K67: =MAX(0,J67)/$B$15 -> 6.805227
A68: 28 | B68: =NORMINV(RAND(),$B$6,$C$6) -> 0.47509496 | C68: =MAX(-0.05,NORMINV(RAND(),$B$7,$C$7)) -> 0.24550326 | D68: =MAX(0.08,NORMINV(RAND(),$B$8,$C$8)) -> 0.14379983 | E68: =MEDIAN(0,NORMINV(RAND(),$B$9,$C$9),1) -> 0 | F68: =$B$12*(1+(B68+$B$17)/2)^9 -> 8258.6456 | G68: =F68*(C68-$B$18+$B$19*E68) -> 1490.7124 | H68: =MAX(0,$B$20*G68)/(1+D68)^9 -> 3114.1652 | I68: =$B$13*((1+$B$8)/(1+D68))^4.5 -> 604.15138 | J68: =H68+I68-$B$14 -> 3047.2447 | K68: =MAX(0,J68)/$B$15 -> 10.910292
A69: 29 | B69: =NORMINV(RAND(),$B$6,$C$6) -> 0.26009342 | C69: =MAX(-0.05,NORMINV(RAND(),$B$7,$C$7)) -> 0.088093871 | D69: =MAX(0.08,NORMINV(RAND(),$B$8,$C$8)) -> 0.15380767 | E69: =MEDIAN(0,NORMINV(RAND(),$B$9,$C$9),1) -> 0.033928208 | F69: =$B$12*(1+(B69+$B$17)/2)^9 -> 3695.1207 | G69: =F69*(C69-$B$18+$B$19*E69) -> 120.43791 | H69: =MAX(0,$B$20*G69)/(1+D69)^9 -> 232.62719 | I69: =$B$13*((1+$B$8)/(1+D69))^4.5 -> 580.9256 | J69: =H69+I69-$B$14 -> 142.48087 | K69: =MAX(0,J69)/$B$15 -> 0.51013558
A70: 30 | B70: =NORMINV(RAND(),$B$6,$C$6) -> 0.57736146 | C70: =MAX(-0.05,NORMINV(RAND(),$B$7,$C$7)) -> 0.1325875 | D70: =MAX(0.08,NORMINV(RAND(),$B$8,$C$8)) -> 0.16116103 | E70: =MEDIAN(0,NORMINV(RAND(),$B$9,$C$9),1) -> 0.043816825 | F70: =$B$12*(1+(B70+$B$17)/2)^9 -> 11822.047 | G70: =F70*(C70-$B$18+$B$19*E70) -> 944.0638 | H70: =MAX(0,$B$20*G70)/(1+D70)^9 -> 1722.1355 | I70: =$B$13*((1+$B$8)/(1+D70))^4.5 -> 564.5532 | J70: =H70+I70-$B$14 -> 1615.6168 | K70: =MAX(0,J70)/$B$15 -> 5.7845214
... A540: 500 | B540: =NORMINV(RAND(),$B$6,$C$6) -> 0.57261237 | C540: =MAX(-0.05,NORMINV(RAND(),$B$7,$C$7)) -> 0.15587932 | D540: =MAX(0.08,NORMINV(RAND(),$B$8,$C$8)) -> 0.14512698 | E540: =MEDIAN(0,NORMINV(RAND(),$B$9,$C$9),1) -> 0.20029479 | F540: =$B$12*(1+(B540+$B$17)/2)^9 -> 11630.387 | G540: =F540*(C540-$B$18+$B$19*E540) -> 1709.2233 | H540: =MAX(0,$B$20*G540)/(1+D540)^9 -> 3533.5726 | I540: =$B$13*((1+$B$8)/(1+D540))^4.5 -> 601.00694 | J540: =H540+I540-$B$14 -> 3463.5076 | K540: =MAX(0,J540)/$B$15 -> 12.400672

Sheet Football_Field
A1: FOOTBALL FIELD — VALUATION SUMMARY ($ per share)
A2: =CONCATENATE("Current price: $",TEXT(Assumptions!B49,"0.00")," · Scenario: ",CHOOSE(Assumptions!B4,"BASE","BULL","BEAR")," · Probability-weighted value: $",TEXT(Monte_Carlo!C38,"0.00")) -> Current price: $6.81 · Scenario: BASE · Probability-weighted value: $7.74
A4: Methodology | B4: Low | C4: High | D4: (base) | E4: (span) | F4: Midpoint
A5: 52-week trading range (e) | B5: 3 | C5: 12 | D5: =MIN(B5,C5) -> 3 | E5: =ABS(C5-B5) -> 9 | F5: =(B5+C5)/2 -> 7.5
A6: Analyst targets (avg ~$10.07; low $7 Alliance Global) | B6: 7 | C6: 13 | D6: =MIN(B6,C6) -> 7 | E6: =ABS(C6-B6) -> 6 | F6: =(B6+C6)/2 -> 10
A7: DCF — Gordon growth (WACC ±2%, g 1.5-2.5%) | B7: =MAX(0,SUMPRODUCT(DCF!$B$10:$J$10,(1+(WACC!$B$20+0.02))^-DCF!$B$11:$J$11)+MAX(0,DCF!$J$10)*(1+0.015)/((WACC!$B$20+0.02)-0.015)/(1+(WACC!$B$20+0.02))^9-DCF!$B$31)/DCF!$B$32 -> 0.39067919 | C7: =MAX(0,SUMPRODUCT(DCF!$B$10:$J$10,(1+(WACC!$B$20-0.02))^-DCF!$B$11:$J$11)+MAX(0,DCF!$J$10)*(1+0.025)/((WACC!$B$20-0.02)-0.025)/(1+(WACC!$B$20-0.02))^9-DCF!$B$31)/DCF!$B$32 -> 1.456251 | D7: =MIN(B7,C7) -> 0.39067919 | E7: =ABS(C7-B7) -> 1.0655718 | F7: =(B7+C7)/2 -> 0.9234651
A8: DCF — exit multiple (5.5-8.5x, WACC ±2%) | B8: =MAX(0,SUMPRODUCT(DCF!$B$10:$J$10,(1+(WACC!$B$20+0.02))^-DCF!$B$11:$J$11)+MAX(0,5.5*Model_3S!$L$25)/(1+(WACC!$B$20+0.02))^9-DCF!$B$31)/DCF!$B$32 -> 1.5580064 | C8: =MAX(0,SUMPRODUCT(DCF!$B$10:$J$10,(1+(WACC!$B$20-0.02))^-DCF!$B$11:$J$11)+MAX(0,8.5*Model_3S!$L$25)/(1+(WACC!$B$20-0.02))^9-DCF!$B$31)/DCF!$B$32 -> 3.9503103 | D8: =MIN(B8,C8) -> 1.5580064 | E8: =ABS(C8-B8) -> 2.3923039 | F8: =(B8+C8)/2 -> 2.7541583
A9: Comps — EV/Revenue (0.8-2.0x FY26E) | B9: =Comps!E15 -> 0.60482665 | C9: =Comps!F15 -> 5.1161048 | D9: =MIN(B9,C9) -> 0.60482665 | E9: =ABS(C9-B9) -> 4.5112782 | F9: =(B9+C9)/2 -> 2.8604657
A10: Comps — EV/EBITDA (5-8x FY29E peak-45X) | B10: =Comps!E16 -> 6.8418514 | C10: =Comps!F16 -> 12.388578 | D10: =MIN(B10,C10) -> 6.8418514 | E10: =ABS(C10-B10) -> 5.5467261 | F10: =(B10+C10)/2 -> 9.6152145
A11: Precedent framework ($0.07-0.15/W capacity) | B11: =Precedents!B18 -> 0 | C11: =Precedents!C18 -> 1.8937633 | D11: =MIN(B11,C11) -> 0 | E11: =ABS(C11-B11) -> 1.8937633 | F11: =(B11+C11)/2 -> 0.94688164
A12: Buyout capacity (25% → 15% IRR) | B12: =LBO!D49 -> 0 | C12: =LBO!D47 -> 0.12123071 | D12: =MIN(B12,C12) -> 0 | E12: =ABS(C12-B12) -> 0.12123071 | F12: =(B12+C12)/2 -> 0.060615354
A13: Monte Carlo P25–P75 (live) | B13: =Monte_Carlo!B27 -> 2.7557878 | C13: =Monte_Carlo!B28 -> 9.303632 | D13: =MIN(B13,C13) -> 2.7557878 | E13: =ABS(C13-B13) -> 6.5478442 | F13: =(B13+C13)/2 -> 6.0297099
A14: Current price (marker) | B14: =Assumptions!B49-0.15 -> 6.66 | C14: =Assumptions!B49+0.15 -> 6.96 | D14: =MIN(B14,C14) -> 6.66 | E14: =ABS(C14-B14) -> 0.3 | F14: =(B14+C14)/2 -> 6.81
A16: 52-wk range estimated (post-rebrand ticker history is short). Analyst dispersion ($7 to $13+) is unusually wide — itself a signal that this is a binary, policy-dependent equity rather than a valuation debate.
