Workbook

Sheet Cover
A1: X-ENERGY, INC. (NASDAQ: XE) — DCF VALUATION & 3-STATEMENT OPERATING MODEL
A2: Prepared July 20, 2026 · $ millions except per-share · Calendar fiscal year · IPO'd April 24, 2026 at $23.00
A4: READ THIS FIRST
C5: X-Energy is a PRE-COMMERCIAL small-modular-reactor (SMR) and TRISO fuel company. Today's revenue is mostly DOE ARDP cost-share; first fuel plant (TX-1) targets H1-2028 operations and first Xe-100 reactors (Dow Seadrift, Amazon Cascade) target ~2030. A DCF here is a scenario framework, not a point estimate: nearly all value sits in the terminal value, the Gordon-growth method is structurally punitive inside a 10-year window (FY2035 is still reinvesting), and ranges are extremely wide. Treat the exit-multiple DCF, comps and Monte Carlo bands together.
A7: CONTENTS
A8: Assumptions | C8: Scenario switch & levers (edit yellow cells)
A9: Historicals | C9: FY2024–FY2025 actuals, Q1-2026, FY2026E build
A10: Model_3S | C10: Linked IS/BS/CF FY2026E–FY2035E; fixed+variable opex, capex program, revolver, working capital
A11: WACC | C11: CAPM; beta proxied from SMR peer group (no trading history)
A12: DCF | C12: Unlevered FCF, Gordon + exit-multiple TV, sensitivities
A13: Comps | C13: SMR peer benchmarks (OKLO, NuScale) — EV per pipeline GW and market-cap comparison
A14: Precedents | C14: Nuclear-sector precedent transactions (limited applicability — flagged)
A15: LBO | C15: All-equity growth take-private; exit on EV/Revenue; IRR thresholds
A16: Monte_Carlo | C16: 500 live trials + scenario probability weights
A17: Football_Field | C17: Valuation summary chart vs. current price
A19: LEGEND
A20: Blue font / yellow fill | C20: Hardcoded input or scenario lever — edit these
A21: Black font | C21: Formula — do not overwrite
A22: Green font | C22: Link to another sheet
A23: 'e' | C23: Estimated figure — see cell notes
A25: KEY SOURCES
A26: Q1-2026 results (8-K/10-Q, June 4, 2026) | C26: https://www.sec.gov/Archives/edgar/data/0002088896/000119312526256369/xe-ex99_1.htm ; globenewswire.com/news-release/2026/06/04/3306595
A27: IPO pricing ($23, upsized, ~$1.02B gross) | C27: businesswire.com/news/home/20260423988681 ; iposcoop.com
A28: FY2024/FY2025 (S-1 / 10-K summaries) | C28: tradingview.com & stocktitan.net 10-Q/10-K summaries: FY25 rev+grants $109.1mm, net loss $389.8mm; FY24 $120.2mm / $126.0mm
A29: Price, range, analyst targets | C29: stockanalysis.com/stocks/xe, marketbeat, benzinga (avg target ~$39.9; range $28 Jefferies – $57 Guggenheim; 8 analysts)
A30: Peers | C30: OKLO mkt cap ~$8.0B (companiesmarketcap), NuScale ~$3.1B (yahoo), July 2026
A31: 10Y UST 4.55% (7/17/2026) | C31: tradingeconomics.com / FRED DGS10
A33: DISCLAIMER | C33: Educational model, not investment advice. Pre-commercial-stage projections are inherently speculative; verify everything against X-Energy's filings.

Sheet Assumptions
A1: ASSUMPTIONS & SCENARIO LEVERS — X-ENERGY
A2: Edit yellow cells. Switch drives Model_3S, DCF, LBO, Monte Carlo.
A4: SCENARIO SWITCH (1 = Base, 2 = Bull, 3 = Bear) | B4: 1 | C4: =CHOOSE($B$4,"BASE — pipeline converts on schedule","BULL — Amazon 5 GWe accelerates + fleet orders","BEAR — deployment slips, fuel-only business") -> BASE — pipeline converts on schedule
A6: Scenario probability weights
B7: Base | C7: Bull | D7: Bear | E7: Total
A8: Probability | B8: 0.45 | C8: 0.25 | D8: 0.3 | E8: =SUM(B8:D8) -> 1 | F8: Higher bear weight than a commercial-stage company — licensing/execution risk
A10: Revenue growth — decays linearly FY2027 → FY2035 (drivers: ARDP services → TRISO fuel from 2028 → Xe-100 deployments from ~2030)
B11: Base | C11: Bull | D11: Bear | E11: Selected
A12: FY2027 revenue growth | B12: 0.55 | C12: 0.7 | D12: 0.15 | E12: =CHOOSE($B$4,B12,C12,D12) -> 0.55
A13: FY2035 revenue growth (terminal-year) | B13: 0.25 | C13: 0.33 | D13: 0 | E13: =CHOOSE($B$4,B13,C13,D13) -> 0.25
A14: Implied FY2035 revenue: Base ~$3.6B (~8-10 Xe-100 deliveries/yr + fuel), Bull ~$7.3B (Amazon 5 GWe on schedule + fleet orders), Bear ~$0.3B (TRISO fuel franchise only). FY2026E revenue $180mm (Q1 annualized, ARDP ramp).
A15: Operating drivers — FY2026 start ramps linearly to FY2035 target
A16: Driver | B16: FY26 start | C16: Base target | D16: Bull target | E16: Bear target | F16: Selected
A17: Gross margin (services / fuel / reactor blend) | B17: 0.05 | C17: 0.3 | D17: 0.35 | E17: 0.15 | F17: =CHOOSE($B$4,C17,D17,E17) -> 0.3
A18: Variable opex (% revenue) | B18: 0.05 | C18: 0.04 | D18: 0.04 | E18: 0.06 | F18: =CHOOSE($B$4,C18,D18,E18) -> 0.04
A19: Stock-based compensation (% revenue) | B19: 0.03 | C19: 0.02 | D19: 0.02 | E19: 0.03 | F19: =CHOOSE($B$4,C19,D19,E19) -> 0.02
A20: Cash tax rate (large NOLs) | B20: 0 | C20: 0.15 | D20: 0.15 | E20: 0 | F20: =CHOOSE($B$4,C20,D20,E20) -> 0.15
A21: Customer deposits / deferred revenue (% revenue) | B21: 0.3 | C21: 0.2 | D21: 0.25 | E21: 0.15 | F21: =CHOOSE($B$4,C21,D21,E21) -> 0.2
A23: Fixed cost & capex programs (scenario growth rates)
B24: Base | C24: Bull | D24: Bear | E24: Selected
A25: Fixed cash opex growth %/yr (R&D, licensing, G&A) | B25: 0.02 | C25: 0.04 | D25: -0.03 | E25: =CHOOSE($B$4,B25,C25,D25) -> 0.02
A26: Capex growth %/yr (TX-1/TX-2 fuel plants, engineering) | B26: 0 | C26: 0.08 | D26: -0.15 | E26: =CHOOSE($B$4,B26,C26,D26) -> 0
A27: Xe-100 plants are owned and largely funded by customers (Dow, Amazon) — X-Energy's capex is fuel fabrication capacity and engineering, not power plants.
A28: Other inputs
A29: Fixed cash opex, FY2026 ($mm) | B29: 255
A30: Capex, FY2026 ($mm) | B30: 250
A31: D&A rate (% of beginning PP&E) | B31: 0.08
A32: Days sales outstanding (DSO) | B32: 60
A33: Days inventory (DIO, on COGS) | B33: 40
A34: Days payable (DPO, on COGS + cash opex) | B34: 60
A35: Other current assets (% revenue) | B35: 0.05
A36: Interest earned on cash | B36: 0.04
A37: Revolver interest rate | B37: 0.075
A38: Minimum cash balance ($mm) | B38: 150
A39: Diluted shares outstanding (mm) | B39: 406 | C39: ~406mm total shares implied by $5.7-5.9B market cap at ~$14; includes Class B. Warrants excluded (liability-classified; MTM excluded from model)
A40: Marginal tax rate (valuation) | B40: 0.25
A41: IPO net proceeds received FY2026 ($mm) | B41: 1100
A43: Terminal value & market inputs
A44: Terminal (perpetuity) growth rate g | B44: 0.035
A45: Exit EV / Adj. EBITDA multiple (FY2035) | B45: 15
A46: Current share price (7/17/2026) | B46: 14.02
A48: FY2035 is still a growth year for XE, so Gordon growth on FY35 FCF is structurally conservative; the exit multiple (15x a ~25%-growth EBITDA stream) is the more meaningful anchor. Both shown.

Sheet Historicals
A1: HISTORICAL FINANCIALS ($mm)
B4: FY2024A | C4: FY2025A | D4: Q1-25A | E4: Q1-26A | F4: FY2026E
A5: Revenue + grant income | B5: 120.2 | C5: 109.1 | D5: 20.8 | E5: 43.4 | F5: 180 | G5: FY2026E: Q1 $43.4mm annualized with continued ARDP ramp (e)
A6: Net loss (GAAP) | B6: -126 | C6: -389.8 | D6: -10.2 | E6: -166.2
A7: Net loss ex-warrant MTM (e) | E7: -57.3
A8: Operating cash flow | E8: -67.3
A9: Cash + investments (period end) | E9: 944
A11: Post-IPO liquidity (~April 2026) | B11: 2000 | C11: $944mm at 3/31/26 + ~$1.1B IPO net proceeds (IPO closed after Q1 end); company cites ~$2B liquidity
A13: Key commercial facts
A14: IPO: April 24, 2026 at $23.00 (upsized; ~$1.02B gross); first-day close $29.20; price 7/17/26: $14.02
A15: Pipeline: >11 GWe / ~144 reactors — Dow (Seadrift TX, industrial heat), Amazon (data centers, 5+ GWe option incl. Cascade WA), Centrica (Hartlepool UK)
A16: TRISO-X TX-1 fuel facility: license received, construction underway, operations targeted H1-2028, initial capacity to fuel ~11 reactors
A17: Q1-26 net loss includes $108.9mm non-cash warrant mark-to-market — excluded from the operating model
A18: Zero debt; revenue today is predominantly DOE ARDP cost-share services + grants
A20: Opening balance sheet, 12/31/2025 (estimated — S-1 detail not fully retrievable):
A21: Cash + investments e | B21: 1175
A22: Receivables e | B22: 30
A23: Inventory e | B23: 20
A24: Other current assets e | B24: 40
A25: PP&E net (incl. TX-1 construction) e | B25: 350
A26: Other LT assets e | B26: 60
A27: Accounts payable + accrued e | B27: 60
A28: Customer deposits / deferred revenue e | B28: 150
A29: Warrant + other LT liabilities e | B29: 300
A30: Total equity (plug)
A32: Sources: Q1-26 8-K/press release (globenewswire 6/4/26), 10-Q summaries (tradingview/stocktitan), IPO releases (businesswire). Full URLs on Cover.

Sheet Model_3S
A1: 3-STATEMENT OPERATING MODEL — FY2026E–FY2035E ($mm; warrant MTM excluded)
A2: =CONCATENATE("Active scenario: ",CHOOSE(Assumptions!$B$4,"BASE","BULL","BEAR")) -> Active scenario: BASE
B4: FY2025A | C4: FY2026E | D4: FY2027E | E4: FY2028E | F4: FY2029E | G4: FY2030E | H4: FY2031E | I4: FY2032E | J4: FY2033E | K4: FY2034E | L4: FY2035E
A6: DRIVERS
A7: Revenue growth % | C7: =C15/B15-1 -> 0.64986251 | D7: =Assumptions!$E$12+(Assumptions!$E$13-Assumptions!$E$12)*0/8 -> 0.55 | E7: =Assumptions!$E$12+(Assumptions!$E$13-Assumptions!$E$12)*1/8 -> 0.5125 | F7: =Assumptions!$E$12+(Assumptions!$E$13-Assumptions!$E$12)*2/8 -> 0.475 | G7: =Assumptions!$E$12+(Assumptions!$E$13-Assumptions!$E$12)*3/8 -> 0.4375 | H7: =Assumptions!$E$12+(Assumptions!$E$13-Assumptions!$E$12)*4/8 -> 0.4 | I7: =Assumptions!$E$12+(Assumptions!$E$13-Assumptions!$E$12)*5/8 -> 0.3625 | J7: =Assumptions!$E$12+(Assumptions!$E$13-Assumptions!$E$12)*6/8 -> 0.325 | K7: =Assumptions!$E$12+(Assumptions!$E$13-Assumptions!$E$12)*7/8 -> 0.2875 | L7: =Assumptions!$E$12+(Assumptions!$E$13-Assumptions!$E$12)*8/8 -> 0.25
A8: Gross margin % | C8: =Assumptions!$B$17 -> 0.05 | D8: =Assumptions!$B$17+(Assumptions!$F$17-Assumptions!$B$17)*1/9 -> 0.077777778 | E8: =Assumptions!$B$17+(Assumptions!$F$17-Assumptions!$B$17)*2/9 -> 0.10555556 | F8: =Assumptions!$B$17+(Assumptions!$F$17-Assumptions!$B$17)*3/9 -> 0.13333333 | G8: =Assumptions!$B$17+(Assumptions!$F$17-Assumptions!$B$17)*4/9 -> 0.16111111 | H8: =Assumptions!$B$17+(Assumptions!$F$17-Assumptions!$B$17)*5/9 -> 0.18888889 | I8: =Assumptions!$B$17+(Assumptions!$F$17-Assumptions!$B$17)*6/9 -> 0.21666667 | J8: =Assumptions!$B$17+(Assumptions!$F$17-Assumptions!$B$17)*7/9 -> 0.24444444 | K8: =Assumptions!$B$17+(Assumptions!$F$17-Assumptions!$B$17)*8/9 -> 0.27222222 | L8: =Assumptions!$B$17+(Assumptions!$F$17-Assumptions!$B$17)*9/9 -> 0.3
A9: Variable opex % rev | C9: =Assumptions!$B$18 -> 0.05 | D9: =Assumptions!$B$18+(Assumptions!$F$18-Assumptions!$B$18)*1/9 -> 0.048888889 | E9: =Assumptions!$B$18+(Assumptions!$F$18-Assumptions!$B$18)*2/9 -> 0.047777778 | F9: =Assumptions!$B$18+(Assumptions!$F$18-Assumptions!$B$18)*3/9 -> 0.046666667 | G9: =Assumptions!$B$18+(Assumptions!$F$18-Assumptions!$B$18)*4/9 -> 0.045555556 | H9: =Assumptions!$B$18+(Assumptions!$F$18-Assumptions!$B$18)*5/9 -> 0.044444444 | I9: =Assumptions!$B$18+(Assumptions!$F$18-Assumptions!$B$18)*6/9 -> 0.043333333 | J9: =Assumptions!$B$18+(Assumptions!$F$18-Assumptions!$B$18)*7/9 -> 0.042222222 | K9: =Assumptions!$B$18+(Assumptions!$F$18-Assumptions!$B$18)*8/9 -> 0.041111111 | L9: =Assumptions!$B$18+(Assumptions!$F$18-Assumptions!$B$18)*9/9 -> 0.04
A10: SBC % rev | C10: =Assumptions!$B$19 -> 0.03 | D10: =Assumptions!$B$19+(Assumptions!$F$19-Assumptions!$B$19)*1/9 -> 0.028888889 | E10: =Assumptions!$B$19+(Assumptions!$F$19-Assumptions!$B$19)*2/9 -> 0.027777778 | F10: =Assumptions!$B$19+(Assumptions!$F$19-Assumptions!$B$19)*3/9 -> 0.026666667 | G10: =Assumptions!$B$19+(Assumptions!$F$19-Assumptions!$B$19)*4/9 -> 0.025555556 | H10: =Assumptions!$B$19+(Assumptions!$F$19-Assumptions!$B$19)*5/9 -> 0.024444444 | I10: =Assumptions!$B$19+(Assumptions!$F$19-Assumptions!$B$19)*6/9 -> 0.023333333 | J10: =Assumptions!$B$19+(Assumptions!$F$19-Assumptions!$B$19)*7/9 -> 0.022222222 | K10: =Assumptions!$B$19+(Assumptions!$F$19-Assumptions!$B$19)*8/9 -> 0.021111111 | L10: =Assumptions!$B$19+(Assumptions!$F$19-Assumptions!$B$19)*9/9 -> 0.02
A11: Cash tax rate % | C11: =Assumptions!$B$20 -> 0 | D11: =Assumptions!$B$20+(Assumptions!$F$20-Assumptions!$B$20)*1/9 -> 0.016666667 | E11: =Assumptions!$B$20+(Assumptions!$F$20-Assumptions!$B$20)*2/9 -> 0.033333333 | F11: =Assumptions!$B$20+(Assumptions!$F$20-Assumptions!$B$20)*3/9 -> 0.05 | G11: =Assumptions!$B$20+(Assumptions!$F$20-Assumptions!$B$20)*4/9 -> 0.066666667 | H11: =Assumptions!$B$20+(Assumptions!$F$20-Assumptions!$B$20)*5/9 -> 0.083333333 | I11: =Assumptions!$B$20+(Assumptions!$F$20-Assumptions!$B$20)*6/9 -> 0.1 | J11: =Assumptions!$B$20+(Assumptions!$F$20-Assumptions!$B$20)*7/9 -> 0.11666667 | K11: =Assumptions!$B$20+(Assumptions!$F$20-Assumptions!$B$20)*8/9 -> 0.13333333 | L11: =Assumptions!$B$20+(Assumptions!$F$20-Assumptions!$B$20)*9/9 -> 0.15
A12: Deposits % rev | C12: =Assumptions!$B$21 -> 0.3 | D12: =Assumptions!$B$21+(Assumptions!$F$21-Assumptions!$B$21)*1/9 -> 0.28888889 | E12: =Assumptions!$B$21+(Assumptions!$F$21-Assumptions!$B$21)*2/9 -> 0.27777778 | F12: =Assumptions!$B$21+(Assumptions!$F$21-Assumptions!$B$21)*3/9 -> 0.26666667 | G12: =Assumptions!$B$21+(Assumptions!$F$21-Assumptions!$B$21)*4/9 -> 0.25555556 | H12: =Assumptions!$B$21+(Assumptions!$F$21-Assumptions!$B$21)*5/9 -> 0.24444444 | I12: =Assumptions!$B$21+(Assumptions!$F$21-Assumptions!$B$21)*6/9 -> 0.23333333 | J12: =Assumptions!$B$21+(Assumptions!$F$21-Assumptions!$B$21)*7/9 -> 0.22222222 | K12: =Assumptions!$B$21+(Assumptions!$F$21-Assumptions!$B$21)*8/9 -> 0.21111111 | L12: =Assumptions!$B$21+(Assumptions!$F$21-Assumptions!$B$21)*9/9 -> 0.2
A14: INCOME STATEMENT
A15: Revenue + grant income | B15: =Historicals!C5 -> 109.1 | C15: =Historicals!F5 -> 180 | D15: =C15*(1+D7) -> 279 | E15: =D15*(1+E7) -> 421.9875 | F15: =E15*(1+F7) -> 622.43156 | G15: =F15*(1+G7) -> 894.74537 | H15: =G15*(1+H7) -> 1252.6435 | I15: =H15*(1+I7) -> 1706.7268 | J15: =I15*(1+J7) -> 2261.413 | K15: =J15*(1+K7) -> 2911.5692 | L15: =K15*(1+L7) -> 3639.4616
A16: Cost of revenue (excl. D&A) | C16: =-C15*(1-C8) -> -171 | D16: =-D15*(1-D8) -> -257.3 | E16: =-E15*(1-E8) -> -377.44437 | F16: =-F15*(1-F8) -> -539.44069 | G16: =-G15*(1-G8) -> -750.59195 | H16: =-H15*(1-H8) -> -1016.0331 | I16: =-I15*(1-I8) -> -1336.936 | J16: =-J15*(1-J8) -> -1708.6232 | ... L16: =-L15*(1-L8) -> -2547.6231
A17: Gross profit | C17: =C15+C16 -> 9 | D17: =D15+D16 -> 21.7 | E17: =E15+E16 -> 44.543125 | F17: =F15+F16 -> 82.990875 | G17: =G15+G16 -> 144.15342 | H17: =H15+H16 -> 236.61044 | I17: =I15+I16 -> 369.79081 | J17: =J15+J16 -> 552.78985 | ... L17: =L15+L16 -> 1091.8385
A18: Fixed cash opex (R&D, licensing, G&A) | C18: =-Assumptions!$B$29*(1+Assumptions!$E$25)^0 -> -255 | D18: =-Assumptions!$B$29*(1+Assumptions!$E$25)^1 -> -260.1 | E18: =-Assumptions!$B$29*(1+Assumptions!$E$25)^2 -> -265.302 | F18: =-Assumptions!$B$29*(1+Assumptions!$E$25)^3 -> -270.60804 | G18: =-Assumptions!$B$29*(1+Assumptions!$E$25)^4 -> -276.0202 | H18: =-Assumptions!$B$29*(1+Assumptions!$E$25)^5 -> -281.5406 | I18: =-Assumptions!$B$29*(1+Assumptions!$E$25)^6 -> -287.17142 | J18: =-Assumptions!$B$29*(1+Assumptions!$E$25)^7 -> -292.91485 | K18: =-Assumptions!$B$29*(1+Assumptions!$E$25)^8 -> -298.77314 | L18: =-Assumptions!$B$29*(1+Assumptions!$E$25)^9 -> -304.7486
A19: Variable opex | C19: =-C15*C9 -> -9 | D19: =-D15*D9 -> -13.64 | E19: =-E15*E9 -> -20.161625 | F19: =-F15*F9 -> -29.046806 | G19: =-G15*G9 -> -40.760622 | H19: =-H15*H9 -> -55.673045 | I19: =-I15*I9 -> -73.958161 | J19: =-J15*J9 -> -95.481882 | ... L19: =-L15*L9 -> -145.57846
A20: Adjusted EBITDA | C20: =C17+C18+C19 -> -255 | D20: =D17+D18+D19 -> -252.04 | E20: =E17+E18+E19 -> -240.9205 | F20: =F17+F18+F19 -> -216.66397 | G20: =G17+G18+G19 -> -172.6274 | H20: =H17+H18+H19 -> -100.60321 | I20: =I17+I18+I19 -> 8.6612276 | J20: =J17+J18+J19 -> 164.39312 | ... L20: =L17+L18+L19 -> 641.5114
A21: Stock-based compensation | C21: =-C15*C10 -> -5.4 | D21: =-D15*D10 -> -8.06 | E21: =-E15*E10 -> -11.721875 | F21: =-F15*F10 -> -16.598175 | G21: =-G15*G10 -> -22.865715 | H21: =-H15*H10 -> -30.620175 | I21: =-I15*I10 -> -39.823625 | J21: =-J15*J10 -> -50.253622 | ... L21: =-L15*L10 -> -72.789231
A22: D&A (% of beginning PP&E) | C22: =-B42*Assumptions!$B$31 -> -28 | D22: =-C42*Assumptions!$B$31 -> -45.76 | E22: =-D42*Assumptions!$B$31 -> -62.0992 | F22: =-E42*Assumptions!$B$31 -> -77.131264 | G22: =-F42*Assumptions!$B$31 -> -90.960763 | H22: =-G42*Assumptions!$B$31 -> -103.6839 | I22: =-H42*Assumptions!$B$31 -> -115.38919 | J22: =-I42*Assumptions!$B$31 -> -126.15805 | ... L22: =-K42*Assumptions!$B$31 -> -145.18018
A23: EBIT | C23: =C20+C21+C22 -> -288.4 | D23: =D20+D21+D22 -> -305.86 | E23: =E20+E21+E22 -> -314.74158 | F23: =F20+F21+F22 -> -310.39341 | G23: =G20+G21+G22 -> -286.45388 | H23: =H20+H21+H22 -> -234.90728 | I23: =I20+I21+I22 -> -146.55159 | J23: =J20+J21+J22 -> -12.018559 | ... L23: =L20+L21+L22 -> 423.54199
A24: Interest income (on beginning cash) | C24: =B63*Assumptions!$B$36 -> 47 | D24: =C63*Assumptions!$B$36 -> 70.607123 | E24: =D63*Assumptions!$B$36 -> 53.818044 | F24: =E63*Assumptions!$B$36 -> 36.912946 | G24: =F63*Assumptions!$B$36 -> 20.402921 | H24: =G63*Assumptions!$B$36 -> 6 | I24: =H63*Assumptions!$B$36 -> 6 | J24: =I63*Assumptions!$B$36 -> 6 | ... L24: =K63*Assumptions!$B$36 -> 6
A25: Interest expense (revolver) | C25: =-B48*Assumptions!$B$37 -> 0 | D25: =-C48*Assumptions!$B$37 -> 0 | E25: =-D48*Assumptions!$B$37 -> 0 | F25: =-E48*Assumptions!$B$37 -> 0 | G25: =-F48*Assumptions!$B$37 -> 0 | H25: =-G48*Assumptions!$B$37 -> -1.7602877 | I25: =-H48*Assumptions!$B$37 -> -26.3335 | J25: =-I48*Assumptions!$B$37 -> -44.743799 | ... L25: =-K48*Assumptions!$B$37 -> -48.82091
A26: Pre-tax income | C26: =C23+C24+C25 -> -241.4 | D26: =D23+D24+D25 -> -235.25288 | E26: =E23+E24+E25 -> -260.92353 | F26: =F23+F24+F25 -> -273.48046 | G26: =G23+G24+G25 -> -266.05096 | H26: =H23+H24+H25 -> -230.66757 | I26: =I23+I24+I25 -> -166.88509 | J26: =J23+J24+J25 -> -50.762358 | ... L26: =L23+L24+L25 -> 380.72108
A27: Taxes (NOL-shielded early years) | C27: =-MAX(0,C26)*C11 -> 0 | D27: =-MAX(0,D26)*D11 -> 0 | E27: =-MAX(0,E26)*E11 -> 0 | F27: =-MAX(0,F26)*F11 -> 0 | G27: =-MAX(0,G26)*G11 -> 0 | H27: =-MAX(0,H26)*H11 -> 0 | I27: =-MAX(0,I26)*I11 -> 0 | J27: =-MAX(0,J26)*J11 -> 0 | ... L27: =-MAX(0,L26)*L11 -> -57.108162
A28: Net income (ex-warrant MTM) | C28: =C26+C27 -> -241.4 | D28: =D26+D27 -> -235.25288 | E28: =E26+E27 -> -260.92353 | F28: =F26+F27 -> -273.48046 | G28: =G26+G27 -> -266.05096 | H28: =H26+H27 -> -230.66757 | I28: =I26+I27 -> -166.88509 | J28: =J26+J27 -> -50.762358 | ... L28: =L26+L27 -> 323.61292
A29: Adj. EBITDA margin % | C29: =C20/C15 -> -1.4166667 | D29: =D20/D15 -> -0.90336918 | E29: =E20/E15 -> -0.57091857 | F29: =F20/F15 -> -0.34809284 | G29: =G20/G15 -> -0.19293467 | H29: =H20/H15 -> -0.080312719 | I29: =I20/I15 -> 0.0050747593 | J29: =J20/J15 -> 0.072694867 | ... L29: =L20/L15 -> 0.17626547
A31: WORKING CAPITAL
A32: Accounts receivable | B32: 30 | C32: =C15*Assumptions!$B$32/365 -> 29.589041 | D32: =D15*Assumptions!$B$32/365 -> 45.863014 | E32: =E15*Assumptions!$B$32/365 -> 69.367808 | F32: =F15*Assumptions!$B$32/365 -> 102.31752 | G32: =G15*Assumptions!$B$32/365 -> 147.08143 | H32: =H15*Assumptions!$B$32/365 -> 205.914 | I32: =I15*Assumptions!$B$32/365 -> 280.55783 | J32: =J15*Assumptions!$B$32/365 -> 371.73912 | ... L32: =L15*Assumptions!$B$32/365 -> 598.26765
A33: Inventory | B33: 20 | C33: =-C16*Assumptions!$B$33/365 -> 18.739726 | D33: =-D16*Assumptions!$B$33/365 -> 28.19726 | E33: =-E16*Assumptions!$B$33/365 -> 41.363767 | F33: =-F16*Assumptions!$B$33/365 -> 59.116788 | G33: =-G16*Assumptions!$B$33/365 -> 82.256652 | H33: =-H16*Assumptions!$B$33/365 -> 111.34609 | I33: =-I16*Assumptions!$B$33/365 -> 146.51353 | J33: =-J16*Assumptions!$B$33/365 -> 187.24637 | ... L33: =-L16*Assumptions!$B$33/365 -> 279.19157
A34: Other current assets | B34: 40 | C34: =C15*Assumptions!$B$35 -> 9 | D34: =D15*Assumptions!$B$35 -> 13.95 | E34: =E15*Assumptions!$B$35 -> 21.099375 | F34: =F15*Assumptions!$B$35 -> 31.121578 | G34: =G15*Assumptions!$B$35 -> 44.737269 | H34: =H15*Assumptions!$B$35 -> 62.632176 | I34: =I15*Assumptions!$B$35 -> 85.33634 | J34: =J15*Assumptions!$B$35 -> 113.07065 | ... L34: =L15*Assumptions!$B$35 -> 181.97308
A35: Accounts payable + accrued | B35: -60 | C35: =(C16+C18+C19)*Assumptions!$B$34/365 -> -71.506849 | D35: =(D16+D18+D19)*Assumptions!$B$34/365 -> -87.294247 | E35: =(E16+E18+E19)*Assumptions!$B$34/365 -> -108.97118 | F35: =(F16+F18+F19)*Assumptions!$B$34/365 -> -137.93351 | G35: =(G16+G18+G19)*Assumptions!$B$34/365 -> -175.45854 | H35: =(H16+H18+H19)*Assumptions!$B$34/365 -> -222.45152 | I35: =(I16+I18+I19)*Assumptions!$B$34/365 -> -279.13407 | J35: =(J16+J18+J19)*Assumptions!$B$34/365 -> -344.7156 | ... L35: =(L16+L18+L19)*Assumptions!$B$34/365 -> -492.81372
A36: Customer deposits / deferred revenue | B36: -150 | C36: =-C15*C12 -> -54 | D36: =-D15*D12 -> -80.6 | E36: =-E15*E12 -> -117.21875 | F36: =-F15*F12 -> -165.98175 | G36: =-G15*G12 -> -228.65715 | H36: =-H15*H12 -> -306.20175 | I36: =-I15*I12 -> -398.23625 | J36: =-J15*J12 -> -502.53622 | ... L36: =-L15*L12 -> -727.89231
A37: Net working capital | B37: =SUM(B32:B36) -> -120 | C37: =SUM(C32:C36) -> -68.178082 | D37: =SUM(D32:D36) -> -79.883973 | E37: =SUM(E32:E36) -> -94.358978 | F37: =SUM(F32:F36) -> -111.35938 | G37: =SUM(G32:G36) -> -130.04034 | H37: =SUM(H32:H36) -> -148.761 | I37: =SUM(I32:I36) -> -164.96262 | ... L37: =SUM(L32:L36) -> -161.27373
A38: (Increase) / decrease in NWC — cash impact | C38: =-(C37-B37) -> -51.821918 | D38: =-(D37-C37) -> 11.70589 | E38: =-(E37-D37) -> 14.475005 | F38: =-(F37-E37) -> 17.000402 | G38: =-(G37-F37) -> 18.680958 | H38: =-(H37-G37) -> 18.720659 | I38: =-(I37-H37) -> 16.20162 | J38: =-(J37-I37) -> 10.233057 | ... L38: =-(L37-K37) -> -14.096293
A40: CAPEX & PP&E (fuel fabrication capacity + engineering)
A41: Capex (program, scenario growth) | C41: =Assumptions!$B$30*(1+Assumptions!$E$26)^0 -> 250 | D41: =Assumptions!$B$30*(1+Assumptions!$E$26)^1 -> 250 | E41: =Assumptions!$B$30*(1+Assumptions!$E$26)^2 -> 250 | F41: =Assumptions!$B$30*(1+Assumptions!$E$26)^3 -> 250 | G41: =Assumptions!$B$30*(1+Assumptions!$E$26)^4 -> 250 | H41: =Assumptions!$B$30*(1+Assumptions!$E$26)^5 -> 250 | I41: =Assumptions!$B$30*(1+Assumptions!$E$26)^6 -> 250 | J41: =Assumptions!$B$30*(1+Assumptions!$E$26)^7 -> 250 | K41: =Assumptions!$B$30*(1+Assumptions!$E$26)^8 -> 250 | L41: =Assumptions!$B$30*(1+Assumptions!$E$26)^9 -> 250
A42: PP&E, net | B42: 350 | C42: =B42+C41+C22 -> 572 | D42: =C42+D41+D22 -> 776.24 | E42: =D42+E41+E22 -> 964.1408 | F42: =E42+F41+F22 -> 1137.0095 | G42: =F42+G41+G22 -> 1296.0488 | H42: =G42+H41+H22 -> 1442.3649 | I42: =H42+I41+I22 -> 1576.9757 | J42: =I42+J41+J22 -> 1700.8176 | ... L42: =K42+L41+L22 -> 1919.572
A44: DEBT SCHEDULE (currently debt-free; revolver models any funding gap)
A45: Revolver — beginning | C45: =B48 -> 0 | D45: =C48 -> 0 | E45: =D48 -> 0 | F45: =E48 -> 0 | G45: =F48 -> 0 | H45: =G48 -> 23.470503 | I45: =H48 -> 351.11334 | J45: =I48 -> 596.58399 | ... L45: =K48 -> 650.94547
A46: Draw (if cash < minimum) | C46: =MAX(0,Assumptions!$B$38-(B63+C28-C21-C22+C38-C41+C59)) -> 0 | D46: =MAX(0,Assumptions!$B$38-(C63+D28-D21-D22+D38-D41+D59)) -> 0 | E46: =MAX(0,Assumptions!$B$38-(D63+E28-E21-E22+E38-E41+E59)) -> 0 | F46: =MAX(0,Assumptions!$B$38-(E63+F28-F21-F22+F38-F41+F59)) -> 0 | G46: =MAX(0,Assumptions!$B$38-(F63+G28-G21-G22+G38-G41+G59)) -> 23.470503 | H46: =MAX(0,Assumptions!$B$38-(G63+H28-H21-H22+H38-H41+H59)) -> 327.64284 | I46: =MAX(0,Assumptions!$B$38-(H63+I28-I21-I22+I38-I41+I59)) -> 245.47065 | J46: =MAX(0,Assumptions!$B$38-(I63+J28-J21-J22+J38-J41+J59)) -> 114.11762 | ... L46: =MAX(0,Assumptions!$B$38-(K63+L28-L21-L22+L38-L41+L59)) -> 0 | M46: Draws indicate an external funding need (equity raise in practice) — watch this row in the Bear case
A47: (Repayment) | C47: =-MIN(C45,MAX(0,(B63+C28-C21-C22+C38-C41+C59)-Assumptions!$B$38)) -> 0 | D47: =-MIN(D45,MAX(0,(C63+D28-D21-D22+D38-D41+D59)-Assumptions!$B$38)) -> 0 | E47: =-MIN(E45,MAX(0,(D63+E28-E21-E22+E38-E41+E59)-Assumptions!$B$38)) -> 0 | F47: =-MIN(F45,MAX(0,(E63+F28-F21-F22+F38-F41+F59)-Assumptions!$B$38)) -> 0 | G47: =-MIN(G45,MAX(0,(F63+G28-G21-G22+G38-G41+G59)-Assumptions!$B$38)) -> 0 | H47: =-MIN(H45,MAX(0,(G63+H28-H21-H22+H38-H41+H59)-Assumptions!$B$38)) -> 0 | I47: =-MIN(I45,MAX(0,(H63+I28-I21-I22+I38-I41+I59)-Assumptions!$B$38)) -> 0 | J47: =-MIN(J45,MAX(0,(I63+J28-J21-J22+J38-J41+J59)-Assumptions!$B$38)) -> 0 | ... L47: =-MIN(L45,MAX(0,(K63+L28-L21-L22+L38-L41+L59)-Assumptions!$B$38)) -> -277.48603
A48: Revolver — ending | B48: 0 | C48: =C45+C46+C47 -> 0 | D48: =D45+D46+D47 -> 0 | E48: =E45+E46+E47 -> 0 | F48: =F45+F46+F47 -> 0 | G48: =G45+G46+G47 -> 23.470503 | H48: =H45+H46+H47 -> 351.11334 | I48: =I45+I46+I47 -> 596.58399 | J48: =J45+J46+J47 -> 710.70162 | ... L48: =L45+L46+L47 -> 373.45944
A49: Total debt — ending | B49: =B48 -> 0 | C49: =C48 -> 0 | D49: =D48 -> 0 | E49: =E48 -> 0 | F49: =F48 -> 0 | G49: =G48 -> 23.470503 | H49: =H48 -> 351.11334 | I49: =I48 -> 596.58399 | ... L49: =L48 -> 373.45944
A51: CASH FLOW STATEMENT
A52: Net income | C52: =C28 -> -241.4 | D52: =D28 -> -235.25288 | E52: =E28 -> -260.92353 | F52: =F28 -> -273.48046 | G52: =G28 -> -266.05096 | H52: =H28 -> -230.66757 | I52: =I28 -> -166.88509 | J52: =J28 -> -50.762358 | ... L52: =L28 -> 323.61292
A53: + D&A | C53: =-C22 -> 28 | D53: =-D22 -> 45.76 | E53: =-E22 -> 62.0992 | F53: =-F22 -> 77.131264 | G53: =-G22 -> 90.960763 | H53: =-H22 -> 103.6839 | I53: =-I22 -> 115.38919 | J53: =-J22 -> 126.15805 | ... L53: =-L22 -> 145.18018
A54: + Stock-based compensation | C54: =-C21 -> 5.4 | D54: =-D21 -> 8.06 | E54: =-E21 -> 11.721875 | F54: =-F21 -> 16.598175 | G54: =-G21 -> 22.865715 | H54: =-H21 -> 30.620175 | I54: =-I21 -> 39.823625 | J54: =-J21 -> 50.253622 | ... L54: =-L21 -> 72.789231
A55: +/- Change in NWC | C55: =C38 -> -51.821918 | D55: =D38 -> 11.70589 | E55: =E38 -> 14.475005 | F55: =F38 -> 17.000402 | G55: =G38 -> 18.680958 | H55: =H38 -> 18.720659 | I55: =I38 -> 16.20162 | J55: =J38 -> 10.233057 | ... L55: =L38 -> -14.096293
A56: Cash from operations | C56: =SUM(C52:C55) -> -259.82192 | D56: =SUM(D52:D55) -> -169.72699 | E56: =SUM(E52:E55) -> -172.62745 | F56: =SUM(F52:F55) -> -162.75062 | G56: =SUM(G52:G55) -> -133.54352 | H56: =SUM(H52:H55) -> -77.642836 | I56: =SUM(I52:I55) -> 4.5293469 | J56: =SUM(J52:J55) -> 135.88238 | ... L56: =SUM(L52:L55) -> 527.48603
A57: - Capex | C57: =-C41 -> -250 | D57: =-D41 -> -250 | E57: =-E41 -> -250 | F57: =-F41 -> -250 | G57: =-G41 -> -250 | H57: =-H41 -> -250 | I57: =-I41 -> -250 | J57: =-J41 -> -250 | ... L57: =-L41 -> -250
A58: Free cash flow | C58: =C56+C57 -> -509.82192 | D58: =D56+D57 -> -419.72699 | E58: =E56+E57 -> -422.62745 | F58: =F56+F57 -> -412.75062 | G58: =G56+G57 -> -383.54352 | H58: =H56+H57 -> -327.64284 | I58: =I56+I57 -> -245.47065 | J58: =J56+J57 -> -114.11762 | ... L58: =L56+L57 -> 277.48603
A59: + Equity issuance (IPO net, FY2026) | C59: =Assumptions!$B$41 -> 1100 | D59: 0 | E59: 0 | F59: 0 | G59: 0 | H59: 0 | I59: 0 | J59: 0 | K59: 0 | L59: 0
A60: + Revolver draws / (repayments) | C60: =C46+C47 -> 0 | D60: =D46+D47 -> 0 | E60: =E46+E47 -> 0 | F60: =F46+F47 -> 0 | G60: =G46+G47 -> 23.470503 | H60: =H46+H47 -> 327.64284 | I60: =I46+I47 -> 245.47065 | J60: =J46+J47 -> 114.11762 | ... L60: =L46+L47 -> -277.48603
A61: Net change in cash | C61: =C58+C59+C60 -> 590.17808 | D61: =D58+D59+D60 -> -419.72699 | E61: =E58+E59+E60 -> -422.62745 | F61: =F58+F59+F60 -> -412.75062 | G61: =G58+G59+G60 -> -360.07302 | H61: =H58+H59+H60 -> 0 | I61: =I58+I59+I60 -> 0 | J61: =J58+J59+J60 -> 0 | ... L61: =L58+L59+L60 -> 0
A62: Cash — beginning | C62: =B63 -> 1175 | D62: =C63 -> 1765.1781 | E62: =D63 -> 1345.4511 | F62: =E63 -> 922.82364 | G62: =F63 -> 510.07302 | H62: =G63 -> 150 | I62: =H63 -> 150 | J62: =I63 -> 150 | ... L62: =K63 -> 150
A63: Cash + investments — ending | B63: 1175 | C63: =C62+C61 -> 1765.1781 | D63: =D62+D61 -> 1345.4511 | E63: =E62+E61 -> 922.82364 | F63: =F62+F61 -> 510.07302 | G63: =G62+G61 -> 150 | H63: =H62+H61 -> 150 | I63: =I62+I61 -> 150 | J63: =J62+J61 -> 150 | ... L63: =L62+L61 -> 150
A65: BALANCE SHEET
A66: Cash + investments | B66: =B63 -> 1175 | C66: =C63 -> 1765.1781 | D66: =D63 -> 1345.4511 | E66: =E63 -> 922.82364 | F66: =F63 -> 510.07302 | G66: =G63 -> 150 | H66: =H63 -> 150 | I66: =I63 -> 150 | ... L66: =L63 -> 150
A67: Accounts receivable | B67: =B32 -> 30 | C67: =C32 -> 29.589041 | D67: =D32 -> 45.863014 | E67: =E32 -> 69.367808 | F67: =F32 -> 102.31752 | G67: =G32 -> 147.08143 | H67: =H32 -> 205.914 | I67: =I32 -> 280.55783 | ... L67: =L32 -> 598.26765
A68: Inventory | B68: =B33 -> 20 | C68: =C33 -> 18.739726 | D68: =D33 -> 28.19726 | E68: =E33 -> 41.363767 | F68: =F33 -> 59.116788 | G68: =G33 -> 82.256652 | H68: =H33 -> 111.34609 | I68: =I33 -> 146.51353 | ... L68: =L33 -> 279.19157
A69: Other current assets | B69: =B34 -> 40 | C69: =C34 -> 9 | D69: =D34 -> 13.95 | E69: =E34 -> 21.099375 | F69: =F34 -> 31.121578 | G69: =G34 -> 44.737269 | H69: =H34 -> 62.632176 | I69: =I34 -> 85.33634 | ... L69: =L34 -> 181.97308
A70: PP&E, net | B70: =B42 -> 350 | C70: =C42 -> 572 | D70: =D42 -> 776.24 | E70: =E42 -> 964.1408 | F70: =F42 -> 1137.0095 | G70: =G42 -> 1296.0488 | H70: =H42 -> 1442.3649 | I70: =I42 -> 1576.9757 | ... L70: =L42 -> 1919.572
A71: Other long-term assets | B71: 60 | C71: =B71 -> 60 | D71: =B71 -> 60 | E71: =B71 -> 60 | F71: =B71 -> 60 | G71: =B71 -> 60 | H71: =B71 -> 60 | I71: =B71 -> 60 | J71: =B71 -> 60 | K71: =B71 -> 60 | L71: =B71 -> 60
A72: TOTAL ASSETS | B72: =SUM(B66:B71) -> 1675 | C72: =SUM(C66:C71) -> 2454.5068 | D72: =SUM(D66:D71) -> 2269.7014 | E72: =SUM(E66:E71) -> 2078.7954 | F72: =SUM(F66:F71) -> 1899.6384 | G72: =SUM(G66:G71) -> 1780.1241 | H72: =SUM(H66:H71) -> 2032.2571 | I72: =SUM(I66:I71) -> 2299.3834 | ... L72: =SUM(L66:L71) -> 3189.0043
A73: Accounts payable + accrued | B73: =-B35 -> 60 | C73: =-C35 -> 71.506849 | D73: =-D35 -> 87.294247 | E73: =-E35 -> 108.97118 | F73: =-F35 -> 137.93351 | G73: =-G35 -> 175.45854 | H73: =-H35 -> 222.45152 | I73: =-I35 -> 279.13407 | ... L73: =-L35 -> 492.81372
A74: Customer deposits / deferred revenue | B74: =-B36 -> 150 | C74: =-C36 -> 54 | D74: =-D36 -> 80.6 | E74: =-E36 -> 117.21875 | F74: =-F36 -> 165.98175 | G74: =-G36 -> 228.65715 | H74: =-H36 -> 306.20175 | I74: =-I36 -> 398.23625 | ... L74: =-L36 -> 727.89231
A75: Revolver | B75: =B48 -> 0 | C75: =C48 -> 0 | D75: =D48 -> 0 | E75: =E48 -> 0 | F75: =F48 -> 0 | G75: =G48 -> 23.470503 | H75: =H48 -> 351.11334 | I75: =I48 -> 596.58399 | ... L75: =L48 -> 373.45944
A76: Warrant + other LT liabilities | B76: 300 | C76: =B76 -> 300 | D76: =B76 -> 300 | E76: =B76 -> 300 | F76: =B76 -> 300 | G76: =B76 -> 300 | H76: =B76 -> 300 | I76: =B76 -> 300 | J76: =B76 -> 300 | K76: =B76 -> 300 | L76: =B76 -> 300
A77: TOTAL LIABILITIES | B77: =SUM(B73:B76) -> 510 | C77: =SUM(C73:C76) -> 425.50685 | D77: =SUM(D73:D76) -> 467.89425 | E77: =SUM(E73:E76) -> 526.18993 | F77: =SUM(F73:F76) -> 603.91526 | G77: =SUM(G73:G76) -> 727.58619 | H77: =SUM(H73:H76) -> 1179.7666 | I77: =SUM(I73:I76) -> 1573.9543 | ... L77: =SUM(L73:L76) -> 1894.1655
A78: Total equity (opening = plug; rolls with NI + SBC + issuance) | B78: =B72-B77 -> 1165 | C78: =B78+C28-C21+C59 -> 2029 | D78: =C78+D28-D21+D59 -> 1801.8071 | E78: =D78+E28-E21+E59 -> 1552.6055 | F78: =E78+F28-F21+F59 -> 1295.7232 | G78: =F78+G28-G21+G59 -> 1052.5379 | H78: =G78+H28-H21+H59 -> 852.49054 | I78: =H78+I28-I21+I59 -> 725.42907 | J78: =I78+J28-J21+J59 -> 724.92034 | ... L78: =K78+L28-L21+L59 -> 1294.8389
A79: TOTAL LIABILITIES + EQUITY | B79: =B77+B78 -> 1675 | C79: =C77+C78 -> 2454.5068 | D79: =D77+D78 -> 2269.7014 | E79: =E77+E78 -> 2078.7954 | F79: =F77+F78 -> 1899.6384 | G79: =G77+G78 -> 1780.1241 | H79: =H77+H78 -> 2032.2571 | I79: =I77+I78 -> 2299.3834 | ... L79: =L77+L78 -> 3189.0043
A80: Balance check (must be 0) | B80: =B72-B79 -> 0 | C80: =C72-C79 -> 0 | D80: =D72-D79 -> 0 | E80: =E72-E79 -> 0 | F80: =F72-F79 -> 0 | G80: =G72-G79 -> 0 | H80: =H72-H79 -> 0 | I80: =I72-I79 -> 0 | ... L80: =L72-L79 -> 0

Sheet WACC
A1: WEIGHTED AVERAGE COST OF CAPITAL — CURRENT MARKET DATA (JULY 2026)
A4: COST OF EQUITY (CAPM)
A5: Risk-free rate — 10Y UST, 7/17/2026 | B5: 0.0455 | C5: tradingeconomics.com / FRED DGS10
A6: Levered beta (proxy) | B6: 2 | C6: XE listed <3 months — proxied from SMR peers (OKLO/NuScale betas ~2.0-3.0); e
A7: Equity risk premium | B7: 0.0475 | C7: Damodaran implied ERP, mid-2026
A8: Company-specific premium | B8: 0 | C8: Licensing/execution risk arguably merits +1-2%; left at 0, beta already high
A9: Cost of equity | B9: =B5+B6*B7+B8 -> 0.1405
A11: COST OF DEBT
A12: Pre-tax cost of debt (hypothetical) | B12: 0.09 | C12: XE has no debt; HY-style rate if it issued
A13: Tax rate | B13: =Assumptions!B40 -> 0.25
A14: After-tax cost of debt | B14: =B12*(1-B13) -> 0.0675
A16: CAPITAL STRUCTURE
A17: Debt / total capital | B17: 0 | C17: All-equity
A18: Equity / total capital | B18: =1-B17 -> 1
A20: WACC | B20: =B18*B9+B17*B14 -> 0.1405
A22: WACC ≈ 14.0%. Sensitivity range in DCF tables: 12% – 16%. For a pre-commercial company the discount rate is the single most contestable input.

Sheet DCF
A1: DISCOUNTED CASH FLOW — UNLEVERED FCF ($mm; valuation as of FY2026 year-end, mid-year convention)
B4: FY2027E | C4: FY2028E | D4: FY2029E | E4: FY2030E | F4: FY2031E | G4: FY2032E | H4: FY2033E | I4: FY2034E | J4: FY2035E
A5: EBIT | B5: =Model_3S!D23 -> -305.86 | C5: =Model_3S!E23 -> -314.74158 | D5: =Model_3S!F23 -> -310.39341 | E5: =Model_3S!G23 -> -286.45388 | F5: =Model_3S!H23 -> -234.90728 | G5: =Model_3S!I23 -> -146.55159 | H5: =Model_3S!J23 -> -12.018559 | I5: =Model_3S!K23 -> 176.59099 | J5: =Model_3S!L23 -> 423.54199
A6: Cash taxes on EBIT | B6: =-MAX(0,B5)*Model_3S!D11 -> 0 | C6: =-MAX(0,C5)*Model_3S!E11 -> 0 | D6: =-MAX(0,D5)*Model_3S!F11 -> 0 | E6: =-MAX(0,E5)*Model_3S!G11 -> 0 | F6: =-MAX(0,F5)*Model_3S!H11 -> 0 | G6: =-MAX(0,G5)*Model_3S!I11 -> 0 | H6: =-MAX(0,H5)*Model_3S!J11 -> 0 | I6: =-MAX(0,I5)*Model_3S!K11 -> -23.545465 | J6: =-MAX(0,J5)*Model_3S!L11 -> -63.531299
A7: + D&A | B7: =-Model_3S!D22 -> 45.76 | C7: =-Model_3S!E22 -> 62.0992 | D7: =-Model_3S!F22 -> 77.131264 | E7: =-Model_3S!G22 -> 90.960763 | F7: =-Model_3S!H22 -> 103.6839 | G7: =-Model_3S!I22 -> 115.38919 | H7: =-Model_3S!J22 -> 126.15805 | I7: =-Model_3S!K22 -> 136.06541 | J7: =-Model_3S!L22 -> 145.18018
A8: − Capex | B8: =-Model_3S!D41 -> -250 | C8: =-Model_3S!E41 -> -250 | D8: =-Model_3S!F41 -> -250 | E8: =-Model_3S!G41 -> -250 | F8: =-Model_3S!H41 -> -250 | G8: =-Model_3S!I41 -> -250 | H8: =-Model_3S!J41 -> -250 | I8: =-Model_3S!K41 -> -250 | J8: =-Model_3S!L41 -> -250
A9: +/− Change in NWC | B9: =Model_3S!D38 -> 11.70589 | C9: =Model_3S!E38 -> 14.475005 | D9: =Model_3S!F38 -> 17.000402 | E9: =Model_3S!G38 -> 18.680958 | F9: =Model_3S!H38 -> 18.720659 | G9: =Model_3S!I38 -> 16.20162 | H9: =Model_3S!J38 -> 10.233057 | I9: =Model_3S!K38 -> 0.17435283 | J9: =Model_3S!L38 -> -14.096293
A10: Unlevered free cash flow | B10: =SUM(B5:B9) -> -498.39411 | C10: =SUM(C5:C9) -> -488.16737 | D10: =SUM(D5:D9) -> -466.26174 | E10: =SUM(E5:E9) -> -426.81216 | F10: =SUM(F5:F9) -> -362.50272 | G10: =SUM(G5:G9) -> -264.96078 | H10: =SUM(H5:H9) -> -125.62745 | I10: =SUM(I5:I9) -> 39.285286 | J10: =SUM(J5:J9) -> 241.09458
A11: Discount period (mid-year) | B11: 0.5 | C11: 1.5 | D11: 2.5 | E11: 3.5 | F11: 4.5 | G11: 5.5 | H11: 6.5 | I11: 7.5 | J11: 8.5
A12: Discount factor @ WACC | B12: =(1+$B$16)^-B11 -> 0.93638049 | C12: =(1+$B$16)^-C11 -> 0.82102629 | D12: =(1+$B$16)^-D11 -> 0.71988276 | E12: =(1+$B$16)^-E11 -> 0.63119927 | F12: =(1+$B$16)^-F11 -> 0.55344083 | G12: =(1+$B$16)^-G11 -> 0.48526158 | H12: =(1+$B$16)^-H11 -> 0.42548144 | I12: =(1+$B$16)^-I11 -> 0.37306571 | J12: =(1+$B$16)^-J11 -> 0.32710715
A13: PV of FCF | B13: =B10*B12 -> -466.68652 | C13: =C10*C12 -> -400.79825 | D13: =D10*D12 -> -335.65379 | E13: =E10*E12 -> -269.40352 | F13: =F10*F12 -> -200.62381 | G13: =G10*G12 -> -128.57529 | H13: =H10*H12 -> -53.452147 | I13: =I10*I12 -> 14.655993 | J13: =J10*J12 -> 78.86376
A14: Explicit-window FCF is NEGATIVE until ~FY2033 (development burn) — the sum of PV of FCF is a cost, and value is carried by the terminal value. This is the honest shape of a pre-commercial DCF.
A15: Sum of PV of explicit FCF (FY27–35) | B15: =SUM(B13:J13) -> -1761.6736
A16: WACC | B16: =WACC!B20 -> 0.1405
A18: TERMINAL VALUE — METHOD 1: GORDON GROWTH (structurally conservative here — FY35 FCF is still depressed by reinvestment)
A19: Terminal growth g | B19: =Assumptions!B44 -> 0.035
A20: Terminal value = FCF35 × (1+g) / (WACC − g) | B20: =J10*(1+B19)/(B16-B19) -> 2365.2406
A21: PV of terminal value (9.0 yrs) | B21: =B20/(1+B16)^9 -> 724.46553
A22: Implied exit EV/EBITDA on FY35 Adj. EBITDA | B22: =B20/Model_3S!L20 -> 3.6869815
A24: TERMINAL VALUE — METHOD 2: EXIT MULTIPLE (primary anchor)
A25: Exit EV/Adj. EBITDA multiple | B25: =Assumptions!B45 -> 15
A26: Terminal value = multiple × FY35 Adj. EBITDA | B26: =B25*Model_3S!L20 -> 9622.671
A27: PV of terminal value | B27: =B26/(1+B16)^9 -> 2947.3929
A28: Implied perpetuity growth from exit TV | B28: =(B16*B26-J10)/(B26+J10) -> 0.11262339
A30: ENTERPRISE → EQUITY VALUE BRIDGE
A31: Net cash, FY2026E year-end | B31: =Model_3S!C63-Model_3S!C49 -> 1765.1781
A32: Diluted shares (mm) | B32: =Assumptions!B39 -> 406
B33: Gordon growth | C33: Exit multiple | D33: Average
A34: Enterprise value | B34: =B15+B21 -> -1037.208 | C34: =B15+B27 -> 1185.7193 | D34: =AVERAGE(B34:C34) -> 74.255634
A35: + Net cash | B35: =$B$31 -> 1765.1781 | C35: =$B$31 -> 1765.1781 | D35: =$B$31 -> 1765.1781
A36: Equity value | B36: =B34+B35 -> 727.97004 | C36: =C34+C35 -> 2950.8974 | D36: =D34+D35 -> 1839.4337
A37: Implied value per share | B37: =B36/$B$32 -> 1.7930297 | C37: =C36/$B$32 -> 7.2682202 | D37: =D36/$B$32 -> 4.5306249
A38: Upside / (downside) vs current price | B38: =B37/Assumptions!$B$46-1 -> -0.87210915 | C38: =C37/Assumptions!$B$46-1 -> -0.48158201 | D38: =D37/Assumptions!$B$46-1 -> -0.67684558
A40: At a 14% WACC the 10-year Base DCF lands below the market price: the market is paying for the 2036+ fleet ramp (Amazon 5 GWe by 2039, 11.5 GWe pipeline) that sits beyond the explicit window. The Bull toggle and exit-multiple sensitivities show what has to be true to justify $14+.
A42: SENSITIVITY — VALUE PER SHARE: WACC × TERMINAL GROWTH (Gordon)
B43: WACC \ g | C43: 0.025 | D43: 0.03 | E43: 0.035 | F43: 0.04 | G43: 0.045
B44: 0.12 | C44: =(SUMPRODUCT($B$10:$J$10,(1+$B$44)^-($B$11:$J$11))+$J$10*(1+C$43)/($B$44-C$43)/(1+$B$44)^9+$B$31)/$B$32 -> 2.1454751 | D44: =(SUMPRODUCT($B$10:$J$10,(1+$B$44)^-($B$11:$J$11))+$J$10*(1+D$43)/($B$44-D$43)/(1+$B$44)^9+$B$31)/$B$32 -> 2.285731 | E44: =(SUMPRODUCT($B$10:$J$10,(1+$B$44)^-($B$11:$J$11))+$J$10*(1+E$43)/($B$44-E$43)/(1+$B$44)^9+$B$31)/$B$32 -> 2.4424876 | F44: =(SUMPRODUCT($B$10:$J$10,(1+$B$44)^-($B$11:$J$11))+$J$10*(1+F$43)/($B$44-F$43)/(1+$B$44)^9+$B$31)/$B$32 -> 2.6188388 | G44: =(SUMPRODUCT($B$10:$J$10,(1+$B$44)^-($B$11:$J$11))+$J$10*(1+G$43)/($B$44-G$43)/(1+$B$44)^9+$B$31)/$B$32 -> 2.8187034
B45: 0.13 | C45: =(SUMPRODUCT($B$10:$J$10,(1+$B$45)^-($B$11:$J$11))+$J$10*(1+C$43)/($B$45-C$43)/(1+$B$45)^9+$B$31)/$B$32 -> 1.8508368 | D45: =(SUMPRODUCT($B$10:$J$10,(1+$B$45)^-($B$11:$J$11))+$J$10*(1+D$43)/($B$45-D$43)/(1+$B$45)^9+$B$31)/$B$32 -> 1.9572057 | E45: =(SUMPRODUCT($B$10:$J$10,(1+$B$45)^-($B$11:$J$11))+$J$10*(1+E$43)/($B$45-E$43)/(1+$B$45)^9+$B$31)/$B$32 -> 2.0747713 | F45: =(SUMPRODUCT($B$10:$J$10,(1+$B$45)^-($B$11:$J$11))+$J$10*(1+F$43)/($B$45-F$43)/(1+$B$45)^9+$B$31)/$B$32 -> 2.2053997 | G45: =(SUMPRODUCT($B$10:$J$10,(1+$B$45)^-($B$11:$J$11))+$J$10*(1+G$43)/($B$45-G$43)/(1+$B$45)^9+$B$31)/$B$32 -> 2.3513962
B46: 0.14 | C46: =(SUMPRODUCT($B$10:$J$10,(1+$B$46)^-($B$11:$J$11))+$J$10*(1+C$43)/($B$46-C$43)/(1+$B$46)^9+$B$31)/$B$32 -> 1.6321173 | D46: =(SUMPRODUCT($B$10:$J$10,(1+$B$46)^-($B$11:$J$11))+$J$10*(1+D$43)/($B$46-D$43)/(1+$B$46)^9+$B$31)/$B$32 -> 1.7143988 | E46: =(SUMPRODUCT($B$10:$J$10,(1+$B$46)^-($B$11:$J$11))+$J$10*(1+E$43)/($B$46-E$43)/(1+$B$46)^9+$B$31)/$B$32 -> 1.8045166 | F46: =(SUMPRODUCT($B$10:$J$10,(1+$B$46)^-($B$11:$J$11))+$J$10*(1+F$43)/($B$46-F$43)/(1+$B$46)^9+$B$31)/$B$32 -> 1.9036462 | G46: =(SUMPRODUCT($B$10:$J$10,(1+$B$46)^-($B$11:$J$11))+$J$10*(1+G$43)/($B$46-G$43)/(1+$B$46)^9+$B$31)/$B$32 -> 2.0132105
B47: 0.15 | C47: =(SUMPRODUCT($B$10:$J$10,(1+$B$47)^-($B$11:$J$11))+$J$10*(1+C$43)/($B$47-C$43)/(1+$B$47)^9+$B$31)/$B$32 -> 1.4694782 | D47: =(SUMPRODUCT($B$10:$J$10,(1+$B$47)^-($B$11:$J$11))+$J$10*(1+D$43)/($B$47-D$43)/(1+$B$47)^9+$B$31)/$B$32 -> 1.5341861 | E47: =(SUMPRODUCT($B$10:$J$10,(1+$B$47)^-($B$11:$J$11))+$J$10*(1+E$43)/($B$47-E$43)/(1+$B$47)^9+$B$31)/$B$32 -> 1.6045208 | F47: =(SUMPRODUCT($B$10:$J$10,(1+$B$47)^-($B$11:$J$11))+$J$10*(1+F$43)/($B$47-F$43)/(1+$B$47)^9+$B$31)/$B$32 -> 1.6812496 | G47: =(SUMPRODUCT($B$10:$J$10,(1+$B$47)^-($B$11:$J$11))+$J$10*(1+G$43)/($B$47-G$43)/(1+$B$47)^9+$B$31)/$B$32 -> 1.7652858
B48: 0.16 | C48: =(SUMPRODUCT($B$10:$J$10,(1+$B$48)^-($B$11:$J$11))+$J$10*(1+C$43)/($B$48-C$43)/(1+$B$48)^9+$B$31)/$B$32 -> 1.3490826 | D48: =(SUMPRODUCT($B$10:$J$10,(1+$B$48)^-($B$11:$J$11))+$J$10*(1+D$43)/($B$48-D$43)/(1+$B$48)^9+$B$31)/$B$32 -> 1.4006874 | E48: =(SUMPRODUCT($B$10:$J$10,(1+$B$48)^-($B$11:$J$11))+$J$10*(1+E$43)/($B$48-E$43)/(1+$B$48)^9+$B$31)/$B$32 -> 1.4564207 | F48: =(SUMPRODUCT($B$10:$J$10,(1+$B$48)^-($B$11:$J$11))+$J$10*(1+F$43)/($B$48-F$43)/(1+$B$48)^9+$B$31)/$B$32 -> 1.5167983 | G48: =(SUMPRODUCT($B$10:$J$10,(1+$B$48)^-($B$11:$J$11))+$J$10*(1+G$43)/($B$48-G$43)/(1+$B$48)^9+$B$31)/$B$32 -> 1.5824262
A50: SENSITIVITY — VALUE PER SHARE: WACC × EXIT EV/EBITDA MULTIPLE
B51: WACC \ x | C51: 10 | D51: 12.5 | E51: 15 | F51: 17.5 | G51: 20
B52: 0.12 | C52: =(SUMPRODUCT($B$10:$J$10,(1+$B$52)^-($B$11:$J$11))+C$51*Model_3S!$L$20/(1+$B$52)^9+$B$31)/$B$32 -> 5.532927 | D52: =(SUMPRODUCT($B$10:$J$10,(1+$B$52)^-($B$11:$J$11))+D$51*Model_3S!$L$20/(1+$B$52)^9+$B$31)/$B$32 -> 6.9574064 | E52: =(SUMPRODUCT($B$10:$J$10,(1+$B$52)^-($B$11:$J$11))+E$51*Model_3S!$L$20/(1+$B$52)^9+$B$31)/$B$32 -> 8.3818857 | F52: =(SUMPRODUCT($B$10:$J$10,(1+$B$52)^-($B$11:$J$11))+F$51*Model_3S!$L$20/(1+$B$52)^9+$B$31)/$B$32 -> 9.806365 | G52: =(SUMPRODUCT($B$10:$J$10,(1+$B$52)^-($B$11:$J$11))+G$51*Model_3S!$L$20/(1+$B$52)^9+$B$31)/$B$32 -> 11.230844
B53: 0.13 | C53: =(SUMPRODUCT($B$10:$J$10,(1+$B$53)^-($B$11:$J$11))+C$51*Model_3S!$L$20/(1+$B$53)^9+$B$31)/$B$32 -> 5.1809738 | D53: =(SUMPRODUCT($B$10:$J$10,(1+$B$53)^-($B$11:$J$11))+D$51*Model_3S!$L$20/(1+$B$53)^9+$B$31)/$B$32 -> 6.4959333 | E53: =(SUMPRODUCT($B$10:$J$10,(1+$B$53)^-($B$11:$J$11))+E$51*Model_3S!$L$20/(1+$B$53)^9+$B$31)/$B$32 -> 7.8108927 | F53: =(SUMPRODUCT($B$10:$J$10,(1+$B$53)^-($B$11:$J$11))+F$51*Model_3S!$L$20/(1+$B$53)^9+$B$31)/$B$32 -> 9.1258522 | G53: =(SUMPRODUCT($B$10:$J$10,(1+$B$53)^-($B$11:$J$11))+G$51*Model_3S!$L$20/(1+$B$53)^9+$B$31)/$B$32 -> 10.440812
B54: 0.14 | C54: =(SUMPRODUCT($B$10:$J$10,(1+$B$54)^-($B$11:$J$11))+C$51*Model_3S!$L$20/(1+$B$54)^9+$B$31)/$B$32 -> 4.8633953 | D54: =(SUMPRODUCT($B$10:$J$10,(1+$B$54)^-($B$11:$J$11))+D$51*Model_3S!$L$20/(1+$B$54)^9+$B$31)/$B$32 -> 6.0781111 | E54: =(SUMPRODUCT($B$10:$J$10,(1+$B$54)^-($B$11:$J$11))+E$51*Model_3S!$L$20/(1+$B$54)^9+$B$31)/$B$32 -> 7.292827 | F54: =(SUMPRODUCT($B$10:$J$10,(1+$B$54)^-($B$11:$J$11))+F$51*Model_3S!$L$20/(1+$B$54)^9+$B$31)/$B$32 -> 8.5075428 | G54: =(SUMPRODUCT($B$10:$J$10,(1+$B$54)^-($B$11:$J$11))+G$51*Model_3S!$L$20/(1+$B$54)^9+$B$31)/$B$32 -> 9.7222586
B55: 0.15 | C55: =(SUMPRODUCT($B$10:$J$10,(1+$B$55)^-($B$11:$J$11))+C$51*Model_3S!$L$20/(1+$B$55)^9+$B$31)/$B$32 -> 4.5768574 | D55: =(SUMPRODUCT($B$10:$J$10,(1+$B$55)^-($B$11:$J$11))+D$51*Model_3S!$L$20/(1+$B$55)^9+$B$31)/$B$32 -> 5.6997488 | E55: =(SUMPRODUCT($B$10:$J$10,(1+$B$55)^-($B$11:$J$11))+E$51*Model_3S!$L$20/(1+$B$55)^9+$B$31)/$B$32 -> 6.8226403 | F55: =(SUMPRODUCT($B$10:$J$10,(1+$B$55)^-($B$11:$J$11))+F$51*Model_3S!$L$20/(1+$B$55)^9+$B$31)/$B$32 -> 7.9455318 | G55: =(SUMPRODUCT($B$10:$J$10,(1+$B$55)^-($B$11:$J$11))+G$51*Model_3S!$L$20/(1+$B$55)^9+$B$31)/$B$32 -> 9.0684233
B56: 0.16 | C56: =(SUMPRODUCT($B$10:$J$10,(1+$B$56)^-($B$11:$J$11))+C$51*Model_3S!$L$20/(1+$B$56)^9+$B$31)/$B$32 -> 4.3183665 | D56: =(SUMPRODUCT($B$10:$J$10,(1+$B$56)^-($B$11:$J$11))+D$51*Model_3S!$L$20/(1+$B$56)^9+$B$31)/$B$32 -> 5.3570816 | E56: =(SUMPRODUCT($B$10:$J$10,(1+$B$56)^-($B$11:$J$11))+E$51*Model_3S!$L$20/(1+$B$56)^9+$B$31)/$B$32 -> 6.3957967 | F56: =(SUMPRODUCT($B$10:$J$10,(1+$B$56)^-($B$11:$J$11))+F$51*Model_3S!$L$20/(1+$B$56)^9+$B$31)/$B$32 -> 7.4345118 | G56: =(SUMPRODUCT($B$10:$J$10,(1+$B$56)^-($B$11:$J$11))+G$51*Model_3S!$L$20/(1+$B$56)^9+$B$31)/$B$32 -> 8.4732269
A58: SENSITIVITY — VALUE PER SHARE: FY2027 GROWTH × TERMINAL GROSS MARGIN (compact approximation, exit-multiple TV)
A59: Rev35 ≈ FY26E rev × (1+avg(g1, FY35 g))^9; EBITDA35 = Rev35 × (GM − variable opex) − fixed opex FY35; interim-FCF PV scaled by revenue ratio. Exact at base point.
B60: FY27 g \ GM | C60: 0.15 | D60: 0.22 | E60: 0.3 | F60: 0.35 | G60: 0.4
B61: 0.15 | C61: =($B$15*(Model_3S!$C$15*(1+($B$61+Assumptions!$E$13)/2)^9)/Model_3S!$L$15+$B$25*((Model_3S!$C$15*(1+($B$61+Assumptions!$E$13)/2)^9)*(C$60-Assumptions!$F$18)+Model_3S!$L$18)/(1+$B$16)^9+$B$31)/$B$32 -> 0.94789868 | D61: =($B$15*(Model_3S!$C$15*(1+($B$61+Assumptions!$E$13)/2)^9)/Model_3S!$L$15+$B$25*((Model_3S!$C$15*(1+($B$61+Assumptions!$E$13)/2)^9)*(D$60-Assumptions!$F$18)+Model_3S!$L$18)/(1+$B$16)^9+$B$31)/$B$32 -> 1.6836133 | E61: =($B$15*(Model_3S!$C$15*(1+($B$61+Assumptions!$E$13)/2)^9)/Model_3S!$L$15+$B$25*((Model_3S!$C$15*(1+($B$61+Assumptions!$E$13)/2)^9)*(E$60-Assumptions!$F$18)+Model_3S!$L$18)/(1+$B$16)^9+$B$31)/$B$32 -> 2.52443 | F61: =($B$15*(Model_3S!$C$15*(1+($B$61+Assumptions!$E$13)/2)^9)/Model_3S!$L$15+$B$25*((Model_3S!$C$15*(1+($B$61+Assumptions!$E$13)/2)^9)*(F$60-Assumptions!$F$18)+Model_3S!$L$18)/(1+$B$16)^9+$B$31)/$B$32 -> 3.0499404 | G61: =($B$15*(Model_3S!$C$15*(1+($B$61+Assumptions!$E$13)/2)^9)/Model_3S!$L$15+$B$25*((Model_3S!$C$15*(1+($B$61+Assumptions!$E$13)/2)^9)*(G$60-Assumptions!$F$18)+Model_3S!$L$18)/(1+$B$16)^9+$B$31)/$B$32 -> 3.5754508
B62: 0.35 | C62: =($B$15*(Model_3S!$C$15*(1+($B$62+Assumptions!$E$13)/2)^9)/Model_3S!$L$15+$B$25*((Model_3S!$C$15*(1+($B$62+Assumptions!$E$13)/2)^9)*(C$60-Assumptions!$F$18)+Model_3S!$L$18)/(1+$B$16)^9+$B$31)/$B$32 -> 0.99941593 | D62: =($B$15*(Model_3S!$C$15*(1+($B$62+Assumptions!$E$13)/2)^9)/Model_3S!$L$15+$B$25*((Model_3S!$C$15*(1+($B$62+Assumptions!$E$13)/2)^9)*(D$60-Assumptions!$F$18)+Model_3S!$L$18)/(1+$B$16)^9+$B$31)/$B$32 -> 2.5114735 | E62: =($B$15*(Model_3S!$C$15*(1+($B$62+Assumptions!$E$13)/2)^9)/Model_3S!$L$15+$B$25*((Model_3S!$C$15*(1+($B$62+Assumptions!$E$13)/2)^9)*(E$60-Assumptions!$F$18)+Model_3S!$L$18)/(1+$B$16)^9+$B$31)/$B$32 -> 4.2395394 | F62: =($B$15*(Model_3S!$C$15*(1+($B$62+Assumptions!$E$13)/2)^9)/Model_3S!$L$15+$B$25*((Model_3S!$C$15*(1+($B$62+Assumptions!$E$13)/2)^9)*(F$60-Assumptions!$F$18)+Model_3S!$L$18)/(1+$B$16)^9+$B$31)/$B$32 -> 5.3195805 | G62: =($B$15*(Model_3S!$C$15*(1+($B$62+Assumptions!$E$13)/2)^9)/Model_3S!$L$15+$B$25*((Model_3S!$C$15*(1+($B$62+Assumptions!$E$13)/2)^9)*(G$60-Assumptions!$F$18)+Model_3S!$L$18)/(1+$B$16)^9+$B$31)/$B$32 -> 6.3996216
B63: 0.55 | C63: =($B$15*(Model_3S!$C$15*(1+($B$63+Assumptions!$E$13)/2)^9)/Model_3S!$L$15+$B$25*((Model_3S!$C$15*(1+($B$63+Assumptions!$E$13)/2)^9)*(C$60-Assumptions!$F$18)+Model_3S!$L$18)/(1+$B$16)^9+$B$31)/$B$32 -> 1.0945697 | D63: =($B$15*(Model_3S!$C$15*(1+($B$63+Assumptions!$E$13)/2)^9)/Model_3S!$L$15+$B$25*((Model_3S!$C$15*(1+($B$63+Assumptions!$E$13)/2)^9)*(D$60-Assumptions!$F$18)+Model_3S!$L$18)/(1+$B$16)^9+$B$31)/$B$32 -> 4.0405544 | E63: =($B$15*(Model_3S!$C$15*(1+($B$63+Assumptions!$E$13)/2)^9)/Model_3S!$L$15+$B$25*((Model_3S!$C$15*(1+($B$63+Assumptions!$E$13)/2)^9)*(E$60-Assumptions!$F$18)+Model_3S!$L$18)/(1+$B$16)^9+$B$31)/$B$32 -> 7.4073941 | F63: =($B$15*(Model_3S!$C$15*(1+($B$63+Assumptions!$E$13)/2)^9)/Model_3S!$L$15+$B$25*((Model_3S!$C$15*(1+($B$63+Assumptions!$E$13)/2)^9)*(F$60-Assumptions!$F$18)+Model_3S!$L$18)/(1+$B$16)^9+$B$31)/$B$32 -> 9.5116688 | G63: =($B$15*(Model_3S!$C$15*(1+($B$63+Assumptions!$E$13)/2)^9)/Model_3S!$L$15+$B$25*((Model_3S!$C$15*(1+($B$63+Assumptions!$E$13)/2)^9)*(G$60-Assumptions!$F$18)+Model_3S!$L$18)/(1+$B$16)^9+$B$31)/$B$32 -> 11.615944
B64: 0.7 | C64: =($B$15*(Model_3S!$C$15*(1+($B$64+Assumptions!$E$13)/2)^9)/Model_3S!$L$15+$B$25*((Model_3S!$C$15*(1+($B$64+Assumptions!$E$13)/2)^9)*(C$60-Assumptions!$F$18)+Model_3S!$L$18)/(1+$B$16)^9+$B$31)/$B$32 -> 1.2117613 | D64: =($B$15*(Model_3S!$C$15*(1+($B$64+Assumptions!$E$13)/2)^9)/Model_3S!$L$15+$B$25*((Model_3S!$C$15*(1+($B$64+Assumptions!$E$13)/2)^9)*(D$60-Assumptions!$F$18)+Model_3S!$L$18)/(1+$B$16)^9+$B$31)/$B$32 -> 5.9237728 | E64: =($B$15*(Model_3S!$C$15*(1+($B$64+Assumptions!$E$13)/2)^9)/Model_3S!$L$15+$B$25*((Model_3S!$C$15*(1+($B$64+Assumptions!$E$13)/2)^9)*(E$60-Assumptions!$F$18)+Model_3S!$L$18)/(1+$B$16)^9+$B$31)/$B$32 -> 11.308929 | F64: =($B$15*(Model_3S!$C$15*(1+($B$64+Assumptions!$E$13)/2)^9)/Model_3S!$L$15+$B$25*((Model_3S!$C$15*(1+($B$64+Assumptions!$E$13)/2)^9)*(F$60-Assumptions!$F$18)+Model_3S!$L$18)/(1+$B$16)^9+$B$31)/$B$32 -> 14.674651 | G64: =($B$15*(Model_3S!$C$15*(1+($B$64+Assumptions!$E$13)/2)^9)/Model_3S!$L$15+$B$25*((Model_3S!$C$15*(1+($B$64+Assumptions!$E$13)/2)^9)*(G$60-Assumptions!$F$18)+Model_3S!$L$18)/(1+$B$16)^9+$B$31)/$B$32 -> 18.040374
B65: 0.85 | C65: =($B$15*(Model_3S!$C$15*(1+($B$65+Assumptions!$E$13)/2)^9)/Model_3S!$L$15+$B$25*((Model_3S!$C$15*(1+($B$65+Assumptions!$E$13)/2)^9)*(C$60-Assumptions!$F$18)+Model_3S!$L$18)/(1+$B$16)^9+$B$31)/$B$32 -> 1.3876876 | D65: =($B$15*(Model_3S!$C$15*(1+($B$65+Assumptions!$E$13)/2)^9)/Model_3S!$L$15+$B$25*((Model_3S!$C$15*(1+($B$65+Assumptions!$E$13)/2)^9)*(D$60-Assumptions!$F$18)+Model_3S!$L$18)/(1+$B$16)^9+$B$31)/$B$32 -> 8.7508342 | E65: =($B$15*(Model_3S!$C$15*(1+($B$65+Assumptions!$E$13)/2)^9)/Model_3S!$L$15+$B$25*((Model_3S!$C$15*(1+($B$65+Assumptions!$E$13)/2)^9)*(E$60-Assumptions!$F$18)+Model_3S!$L$18)/(1+$B$16)^9+$B$31)/$B$32 -> 17.165859 | F65: =($B$15*(Model_3S!$C$15*(1+($B$65+Assumptions!$E$13)/2)^9)/Model_3S!$L$15+$B$25*((Model_3S!$C$15*(1+($B$65+Assumptions!$E$13)/2)^9)*(F$60-Assumptions!$F$18)+Model_3S!$L$18)/(1+$B$16)^9+$B$31)/$B$32 -> 22.425249 | G65: =($B$15*(Model_3S!$C$15*(1+($B$65+Assumptions!$E$13)/2)^9)/Model_3S!$L$15+$B$25*((Model_3S!$C$15*(1+($B$65+Assumptions!$E$13)/2)^9)*(G$60-Assumptions!$F$18)+Model_3S!$L$18)/(1+$B$16)^9+$B$31)/$B$32 -> 27.68464

Sheet Comps
A1: PEER BENCHMARKS — SMR / ADVANCED NUCLEAR (July 2026; conventional multiples don't exist pre-revenue)
A4: Company | B4: Ticker | C4: Mkt cap ($B) | D4: Pipeline (GWe) e | E4: EV / pipeline GW ($B) e | F4: Note
A5: Oklo | B5: OKLO | C5: 8 | D5: 14 | E5: =(C5-IF(B5="XE",2,0.5))/D5 -> 0.53571429 | F5: Aurora fast reactors; pre-revenue; mkt cap per companiesmarketcap 7/2026
A6: NuScale Power | B6: SMR | C6: 3.1 | D6: 6 | E6: =(C6-IF(B6="XE",2,0.5))/D6 -> 0.43333333 | F6: Only NRC-certified design; ~$38mm LTM revenue
A7: X-Energy (self) | B7: XE | C7: 5.7 | D7: 11.5 | E7: =(C7-IF(B7="XE",2,0.5))/D7 -> 0.32173913 | F7: ~406mm shares × $14.02; ~$2.0B net cash
A9: EV = mkt cap − est. net cash (XE ~$2.0B; peers ~$0.5B each, e). Pipeline GWe are company-disclosed targets, not contracted backlog — treat as soft.
A11: IMPLIED VALUE PER SHARE
A12: Method | B12: Low | C12: High | D12: Metric | E12: $/sh low | F12: $/sh high
A13: EV per pipeline GW ($B/GW) × 11.5 GWe | B13: 0.35 | C13: 0.7 | D13: 11.5 | E13: =(B13*D13*1000+DCF!$B$31)/Assumptions!$B$39 -> 14.261522 | F13: =(C13*D13*1000+DCF!$B$31)/Assumptions!$B$39 -> 24.175315
A14: EV / FY2030E revenue (×), discounted 4 yrs @ WACC | B14: 4 | C14: 8 | D14: =Model_3S!G15 -> 894.74537 | E14: =(B14*D14/(1+WACC!$B$20)^4+DCF!$B$31)/Assumptions!$B$39 -> 9.5579037 | F14: =(C14*D14/(1+WACC!$B$20)^4+DCF!$B$31)/Assumptions!$B$39 -> 14.768078
A16: Band spans NuScale-like (~$0.4B/GW) to Oklo-like (~$0.55-0.7B/GW) per-pipeline-GW valuations. Both methods are rough by nature — the market prices these stocks on narrative, funding and milestones.

Sheet Precedents
A1: PRECEDENT TRANSACTIONS — NUCLEAR TECHNOLOGY (limited applicability to a pre-commercial SMR developer)
A4: Date | B4: Acquirer | C4: Target | D4: EV ($mm) | E4: Basis | F4: Note
A5: Oct-2022 | B5: Cameco / Brookfield | C5: Westinghouse (49%/51%) | D5: 7875 | E5: ~10x EBITDA e | F5: Mature nuclear services/fuel franchise
A6: Jan-2018 | B6: Brookfield | C6: Westinghouse (from Toshiba bankruptcy) | D6: 4600 | E6: ~8x EBITDA e | F6: Distressed
A7: 2021-24 | B7: Various SPACs | C7: Oklo, NuScale, TerraPower (private rounds) | E7: $1-4B pre-revenue e | F7: Financing marks, not M&A
A8: Nov-2023 | B8: (failed) Ares SPAC | C8: X-Energy itself | D8: 1800 | E8: pre-revenue e | F8: Terminated SPAC valued XE ~$1.8B in 2023; IPO 2026 at ~$8B
A10: There is no true M&A market for SMR developers yet — control transactions have only happened for mature nuclear franchises (Westinghouse) or as financing events. The applied range below borrows the comps' EV-per-pipeline-GW framework at an M&A (no-hype) discount.
A12: APPLIED RANGE
B13: Low | C13: High
A14: EV per pipeline GW ($B/GW) — strategic acquirer | B14: 0.25 | C14: 0.55
A15: Implied EV ($mm, × 11.5 GWe) | B15: =B14*Comps!$D$13*1000 -> 2875 | C15: =C14*Comps!$D$13*1000 -> 6325
A16: Implied value per share | B16: =(B15+DCF!$B$31)/Assumptions!$B$39 -> 11.42901 | C16: =(C15+DCF!$B$31)/Assumptions!$B$39 -> 19.926547

Sheet LBO
A1: GROWTH TAKE-PRIVATE ANALYSIS — 5-YEAR HOLD (ENTRY END-FY2026, EXIT END-FY2031) ($mm)
A2: A conventional LBO is impossible: EBITDA is negative, so debt capacity is zero. This is an ALL-EQUITY take-private (growth buyout): the sponsor buys the equity, inherits ~$2B cash, funds the remaining burn, and exits on an EV/Revenue multiple.
A4: ENTRY
A5: Entry premium to current price | B5: 0.3
A6: Entry price per share | B6: =Assumptions!B46*(1+B5) -> 18.226
A7: Diluted shares (mm) | B7: =Assumptions!B39 -> 406
A8: Equity purchase price | B8: =B6*B7 -> 7399.756
A9: Net cash acquired (FY2026E year-end) | B9: =DCF!B31 -> 1765.1781
A10: Debt capacity (EBITDA-based) | B10: =4.5*MAX(0,Model_3S!C20) -> 0 | C10: 4.5x leverage × max(0, FY26E EBITDA) — zero while EBITDA is negative
A12: HOLD-PERIOD FUNDING (FY2027–FY2031)
A13: Cumulative negative unlevered FCF (burn) | B13: =-SUMIF(DCF!B10:F10,"<0") -> 2242.1381
A14: Funded by acquired cash | B14: =MIN(B9,B13) -> 1765.1781
A15: Additional sponsor funding required | B15: =MAX(0,B13-B9) -> 476.96002
A16: Residual cash at exit (if burn < acquired cash) | B16: =MAX(0,B9-B13)+SUMIF(DCF!B10:F10,">0") -> 0
A17: Total sponsor commitment | B17: =B8+B15 -> 7876.716
A19: EXIT & RETURNS
A20: FY2031E revenue | B20: =Model_3S!H15 -> 1252.6435
A21: Exit EV / Revenue multiple | B21: 5 | C21: SMR-sector scale-up multiple; sensitive input — flex it
A22: Exit enterprise value | B22: =B20*B21 -> 6263.2176
A23: Plus: residual cash | B23: =B16 -> 0
A24: Exit equity value | B24: =B22+B23 -> 6263.2176
A25: MOIC (on total commitment) | B25: =B24/B17 -> 0.79515595
A26: IRR (5-yr, commitment treated as upfront — conservative) | B26: =(B25)^(1/5)-1 -> -0.044808471
A28: MAXIMUM ENTRY PRICE AT TARGET IRR THRESHOLDS
A29: Target IRR | B29: Max total commitment | C29: Max equity purchase | D29: Implied price/share | E29: Prem/(disc) to market
A30: 0.15 | B30: =$B$24/(1+A30)^5 -> 3113.9261 | C30: =B30-$B$15 -> 2636.9661 | D30: =C30/$B$7 -> 6.4949903 | E30: =D30/Assumptions!$B$46-1 -> -0.53673393
A31: 0.2 | B31: =$B$24/(1+A31)^5 -> 2517.0467 | C31: =B31-$B$15 -> 2040.0867 | D31: =C31/$B$7 -> 5.024844 | E31: =D31/Assumptions!$B$46-1 -> -0.64159458
A32: 0.25 | B32: =$B$24/(1+A32)^5 -> 2052.3311 | C32: =B32-$B$15 -> 1575.3711 | D32: =C32/$B$7 -> 3.8802244 | E32: =D32/Assumptions!$B$46-1 -> -0.72323649
A33: 0.3 | B33: =$B$24/(1+A33)^5 -> 1686.8666 | C33: =B33-$B$15 -> 1209.9066 | D33: =C33/$B$7 -> 2.9800655 | E33: =D33/Assumptions!$B$46-1 -> -0.78744184
A35: Exit equity held constant across the table (burn and exit revenue don't depend on entry price). Read: the price a financial buyer could pay at each hurdle, exiting at the assumed EV/Revenue multiple.

Sheet Monte_Carlo
A1: MONTE CARLO SIMULATION — 500 LIVE TRIALS (press F9 / recalc to refresh)
A2: Wide σ by design — pre-commercial outcomes are close to binary. EBITDA35 = Rev35 × (GM − var. opex) − fixed opex; PV of interim burn scales with revenue.
A4: Distribution parameters — Normal(mean, σ)
A5: Variable | B5: Mean (linked) | C5: σ (input)
A6: FY2027 revenue growth | B6: =Assumptions!E12 -> 0.55 | C6: 0.1
A7: Terminal gross margin (FY35) | B7: =Assumptions!F17 -> 0.3 | C7: 0.05
A8: WACC | B8: =WACC!B20 -> 0.1405 | C8: 0.015
A9: Exit EV/EBITDA multiple | B9: =Assumptions!B45 -> 15 | C9: 3
A11: Calibration statics (linked)
A12: Base FY2035 Adj. EBITDA | B12: =Model_3S!L20 -> 641.5114
A13: Base PV of explicit FCF (negative = burn) | B13: =DCF!B15 -> -1761.6736
A14: Net cash FY2026E | B14: =DCF!B31 -> 1765.1781
A15: Diluted shares (mm) | B15: =Assumptions!B39 -> 406
A16: Current share price | B16: =Assumptions!B46 -> 14.02
A17: FY2035 growth (selected) | B17: =Assumptions!E13 -> 0.25
A18: FY2026E revenue | B18: =Model_3S!C15 -> 180
A19: Base FY2035 revenue | B19: =Model_3S!L15 -> 3639.4616
A20: FY2035 fixed opex (negative) | B20: =Model_3S!L18 -> -304.7486
A22: Simulation results ($/share)
A23: Mean | B23: =AVERAGE($K$41:$K$540) -> 7.7473543
A24: Median | B24: =MEDIAN($K$41:$K$540) -> 6.9386816
A25: Standard deviation | B25: =STDEV($K$41:$K$540) -> 3.7844602
A26: 5th percentile | B26: =PERCENTILE($K$41:$K$540,0.05) -> 3.1557385
A27: 25th percentile | B27: =PERCENTILE($K$41:$K$540,0.25) -> 5.2382988
A28: 75th percentile | B28: =PERCENTILE($K$41:$K$540,0.75) -> 9.359192
A29: 95th percentile | B29: =PERCENTILE($K$41:$K$540,0.95) -> 15.700471
A30: P(value > current price) | B30: =COUNTIF($K$41:$K$540,">"&B16)/500 -> 0.082
A32: Scenario probability-weighted value (compact DCF per scenario)
A33: Scenario | B33: Probability | C33: Value / share
A34: Base | B34: =Assumptions!B8 -> 0.45 | C34: =($B$13*($B$18*(1+(Assumptions!B12+Assumptions!B13)/2)^9)/$B$19+Assumptions!$B$45*(($B$18*(1+(Assumptions!B12+Assumptions!B13)/2)^9)*(Assumptions!C17-Assumptions!C18)-Assumptions!$B$29*(1+Assumptions!B25)^9)/(1+$B$8)^9+$B$14)/$B$15 -> 7.4073941
A35: Bull | B35: =Assumptions!C8 -> 0.25 | C35: =($B$13*($B$18*(1+(Assumptions!C12+Assumptions!C13)/2)^9)/$B$19+Assumptions!$B$45*(($B$18*(1+(Assumptions!C12+Assumptions!C13)/2)^9)*(Assumptions!D17-Assumptions!D18)-Assumptions!$B$29*(1+Assumptions!C25)^9)/(1+$B$8)^9+$B$14)/$B$15 -> 17.767011
A36: Bear | B36: =Assumptions!D8 -> 0.3 | C36: =($B$13*($B$18*(1+(Assumptions!D12+Assumptions!D13)/2)^9)/$B$19+Assumptions!$B$45*(($B$18*(1+(Assumptions!D12+Assumptions!D13)/2)^9)*(Assumptions!E17-Assumptions!E18)-Assumptions!$B$29*(1+Assumptions!D25)^9)/(1+$B$8)^9+$B$14)/$B$15 -> 2.0939819
A37: Probability-weighted value | C37: =SUMPRODUCT(B34:B36,C34:C36) -> 8.4032747
A38: Bear value ≈ net cash less remaining burn — the downside anchor. Compact approximation, most accurate with switch = 1/Base.
A39: TRIALS
A40: # | B40: g FY27 | C40: Term GM | D40: WACC | E40: Exit x | F40: Rev FY35 | G40: EBITDA FY35 | H40: PV(TV) | I40: PV(FCF) | J40: Equity | K40: $ / share | N40: Bin ($/sh) | O40: low | P40: high | Q40: Count
A41: 1 | B41: =NORMINV(RAND(),$B$6,$C$6) -> 0.46466123 | C41: =MAX(0.05,NORMINV(RAND(),$B$7,$C$7)) -> 0.33950986 | D41: =MAX(0.08,NORMINV(RAND(),$B$8,$C$8)) -> 0.14510836 | E41: =MAX(5,NORMINV(RAND(),$B$9,$C$9)) -> 16.320023 | F41: =$B$18*(1+(B41+$B$17)/2)^9 -> 2814.7725 | G41: =F41*(C41-Assumptions!$F$18)+$B$20 -> 538.30352 | H41: =E41*G41/(1+D41)^9 -> 2594.9484 | I41: =$B$13*F41/$B$19*((1+$B$8)/(1+D41))^4.5 -> -1337.9836 | J41: =H41+I41+$B$14 -> 3022.1429 | K41: =J41/$B$15 -> 7.4437017 | N41: <-2.5 | O41: -5 | P41: -2.5 | Q41: =COUNTIF($K$41:$K$540,"<"&P41) -> 0
A42: 2 | B42: =NORMINV(RAND(),$B$6,$C$6) -> 0.3707849 | C42: =MAX(0.05,NORMINV(RAND(),$B$7,$C$7)) -> 0.24256936 | D42: =MAX(0.08,NORMINV(RAND(),$B$8,$C$8)) -> 0.15115035 | E42: =MAX(5,NORMINV(RAND(),$B$9,$C$9)) -> 8.0186719 | F42: =$B$18*(1+(B42+$B$17)/2)^9 -> 2050.6188 | G42: =F42*(C42-Assumptions!$F$18)+$B$20 -> 110.64394 | H42: =E42*G42/(1+D42)^9 -> 249.94338 | I42: =$B$13*F42/$B$19*((1+$B$8)/(1+D42))^4.5 -> -951.93617 | J42: =H42+I42+$B$14 -> 1063.1853 | K42: =J42/$B$15 -> 2.618683 | N42: -2.5-0 | O42: -2.5 | P42: 0 | Q42: =COUNTIFS($K$41:$K$540,">="&O42,$K$41:$K$540,"<"&P42) -> 0
A43: 3 | B43: =NORMINV(RAND(),$B$6,$C$6) -> 0.47200581 | C43: =MAX(0.05,NORMINV(RAND(),$B$7,$C$7)) -> 0.23195564 | D43: =MAX(0.08,NORMINV(RAND(),$B$8,$C$8)) -> 0.13486825 | E43: =MAX(5,NORMINV(RAND(),$B$9,$C$9)) -> 14.253997 | F43: =$B$18*(1+(B43+$B$17)/2)^9 -> 2884.0579 | G43: =F43*(C43-Assumptions!$F$18)+$B$20 -> 248.86256 | H43: =E43*G43/(1+D43)^9 -> 1136.0233 | I43: =$B$13*F43/$B$19*((1+$B$8)/(1+D43))^4.5 -> -1427.4686 | J43: =H43+I43+$B$14 -> 1473.7327 | K43: =J43/$B$15 -> 3.6298836 | N43: 0-2.5 | O43: 0 | P43: 2.5 | Q43: =COUNTIFS($K$41:$K$540,">="&O43,$K$41:$K$540,"<"&P43) -> 10
A44: 4 | B44: =NORMINV(RAND(),$B$6,$C$6) -> 0.58110099 | C44: =MAX(0.05,NORMINV(RAND(),$B$7,$C$7)) -> 0.29576771 | D44: =MAX(0.08,NORMINV(RAND(),$B$8,$C$8)) -> 0.14011159 | E44: =MAX(5,NORMINV(RAND(),$B$9,$C$9)) -> 15.387898 | F44: =$B$18*(1+(B44+$B$17)/2)^9 -> 4107.7197 | G44: =F44*(C44-Assumptions!$F$18)+$B$20 -> 745.87343 | H44: =E44*G44/(1+D44)^9 -> 3526.2914 | I44: =$B$13*F44/$B$19*((1+$B$8)/(1+D44))^4.5 -> -1991.383 | J44: =H44+I44+$B$14 -> 3300.0865 | K44: =J44/$B$15 -> 8.1282919 | N44: 2.5-5 | O44: 2.5 | P44: 5 | Q44: =COUNTIFS($K$41:$K$540,">="&O44,$K$41:$K$540,"<"&P44) -> 100
A45: 5 | B45: =NORMINV(RAND(),$B$6,$C$6) -> 0.52678363 | C45: =MAX(0.05,NORMINV(RAND(),$B$7,$C$7)) -> 0.36357807 | D45: =MAX(0.08,NORMINV(RAND(),$B$8,$C$8)) -> 0.14161982 | E45: =MAX(5,NORMINV(RAND(),$B$9,$C$9)) -> 21.216927 | F45: =$B$18*(1+(B45+$B$17)/2)^9 -> 3450.4911 | G45: =F45*(C45-Assumptions!$F$18)+$B$20 -> 811.75466 | H45: =E45*G45/(1+D45)^9 -> 5228.9412 | I45: =$B$13*F45/$B$19*((1+$B$8)/(1+D45))^4.5 -> -1662.843 | J45: =H45+I45+$B$14 -> 5331.2763 | K45: =J45/$B$15 -> 13.131222 | N45: 5-7.5 | O45: 5 | P45: 7.5 | Q45: =COUNTIFS($K$41:$K$540,">="&O45,$K$41:$K$540,"<"&P45) -> 169
A46: 6 | B46: =NORMINV(RAND(),$B$6,$C$6) -> 0.69058309 | C46: =MAX(0.05,NORMINV(RAND(),$B$7,$C$7)) -> 0.30164887 | D46: =MAX(0.08,NORMINV(RAND(),$B$8,$C$8)) -> 0.16051056 | E46: =MAX(5,NORMINV(RAND(),$B$9,$C$9)) -> 11.140656 | F46: =$B$18*(1+(B46+$B$17)/2)^9 -> 5779.678 | G46: =F46*(C46-Assumptions!$F$18)+$B$20 -> 1207.4976 | H46: =E46*G46/(1+D46)^9 -> 3523.3447 | I46: =$B$13*F46/$B$19*((1+$B$8)/(1+D46))^4.5 -> -2587.0201 | J46: =H46+I46+$B$14 -> 2701.5027 | K46: =J46/$B$15 -> 6.6539475 | N46: 7.5-10 | O46: 7.5 | P46: 10 | Q46: =COUNTIFS($K$41:$K$540,">="&O46,$K$41:$K$540,"<"&P46) -> 115
A47: 7 | B47: =NORMINV(RAND(),$B$6,$C$6) -> 0.54542519 | C47: =MAX(0.05,NORMINV(RAND(),$B$7,$C$7)) -> 0.27941619 | D47: =MAX(0.08,NORMINV(RAND(),$B$8,$C$8)) -> 0.16236105 | E47: =MAX(5,NORMINV(RAND(),$B$9,$C$9)) -> 13.69471 | F47: =$B$18*(1+(B47+$B$17)/2)^9 -> 3664.6577 | G47: =F47*(C47-Assumptions!$F$18)+$B$20 -> 572.62975 | H47: =E47*G47/(1+D47)^9 -> 2024.6843 | I47: =$B$13*F47/$B$19*((1+$B$8)/(1+D47))^4.5 -> -1628.6051 | J47: =H47+I47+$B$14 -> 2161.2572 | K47: =J47/$B$15 -> 5.3232936 | N47: 10-12.5 | O47: 10 | P47: 12.5 | Q47: =COUNTIFS($K$41:$K$540,">="&O47,$K$41:$K$540,"<"&P47) -> 53
A48: 8 | B48: =NORMINV(RAND(),$B$6,$C$6) -> 0.50772759 | C48: =MAX(0.05,NORMINV(RAND(),$B$7,$C$7)) -> 0.26674501 | D48: =MAX(0.08,NORMINV(RAND(),$B$8,$C$8)) -> 0.14690078 | E48: =MAX(5,NORMINV(RAND(),$B$9,$C$9)) -> 18.013605 | F48: =$B$18*(1+(B48+$B$17)/2)^9 -> 3243.1335 | G48: =F48*(C48-Assumptions!$F$18)+$B$20 -> 430.61574 | H48: =E48*G48/(1+D48)^9 -> 2259.2167 | I48: =$B$13*F48/$B$19*((1+$B$8)/(1+D48))^4.5 -> -1530.79 | J48: =H48+I48+$B$14 -> 2493.6048 | K48: =J48/$B$15 -> 6.1418837 | N48: 12.5-15 | O48: 12.5 | P48: 15 | Q48: =COUNTIFS($K$41:$K$540,">="&O48,$K$41:$K$540,"<"&P48) -> 24
A49: 9 | B49: =NORMINV(RAND(),$B$6,$C$6) -> 0.33747122 | C49: =MAX(0.05,NORMINV(RAND(),$B$7,$C$7)) -> 0.33788396 | D49: =MAX(0.08,NORMINV(RAND(),$B$8,$C$8)) -> 0.14051208 | E49: =MAX(5,NORMINV(RAND(),$B$9,$C$9)) -> 18.243179 | F49: =$B$18*(1+(B49+$B$17)/2)^9 -> 1827.6048 | G49: =F49*(C49-Assumptions!$F$18)+$B$20 -> 239.66555 | H49: =E49*G49/(1+D49)^9 -> 1339.0819 | I49: =$B$13*F49/$B$19*((1+$B$8)/(1+D49))^4.5 -> -884.60604 | J49: =H49+I49+$B$14 -> 2219.6539 | K49: =J49/$B$15 -> 5.4671279 | N49: 15-17.5 | O49: 15 | P49: 17.5 | Q49: =COUNTIFS($K$41:$K$540,">="&O49,$K$41:$K$540,"<"&P49) -> 15
A50: 10 | B50: =NORMINV(RAND(),$B$6,$C$6) -> 0.41786176 | C50: =MAX(0.05,NORMINV(RAND(),$B$7,$C$7)) -> 0.23714523 | D50: =MAX(0.08,NORMINV(RAND(),$B$8,$C$8)) -> 0.14107233 | E50: =MAX(5,NORMINV(RAND(),$B$9,$C$9)) -> 13.610017 | F50: =$B$18*(1+(B50+$B$17)/2)^9 -> 2406.9798 | G50: =F50*(C50-Assumptions!$F$18)+$B$20 -> 169.77598 | H50: =E50*G50/(1+D50)^9 -> 704.55735 | I50: =$B$13*F50/$B$19*((1+$B$8)/(1+D50))^4.5 -> -1162.466 | J50: =H50+I50+$B$14 -> 1307.2694 | K50: =J50/$B$15 -> 3.2198754 | N50: 17.5-20 | O50: 17.5 | P50: 20 | Q50: =COUNTIFS($K$41:$K$540,">="&O50,$K$41:$K$540,"<"&P50) -> 8
A51: 11 | B51: =NORMINV(RAND(),$B$6,$C$6) -> 0.37437437 | C51: =MAX(0.05,NORMINV(RAND(),$B$7,$C$7)) -> 0.21501237 | D51: =MAX(0.08,NORMINV(RAND(),$B$8,$C$8)) -> 0.13393952 | E51: =MAX(5,NORMINV(RAND(),$B$9,$C$9)) -> 13.420801 | F51: =$B$18*(1+(B51+$B$17)/2)^9 -> 2076.0348 | G51: =F51*(C51-Assumptions!$F$18)+$B$20 -> 58.583175 | H51: =E51*G51/(1+D51)^9 -> 253.65435 | I51: =$B$13*F51/$B$19*((1+$B$8)/(1+D51))^4.5 -> -1031.329 | J51: =H51+I51+$B$14 -> 987.50344 | K51: =J51/$B$15 -> 2.4322745 | N51: 20-22.5 | O51: 20 | P51: 22.5 | Q51: =COUNTIFS($K$41:$K$540,">="&O51,$K$41:$K$540,"<"&P51) -> 6
A52: 12 | B52: =NORMINV(RAND(),$B$6,$C$6) -> 0.60076465 | C52: =MAX(0.05,NORMINV(RAND(),$B$7,$C$7)) -> 0.28485763 | D52: =MAX(0.08,NORMINV(RAND(),$B$8,$C$8)) -> 0.13326431 | E52: =MAX(5,NORMINV(RAND(),$B$9,$C$9)) -> 21.603744 | F52: =$B$18*(1+(B52+$B$17)/2)^9 -> 4371.745 | G52: =F52*(C52-Assumptions!$F$18)+$B$20 -> 765.70652 | H52: =E52*G52/(1+D52)^9 -> 5365.5032 | I52: =$B$13*F52/$B$19*((1+$B$8)/(1+D52))^4.5 -> -2177.6169 | J52: =H52+I52+$B$14 -> 4953.0644 | K52: =J52/$B$15 -> 12.199666 | N52: 22.5-25 | O52: 22.5 | P52: 25 | Q52: =COUNTIFS($K$41:$K$540,">="&O52,$K$41:$K$540,"<"&P52) -> 0
A53: 13 | B53: =NORMINV(RAND(),$B$6,$C$6) -> 0.55773005 | C53: =MAX(0.05,NORMINV(RAND(),$B$7,$C$7)) -> 0.2940403 | D53: =MAX(0.08,NORMINV(RAND(),$B$8,$C$8)) -> 0.15225307 | E53: =MAX(5,NORMINV(RAND(),$B$9,$C$9)) -> 16.968277 | F53: =$B$18*(1+(B53+$B$17)/2)^9 -> 3812.4196 | G53: =F53*(C53-Assumptions!$F$18)+$B$20 -> 663.7596 | H53: =E53*G53/(1+D53)^9 -> 3145.7029 | I53: =$B$13*F53/$B$19*((1+$B$8)/(1+D53))^4.5 -> -1762.1885 | J53: =H53+I53+$B$14 -> 3148.6925 | K53: =J53/$B$15 -> 7.7554001 | N53: 25-27.5 | O53: 25 | P53: 27.5 | Q53: =COUNTIFS($K$41:$K$540,">="&O53,$K$41:$K$540,"<"&P53) -> 0
... A60: 20 | B60: =NORMINV(RAND(),$B$6,$C$6) -> 0.54390366 | C60: =MAX(0.05,NORMINV(RAND(),$B$7,$C$7)) -> 0.32338574 | D60: =MAX(0.08,NORMINV(RAND(),$B$8,$C$8)) -> 0.11605798 | E60: =MAX(5,NORMINV(RAND(),$B$9,$C$9)) -> 11.48102 | F60: =$B$18*(1+(B60+$B$17)/2)^9 -> 3646.7449 | G60: =F60*(C60-Assumptions!$F$18)+$B$20 -> 728.68692 | H60: =E60*G60/(1+D60)^9 -> 3114.1579 | I60: =$B$13*F60/$B$19*((1+$B$8)/(1+D60))^4.5 -> -1945.9518 | J60: =H60+I60+$B$14 -> 2933.3841 | K60: =J60/$B$15 -> 7.2250841 | N60: 42.5-45 | O60: 42.5 | P60: 45 | Q60: =COUNTIFS($K$41:$K$540,">="&O60,$K$41:$K$540,"<"&P60) -> 0
A61: 21 | B61: =NORMINV(RAND(),$B$6,$C$6) -> 0.65704244 | C61: =MAX(0.05,NORMINV(RAND(),$B$7,$C$7)) -> 0.27626621 | D61: =MAX(0.08,NORMINV(RAND(),$B$8,$C$8)) -> 0.14789668 | E61: =MAX(5,NORMINV(RAND(),$B$9,$C$9)) -> 16.920345 | F61: =$B$18*(1+(B61+$B$17)/2)^9 -> 5212.7259 | G61: =F61*(C61-Assumptions!$F$18)+$B$20 -> 926.84237 | H61: =E61*G61/(1+D61)^9 -> 4531.9999 | I61: =$B$13*F61/$B$19*((1+$B$8)/(1+D61))^4.5 -> -2450.865 | J61: =H61+I61+$B$14 -> 3846.3129 | K61: =J61/$B$15 -> 9.4736771 | N61: 45+ | O61: 45 | P61: 47.5 | Q61: =COUNTIF($K$41:$K$540,">="&O61) -> 0
A62: 22 | B62: =NORMINV(RAND(),$B$6,$C$6) -> 0.40863812 | C62: =MAX(0.05,NORMINV(RAND(),$B$7,$C$7)) -> 0.28988759 | D62: =MAX(0.08,NORMINV(RAND(),$B$8,$C$8)) -> 0.16911311 | E62: =MAX(5,NORMINV(RAND(),$B$9,$C$9)) -> 13.022499 | F62: =$B$18*(1+(B62+$B$17)/2)^9 -> 2333.112 | G62: =F62*(C62-Assumptions!$F$18)+$B$20 -> 278.26713 | H62: =E62*G62/(1+D62)^9 -> 888.07051 | I62: =$B$13*F62/$B$19*((1+$B$8)/(1+D62))^4.5 -> -1010.1789 | J62: =H62+I62+$B$14 -> 1643.0697 | K62: =J62/$B$15 -> 4.0469696
A63: 23 | B63: =NORMINV(RAND(),$B$6,$C$6) -> 0.64314198 | C63: =MAX(0.05,NORMINV(RAND(),$B$7,$C$7)) -> 0.25695256 | D63: =MAX(0.08,NORMINV(RAND(),$B$8,$C$8)) -> 0.13448084 | E63: =MAX(5,NORMINV(RAND(),$B$9,$C$9)) -> 10.584536 | F63: =$B$18*(1+(B63+$B$17)/2)^9 -> 4992.6402 | G63: =F63*(C63-Assumptions!$F$18)+$B$20 -> 778.41749 | H63: =E63*G63/(1+D63)^9 -> 2646.7318 | I63: =$B$13*F63/$B$19*((1+$B$8)/(1+D63))^4.5 -> -2474.9141 | J63: =H63+I63+$B$14 -> 1936.9957 | K63: =J63/$B$15 -> 4.7709255
A64: 24 | B64: =NORMINV(RAND(),$B$6,$C$6) -> 0.6194055 | C64: =MAX(0.05,NORMINV(RAND(),$B$7,$C$7)) -> 0.26733866 | D64: =MAX(0.08,NORMINV(RAND(),$B$8,$C$8)) -> 0.13954645 | E64: =MAX(5,NORMINV(RAND(),$B$9,$C$9)) -> 13.857268 | F64: =$B$18*(1+(B64+$B$17)/2)^9 -> 4635.8555 | G64: =F64*(C64-Assumptions!$F$18)+$B$20 -> 749.16058 | H64: =E64*G64/(1+D64)^9 -> 3203.7914 | I64: =$B$13*F64/$B$19*((1+$B$8)/(1+D64))^4.5 -> -2252.438 | J64: =H64+I64+$B$14 -> 2716.5315 | K64: =J64/$B$15 -> 6.6909644
A65: 25 | B65: =NORMINV(RAND(),$B$6,$C$6) -> 0.47482804 | C65: =MAX(0.05,NORMINV(RAND(),$B$7,$C$7)) -> 0.35702132 | D65: =MAX(0.08,NORMINV(RAND(),$B$8,$C$8)) -> 0.13901511 | E65: =MAX(5,NORMINV(RAND(),$B$9,$C$9)) -> 19.651793 | F65: =$B$18*(1+(B65+$B$17)/2)^9 -> 2911.082 | G65: =F65*(C65-Assumptions!$F$18)+$B$20 -> 618.12646 | H65: =E65*G65/(1+D65)^9 -> 3764.5593 | I65: =$B$13*F65/$B$19*((1+$B$8)/(1+D65))^4.5 -> -1417.3884 | J65: =H65+I65+$B$14 -> 4112.3491 | K65: =J65/$B$15 -> 10.128939
A66: 26 | B66: =NORMINV(RAND(),$B$6,$C$6) -> 0.72376082 | C66: =MAX(0.05,NORMINV(RAND(),$B$7,$C$7)) -> 0.32651763 | D66: =MAX(0.08,NORMINV(RAND(),$B$8,$C$8)) -> 0.12181801 | E66: =MAX(5,NORMINV(RAND(),$B$9,$C$9)) -> 17.484709 | F66: =$B$18*(1+(B66+$B$17)/2)^9 -> 6393.7679 | G66: =F66*(C66-Assumptions!$F$18)+$B$20 -> 1527.1786 | H66: =E66*G66/(1+D66)^9 -> 9489.571 | I66: =$B$13*F66/$B$19*((1+$B$8)/(1+D66))^4.5 -> -3333.674 | J66: =H66+I66+$B$14 -> 7921.0751 | K66: =J66/$B$15 -> 19.510037
A67: 27 | B67: =NORMINV(RAND(),$B$6,$C$6) -> 0.60204701 | C67: =MAX(0.05,NORMINV(RAND(),$B$7,$C$7)) -> 0.26985843 | D67: =MAX(0.08,NORMINV(RAND(),$B$8,$C$8)) -> 0.16788155 | E67: =MAX(5,NORMINV(RAND(),$B$9,$C$9)) -> 8.849861 | F67: =$B$18*(1+(B67+$B$17)/2)^9 -> 4389.4758 | G67: =F67*(C67-Assumptions!$F$18)+$B$20 -> 704.2094 | H67: =E67*G67/(1+D67)^9 -> 1541.8747 | I67: =$B$13*F67/$B$19*((1+$B$8)/(1+D67))^4.5 -> -1909.5682 | J67: =H67+I67+$B$14 -> 1397.4846 | K67: =J67/$B$15 -> 3.4420802
A68: 28 | B68: =NORMINV(RAND(),$B$6,$C$6) -> 0.59534694 | C68: =MAX(0.05,NORMINV(RAND(),$B$7,$C$7)) -> 0.23026552 | D68: =MAX(0.08,NORMINV(RAND(),$B$8,$C$8)) -> 0.12758676 | E68: =MAX(5,NORMINV(RAND(),$B$9,$C$9)) -> 11.554721 | F68: =$B$18*(1+(B68+$B$17)/2)^9 -> 4297.5368 | G68: =F68*(C68-Assumptions!$F$18)+$B$20 -> 512.92445 | H68: =E68*G68/(1+D68)^9 -> 2011.2366 | I68: =$B$13*F68/$B$19*((1+$B$8)/(1+D68))^4.5 -> -2189.5853 | J68: =H68+I68+$B$14 -> 1586.8294 | K68: =J68/$B$15 -> 3.9084468
A69: 29 | B69: =NORMINV(RAND(),$B$6,$C$6) -> 0.5476133 | C69: =MAX(0.05,NORMINV(RAND(),$B$7,$C$7)) -> 0.2548518 | D69: =MAX(0.08,NORMINV(RAND(),$B$8,$C$8)) -> 0.15716958 | E69: =MAX(5,NORMINV(RAND(),$B$9,$C$9)) -> 15.987954 | F69: =$B$18*(1+(B69+$B$17)/2)^9 -> 3690.5552 | G69: =F69*(C69-Assumptions!$F$18)+$B$20 -> 488.17382 | H69: =E69*G69/(1+D69)^9 -> 2097.9459 | I69: =$B$13*F69/$B$19*((1+$B$8)/(1+D69))^4.5 -> -1673.4867 | J69: =H69+I69+$B$14 -> 2189.6372 | K69: =J69/$B$15 -> 5.3931952
A70: 30 | B70: =NORMINV(RAND(),$B$6,$C$6) -> 0.58062245 | C70: =MAX(0.05,NORMINV(RAND(),$B$7,$C$7)) -> 0.32556822 | D70: =MAX(0.08,NORMINV(RAND(),$B$8,$C$8)) -> 0.1487033 | E70: =MAX(5,NORMINV(RAND(),$B$9,$C$9)) -> 13.906762 | F70: =$B$18*(1+(B70+$B$17)/2)^9 -> 4101.475 | G70: =F70*(C70-Assumptions!$F$18)+$B$20 -> 866.5023 | H70: =E70*G70/(1+D70)^9 -> 3460.3892 | I70: =$B$13*F70/$B$19*((1+$B$8)/(1+D70))^4.5 -> -1922.3027 | J70: =H70+I70+$B$14 -> 3303.2646 | K70: =J70/$B$15 -> 8.1361197
A71: 31 | B71: =NORMINV(RAND(),$B$6,$C$6) -> 0.48692136 | C71: =MAX(0.05,NORMINV(RAND(),$B$7,$C$7)) -> 0.29927146 | D71: =MAX(0.08,NORMINV(RAND(),$B$8,$C$8)) -> 0.13617229 | E71: =MAX(5,NORMINV(RAND(),$B$9,$C$9)) -> 17.075095 | F71: =$B$18*(1+(B71+$B$17)/2)^9 -> 3029.4474 | G71: =F71*(C71-Assumptions!$F$18)+$B$20 -> 480.70063 | H71: =E71*G71/(1+D71)^9 -> 2601.5973 | I71: =$B$13*F71/$B$19*((1+$B$8)/(1+D71))^4.5 -> -1491.7006 | J71: =H71+I71+$B$14 -> 2875.0749 | K71: =J71/$B$15 -> 7.0814651
A72: 32 | B72: =NORMINV(RAND(),$B$6,$C$6) -> 0.71062537 | C72: =MAX(0.05,NORMINV(RAND(),$B$7,$C$7)) -> 0.30569151 | D72: =MAX(0.08,NORMINV(RAND(),$B$8,$C$8)) -> 0.13028129 | E72: =MAX(5,NORMINV(RAND(),$B$9,$C$9)) -> 13.785792 | F72: =$B$18*(1+(B72+$B$17)/2)^9 -> 6144.0345 | G72: =F72*(C72-Assumptions!$F$18)+$B$20 -> 1327.6692 | H72: =E72*G72/(1+D72)^9 -> 6079.1486 | I72: =$B$13*F72/$B$19*((1+$B$8)/(1+D72))^4.5 -> -3096.9295 | J72: =H72+I72+$B$14 -> 4747.3971 | K72: =J72/$B$15 -> 11.693096
A73: 33 | B73: =NORMINV(RAND(),$B$6,$C$6) -> 0.59487348 | C73: =MAX(0.05,NORMINV(RAND(),$B$7,$C$7)) -> 0.30423614 | D73: =MAX(0.08,NORMINV(RAND(),$B$8,$C$8)) -> 0.1581295 | E73: =MAX(5,NORMINV(RAND(),$B$9,$C$9)) -> 15.705239 | F73: =$B$18*(1+(B73+$B$17)/2)^9 -> 4291.1052 | G73: =F73*(C73-Assumptions!$F$18)+$B$20 -> 829.11645 | H73: =E73*G73/(1+D73)^9 -> 3474.1291 | I73: =$B$13*F73/$B$19*((1+$B$8)/(1+D73))^4.5 -> -1938.5598 | J73: =H73+I73+$B$14 -> 3300.7474 | K73: =J73/$B$15 -> 8.1299197
... A540: 500 | B540: =NORMINV(RAND(),$B$6,$C$6) -> 0.65788964 | C540: =MAX(0.05,NORMINV(RAND(),$B$7,$C$7)) -> 0.28218337 | D540: =MAX(0.08,NORMINV(RAND(),$B$8,$C$8)) -> 0.12204326 | E540: =MAX(5,NORMINV(RAND(),$B$9,$C$9)) -> 12.870797 | F540: =$B$18*(1+(B540+$B$17)/2)^9 -> 5226.4142 | G540: =F540*(C540-Assumptions!$F$18)+$B$20 -> 961.00201 | H540: =E540*G540/(1+D540)^9 -> 4387.7648 | I540: =$B$13*F540/$B$19*((1+$B$8)/(1+D540))^4.5 -> -2722.5617 | J540: =H540+I540+$B$14 -> 3430.3812 | K540: =J540/$B$15 -> 8.4492149

Sheet Football_Field
A1: FOOTBALL FIELD — VALUATION SUMMARY ($ per share)
A2: =CONCATENATE("Current price: $",TEXT(Assumptions!B46,"0.00")," · Scenario: ",CHOOSE(Assumptions!B4,"BASE","BULL","BEAR")," · Probability-weighted value: $",TEXT(Monte_Carlo!C37,"0.00")) -> Current price: $14.02 · Scenario: BASE · Probability-weighted value: $8.40
A4: Methodology | B4: Low | C4: High | D4: (base) | E4: (span) | F4: Midpoint
A5: Trading range since 4/24/26 IPO (e) | B5: 13.2 | C5: 30.7 | D5: =B5 -> 13.2 | E5: =C5-B5 -> 17.5 | F5: =(B5+C5)/2 -> 21.95
A6: Analyst targets (avg ~$40, n=8) | B6: 28 | C6: 57 | D6: =B6 -> 28 | E6: =C6-B6 -> 29 | F6: =(B6+C6)/2 -> 42.5
A7: DCF — Gordon growth (WACC ±1.5%, g 3.0–4.0%) | B7: =(SUMPRODUCT(DCF!$B$10:$J$10,(1+(WACC!$B$20+0.015))^-DCF!$B$11:$J$11)+DCF!$J$10*(1+0.03)/((WACC!$B$20+0.015)-0.03)/(1+(WACC!$B$20+0.015))^9+DCF!$B$31)/DCF!$B$32 -> 1.4557849 | C7: =(SUMPRODUCT(DCF!$B$10:$J$10,(1+(WACC!$B$20-0.015))^-DCF!$B$11:$J$11)+DCF!$J$10*(1+0.04)/((WACC!$B$20-0.015)-0.04)/(1+(WACC!$B$20-0.015))^9+DCF!$B$31)/DCF!$B$32 -> 2.3751307 | D7: =B7 -> 1.4557849 | E7: =C7-B7 -> 0.91934581 | F7: =(B7+C7)/2 -> 1.9154578
A8: DCF — exit multiple (12.5–17.5x, WACC ±1.5%) | B8: =(SUMPRODUCT(DCF!$B$10:$J$10,(1+(WACC!$B$20+0.015))^-DCF!$B$11:$J$11)+12.5*Model_3S!$L$20/(1+(WACC!$B$20+0.015))^9+DCF!$B$31)/DCF!$B$32 -> 5.5070893 | C8: =(SUMPRODUCT(DCF!$B$10:$J$10,(1+(WACC!$B$20-0.015))^-DCF!$B$11:$J$11)+17.5*Model_3S!$L$20/(1+(WACC!$B$20-0.015))^9+DCF!$B$31)/DCF!$B$32 -> 9.4240084 | D8: =B8 -> 5.5070893 | E8: =C8-B8 -> 3.9169191 | F8: =(B8+C8)/2 -> 7.4655489
A9: Comps — EV per pipeline GW ($0.35–0.70B) | B9: =Comps!E13 -> 14.261522 | C9: =Comps!F13 -> 24.175315 | D9: =B9 -> 14.261522 | E9: =C9-B9 -> 9.9137931 | F9: =(B9+C9)/2 -> 19.218419
A10: Comps — EV/FY2030E revenue (4–8x, disc.) | B10: =Comps!E14 -> 9.5579037 | C10: =Comps!F14 -> 14.768078 | D10: =B10 -> 9.5579037 | E10: =C10-B10 -> 5.2101744 | F10: =(B10+C10)/2 -> 12.162991
A11: Precedent framework ($0.25–0.55B per GW) | B11: =Precedents!B16 -> 11.42901 | C11: =Precedents!C16 -> 19.926547 | D11: =B11 -> 11.42901 | E11: =C11-B11 -> 8.4975369 | F11: =(B11+C11)/2 -> 15.677779
A12: Take-private capacity (25% → 15% IRR) | B12: =LBO!D32 -> 3.8802244 | C12: =LBO!D30 -> 6.4949903 | D12: =B12 -> 3.8802244 | E12: =C12-B12 -> 2.6147659 | F12: =(B12+C12)/2 -> 5.1876074
A13: Monte Carlo P25–P75 (live) | B13: =Monte_Carlo!B27 -> 5.2382988 | C13: =Monte_Carlo!B28 -> 9.359192 | D13: =B13 -> 5.2382988 | E13: =C13-B13 -> 4.1208932 | F13: =(B13+C13)/2 -> 7.2987454
A14: Current price (marker) | B14: =Assumptions!B46-0.35 -> 13.67 | C14: =Assumptions!B46+0.35 -> 14.37 | D14: =B14 -> 13.67 | E14: =C14-B14 -> 0.7 | F14: =(B14+C14)/2 -> 14.02
A16: Since-IPO range estimated from IPO-day high ~$30.70 and recent low ~$13.20 (stock listed 4/24/26 — no 52-week history yet). Analyst range: Jefferies $28 to Guggenheim $57. Intrinsic (DCF) ranges sit below market and analyst views because most SMR value lies beyond a 10-year window.
